Workbook
Name ________ys1: {#N/A,#N/A,FALSE,"abs";#N/A,#N/A,FALSE,"Annex-I";#N/A,#N/A,FALSE,"Annex-II";#N/A,#N/A,FALSE,"Annex-III";#N/A,#N/A,FALSE,"Annex-IV";#N/A,#N/A,FALSE,"Annex-V";#N/A,#N/A,FALSE,"Annex-VI"}
Name ________ys1: {#N/A,#N/A,FALSE,"abs";#N/A,#N/A,FALSE,"Annex-I";#N/A,#N/A,FALSE,"Annex-II";#N/A,#N/A,FALSE,"Annex-III";#N/A,#N/A,FALSE,"Annex-IV";#N/A,#N/A,FALSE,"Annex-V";#N/A,#N/A,FALSE,"Annex-VI"}
Name ________ys1: {#N/A,#N/A,FALSE,"abs";#N/A,#N/A,FALSE,"Annex-I";#N/A,#N/A,FALSE,"Annex-II";#N/A,#N/A,FALSE,"Annex-III";#N/A,#N/A,FALSE,"Annex-IV";#N/A,#N/A,FALSE,"Annex-V";#N/A,#N/A,FALSE,"Annex-VI"}
Name _______ys1: {#N/A,#N/A,FALSE,"abs";#N/A,#N/A,FALSE,"Annex-I";#N/A,#N/A,FALSE,"Annex-II";#N/A,#N/A,FALSE,"Annex-III";#N/A,#N/A,FALSE,"Annex-IV";#N/A,#N/A,FALSE,"Annex-V";#N/A,#N/A,FALSE,"Annex-VI"}
Name _______ys1: {#N/A,#N/A,FALSE,"abs";#N/A,#N/A,FALSE,"Annex-I";#N/A,#N/A,FALSE,"Annex-II";#N/A,#N/A,FALSE,"Annex-III";#N/A,#N/A,FALSE,"Annex-IV";#N/A,#N/A,FALSE,"Annex-V";#N/A,#N/A,FALSE,"Annex-VI"}
Name _______ys1: {#N/A,#N/A,FALSE,"abs";#N/A,#N/A,FALSE,"Annex-I";#N/A,#N/A,FALSE,"Annex-II";#N/A,#N/A,FALSE,"Annex-III";#N/A,#N/A,FALSE,"Annex-IV";#N/A,#N/A,FALSE,"Annex-V";#N/A,#N/A,FALSE,"Annex-VI"}
Name ______ys1: {#N/A,#N/A,FALSE,"abs";#N/A,#N/A,FALSE,"Annex-I";#N/A,#N/A,FALSE,"Annex-II";#N/A,#N/A,FALSE,"Annex-III";#N/A,#N/A,FALSE,"Annex-IV";#N/A,#N/A,FALSE,"Annex-V";#N/A,#N/A,FALSE,"Annex-VI"}
Name ______ys1: {#N/A,#N/A,FALSE,"abs";#N/A,#N/A,FALSE,"Annex-I";#N/A,#N/A,FALSE,"Annex-II";#N/A,#N/A,FALSE,"Annex-III";#N/A,#N/A,FALSE,"Annex-IV";#N/A,#N/A,FALSE,"Annex-V";#N/A,#N/A,FALSE,"Annex-VI"}
Name ______ys1: {#N/A,#N/A,FALSE,"abs";#N/A,#N/A,FALSE,"Annex-I";#N/A,#N/A,FALSE,"Annex-II";#N/A,#N/A,FALSE,"Annex-III";#N/A,#N/A,FALSE,"Annex-IV";#N/A,#N/A,FALSE,"Annex-V";#N/A,#N/A,FALSE,"Annex-VI"}
Name _____ys1: {#N/A,#N/A,FALSE,"abs";#N/A,#N/A,FALSE,"Annex-I";#N/A,#N/A,FALSE,"Annex-II";#N/A,#N/A,FALSE,"Annex-III";#N/A,#N/A,FALSE,"Annex-IV";#N/A,#N/A,FALSE,"Annex-V";#N/A,#N/A,FALSE,"Annex-VI"}
Name _____ys1: {#N/A,#N/A,FALSE,"abs";#N/A,#N/A,FALSE,"Annex-I";#N/A,#N/A,FALSE,"Annex-II";#N/A,#N/A,FALSE,"Annex-III";#N/A,#N/A,FALSE,"Annex-IV";#N/A,#N/A,FALSE,"Annex-V";#N/A,#N/A,FALSE,"Annex-VI"}
Name _____ys1: {#N/A,#N/A,FALSE,"abs";#N/A,#N/A,FALSE,"Annex-I";#N/A,#N/A,FALSE,"Annex-II";#N/A,#N/A,FALSE,"Annex-III";#N/A,#N/A,FALSE,"Annex-IV";#N/A,#N/A,FALSE,"Annex-V";#N/A,#N/A,FALSE,"Annex-VI"}
Name ____d2: {#N/A,#N/A,FALSE,"mgtsum.XLS";#N/A,#N/A,FALSE,"CAPONE";#N/A,#N/A,FALSE,"CAPTWO";#N/A,#N/A,FALSE,"CAPTHREE"}
Name ____d2: {#N/A,#N/A,FALSE,"mgtsum.XLS";#N/A,#N/A,FALSE,"CAPONE";#N/A,#N/A,FALSE,"CAPTWO";#N/A,#N/A,FALSE,"CAPTHREE"}
Name ____d2: {#N/A,#N/A,FALSE,"mgtsum.XLS";#N/A,#N/A,FALSE,"CAPONE";#N/A,#N/A,FALSE,"CAPTWO";#N/A,#N/A,FALSE,"CAPTHREE"}
Name ____ys1: {#N/A,#N/A,FALSE,"abs";#N/A,#N/A,FALSE,"Annex-I";#N/A,#N/A,FALSE,"Annex-II";#N/A,#N/A,FALSE,"Annex-III";#N/A,#N/A,FALSE,"Annex-IV";#N/A,#N/A,FALSE,"Annex-V";#N/A,#N/A,FALSE,"Annex-VI"}
Name ____ys1: {#N/A,#N/A,FALSE,"abs";#N/A,#N/A,FALSE,"Annex-I";#N/A,#N/A,FALSE,"Annex-II";#N/A,#N/A,FALSE,"Annex-III";#N/A,#N/A,FALSE,"Annex-IV";#N/A,#N/A,FALSE,"Annex-V";#N/A,#N/A,FALSE,"Annex-VI"}
Name ____ys1: {#N/A,#N/A,FALSE,"abs";#N/A,#N/A,FALSE,"Annex-I";#N/A,#N/A,FALSE,"Annex-II";#N/A,#N/A,FALSE,"Annex-III";#N/A,#N/A,FALSE,"Annex-IV";#N/A,#N/A,FALSE,"Annex-V";#N/A,#N/A,FALSE,"Annex-VI"}
Name ___d2: {#N/A,#N/A,FALSE,"mgtsum.XLS";#N/A,#N/A,FALSE,"CAPONE";#N/A,#N/A,FALSE,"CAPTWO";#N/A,#N/A,FALSE,"CAPTHREE"}
Name ___d2: {#N/A,#N/A,FALSE,"mgtsum.XLS";#N/A,#N/A,FALSE,"CAPONE";#N/A,#N/A,FALSE,"CAPTWO";#N/A,#N/A,FALSE,"CAPTHREE"}
Name ___d2: {#N/A,#N/A,FALSE,"mgtsum.XLS";#N/A,#N/A,FALSE,"CAPONE";#N/A,#N/A,FALSE,"CAPTWO";#N/A,#N/A,FALSE,"CAPTHREE"}
Name ___fco2: {#N/A,#N/A,FALSE,"gc (2)"}
Name ___fco2: {#N/A,#N/A,FALSE,"gc (2)"}
Name ___fco2: {#N/A,#N/A,FALSE,"gc (2)"}
Name ___ns1: {#N/A,#N/A,FALSE,"COVER1.XLS ";#N/A,#N/A,FALSE,"RACT1.XLS";#N/A,#N/A,FALSE,"RACT2.XLS";#N/A,#N/A,FALSE,"ECCMP";#N/A,#N/A,FALSE,"WELDER.XLS"}
Name ___ns1: {#N/A,#N/A,FALSE,"COVER1.XLS ";#N/A,#N/A,FALSE,"RACT1.XLS";#N/A,#N/A,FALSE,"RACT2.XLS";#N/A,#N/A,FALSE,"ECCMP";#N/A,#N/A,FALSE,"WELDER.XLS"}
Name ___ns1: {#N/A,#N/A,FALSE,"COVER1.XLS ";#N/A,#N/A,FALSE,"RACT1.XLS";#N/A,#N/A,FALSE,"RACT2.XLS";#N/A,#N/A,FALSE,"ECCMP";#N/A,#N/A,FALSE,"WELDER.XLS"}
Name ___ram1: {#N/A,#N/A,FALSE,"gc (2)"}
Name ___ram1: {#N/A,#N/A,FALSE,"gc (2)"}
Name ___ram1: {#N/A,#N/A,FALSE,"gc (2)"}
Name ___sti02: {#N/A,#N/A,FALSE,"gc (2)"}
Name ___sti02: {#N/A,#N/A,FALSE,"gc (2)"}
Name ___sti02: {#N/A,#N/A,FALSE,"gc (2)"}
Name ___ta1: {#N/A,#N/A,TRUE,"Financials";#N/A,#N/A,TRUE,"Operating Statistics";#N/A,#N/A,TRUE,"Capex & Depreciation";#N/A,#N/A,TRUE,"Debt"}
Name ___ta1: {#N/A,#N/A,TRUE,"Financials";#N/A,#N/A,TRUE,"Operating Statistics";#N/A,#N/A,TRUE,"Capex & Depreciation";#N/A,#N/A,TRUE,"Debt"}
Name ___ta1: {#N/A,#N/A,TRUE,"Financials";#N/A,#N/A,TRUE,"Operating Statistics";#N/A,#N/A,TRUE,"Capex & Depreciation";#N/A,#N/A,TRUE,"Debt"}
Name ___tb1: {#N/A,#N/A,FALSE,"One Pager";#N/A,#N/A,FALSE,"Technical"}
Name ___tb1: {#N/A,#N/A,FALSE,"One Pager";#N/A,#N/A,FALSE,"Technical"}
Name ___tb1: {#N/A,#N/A,FALSE,"One Pager";#N/A,#N/A,FALSE,"Technical"}
Name ___xlfn.BAHTTEXT: #NAME?
Name ___ys1: {#N/A,#N/A,FALSE,"abs";#N/A,#N/A,FALSE,"Annex-I";#N/A,#N/A,FALSE,"Annex-II";#N/A,#N/A,FALSE,"Annex-III";#N/A,#N/A,FALSE,"Annex-IV";#N/A,#N/A,FALSE,"Annex-V";#N/A,#N/A,FALSE,"Annex-VI"}
Name ___ys1: {#N/A,#N/A,FALSE,"abs";#N/A,#N/A,FALSE,"Annex-I";#N/A,#N/A,FALSE,"Annex-II";#N/A,#N/A,FALSE,"Annex-III";#N/A,#N/A,FALSE,"Annex-IV";#N/A,#N/A,FALSE,"Annex-V";#N/A,#N/A,FALSE,"Annex-VI"}
Name ___ys1: {#N/A,#N/A,FALSE,"abs";#N/A,#N/A,FALSE,"Annex-I";#N/A,#N/A,FALSE,"Annex-II";#N/A,#N/A,FALSE,"Annex-III";#N/A,#N/A,FALSE,"Annex-IV";#N/A,#N/A,FALSE,"Annex-V";#N/A,#N/A,FALSE,"Annex-VI"}
Name __d2: {#N/A,#N/A,FALSE,"mgtsum.XLS";#N/A,#N/A,FALSE,"CAPONE";#N/A,#N/A,FALSE,"CAPTWO";#N/A,#N/A,FALSE,"CAPTHREE"}
Name __d2: {#N/A,#N/A,FALSE,"mgtsum.XLS";#N/A,#N/A,FALSE,"CAPONE";#N/A,#N/A,FALSE,"CAPTWO";#N/A,#N/A,FALSE,"CAPTHREE"}
Name __d2: {#N/A,#N/A,FALSE,"mgtsum.XLS";#N/A,#N/A,FALSE,"CAPONE";#N/A,#N/A,FALSE,"CAPTWO";#N/A,#N/A,FALSE,"CAPTHREE"}
Name __FDS_HYPERLINK_TOGGLE_STATE__: "ON"
Name __IntlFixup: TRUE
Name __ta1: {#N/A,#N/A,TRUE,"Financials";#N/A,#N/A,TRUE,"Operating Statistics";#N/A,#N/A,TRUE,"Capex & Depreciation";#N/A,#N/A,TRUE,"Debt"}
Name __ta1: {#N/A,#N/A,TRUE,"Financials";#N/A,#N/A,TRUE,"Operating Statistics";#N/A,#N/A,TRUE,"Capex & Depreciation";#N/A,#N/A,TRUE,"Debt"}
Name __ta1: {#N/A,#N/A,TRUE,"Financials";#N/A,#N/A,TRUE,"Operating Statistics";#N/A,#N/A,TRUE,"Capex & Depreciation";#N/A,#N/A,TRUE,"Debt"}
Name __tb1: {#N/A,#N/A,FALSE,"One Pager";#N/A,#N/A,FALSE,"Technical"}
Name __tb1: {#N/A,#N/A,FALSE,"One Pager";#N/A,#N/A,FALSE,"Technical"}
Name __tb1: {#N/A,#N/A,FALSE,"One Pager";#N/A,#N/A,FALSE,"Technical"}
Name __xlfn.BAHTTEXT: #NAME?
Name __ys1: {#N/A,#N/A,FALSE,"abs";#N/A,#N/A,FALSE,"Annex-I";#N/A,#N/A,FALSE,"Annex-II";#N/A,#N/A,FALSE,"Annex-III";#N/A,#N/A,FALSE,"Annex-IV";#N/A,#N/A,FALSE,"Annex-V";#N/A,#N/A,FALSE,"Annex-VI"}
Name __ys1: {#N/A,#N/A,FALSE,"abs";#N/A,#N/A,FALSE,"Annex-I";#N/A,#N/A,FALSE,"Annex-II";#N/A,#N/A,FALSE,"Annex-III";#N/A,#N/A,FALSE,"Annex-IV";#N/A,#N/A,FALSE,"Annex-V";#N/A,#N/A,FALSE,"Annex-VI"}
Name __ys1: {#N/A,#N/A,FALSE,"abs";#N/A,#N/A,FALSE,"Annex-I";#N/A,#N/A,FALSE,"Annex-II";#N/A,#N/A,FALSE,"Annex-III";#N/A,#N/A,FALSE,"Annex-IV";#N/A,#N/A,FALSE,"Annex-V";#N/A,#N/A,FALSE,"Annex-VI"}
Name _abs123: {#N/A,#N/A,FALSE,"M&B_43A_fab";#N/A,#N/A,FALSE,"M&B_43A_ERE.";#N/A,#N/A,FALSE,"M&B-43A-ALIGN"}
Name _abs123: {#N/A,#N/A,FALSE,"M&B_43A_fab";#N/A,#N/A,FALSE,"M&B_43A_ERE.";#N/A,#N/A,FALSE,"M&B-43A-ALIGN"}

Sheet SUMMARY
A1: CLIENT | B1: M/s. Paytm Bengaluru
A2: SUBJECT | B2: Detailed Offer
A3: DATE | B3: 46125
A4: CARPET AREA | B4: 12377
A5: REVISION | B5: R0
A6: SR NO | B6: PARTICULARS | C6: PER SFT | D6: AMOUNT | E6: REMARKS
A7: PART - C | B7: MEP WORKS
A8: 1 | B8: ELECTRICAL WORKS | C8: =D8/B$4 -> 458.62115 | D8: ='MEP SUMMARY'!E6 -> 5676354
A9: =+A8+1 -> 2 | B9: LIGHT FIXTURES | C9: =D9/B$4 -> 10.167973 | D9: ='MEP SUMMARY'!E7 -> 125849
A10: =+A9+1 -> 3 | B10: UPS | C10: =D10/B$4 -> #REF! | D10: =#REF! -> #REF!
A11: =+A10+1 -> 4 | B11: HVAC WORKS | C11: =D11/B$4 -> 339.3391 | D11: ='MEP SUMMARY'!E8 -> 4200000
A12: =+A11+1 -> 5 | B12: FIRE AND SAFTY | C12: =D12/B$4 -> 233.84791 | D12: ='MEP SUMMARY'!E9 -> 2894335.6
A13: =+A12+1 -> 6 | B13: ACCESS AND CCTV | C13: =D13/B$4 -> 99.16054 | D13: ='MEP SUMMARY'!E10 -> 1227310
A14: =+A13+1 -> 7 | B14: BMS
A15: =+A14+1 -> 8 | B15: NETWORKING
A16: =+A15+1 -> 9 | B16: HDMI CABLES /USB CABLES
A17: =+A16+1 -> 10 | B17: AV WORK
B18: TOTAL FOR PART - C | C18: =D18/B$4 -> #REF! | D18: =SUM(D8:D17) -> #REF!
A20: I | B20: TOTAL - WITHOUT TAXES | C20: =D20/B$4 -> #REF! | D20: =SUM(D7:D18)/2 -> #REF!
A21: a | B21: ADD LABOR CESS @1% | C21: =D21/B$4 -> #REF! | D21: =N(D20*1%) -> #REF!
A22: II | B22: TOTAL - WITH BOCW | C22: =D22/B$4 -> #REF! | D22: =SUM(D20:D21) -> #REF!
B24: KITCHEN EQUIPMENTS | C24: =D24/B$4 -> 0 | D24: 0 | E24: Not Applicable

Sheet MEP SUMMARY
A1: PAYTM MEP COSTING SUMMERY SHEET
A2: Project Location | C2: Bangalore
A3: Area
A4: Sl.No | B4: Package | C4: Supply | D4: Installation | E4: Total | F4: Remarks
A6: 1 | B6: ELECTRICAL WORKS | C6: ='ELEC BOQ'!H1400 -> 4715431 | D6: ='ELEC BOQ'!I1400 -> 960923 | E6: =SUM(C6:D6) -> 5676354
A7: =A6+1 -> 2 | B7: LIGHT FIXTURES | C7: ='LGT BOQ'!I69 -> 0 | D7: ='LGT BOQ'!J69 -> 125849 | E7: =SUM(C7:D7) -> 125849
A8: =A7+1 -> 3 | B8: HVAC WORKS | C8: ='HVAC BOQ'!G401 -> 3463623 | D8: ='HVAC BOQ'!H401 -> 736377 | E8: =SUM(C8:D8) -> 4200000
A9: =A8+1 -> 4 | B9: FIRE AND SAFTY | C9: ='FIRE & SAFETY'!G188 -> 2437564 | D9: ='FIRE & SAFETY'!H188 -> 456771.6 | E9: =SUM(C9:D9) -> 2894335.6
A10: =A9+1 -> 5 | B10: ACCESS AND CCTV | C10: ='ACS & CCTV '!H88 -> 1115510 | D10: ='ACS & CCTV '!I88 -> 111800 | E10: =SUM(C10:D10) -> 1227310
B11: Grand TOTAL | C11: =SUM(C6:C10) -> 11732128 | D11: =SUM(D6:D10) -> 2391720.6 | E11: =SUM(E6:E10) -> 14123849

Sheet PREAMBLE
A1: Preamble Points:
B3: Following is integral part of Contractors Scope of Work points and Contractor to take note of same while quoting and during execution for the work:
A5: 1 | B5: The Preamble to the Bills of Quantities must be read with the Drawings, Conditions of Contract and the Specification and the tenderer shall be deemed to have examined the Drawings, Specifications, Conditions of Contract and to have acquainted himself with the Works to be done and the way in which they are to be carried out. This preamble to the Bills of Quantities shall form part of the Contract.
A6: =A5+1 -> 2 | B6: The Tenderers are requested to inspect the site and obtain for themselves at their own expense all necessary information and particulars to enable them to submit the tender.
A7: =A6+1 -> 3 | B7: The dimensions shown in the drawings shall have to be verified by the contractor at site before execution of the items and necessary allowance's) have to be made as per the actual dimensions available at site.
A8: =A7+1 -> 4 | B8: For the items of works having Basic rate of material, price adjustment will be made only on the actual quantity measured. Wastage & Installation shall be to Contractors account. Basic rate indicates loading unloading, transportation etc.
A9: =A8+1 -> 5 | B9: The contractor should refer to the tender drawings / 3D views / Technical specifications for details. In case of any discrepancy, the drawing will take precedence, unless specifically mentioned in the BOQ.
A10: =A9+1 -> 6 | B10: All pre-fabrication works wherever possible shall be carried outside the client's premises, only assembling and finishing work will be allowed within the Site. This is specific to finishing works involving high VOC items which are not permissible to be executed within the premises. The list of such works will be mutually agreed during the kick off meeting.
A11: =A10+1 -> 7 | B11: Unless specifically mentioned otherwise in the contract, the tenderer shall quote for the finished items and shall provide for the complete cost towards labour, materials, plant and machinery, operational costs, levies, taxes, transport, repairs, rectification, maintenance till handing over, revenue expenses, contingencies, overheads, profits and all incidental items not specifically mentioned but reasonably implied and necessary to complete the works according to the contract.
A12: =A11+1 -> 8 | B12: The quantities of the various items mentioned in the schedule of items are approximate and may vary up to any extent or be deleted altogether. The quoted rates of each item shall remain firm for all works. The contractor, in his own interest, should get an indication of the probable extent of the work to be executed under any item in this schedule, before undertaking any preliminary and enabling work or purchasing bought out components related to the work.
A13: =A12+1 -> 9 | B13: Sample: Contractor at his own cost shall produce the samples for approval from Architect or EIC, after the due approval of sample contractor shall go for procurement, if architect ask for more samples contractor shall arrange for the same without delay.
A14: =A13+1 -> 10 | B14: Mock-ups: Contractor shall make or Build mock-ups to verify selections made under sample Submittals and to demonstrate aesthetic effects and qualities of materials and execution as instructed by EIC. Approval of mock-ups does not constitute approval of deviations from the Contract Documents contained in mock-ups unless Architect specifically approves such deviations in writing. Approved mock-ups may become part of the completed Work if undisturbed at time of Substantial Completion. The mock up shall be free of cost.
A15: =A14+1 -> 11 | B15: Procedure of work: The contractor shall arrange the operations that have been agreed to by the Project consultants /Employer. He shall adhere to the schedule presented by him and agreed by the project consultants and shall complete all works allotted to him in time, giving best workmanship to the entire satisfaction of the Project consultants.
A16: =A15+1 -> 12 | B16: Protection of work: Contractor shall do protection of asset’s which are not to be demolished and asset’s which are to be handover to client. He shall also provide and maintain any other temporary covering that required for the protection of financed / unfinished woodwork that may be damaged during the progress of the work if left unprotected.
A17: =A16+1 -> 13 | B17: Contractor should protect with PVC bubble guard sheet of 6mm thk all the completed works in his scope and uncover the same while it’s being handed over.
... A23: =A22+1 -> 19 | B23: Safety of contractor supplied material is contractor scope.
A24: =A23+1 -> 20
A25: =A24+1 -> 21 | B25: Items of work provided in this schedule but not covered in the specifications shall be executed strictly as per instructions of the project manager/architect.
A26: =A25+1 -> 22 | B26: All stones mentioned in the tender shall be brought to site only from the lots pre-approved /selected by the architects.
A27: =A26+1 -> 23 | B27: All Samples of tiles, fittings etc. shall be presented after ensuring that the necessary quantities of the relevant item(s) for which the same are invited are available, (ex-stock, or otherwise) and shall be approved by the architect before placing of mass orders.
A28: =A27+1 -> 24 | B28: All the Dado and/ Flooring shall include rates of the 3mm thk spacers with colour matching grouts and Edge Guards of matching colour of the dado wherever the walls are in right angles, as per instructions / related specifications towards the same, by the consulting architects
A29: =A28+1 -> 25 | B29: All joints, wherever necessary, shall be undertaken after prior approval of the same from the Architects.
A30: =A29+1 -> 26 | B30: All materials utilized shall be as per tender recommendations and shall be applied according to manufacturer's specifications.
A31: =A30+1 -> 27 | B31: The rates for all tiles, slabs of marble, granite, Kota or any other stone should be inclusive of all materials, transport, loading unloading, Octroi and all taxes thereon. The rate mentioned is the maximum and in no way should exceed, the one mentioned.
A32: =A31+1 -> 28 | B32: Rates quoted for items of counter, etc. shall be inclusive of making necessary cutouts for sinks, basins and inclusive of polishing the cut edge to the profile as indicated on the drawings, to the entire satisfaction of the supervising architects.
A33: =A32+1 -> 29 | B33: Rates quoted for the Ramps/ treads of the staircases shall be deemed to be inclusive of making all necessary cutouts, for railing balustrades, etc., in 'workmanlike manner, and, to the entire satisfaction of the supervising architects
A34: =A33+1 -> 30 | B34: Unless other wise specified all rates shall be in INR
A35: =A34+1 -> 31 | B35: Work shall be at all heights including double and triple heights and rate shall include the cost of necessary scaffolding and staging
A36: =A35+1 -> 32 | B36: Any/all inserts/U/Hat/Corner etc. profiles/grooving and laying patterns shall be as per architects specifications and shall form part of the relevant panelling detail(s) and shall not be paid for extra, unless otherwise specified/ mentioned
... A53: =A52+1 -> 49 | B53: Make list to be as per Architect / Consultants choice.

Sheet MAKES - MEP 
A1: PROJECT | B1: PAYTM
A2: SUBJECT | B2: MAKE LIST
A3: DATE | B3: 46113
A4: VERSION | B4: V0
A6: SUBJECT: STANDARD MAKES- PAYTM
B7: ITEMS | C7: MAKES
A8: A | B8: ELECTRICAL&ELV
A9: 1 | B9: LT CABLES | C9: KEI/ POLYCAB/ RR KABEL | D9: Polycab
A10: 2 | B10: CABLE GLANDS & LUGS | C10: BRACO / DOWELS / JAISON / SMI / HMI | D10: Dowells
A11: 3 | B11: FRLS / ZHFR WIRES & MULTI CORE FLEXIBLE CABLES | C11: POLYCAB / KEI/ RR KABEL | D11: Polycab
A12: 4 | B12: TECHNICAL LIGHT FIXTURES | C12: WIPRO/ PHILIPS/ARRAY STORM/ LEGERO / CENZER
A13: 5 | B13: DECORATIVE LIGHT FIXTURES | C13: LEGERO/RIPPL/ LUNNARK / PURPLE TURTLES /LANCE
A14: 6 | B14: LIGHTING CONTROL SENSORS | C14: HONEYWELL / ZEN CONTROL / LUTRON
A15: 7 | B15: FANS & EXHAUST FANS | C15: CROMPTON/ BAJAJ/ HAVELLS | D15: Caryaire
A16: 8 | B16: FLOOR BOXES & WORKSTATION POP Ups | C16: Connect System / CJ Infra
A17: 9 | B17: SWITCHES / SOCKETS & MODULAR FACE PLATES | C17: ANCHOR- ROMA / SCHNEIDER - LIVIA / LEGRAND / INDOASIA SHYNORA / SIEMENS
A18: 10 | B18: DISTRIBUTION BOARDS | C18: ABB / SCHNEIDER/ LEGRAND/ SIEMENS
A19: 11 | B19: MCBs/RCCB/RCBOs/ Isolators | C19: ABB / SCHNEIDER/ LEGRAND/ SIEMENS
A20: 12 | B20: MCCBs | C20: ABB / SCHNEIDER/ LEGRAND/ SIEMENS
A21: 13 | B21: INDUSTRIAL SOCKETS | C21: LEGRAND / SCAME / NEPTUNE / HAGER
A22: 14 | B22: PVC CONDUITS & ACCESSORIES | C22: VIP / AVANPLAST | D22: VIP
A23: 15 | B23: MS / GI CONDUITS & ACCESSORIES | C23: GUPTA / AKG/ GB
A24: 16 | B24: GI RACEWAYS / CABLE TRAYS | C24: CLASSIC / PUSHPAK / PROFAB | D24: Vickram
A25: 17 | B25: ALUMINIUM RACEWAYS | C25: JINDAL
A26: 18 | B26: UPVC TRUNKING/RACEWAY | C26: MK/ OBO BETTERMANN/ LEGRAND | D26: OBO
A27: 19 | B27: HRC SWITCH FUSE UNITS | C27: GE / L&T / SIEMENS / ABB / SCHNEIDER (MERLIN GERIN)
A28: 20 | B28: RG59 OUTLETS | C28: ANCHOR / CRABTREE(VERONA)
A29: 21 | B29: RG59 COAXIAL CABLE | C29: FINOLEX / POLYCAB
A30: 22 | B30: LOAD MANAGERS / MEASURING INSTRUMENT | C30: TRINITY / HPL / ENERCON / SECURE / SCHNEIDER / ELMEASURE
A31: 23 | B31: CONTACTORS | C31: L & T / SCHNEIDER (MERLIN GERIN) / LEGRAND
A32: 24 | B32: C.T UNIT | C32: INDCOIL / MECO / SIEMENS
A33: 25 | B33: CAPACITOR | C33: SUBODHAN / LEGRAND / EPCOS / SIEMENS
A34: 26 | B34: P.F. RELAY | C34: TRINITY / ENERCON / SECURE / L&T / SIEMENS
A35: 27 | B35: MANUAL CHANGE OVER SWITCH | C35: L & T / SCHNEIDER (MERLIN GERIN) / SOCOMEC
A36: 28 | B36: AUTOMATIC TRANSFER SWITCH (ATS) | C36: ASCO / LT / SOCOMEC
A37: 29 | B37: PANEL ACCESSORIES | C37: L&T / SIEMENS / MG / GE
A38: 30 | B38: SPD/TVSS | C38: LEGRAND / SCHNEIDER (MERLIN GERIN) / HAGER/OBO
A39: 31 | B39: LT PANELS & Fabricated DBs | C39: SHARAN CONTROLS/ MASS ENGINEERING/ SAMRUDHI CONTROLS
A41: B | B41: UPS & INVERTERS
A42: 1 | B42: UPS | C42: Vertiv / APC Schenider
A43: 2 | B43: UPS BATTERY | C43: Amar Raja/ Exide/ Quanta
A44: 3 | B44: ONLINE INVERTOR | C44: Microtec/ Luminous/ Su-Kam/ Consul Neowatt | D44: microtec
A45: 4 | B45: INVERTOR BATTERY | C45: Amar Raja/ Exide /Rocket/ Quanta | D45: Exide
A47: C | B47: NETWORKING
A48: 1 | B48: CAT-6/ Cat6A cable / Patchpanels / IOs & patch cords | C48: COMSCOPE net connect /AMP / MOLEX | D48: commscope
A49: 2 | B49: Racks | C49: NETRACK / VALRACK | D49: netrack
A50: 3 | B50: Lables | C50: Panduit / Equivalent
A51: 4 | B51: MDF & Connectors | C51: KRONE
A52: 5 | B52: Telephone wires | C52: DELTON / FINOLEX / Polycab
A54: D | B54: FIRE ALARM SYSTEM
A55: 1 | B55: Fire Alarm Panel | C55: Edwards / Simplex / Notifier | D55: Edwards
A56: 2 | B56: Loop Cards | C56: Edwards / Simplex / Notifier | D56: Edwards
A57: 3 | B57: Repeater Panel | C57: Edwards / Simplex / Notifier | D57: Edwards
A58: 5 | B58: Photelectric Smoke Detectors | C58: Edwards / Simplex / Notifier | D58: Edwards
A59: 6 | B59: Heat Detectors | C59: Edwards / Simplex / Notifier | D59: Edwards
A60: 7 | B60: Multisensor Detectors | C60: Edwards | D60: Edwards
A61: 8 | B61: Interface Modules : Monitor / Relay / Control etc. | C61: Edwards | D61: Edwards
A62: 9 | B62: Sounders / Sounder cum Strobes | C62: Edwards | D62: Edwards
A63: 10 | B63: Manual Pull Stations | C63: Edwards | D63: Edwards
A64: 11 | B64: Fault Isolator Modules | C64: Edwards | D64: Edwards
A65: 12 | B65: Response indicators | C65: Edwards | D65: Edwards
A66: 13 | B66: Control Cables | C66: Varsha / Ravicab / KEI | D66: polycab
A67: 14 | B67: MS / GI CONDUITS & ACCESSORIES | C67: GUPTA / AKG/ GB
A69: E | B69: PUBLIC ADDRESS SYSTEMS
A70: 1 | B70: Main PA Controller | C70: Bosch / Honeywell / Heinrich | D70: Bosch
A71: 2 | B71: Slave Controller | C71: Bosch / Honeywell / Heinrich | D71: Bosch
A72: 3 | B72: Audio Amplifier | C72: Bosch | D72: Bosch
A73: 4 | B73: Call station / Keypad | C73: Bosch | D73: Bosch
A74: 6 | B74: Gooseneck Microphone | C74: Bosch | D74: Bosch
A75: 7 | B75: Speakers (Ceiling/Wall Mount) | C75: Bosch | D75: Bosch
A76: 8 | B76: Background Music Source | C76: Bosch | D76: Bosch
A77: 9 | B77: Control Cables | C77: Varsha / Ravicab / KEI | D77: polycab
A78: 10 | B78: PVC Conduits | C78: VIP / AVANPLAST / ISI Marked equivalent | D78: VIP
A79: 11 | B79: Cable Tray | C79: CLASSIC / PUSHPAK / PROFAB | D79: Vickram
A80: 12 | B80: MS / GI CONDUITS & ACCESSORIES | C80: GUPTA / AKG/ GB
A82: F | B82: SPRINKLER SYSTEM
A83: 1 | B83: MS / GI Pipes | C83: Tata / Jindal
A84: 2 | B84: Pipe Fittings | C84: On sample approval
A85: 3 | B85: Sprinkler bulbs | C85: Tyco / Viking | D85: Tyco
A86: 4 | B86: Flexible drops | C86: Tyco / Viking/ Youngjin/ New age | D86: Newage
A87: 5 | B87: Butterfly valves | C87: Asian / Normax/ Syatem sensor/ Tyco | D87: Sant
A88: 6 | B88: Pressure gauges | C88: H Guru / Equivalent | D88: H guru
A89: 7 | B89: Flow switches | C89: Tyco/ System sensor/ Honeywell | D89: Honeywell
A90: 8 | B90: Paints | C90: Berger / Asian
A91: 9 | B91: Threded rods & supports | C91: Hilti/ Equivalent | D91: Equivalent
A93: G | B93: IP BASED CCTV SYSTEM
A94: 1 | B94: IP Dome / Bullet Cameras | C94: PRAMA | D94: Prama
A95: 2 | B95: NVR & Softwere | C95: PRAMA | D95: Prama
A96: 3 | B96: Storage hard discs | C96: WD / Seagate | D96: Seagate
A97: 4 | B97: PC / Monitors | C97: Lenovo/ Dell/ Samsung
A98: 5 | B98: Power Supplies | C98: Reputed
A99: 6 | B99: Copper Cables | C99: Varsha / Ravicab / KEI
A100: 7 | B100: CAT-6 cables & accessories | C100: AMP / BELDEN/ MOLEX
A101: 8 | B101: Conduits | C101: VIP / AVANPLAST / ISI Marked equivalent
A102: 9 | B102: MS / GI CONDUITS & ACCESSORIES | C102: GUPTA / AKG/ GB
A104: H | B104: ACCESS CONTROL SYSTEMS
A105: 1 | B105: Proximity Card Readers | C105: "Current ACS Detailed Spec EM Lock Single 600 LBS with L Bracket 83014090 Make Bel EDR Reputed brand Oryggi 4 Door 4 Reader controller with enclosure and PSU Access Card Reader Smart-I SPR-501 Oryggi 4 Door 4 Reader controller with enclosure and PSU Enclosure Box For Controller Oryggi Controller License Oryggi Bio metric reader for Server Room"
A106: 2 | B106: Biomatric readers
A107: 3 | B107: Access Controller
A108: 5 | B108: Access Control Software
...

Sheet ELEC  BOQ
A1: PROJECT | B1: : PAYTM BANGALORE
A2: SUBJECT | B2: : BILL OF QUANTITIES - ELECTRICAL
A3: DATE | B3: : 30.03.2026
A4: VERSION | B4: : V0 | D4: Quantity
A5: Sl.No. | B5: DESCRIPTION | C5: UNIT | D5: 6F | E5: Total | F5: RATE | H5: AMOUNT | J5: Total | K5: REMARKS
F6: Supply | G6: Installation | H6: Supply | I6: Installation
A8: =ROMAN(1) -> I | B8: LT PANELS :
A9: A | B9: All Panels Should be as per Technical specifications & Power distribution scheme
B10: Supply, installation, testing & commisioning of 3 Phase, 4 wire, 415 V, 50 Hz panels. The fabrication shall be made with cold rolled annealed sheet with Machine pressing. The surface shall be rigorously treated for derusting in 7 tank process with powder coating. The panel shall be totally enclosed metal clad type with double gasketting with rubber / foam gasketting. The panel shall be off- white painted inside and shall be having control directory pasted on the inside surface of the panel door. The panel shall be suitable for mounting on existing trench and shall have cable entry provision from the top and bottom with suitable alley as the case may be. The panel shall be tested for the same KA rating of the relevant highest rating of breaker. All components shall be of approved make and shall have relevant IS/IEC approvals (Fabrication, drawing, list of components and panel detail shall be got approved before fabrication). The panel shall include base frame channel support.All complete as per relevant standard, technical specification, SLD, data sheets and direction of Engineer-in-charge.
B11: Indoor type LT Switchboards, Floor mounting type, Bottom/Top entry. Refer enclosed SLD for component details.
B12: Doors:2mm Body:2mm Gland Plate :3mm covers and partitions:1.6mm
B13: IP class:IP52 for Indoor/IP55 with weather proof enclosure with top cover for outdoor
B14: Bus bars: Electrolytic grade conductivity as per standard IS 5082
B15: Bus bar Material: As per SLD
B16: Bus bar supports: DMC/FRP/SMC
B17: Bus bar joints: Shrouded/Tinned
B18: Protection releases: As per SLD (Adjustable over current & short circuit unless otherwise specified)
B19: Shade: Epoxy powder coated RAL 7032 for RP Panel & another colour for UPS Panel
B20: Design: Modular type & Form 3B Construction
B21: Cable entry: As per site condition
... B69: CPRI certified
A71: 1.1 | B71: FLOOR LT PANEL | C71: No. | D71: 1 | E71: =D71 -> 1 | F71: 336995 | G71: 30742 | H71: =+N($E71)*N(F71) -> 336995 | I71: =+N($E71)*N(G71) -> 30742 | J71: =SUM(H71:I71) -> 367737
E72: =D72 | H72: =+N($E72)*N(F72) -> 0 | I72: =+N($E72)*N(G72) -> 0 | J72: =SUM(H72:I72) -> 0
A73: =A71+0.1 -> 1.2 | B73: WORKSTATION UPS OUTPUT PANEL | C73: No. | D73: 1 | E73: =D73 -> 1 | F73: 106006 | G73: 13176 | H73: =+N($E73)*N(F73) -> 106006 | I73: =+N($E73)*N(G73) -> 13176 | J73: =SUM(H73:I73) -> 119182
E74: =D74 | H74: =+N($E74)*N(F74) -> 0 | I74: =+N($E74)*N(G74) -> 0 | J74: =SUM(H74:I74) -> 0
A75: =A73+0.1 -> 1.3 | B75: Supply, Installation, testing & commisioning of 160A, 36kA 4P MCCB Tapoff Box with RYB indicating lamps with MCB control & Meter.Tap-off to be fixed to existing rising main. For Cable termination Additional Box to be considered in costing. Existing Rising main make : All standrads to be matched with installed tap-off ratings & quality | C75: No. | D75: RO | E75: =D75 -> RO | H75: =+N($E75)*N(F75) -> 0 | I75: =+N($E75)*N(G75) -> 0 | J75: =SUM(H75:I75) -> 0
E76: =D76 | H76: =+N($E76)*N(F76) -> 0 | I76: =+N($E76)*N(G76) -> 0 | J76: =SUM(H76:I76) -> 0
A77: =A75+0.1 -> 1.4 | B77: Supply, Installation, testing & commisioning of 200A, 36kA 4P MCCB Tapoff Box with RYB indicating lamps with MCB control & Meter.Tap-off to be fixed to existing rising main. For Cable termination Additional Box to be considered in costing. Existing Rising main make : All standrads to be matched with installed tap-off ratings & quality | C77: No. | D77: RO | E77: =D77 -> RO | H77: =+N($E77)*N(F77) -> 0 | I77: =+N($E77)*N(G77) -> 0 | J77: =SUM(H77:I77) -> 0
E78: =D78 | H78: =+N($E78)*N(F78) -> 0 | I78: =+N($E78)*N(G78) -> 0 | J78: =SUM(H78:I78) -> 0
A79: =A77+0.1 -> 1.5 | B79: Supply, Installation, testing & commisioning of 400A, 36kA 4P MCCB Tapoff Box with RYB indicating lamps with MCB control & Meter.Tap-off to be fixed to existing rising main. For Cable termination Additional Box to be considered in costing. Existing Rising main make : All standrads to be matched with installed tap-off ratings & quality | C79: No. | D79: RO | E79: =D79 -> RO | H79: =+N($E79)*N(F79) -> 0 | I79: =+N($E79)*N(G79) -> 0 | J79: =SUM(H79:I79) -> 0
E80: =D80 | H80: =+N($E80)*N(F80) -> 0 | I80: =+N($E80)*N(G80) -> 0 | J80: =SUM(H80:I80) -> 0
A81: =A79+0.1 -> 1.6 | B81: Supply, Installation, testing & commisioning of 630A, 36kA 4P MCCB Tapoff Box with RYB indicating lamps with MCB control & Meter.Tap-off to be fixed to existing rising main. For Cable termination Additional Box to be considered in costing. Existing Rising main make : All standrads to be matched with installed tap-off ratings & quality | C81: No. | D81: RO | E81: =D81 -> RO | H81: =+N($E81)*N(F81) -> 0 | I81: =+N($E81)*N(G81) -> 0 | J81: =SUM(H81:I81) -> 0
E82: =D82 | H82: =+N($E82)*N(F82) -> 0 | I82: =+N($E82)*N(G82) -> 0 | J82: =SUM(H82:I82) -> 0
A83: =A81+0.1 -> 1.7 | B83: Supply, installation, testing & commissioning of 160A 4P MCCB 36KA to existing Builder Main panel . Costing shall include all necessary accessories like indication lamp , Meters , CT & control wiring etc. Vendor should do the site survey for better understanding & clarity. Panel RAL colour & Quality of additional works should match with existing panel.Costing shall include opening of cutout , cable box as per site condition & site survey to be done for any clarification .. Required all costing to be quoted in this line item to complete the works | C83: No. | D83: RO | E83: =D83 -> RO | H83: =+N($E83)*N(F83) -> 0 | I83: =+N($E83)*N(G83) -> 0 | J83: =SUM(H83:I83) -> 0
E84: =D84 | H84: =+N($E84)*N(F84) -> 0 | I84: =+N($E84)*N(G84) -> 0 | J84: =SUM(H84:I84) -> 0
A85: =A83+0.1 -> 1.8 | B85: Supply, installation, testing & commissioning of 250A 4P MCCB 36KA to existing Builder Main panel . Costing shall include all necessary accessories like indication lamp , Meters , CT & control wiring etc. Vendor should do the site survey for better understanding & clarity. Panel RAL colour & Quality of additional works should match with existing panel.Costing shall include opening of cutout , cable box as per site condition & site survey to be done for any clarification .. Required all costing to be quoted in this line item to complete the works | C85: No. | D85: RO | E85: =D85 -> RO | H85: =+N($E85)*N(F85) -> 0 | I85: =+N($E85)*N(G85) -> 0 | J85: =SUM(H85:I85) -> 0
E86: =D86 | H86: =+N($E86)*N(F86) -> 0 | I86: =+N($E86)*N(G86) -> 0 | J86: =SUM(H86:I86) -> 0
A87: =A85+0.1 -> 1.9 | B87: Supply, installation, testing & commissioning of 400A 4P MCCB 36KA to existing Builder Main panel . Costing shall include all necessary accessories like indication lamp , Meters , CT & control wiring etc. Vendor should do the site survey for better understanding & clarity. Panel RAL colour & Quality of additional works should match with existing panel.Costing shall include opening of cutout , cable box as per site condition & site survey to be done for any clarification .. Required all costing to be quoted in this line item to complete the works | C87: No. | D87: RO | E87: =D87 -> RO | H87: =+N($E87)*N(F87) -> 0 | I87: =+N($E87)*N(G87) -> 0 | J87: =SUM(H87:I87) -> 0
E88: =D88 | H88: =+N($E88)*N(F88) -> 0 | I88: =+N($E88)*N(G88) -> 0 | J88: =SUM(H88:I88) -> 0
A89: =A87-0.8 -> 1.1 | B89: Supply, installation, testing & commissioning of 630A 4P MCCB 36KA to existing Builder Main panel . Costing shall include all necessary accessories like indication lamp , Meters , CT & control wiring etc. Vendor should do the site survey for better understanding & clarity. Panel RAL colour & Quality of additional works should match with existing panel.Costing shall include opening of cutout , cable box as per site condition & site survey to be done for any clarification .. Required all costing to be quoted in this line item to complete the works | C89: No. | D89: RO | E89: =D89 -> RO | H89: =+N($E89)*N(F89) -> 0 | I89: =+N($E89)*N(G89) -> 0 | J89: =SUM(H89:I89) -> 0
E90: =D90 | H90: =+N($E90)*N(F90) -> 0 | I90: =+N($E90)*N(G90) -> 0 | J90: =SUM(H90:I90) -> 0
A91: =A89+0.01 -> 1.11 | B91: 63A , 4P MCOS FOR CRITICAL HVAC UNITS | C91: No. | D91: RO | E91: =D91 -> RO | H91: =+N($E91)*N(F91) -> 0 | I91: =+N($E91)*N(G91) -> 0 | J91: =SUM(H91:I91) -> 0
E92: =D92 | H92: =+N($E92)*N(F92) -> 0 | I92: =+N($E92)*N(G92) -> 0 | J92: =SUM(H92:I92) -> 0
A93: =A91+0.01 -> 1.12 | B93: 40A , 4P MCOS FOR CRITICAL HVAC UNITS | C93: No. | D93: RO | E93: =D93 -> RO | H93: =+N($E93)*N(F93) -> 0 | I93: =+N($E93)*N(G93) -> 0 | J93: =SUM(H93:I93) -> 0
E94: =D94 | H94: =+N($E94)*N(F94) -> 0 | I94: =+N($E94)*N(G94) -> 0 | J94: =SUM(H94:I94) -> 0
A95: B | B95: Supply, Installation, testing & commisioning of Fully Automatic DOL/ Star Delta starters with features like Local/Remote, Auto/Manual & programmable timer for auto operation. The necessary NO NC shall be provided with BMS compatibility. The space provision for VFD with bypass facility shall be provided wherever it is specified as below. Starters will be used in case of VFD Panel Maintenance/Failure. Starters to be tripped in case of fire, hence necessary contactors for the same to be provided.The cost shall include free standing support for starter Isolator Box | E95: =D95 | H95: =+N($E95)*N(F95) -> 0 | I95: =+N($E95)*N(G95) -> 0 | J95: =SUM(H95:I95) -> 0
B96: INDOOR TYPE - IP 52 | E96: =D96 | H96: =+N($E96)*N(F96) -> 0 | I96: =+N($E96)*N(G96) -> 0 | J96: =SUM(H96:I96) -> 0
E97: =D97 | H97: =+N($E97)*N(F97) -> 0 | I97: =+N($E97)*N(G97) -> 0 | J97: =SUM(H97:I97) -> 0
A98: =A93+0.01 -> 1.13 | B98: 0.5 kW DOL Starter | C98: No. | D98: RO | E98: =D98 -> RO | H98: =+N($E98)*N(F98) -> 0 | I98: =+N($E98)*N(G98) -> 0 | J98: =SUM(H98:I98) -> 0
E99: =D99 | H99: =+N($E99)*N(F99) -> 0 | I99: =+N($E99)*N(G99) -> 0 | J99: =SUM(H99:I99) -> 0
A100: =A98+0.01 -> 1.14 | B100: 1.0 kW DOL Starter | C100: No. | D100: RO | E100: =D100 -> RO | H100: =+N($E100)*N(F100) -> 0 | I100: =+N($E100)*N(G100) -> 0 | J100: =SUM(H100:I100) -> 0
E101: =D101 | H101: =+N($E101)*N(F101) -> 0 | I101: =+N($E101)*N(G101) -> 0 | J101: =SUM(H101:I101) -> 0
A102: =A100+0.01 -> 1.15 | B102: 1.5kW DOL Starter | C102: No. | D102: RO | E102: =D102 -> RO | H102: =+N($E102)*N(F102) -> 0 | I102: =+N($E102)*N(G102) -> 0 | J102: =SUM(H102:I102) -> 0
E103: =D103 | H103: =+N($E103)*N(F103) -> 0 | I103: =+N($E103)*N(G103) -> 0 | J103: =SUM(H103:I103) -> 0
A104: =A102+0.01 -> 1.16 | B104: 2.2 kW DOL Starter | C104: No. | D104: RO | E104: =D104 -> RO | H104: =+N($E104)*N(F104) -> 0 | I104: =+N($E104)*N(G104) -> 0 | J104: =SUM(H104:I104) -> 0
E105: =D105 | H105: =+N($E105)*N(F105) -> 0 | I105: =+N($E105)*N(G105) -> 0 | J105: =SUM(H105:I105) -> 0
A106: =A104+0.01 -> 1.17 | B106: 4.4 kW DOL Starter | C106: No. | D106: RO | E106: =D106 -> RO | H106: =+N($E106)*N(F106) -> 0 | I106: =+N($E106)*N(G106) -> 0 | J106: =SUM(H106:I106) -> 0
E107: =D107 | H107: =+N($E107)*N(F107) -> 0 | I107: =+N($E107)*N(G107) -> 0 | J107: =SUM(H107:I107) -> 0
A108: =A106+0.01 -> 1.18 | B108: 5.5kW Star/Delta Starter with VFD Space Provision | C108: No. | D108: RO | E108: =D108 -> RO | H108: =+N($E108)*N(F108) -> 0 | I108: =+N($E108)*N(G108) -> 0 | J108: =SUM(H108:I108) -> 0
E109: =D109 | H109: =+N($E109)*N(F109) -> 0 | I109: =+N($E109)*N(G109) -> 0 | J109: =SUM(H109:I109) -> 0
A110: =A108+0.01 -> 1.19 | B110: 7.5kW Star/Delta Starter with VFD Space Provision | C110: No. | D110: RO | E110: =D110 -> RO | H110: =+N($E110)*N(F110) -> 0 | I110: =+N($E110)*N(G110) -> 0 | J110: =SUM(H110:I110) -> 0
E111: =D111 | H111: =+N($E111)*N(F111) -> 0 | I111: =+N($E111)*N(G111) -> 0 | J111: =SUM(H111:I111) -> 0
A112: =A110+0.01 -> 1.2 | B112: 9.3kW Star/Delta Starter with VFD Space Provision | C112: No. | D112: RO | E112: =D112 -> RO | H112: =+N($E112)*N(F112) -> 0 | I112: =+N($E112)*N(G112) -> 0 | J112: =SUM(H112:I112) -> 0
E113: =D113 | H113: =+N($E113)*N(F113) -> 0 | I113: =+N($E113)*N(G113) -> 0 | J113: =SUM(H113:I113) -> 0
A114: =A112+0.01 -> 1.21 | B114: 11kW Star/Delta Starter with VFD Space Provision | C114: No. | D114: RO | E114: =D114 -> RO | H114: =+N($E114)*N(F114) -> 0 | I114: =+N($E114)*N(G114) -> 0 | J114: =SUM(H114:I114) -> 0
E115: =D115 | H115: =+N($E115)*N(F115) -> 0 | I115: =+N($E115)*N(G115) -> 0 | J115: =SUM(H115:I115) -> 0
A116: =A114+0.01 -> 1.22 | B116: 15kW Star/Delta Starter with VFD Space Provision | C116: No. | D116: RO | E116: =D116 -> RO | H116: =+N($E116)*N(F116) -> 0 | I116: =+N($E116)*N(G116) -> 0 | J116: =SUM(H116:I116) -> 0
E117: =D117 | H117: =+N($E117)*N(F117) -> 0 | I117: =+N($E117)*N(G117) -> 0 | J117: =SUM(H117:I117) -> 0
B118: OUTDOOR TYPE - IP 55 | E118: =D118 | H118: =+N($E118)*N(F118) -> 0 | I118: =+N($E118)*N(G118) -> 0 | J118: =SUM(H118:I118) -> 0
E119: =D119 | H119: =+N($E119)*N(F119) -> 0 | I119: =+N($E119)*N(G119) -> 0 | J119: =SUM(H119:I119) -> 0
A120: =A116+0.01 -> 1.23 | B120: 0.5 kW DOL Starter | C120: No. | D120: RO | E120: =D120 -> RO | H120: =+N($E120)*N(F120) -> 0 | I120: =+N($E120)*N(G120) -> 0 | J120: =SUM(H120:I120) -> 0
E121: =D121 | H121: =+N($E121)*N(F121) -> 0 | I121: =+N($E121)*N(G121) -> 0 | J121: =SUM(H121:I121) -> 0
A122: =A120+0.01 -> 1.24 | B122: 1.0 kW DOL Starter | C122: No. | D122: RO | E122: =D122 -> RO | H122: =+N($E122)*N(F122) -> 0 | I122: =+N($E122)*N(G122) -> 0 | J122: =SUM(H122:I122) -> 0
E123: =D123 | H123: =+N($E123)*N(F123) -> 0 | I123: =+N($E123)*N(G123) -> 0 | J123: =SUM(H123:I123) -> 0
A124: =A122+0.01 -> 1.25 | B124: 1.5kW DOL Starter | C124: No. | D124: RO | E124: =D124 -> RO | H124: =+N($E124)*N(F124) -> 0 | I124: =+N($E124)*N(G124) -> 0 | J124: =SUM(H124:I124) -> 0
E125: =D125 | H125: =+N($E125)*N(F125) -> 0 | I125: =+N($E125)*N(G125) -> 0 | J125: =SUM(H125:I125) -> 0
A126: =A124+0.01 -> 1.26 | B126: 2.2 kW DOL Starter | C126: No. | D126: RO | E126: =D126 -> RO | H126: =+N($E126)*N(F126) -> 0 | I126: =+N($E126)*N(G126) -> 0 | J126: =SUM(H126:I126) -> 0
E127: =D127 | H127: =+N($E127)*N(F127) -> 0 | I127: =+N($E127)*N(G127) -> 0 | J127: =SUM(H127:I127) -> 0
A128: =A126+0.01 -> 1.27 | B128: 4.4 kW DOL Starter | C128: No. | D128: RO | E128: =D128 -> RO | H128: =+N($E128)*N(F128) -> 0 | I128: =+N($E128)*N(G128) -> 0 | J128: =SUM(H128:I128) -> 0
E129: =D129 | H129: =+N($E129)*N(F129) -> 0 | I129: =+N($E129)*N(G129) -> 0 | J129: =SUM(H129:I129) -> 0
A130: =A128+0.01 -> 1.28 | B130: 5.5kW Star/Delta Starter with VFD Space Provision | C130: No. | D130: RO | E130: =D130 -> RO | H130: =+N($E130)*N(F130) -> 0 | I130: =+N($E130)*N(G130) -> 0 | J130: =SUM(H130:I130) -> 0
E131: =D131 | H131: =+N($E131)*N(F131) -> 0 | I131: =+N($E131)*N(G131) -> 0 | J131: =SUM(H131:I131) -> 0
A132: =A130+0.01 -> 1.29 | B132: 7.5kW Star/Delta Starter with VFD Space Provision | C132: No. | D132: RO | E132: =D132 -> RO | H132: =+N($E132)*N(F132) -> 0 | I132: =+N($E132)*N(G132) -> 0 | J132: =SUM(H132:I132) -> 0
E133: =D133 | H133: =+N($E133)*N(F133) -> 0 | I133: =+N($E133)*N(G133) -> 0 | J133: =SUM(H133:I133) -> 0
A134: =A132+0.01 -> 1.3 | B134: 9.3kW Star/Delta Starter with VFD Space Provision | C134: No. | D134: RO | E134: =D134 -> RO | H134: =+N($E134)*N(F134) -> 0 | I134: =+N($E134)*N(G134) -> 0 | J134: =SUM(H134:I134) -> 0
E135: =D135 | H135: =+N($E135)*N(F135) -> 0 | I135: =+N($E135)*N(G135) -> 0 | J135: =SUM(H135:I135) -> 0
A136: =A134+0.01 -> 1.31 | B136: 11kW Star/Delta Starter with VFD Space Provision | C136: No. | D136: RO | E136: =D136 -> RO | H136: =+N($E136)*N(F136) -> 0 | I136: =+N($E136)*N(G136) -> 0 | J136: =SUM(H136:I136) -> 0
E137: =D137 | H137: =+N($E137)*N(F137) -> 0 | I137: =+N($E137)*N(G137) -> 0 | J137: =SUM(H137:I137) -> 0
A138: =A136+0.01 -> 1.32 | B138: 15kW Star/Delta Starter with VFD Space Provision | C138: No. | D138: RO | E138: =D138 -> RO | H138: =+N($E138)*N(F138) -> 0 | I138: =+N($E138)*N(G138) -> 0 | J138: =SUM(H138:I138) -> 0
E139: =D139 | H139: =+N($E139)*N(F139) -> 0 | I139: =+N($E139)*N(G139) -> 0 | J139: =SUM(H139:I139) -> 0
A140: C | B140: 4P MCCB BOX wall Mounting type polycarbonate enclosures | E140: =D140 | H140: =+N($E140)*N(F140) -> 0 | I140: =+N($E140)*N(G140) -> 0 | J140: =SUM(H140:I140) -> 0
E141: =D141 | H141: =+N($E141)*N(F141) -> 0 | I141: =+N($E141)*N(G141) -> 0 | J141: =SUM(H141:I141) -> 0
B142: INDOOR TYPE - IP 52 (Ka Rating - 36ka ) | E142: =D142 | H142: =+N($E142)*N(F142) -> 0 | I142: =+N($E142)*N(G142) -> 0 | J142: =SUM(H142:I142) -> 0
E143: =D143 | H143: =+N($E143)*N(F143) -> 0 | I143: =+N($E143)*N(G143) -> 0 | J143: =SUM(H143:I143) -> 0
A144: =A138+0.01 -> 1.33 | B144: 100A | C144: No. | D144: RO | E144: =D144 -> RO | H144: =+N($E144)*N(F144) -> 0 | I144: =+N($E144)*N(G144) -> 0 | J144: =SUM(H144:I144) -> 0
E145: =D145 | H145: =+N($E145)*N(F145) -> 0 | I145: =+N($E145)*N(G145) -> 0 | J145: =SUM(H145:I145) -> 0
A146: =A144+0.01 -> 1.34 | B146: 125A to 160A | C146: No. | D146: RO | E146: =D146 -> RO | H146: =+N($E146)*N(F146) -> 0 | I146: =+N($E146)*N(G146) -> 0 | J146: =SUM(H146:I146) -> 0
E147: =D147 | H147: =+N($E147)*N(F147) -> 0 | I147: =+N($E147)*N(G147) -> 0 | J147: =SUM(H147:I147) -> 0
A148: =A146+0.01 -> 1.35 | B148: 200A to 250A | C148: No. | D148: RO | E148: =D148 -> RO | H148: =+N($E148)*N(F148) -> 0 | I148: =+N($E148)*N(G148) -> 0 | J148: =SUM(H148:I148) -> 0
E149: =D149 | H149: =+N($E149)*N(F149) -> 0 | I149: =+N($E149)*N(G149) -> 0 | J149: =SUM(H149:I149) -> 0
...

Sheet LGT BOQ
A1: PROJECT | B1: : PAYTM BANGALORE
A2: SUBJECT | B2: : BILL OF QUANTITES - LIGHTING
A3: DATE | B3: : 30.03.2026
A4: VERSION | B4: : V0
A6: Sl.No. | B6: DESCRIPTION | C6: REFERENCE IMAGES | D6: UNIT | E6: 6F | F6: Total | G6: RATE | I6: TOTAL | K6: TOTAL AMOUNT | L6: REMARKS
G7: Supply | H7: Installation | I7: Supply | J7: Installation
A9: =ROMAN(13) -> XIII | B9: Supply, Installation, testing & commissioning of Light fixtures and lamps with all accessories, fixing on the wall / ceiling/false ceiling/open ceiling with wooden blocks, screws ,hardware's ,suspension chain hooks/ wires with anchor fasteners as required as per the site conditions (including the earthing of fixture)
B10: Light fixtures complete with accessories like control gear, low loss (<5W ) HF Electronic ballast ,HF Electronic analogue driver, HF dimmable dali driver, HPF condensor (PF shall be >0.85 lag. ) , energy efficient high lumen output LED/fluorescent tubes / CFL lamps etc.,
B11: Note : The make & the catalogue no. mentioned here is only indicative & any of the make mentioned in recommended list of makes is preferred.
B12: The rate shall include for fittings along with transformers where required, diffuser, drivers, power factor improvement capacitors, wires, downrods etc., complete with all accessories to complete the installation as required.
B13: The Electronic analogue driver & dimmable dali driver shall be with THD between 6-8 %.
B14: Glare free symmetrical distribution
B15: IP 20
B16: Light Distribution: Direct symmetrical.
B17: CRI(Ra) >= 80
B18: surge protection: 2.5kV.
B19: Electrical protection: Class II
B20: Uniformity factor 0.8
B21: LED colour to be 6500k or as per Architect/client approval.
... B29: Note : Cost shall Include all necessary supports required for Functional as well as Decorative light fixtures
A31: A | B31: OFFICE AREA LIGHTS
A33: 13.1 | B33: Supply, Installation, testing & commisioning of Pendant Luminaire VIRAJ 70 with LED (Light Emitting Diode ) system power 30W / Meter , Should be,Luminous Flux of luminaire is ,6500k , Neutral White ,CRI >80, 230V, Direct Emission, Profile in Anodised Aluminium with Natural , Black , Champagne Light , Champagne Dark and Brown Anodising , Pre-wired batten made of Anodised Aluminium , Snap-Fit System , Screw less End-caps, Halogen free internal wiring , PMMA Diamond Prism Diffuser for Homogenous Light distribution.length - 1200mm (L ) x 80mm (H)x 60mm (W) | D33: Mtrs | E33: =40+15 -> 55 | F33: =SUM(E33) -> 55 | H33: 316 | I33: =+N($F33)*N(G33) -> 0 | J33: =+N($F33)*N(H33) -> 17380 | K33: =+SUM(I33:J33) -> 17380
F34: =SUM(E34) -> 0 | H34: 0 | I34: =+N($F34)*N(G34) -> 0 | J34: =+N($F34)*N(H34) -> 0 | K34: =+SUM(I34:J34) -> 0
A35: =A33+0.1 -> 13.2 | B35: Supply, Installation, testing & commisioning of Pendant Luminaire VIRAJ 70 with LED (Light Emitting Diode ) system power 30W / Meter , Should be,Luminous Flux of luminaire is 6500k , Neutral White ,CRI >80, 230V, Direct Emission, Profile in Anodised Aluminium with Natural , Black , Champagne Light , Champagne Dark and Brown Anodising , Pre-wired batten made of Anodised Aluminium , Snap-Fit System , Screw less End-caps, Halogen free internal wiring , PMMA Diamond Prism Diffuser for Homogenous Light distribution.length - 1200mm (L ) x 80mm (H)x 60mm (W)(DALI DIMMABLE DRIVER) | D35: Mtrs | E35: =35+10 -> 45 | F35: =SUM(E35) -> 45 | H35: 316 | I35: =+N($F35)*N(G35) -> 0 | J35: =+N($F35)*N(H35) -> 14220 | K35: =+SUM(I35:J35) -> 14220
H36: 0
A37: =A35+0.1 -> 13.3 | B37: Supply, Installation, testing & commisioning of Pendant Luminaire VIRAJ 70 with LED (Light Emitting Diode ) system power 30W / Meter , Should be,Luminous Flux of luminaire is ,6500k , Neutral White ,CRI >80, 230V, Direct Emission, Profile in Anodised Aluminium with Natural , Black , Champagne Light , Champagne Dark and Brown Anodising , Pre-wired batten made of Anodised Aluminium , Snap-Fit System , Screw less End-caps, Halogen free internal wiring , PMMA Diamond Prism Diffuser for Homogenous Light distribution.length - 1500mm (L ) x 80mm (H)x 60mm (W) | D37: Mtrs | E37: 16 | F37: =SUM(E37) -> 16 | H37: 316 | I37: =+N($F37)*N(G37) -> 0 | J37: =+N($F37)*N(H37) -> 5056 | K37: =+SUM(I37:J37) -> 5056
F38: =SUM(E38) -> 0 | H38: 0 | I38: =+N($F38)*N(G38) -> 0 | J38: =+N($F38)*N(H38) -> 0 | K38: =+SUM(I38:J38) -> 0
A39: =A37+0.1 -> 13.4 | B39: Supply of Recessed linear Luminaire with LED (Light Emitting Diode ) system power 26W / Meter ,230V, Direct Emission, Profile in Anodized Aluminum with Natural , Black , Champagne Light , Champagne Dark and Brown Anodizing , Pre-wired batten made of Anodized Aluminum , Snap-Fit System , Screw less End-caps, Halogen free internal wiring , PMMA Diamond Prism Diffuser for Homogenous Light distribution. | D39: Mtrs | E39: =45-45 -> 0 | F39: =SUM(E39) -> 0 | H39: 0 | I39: =+N($F39)*N(G39) -> 0 | J39: =+N($F39)*N(H39) -> 0 | K39: =+SUM(I39:J39) -> 0
F40: =SUM(E40) -> 0 | H40: 0 | I40: =+N($F40)*N(G40) -> 0 | J40: =+N($F40)*N(H40) -> 0 | K40: =+SUM(I40:J40) -> 0
A41: =A39+0.1 -> 13.5 | B41: Supply of Recessed linear Luminaire with LED (Light Emitting Diode ) system power 20 W / Meter , (with Dali dimmable driver) 230V, Direct Emission, Profile in Anodized Aluminum with Natural , Black , Champagne Light , Champagne Dark and Brown Anodizing , Pre-wired batten made of Anodized Aluminum , Snap-Fit System , Screw less End-caps, Halogen free internal wiring , PMMA Diamond Prism Diffuser for Homogenous Light distribution. | D41: Mtrs | E41: 45 | F41: =SUM(E41) -> 45 | H41: 271 | I41: =+N($F41)*N(G41) -> 0 | J41: =+N($F41)*N(H41) -> 12195 | K41: =+SUM(I41:J41) -> 12195
F42: =SUM(E42) -> 0 | H42: 0 | I42: =+N($F42)*N(G42) -> 0 | J42: =+N($F42)*N(H42) -> 0 | K42: =+SUM(I42:J42) -> 0
A43: =A41+0.1 -> 13.6 | B43: Supply, Installation, testing & commissioning of Recessed ceiling luminaire GENISO LED for LED(Light Emitting Diode ) 30W 230V, direct light emission, Sheet metal housing, powder coated white, opal diffuser in synthetic material, fixation with of support, halogen-free internal wiring, HF electronic control gear Protection class I, IP40 L = 595 mm B = 595 mm , H=60mm | D43: Nos | E43: =34-28 -> 6 | F43: =SUM(E43) -> 6 | H43: 226 | I43: =+N($F43)*N(G43) -> 0 | J43: =+N($F43)*N(H43) -> 1356 | K43: =+SUM(I43:J43) -> 1356
F44: =SUM(E44) -> 0 | H44: 0 | I44: =+N($F44)*N(G44) -> 0 | J44: =+N($F44)*N(H44) -> 0 | K44: =+SUM(I44:J44) -> 0
A45: =A43+0.1 -> 13.7 | B45: Supply, Installation, testing & commissioning of Recessed ceiling luminaire GENISO LED for LED(Light Emitting Diode ) 30W (with Dali dimmable driver) 230V, direct light emission, Sheet metal housing, powder coated white, opal diffuser in synthetic material, fixation with of support, halogen-free internal wiring, HF electronic control gear Protection class I, IP40 L = 595 mm B = 595 mm , H=60mm | D45: Nos | E45: 34 | F45: =SUM(E45) -> 34 | H45: 226 | I45: =+N($F45)*N(G45) -> 0 | J45: =+N($F45)*N(H45) -> 7684 | K45: =+SUM(I45:J45) -> 7684
F46: =SUM(E46) -> 0 | H46: 0 | I46: =+N($F46)*N(G46) -> 0 | J46: =+N($F46)*N(H46) -> 0 | K46: =+SUM(I46:J46) -> 0
A47: =A45+0.1 -> 13.8 | B47: Supply, Installation, testing & commissioning of Recessed ceiling luminaire GENISO LED for LED(Light Emitting Diode ) 30W. 230V, direct light emission, Sheet metal housing, powder coated white, opal diffuser in synthetic material, fixation with of support, halogen-free internal wiring, HF electronic control gear Protection class I, IP65 L = 595 mm B = 595 mm , H=60mm (For kitchen area) | D47: Nos | F47: =SUM(E47) -> 0 | H47: 0 | I47: =+N($F47)*N(G47) -> 0 | J47: =+N($F47)*N(H47) -> 0 | K47: =+SUM(I47:J47) -> 0
F48: =SUM(E48) -> 0 | H48: 0 | I48: =+N($F48)*N(G48) -> 0 | J48: =+N($F48)*N(H48) -> 0 | K48: =+SUM(I48:J48) -> 0
A49: =A47+0.1 -> 13.9 | B49: 4ft Linear LED Batten with a nominal system lumen output of 2000 lumens and a minimum system efficacy of 105 lm/W. System wattage should not exceed 19W. The luminaire housing should be made of CRCA with a PC glossy diffuser. | D49: Nos | E49: 12 | F49: =SUM(E49) -> 12 | H49: 136 | I49: =+N($F49)*N(G49) -> 0 | J49: =+N($F49)*N(H49) -> 1632 | K49: =+SUM(I49:J49) -> 1632
F50: =SUM(E50) -> 0 | H50: 0 | I50: =+N($F50)*N(G50) -> 0 | J50: =+N($F50)*N(H50) -> 0 | K50: =+SUM(I50:J50) -> 0
A51: =A49+0.1 -> 14 | B51: Supply, Installation, testing & commissioning of Recessed light with LED (Light Emitting Diode) System Power -12W with 6 inch diameter | D51: Nos | E51: =139-40+10 -> 109 | F51: =SUM(E51) -> 109 | H51: 226 | I51: =+N($F51)*N(G51) -> 0 | J51: =+N($F51)*N(H51) -> 24634 | K51: =+SUM(I51:J51) -> 24634
F52: =SUM(E52) -> 0 | H52: 0 | I52: =+N($F52)*N(G52) -> 0 | J52: =+N($F52)*N(H52) -> 0 | K52: =+SUM(I52:J52) -> 0
A53: =A51-0.8 -> 13.2 | B53: Supply, Installation, testing & commissioning of Recessed light with LED (Light Emitting Diode) System Power -12W (with Dali dimmable driver) with 6 inch diameter | D53: Nos | E53: 40 | F53: =SUM(E53) -> 40 | H53: 226 | I53: =+N($F53)*N(G53) -> 0 | J53: =+N($F53)*N(H53) -> 9040 | K53: =+SUM(I53:J53) -> 9040
F54: =SUM(E54) -> 0 | H54: 0 | I54: =+N($F54)*N(G54) -> 0 | J54: =+N($F54)*N(H54) -> 0 | K54: =+SUM(I54:J54) -> 0
A55: =A53+0.01 -> 13.21 | B55: Supply, Installation, testing & commissioning of Recessed light with LED (Light Emitting Diode) System Power -12W with 6 inch diameter | D55: Nos | F55: =SUM(E55) -> 0 | H55: 0 | I55: =+N($F55)*N(G55) -> 0 | J55: =+N($F55)*N(H55) -> 0 | K55: =+SUM(I55:J55) -> 0
F56: =SUM(E56) -> 0 | H56: 0 | I56: =+N($F56)*N(G56) -> 0 | J56: =+N($F56)*N(H56) -> 0 | K56: =+SUM(I56:J56) -> 0
A57: =A53+0.01 -> 13.21 | B57: Supply, installation, testing & commisioning of MACTY ROUND pendant with LED (Light Emitting Diode) COB, 230V, System power-15W, Luminous Flux of Luminnaire-1168.5lm, direct light emission, housing in Aluminium Die casting white, electronic control gear, On/OffProtection class I, IP20 MACTY ROUND , Dia.=150mm, H=300mm | D57: Nos | E57: =90-35 -> 55 | F57: =SUM(E57) -> 55 | H57: 271 | I57: =+N($F57)*N(G57) -> 0 | J57: =+N($F57)*N(H57) -> 14905 | K57: =+SUM(I57:J57) -> 14905
F58: =SUM(E58) -> 0 | H58: 0 | I58: =+N($F58)*N(G58) -> 0 | J58: =+N($F58)*N(H58) -> 0 | K58: =+SUM(I58:J58) -> 0
A59: =A57+0.01 -> 13.22 | B59: Supply, installation, testing & commisioning of MACTY ROUND pendant with LED (Light Emitting Diode) COB, 230V, System power-15W, (with dali dimmable drivers) Luminous Flux of Luminnaire-1168.5lm, direct light emission, housing in Aluminium Die casting white, electronic control gear, On/OffProtection class I, IP20 MACTY ROUND , Dia.=150mm, H=300mm | D59: Nos | E59: 35 | F59: =SUM(E59) -> 35 | H59: 271 | I59: =+N($F59)*N(G59) -> 0 | J59: =+N($F59)*N(H59) -> 9485 | K59: =+SUM(I59:J59) -> 9485
F60: =SUM(E60) -> 0 | H60: 0 | I60: =+N($F60)*N(G60) -> 0 | J60: =+N($F60)*N(H60) -> 0 | K60: =+SUM(I60:J60) -> 0
A61: PART B | B61: DECORATIVE LIGHTS | F61: =SUM(E61) -> 0 | H61: 0 | I61: =+N($F61)*N(G61) -> 0 | J61: =+N($F61)*N(H61) -> 0 | K61: =+SUM(I61:J61) -> 0
F62: =SUM(E62) -> 0 | H62: 0 | I62: =+N($F62)*N(G62) -> 0 | J62: =+N($F62)*N(H62) -> 0 | K62: =+SUM(I62:J62) -> 0
A63: =A59+0.01 -> 13.23 | B63: Supply, Installation, testing & commissioning of LED strip(Light Emitting Diode ) system power 5.5W per mtr ,3000/4000k , Warm White ,CRI >70, 230V, Direct Emission Halogen free internal wiring | D63: Mtrs | E63: =20+30 -> 50 | F63: =SUM(E63) -> 50 | H63: 46 | I63: =+N($F63)*N(G63) -> 0 | J63: =+N($F63)*N(H63) -> 2300 | K63: =+SUM(I63:J63) -> 2300
F64: =SUM(E64) -> 0 | H64: 0 | I64: =+N($F64)*N(G64) -> 0 | J64: =+N($F64)*N(H64) -> 0 | K64: =+SUM(I64:J64) -> 0
A65: =A63+0.01 -> 13.24 | B65: SITC of decorative lights 20W as per design approval | D65: Nos | E65: 1 | F65: =SUM(E65) -> 1 | H65: 271 | I65: =+N($F65)*N(G65) -> 0 | J65: =+N($F65)*N(H65) -> 271 | K65: =+SUM(I65:J65) -> 271 | L65: Reception
F66: =SUM(E66) -> 0 | H66: 0 | I66: =+N($F66)*N(G66) -> 0 | J66: =+N($F66)*N(H66) -> 0 | K66: =+SUM(I66:J66) -> 0
A67: =A65+0.01 -> 13.25 | B67: SITC of decorative lights 20W as per Image | D67: Nos | E67: 11 | F67: =SUM(E67) -> 11 | H67: 271 | I67: =+N($F67)*N(G67) -> 0 | J67: =+N($F67)*N(H67) -> 2981 | K67: =+SUM(I67:J67) -> 2981
A68: 13.5 | B68: SITC of decorative lights 20W as per design approval | D68: Nos | E68: 10 | F68: =SUM(E68) -> 10 | H68: 271 | I68: =+N($F68)*N(G68) -> 0 | J68: =+N($F68)*N(H68) -> 2710 | K68: =+SUM(I68:J68) -> 2710
B69: TOTAL - LIGHTS | I69: =SUM(I28:I68) -> 0 | J69: =SUM(J28:J68) -> 125849 | K69: =SUM(K28:K68) -> 125849

Sheet HVAC BOQ
A1: PROJECT | B1: PAYTM
A2: SUBJECT | B2: HVAC BOQ
A3: VERSION | B3: V0
A4: Sl.No. | B4: DESCRIPTION | C4: UNIT | D4: QNT | E4: RATE | G4: AMOUNT | I4: Total
E5: Supply | F5: Installation | G5: Supply | H5: Installation
B6: Note :Prices quoted in this tender shall be inclusive of cost of materials, labours, supervision, Supply ,installation, testing and commissioning, materials erection, tools, plant appliances, scaffolding, sleeves, cutting, patching, painting, storage of material, service connections, transport to site,
A7: PART -A | B7: AIR DISTRIBUTION WORKS
A9: 1 | B9: GI FACTORY FABRICATED SUPPLY AIR PLENUMS
B10: SITC of 50 mm thk double skin panel factory fabricated plenum as per shop drawing. Plenum shall be made of outer skin 20 G powder coated G.I sheet and inner skin shall be of with 22 G plain GSS with aluminium extrusions. Density of puf panel shall be 48 kg / cub mt. with 40mm thick puf insulation ,Plenum shall suitable size to handle the required cfm not exceeding 750 fpm velocity. The price quoted shall include MS supporting arrangement for suspending the plenum from the ceiling slab ,Canvas connection to be part of scope for AHU connection ,Access doors shall be not less than 60 cm x 60 cm in size.Appropriate cutout to be made to connecte the branch ducts with dampers as per approved drawing | C10: Sqmt | D10: 25 | E10: 3300 | F10: 350 | G10: =+N($D10)*N(E10) -> 82500 | H10: =+N($D10)*N(F10) -> 8750 | I10: =+SUM(G10:H10) -> 91250
D11: 0 | G11: =+N($D11)*N(E11) -> 0 | H11: =+N($D11)*N(F11) -> 0 | I11: =+SUM(G11:H11) -> 0
A12: 2 | B12: SITC of duct silencers / Sound attenuators in supply and return air path in AHU rooms as per the approved drawings. | D12: 0 | G12: =+N($D12)*N(E12) -> 0 | H12: =+N($D12)*N(F12) -> 0 | I12: =+SUM(G12:H12) -> 0
B13: Sound attenuator qty shall be on surface area basis. | D13: 0 | G13: =+N($D13)*N(E13) -> 0 | H13: =+N($D13)*N(F13) -> 0 | I13: =+SUM(G13:H13) -> 0
B14: COMPUTER SELECTION SHOULD BE ATTACHED | D14: 0 | G14: =+N($D14)*N(E14) -> 0 | H14: =+N($D14)*N(F14) -> 0 | I14: =+SUM(G14:H14) -> 0
B15: Sound Attenuators made dissipative type to be provided on the supply & Return air duct entering the AHU Room. | D15: 0 | G15: =+N($D15)*N(E15) -> 0 | H15: =+N($D15)*N(F15) -> 0 | I15: =+SUM(G15:H15) -> 0
B16: Sound Attenuators shall consist of outer casing, sound absorbing material and internal baffles, splitters and supports ,The sound attenuators shall be suitable for minimum 18dB reduction at 250Hz octave band. | D16: 0 | G16: =+N($D16)*N(E16) -> 0 | H16: =+N($D16)*N(F16) -> 0 | I16: =+SUM(G16:H16) -> 0
B17: Casing shall be of galvanized steel of not less than 20G in thickness. Casings shall be tested to 150mmwg and shall show no leakage or distortion in this condition. | D17: 0 | G17: =+N($D17)*N(E17) -> 0 | H17: =+N($D17)*N(F17) -> 0 | I17: =+SUM(G17:H17) -> 0
B18: Sound absorbing material shall be high density Fiber glass held in place with at least 5% compression to prevent voids due to settling. Absorption material density shall be minimum 48 kg/cum. Fiberglass faced with minimum 24 g perforated galvanized sheet metal of minimum 40% open area. | D18: 0 | G18: =+N($D18)*N(E18) -> 0 | H18: =+N($D18)*N(F18) -> 0 | I18: =+SUM(G18:H18) -> 0
B19: Supply, Installation & commissioning | C19: Sqm | D19: 15 | E19: 3450 | F19: 2350 | G19: =+N($D19)*N(E19) -> 51750 | H19: =+N($D19)*N(F19) -> 35250 | I19: =+SUM(G19:H19) -> 87000
D20: 0 | G20: =+N($D20)*N(E20) -> 0 | H20: =+N($D20)*N(F20) -> 0 | I20: =+SUM(G20:H20) -> 0
A21: 3 | B21: SITC of Motorised Fire dampers -Multi blade motorised 16G GI TDF flanges type Fire Dampers with necessary accessories for supply air ducts along with motorized actuator including fire damper control panel for supply air ducts . The fire rating of the damper shall be of 90min and shall be with 600 mm sleeves suitable for the wall mounting, CBRI approved.Fire Damper shall be complete with 240/24 transformer, damper on/off indicating lamps and distribution Price shall be inclusive of copper power cabling ,control wiring,actuator with control panel, sensor and inter-locking / wiring / connection for tripping of AHU fan motor , FA intergation. | C21: Sqm | D21: 6 | E21: 10800 | F21: 2200 | G21: =+N($D21)*N(E21) -> 64800 | H21: =+N($D21)*N(F21) -> 13200 | I21: =+SUM(G21:H21) -> 78000
B22: Actuators with Control Panel for above fire dampers- actuotors should have potential free contact to know the status of the actuator Fast acting actuators Should be of High Torque Type ( 20 sec closure max, 75sec opening max ) Spring return type : 10NM (up to 0.6sqm);16NM (up to 1.6 sqm);20NM (up to 3.2sqm) | C22: No's | D22: 12 | E22: 13500 | F22: 1250 | G22: =+N($D22)*N(E22) -> 162000 | H22: =+N($D22)*N(F22) -> 15000 | I22: =+SUM(G22:H22) -> 177000
D23: 0 | G23: =+N($D23)*N(E23) -> 0 | H23: =+N($D23)*N(F23) -> 0 | I23: =+SUM(G23:H23) -> 0
A24: 4 | B24: Fire dampers -Fusible link & confirm to UL listed. | D24: 0 | G24: =+N($D24)*N(E24) -> 0 | H24: =+N($D24)*N(F24) -> 0 | I24: =+SUM(G24:H24) -> 0
B25: Supply, Installation, Testing & Commissioning of Fusible link type fire damper. Should be UL (555) listed & CBRI approved. With one or 2 side flanges as per the site condition. Fire rating should be 90min as per the UL 555. Blades shall be held in position through fusible link of temp. of 74 deg. c. Gauge of blades & frame should be 16 G. Should supply with GI made Transition piece(22Gauge) & Back draft(Gravity) damper. | C25: Sqm | D25: 1 | E25: 7841 | F25: 1623 | G25: =+N($D25)*N(E25) -> 7841 | H25: =+N($D25)*N(F25) -> 1623 | I25: =+SUM(G25:H25) -> 9464
D26: 0 | G26: =+N($D26)*N(E26) -> 0 | H26: =+N($D26)*N(F26) -> 0 | I26: =+SUM(G26:H26) -> 0
D27: 0 | G27: =+N($D27)*N(E27) -> 0 | H27: =+N($D27)*N(F27) -> 0 | I27: =+SUM(G27:H27) -> 0
A28: 5 | B28: AIR DISTRIBUTION SYSTEM: | D28: 0 | G28: =+N($D28)*N(E28) -> 0 | H28: =+N($D28)*N(F28) -> 0 | I28: =+SUM(G28:H28) -> 0
B29: RECTANGULAR DUCT -FACTORY FABRICATED DUCTING - TDF /TDC FLANGES | D29: 0 | G29: =+N($D29)*N(E29) -> 0 | H29: =+N($D29)*N(F29) -> 0 | I29: =+SUM(G29:H29) -> 0
B30: Supply, Installation Testing & Commissioning of factory fabricated GSS Ducting with TDF /TDC flange with GI bolt & nuts (the cleat into the flange Used for C and G together with Bolt) and necessary supporting arrangement using GI full threaded rods and slotted rail. | G30: =+N($D30)*N(E30) -> 0 | H30: =+N($D30)*N(F30) -> 0 | I30: =+SUM(G30:H30) -> 0
B31: Ducting shall be designed for 500pa pressure, Galvanized steel sheet shall be of Class VIII – 120 gm /sqm zinc coating IS-277.All ducts above 1000 mm shall have Stiffener rod made of GI 1.6mm thick . | G31: =+N($D31)*N(E31) -> 0 | H31: =+N($D31)*N(F31) -> 0 | I31: =+SUM(G31:H31) -> 0
B32: Spacing between duct supports should not exceed 2m i.e GI rods with GI "C" channels. In case of duct sizes above 1800mm, MS angles duly painted with black enamel paint should be used along with neoprene pad in between the duct & MS angle. All duct support to be provided with check nuts (lock nuts). | G32: =+N($D32)*N(E32) -> 0 | H32: =+N($D32)*N(F32) -> 0 | I32: =+SUM(G32:H32) -> 0
B33: All duct construction and installation shall be as per SMACNA standards | G33: =+N($D33)*N(E33) -> 0 | H33: =+N($D33)*N(F33) -> 0 | I33: =+SUM(G33:H33) -> 0
B34: The scope shall include duct supports (including MS angle/channel arrangements for vibration-free installation), scaffolding charges, cleat joints, elbows, bends, shoe pieces, vanes, stripper rods, gaskets, bolts & nuts, end caps, Y-branches, cut ducts, droppers, offsets, mouth pieces, duct covers for transportation/installation/storage, and a 450x450 vertical trap door with handle in main ducts for servicing and cleaning | D34: 0 | G34: =+N($D34)*N(E34) -> 0 | H34: =+N($D34)*N(F34) -> 0 | I34: =+SUM(G34:H34) -> 0
B35: Pressure Testing of Ducts - Pressure testing of sheet metal ducts with necessary components like semi-rigid flexible ducts, fans and the measuring kit. Pressure testing shall be carried out for complete air distribution system excluding flexible ducts, diffuser box, diffusers and grilles. Pressure testing shall be carried out prior to thermal insulation and light test as per SMACNA standards and approval shall be obtained from PMC and consultants. , | D35: 0 | G35: =+N($D35)*N(E35) -> 0 | H35: =+N($D35)*N(F35) -> 0 | I35: =+SUM(G35:H35) -> 0
B36: Air Balancing of Air Distribution System - Third party Air balancing should be done for two times - Pre occupancy & Post occupancy along with client/PMC & Facility teams. Duct pressure testing should be with Duct leak testing machine and Air-balancing should be with Digital Hood method. All necessary tools(digital hood) should be consider in costing. Air Balancing of each individual supply air outlet to within +10% or -5% of the design air quantity and tabulating the same in a form of report and also the final air balancing figures to be indicated against each measured outlets in the as built drawings. Balancing also includes balancing of return air, supply air and outdoor fresh air quantity. Air flow hoods to be used for measuring the air flow across the Grill/diffusers. | D36: 0 | G36: =+N($D36)*N(E36) -> 0 | H36: =+N($D36)*N(F36) -> 0 | I36: =+SUM(G36:H36) -> 0
B37: Testing shall be coordinated through licensed Test and Balance supplier with the Commissioning Agent , All the duct work and equipment to be labelled with the direction of flow ,Duct system will be capable of air balancing at each floor and sub main by means of a manual damper, Adequate test ports to be provided for testing and commissioning ,Materials of construction welded galvanized steel . Note :- All the ducts laying in open ceiling has to be painted as per architect colour recomendation /specification. Painting to be considered as one coat primer and two coats of paints (Spray paint/ roller finishing). Paint cost should be part of the duct cost itself | G37: =+N($D37)*N(E37) -> 0 | H37: =+N($D37)*N(F37) -> 0 | I37: =+SUM(G37:H37) -> 0
B38: 0.50 mm (26 WG) | C38: Sqmt | D38: RO | G38: =+N($D38)*N(E38) -> 0 | H38: =+N($D38)*N(F38) -> 0 | I38: =+SUM(G38:H38) -> 0
B39: 0.63 mm (24 WG) | C39: Sqmt | D39: =150+20 -> 170 | E39: 840 | F39: 217 | G39: =+N($D39)*N(E39) -> 142800 | H39: =+N($D39)*N(F39) -> 36890 | I39: =+SUM(G39:H39) -> 179690
B40: 0.80 mm (22 WG) | C40: Sqmt | D40: 100 | E40: 940 | F40: 217 | G40: =+N($D40)*N(E40) -> 94000 | H40: =+N($D40)*N(F40) -> 21700 | I40: =+SUM(G40:H40) -> 115700
B41: 1.00 mm (20 WG) | C41: Sqmt | D41: 150 | E41: 1000 | F41: 217 | G41: =+N($D41)*N(E41) -> 150000 | H41: =+N($D41)*N(F41) -> 32550 | I41: =+SUM(G41:H41) -> 182550
B42: 1.25 mm (18 WG) | C42: Sqmt | D42: RO | G42: =+N($D42)*N(E42) -> 0 | H42: =+N($D42)*N(F42) -> 0 | I42: =+SUM(G42:H42) -> 0
D43: 0 | G43: =+N($D43)*N(E43) -> 0 | H43: =+N($D43)*N(F43) -> 0 | I43: =+SUM(G43:H43) -> 0
A44: 6 | B44: Elliptical ducts | D44: 0 | G44: =+N($D44)*N(E44) -> 0 | H44: =+N($D44)*N(F44) -> 0 | I44: =+SUM(G44:H44) -> 0
B45: ELLIPTICAL /OVAL DUCT -FACTORY FABRICATED DUCTING - TDF /TDC FLANGES WITH INTERNAL INSULATION | G45: =+N($D45)*N(E45) -> 0 | H45: =+N($D45)*N(F45) -> 0 | I45: =+SUM(G45:H45) -> 0
B46: Supply, installation, testing & Commissioning of Factory fabricated oval GSS ducting with Hitech Supports and with with TDF /TDC flange with GI bolt & nuts ( the cleat into the flange Used for C and G together with Bolt).Necessary bends should be made as per the drawing, All ducts should be supported with wire rope supports and shall be hang through the cleats or wire rope threaded studs can be screwed into the anchor fasteners. | G46: =+N($D46)*N(E46) -> 0 | H46: =+N($D46)*N(F46) -> 0 | I46: =+SUM(G46:H46) -> 0
B47: Ducting shall be designed for 500pa pressure, Galvanized steel sheet shall be of Class VIII – 120 gm /sqm zinc coating IS-277.All ducts above 1000 mm shall have Stiffener rod made of GI 1.6mm thick ,Ducting to brought at site in box form. | G47: =+N($D47)*N(E47) -> 0 | H47: =+N($D47)*N(F47) -> 0 | I47: =+SUM(G47:H47) -> 0
B48: Spacing between duct supports should not exceed 2m i.e Wire Rope Hanger support . In case of Wire Rope Hanger support for duct sizes above 1800mm, MS angles duly painted with black enamel paint should be used along with neoprene pad in between the duct & MS angle. All duct support to be provided with check nuts (lock nuts). | G48: =+N($D48)*N(E48) -> 0 | H48: =+N($D48)*N(F48) -> 0 | I48: =+SUM(G48:H48) -> 0
B49: All duct construction and installation shall be as per SMACNA standards | G49: =+N($D49)*N(E49) -> 0 | H49: =+N($D49)*N(F49) -> 0 | I49: =+SUM(G49:H49) -> 0
B50: The scope shall include Wire rope supports ,Ring clamp ,universal clamps,studs, screws , anchor fasteners , scaffolding charges, cleat joints, elbows, bends, shoe pieces, vanes, stripper rods, gaskets, bolts & nuts, end caps, Y-branches, cut ducts, droppers, offsets, mouth pieces, duct covers for transportation/installation/storage, and a 450x450 vertical trap door with handle in main ducts for servicing and cleaning | G50: =+N($D50)*N(E50) -> 0 | H50: =+N($D50)*N(F50) -> 0 | I50: =+SUM(G50:H50) -> 0
B51: Ducts to be provided with internal thermal insulation with 13mm thick closed cell elastromeric nitrile rubber insulation manafactured as per ASTM E 84 test with density between 40-60 kg / m³ , Material shall be FM GLOBAL approved, food grade material with antimicrobial properties, Class 'O'. Insulation material should meet NFPA 90A ,Insulation sheets should have factory applied self-adhesive backing for faster installation and better quality. The adhesive used in self-adhesive backing should be Fire Retardant, LEED compliant and zero VOC. open cell 15mm thick Elastromeric nitrile rubber insulation manafactured as per ASTM E 84 test with density140- 180 kg / m³, Material shall be FM rated ,First 5 Meters from outlet of AC unit to be considered with acoustic insulation | G51: =+N($D51)*N(E51) -> 0 | H51: =+N($D51)*N(F51) -> 0 | I51: =+SUM(G51:H51) -> 0
B52: Pressure Testing of Ducts - Pressure testing of sheet metal ducts with necessary components like semi-rigid flexible ducts, fans and the measuring kit. Pressure testing shall be carried out for complete air distribution system excluding flexible ducts, diffuser box, diffusers and grilles. Pressure testing shall be carried out prior to thermal insulation and light test as per SMACNA standards and approval shall be obtained from PMC and consultants. | D52: 0 | G52: =+N($D52)*N(E52) -> 0 | H52: =+N($D52)*N(F52) -> 0 | I52: =+SUM(G52:H52) -> 0
B53: Air Balancing of Air Distribution System - Third party Air balancing should be done for two times - Pre occupancy & Post occupancy along with client/PMC & Facility teams. Duct pressure testing should be with Duct leak testing machine and Air-balancing should be with Digital Hood method. All necessary tools(digital hood) should be consider in costing. Air Balancing of each individual supply air outlet to within +10% or -5% of the design air quantity and tabulating the same in a form of report and also the final air balancing figures to be indicated against each measured outlets in the as built drawings. Balancing also includes balancing of return air, supply air and outdoor fresh air quantity. Air flow hoods to be used for measuring the air flow across the Grill/diffusers. | D53: 0 | G53: =+N($D53)*N(E53) -> 0 | H53: =+N($D53)*N(F53) -> 0 | I53: =+SUM(G53:H53) -> 0
B54: Testing shall be coordinated through licensed Test and Balance supplier with the Commissioning Agent , All the duct work and equipment to be labelled with the direction of flow ,Duct system will be capable of air balancing at each floor and sub main by means of a manual damper, Adequate test ports to be provided for testing and commissioning ,Materials of construction welded galvanized steel .Air flow testing should be done with Hoods , Note : All supply ducts laying in open area has to be internally insulated & all ducts will be painted as per architect colour specification.Painting to be considered as one coat primer and two coats of paints (Spray paint/ roller finishing). Internal insulation labour charge & Painting cost should be part of the duct costing itself. | D54: 0 | G54: =+N($D54)*N(E54) -> 0 | H54: =+N($D54)*N(F54) -> 0 | I54: =+SUM(G54:H54) -> 0
B55: 0.50 mm (26 WG) | C55: Sqmt | D55: 200 | E55: 1140 | F55: 217 | G55: =+N($D55)*N(E55) -> 228000 | H55: =+N($D55)*N(F55) -> 43400 | I55: =+SUM(G55:H55) -> 271400
B56: 0.63 mm (24 WG) | C56: Sqmt | D56: =100+30 -> 130 | E56: 1290 | F56: 217 | G56: =+N($D56)*N(E56) -> 167700 | H56: =+N($D56)*N(F56) -> 28210 | I56: =+SUM(G56:H56) -> 195910
B57: 0.80 mm (22 WG) | C57: Sqmt | D57: 100 | E57: 1390 | F57: 217 | G57: =+N($D57)*N(E57) -> 139000 | H57: =+N($D57)*N(F57) -> 21700 | I57: =+SUM(G57:H57) -> 160700
B58: 1.00 mm (20 WG) | C58: Sqmt | D58: RO | G58: =+N($D58)*N(E58) -> 0 | H58: =+N($D58)*N(F58) -> 0 | I58: =+SUM(G58:H58) -> 0
A59: 6.1 | B59: Flatoval duct volume control damper -Supply, installation and testing of GSS construction of opposed blade volume control dampers with in elliptical /spiral ducts to be provided with suitable links, levers and quadrants for manual control of volume of air flow. Note: Elliptical VCD gague should be one gauge higher than duct. | C59: Sqmt | D59: 4 | E59: 9017 | F59: 1623 | G59: =+N($D59)*N(E59) -> 36068 | H59: =+N($D59)*N(F59) -> 6492 | I59: =+SUM(G59:H59) -> 42560
G60: =+N($D60)*N(E60) -> 0 | H60: =+N($D60)*N(F60) -> 0 | I60: =+SUM(G60:H60) -> 0
A61: 6.2 | B61: Rectangular duct volume control damper -Supply, installation and testing of GSS construction of opposed blade volume control dampers with in elliptical /spiral ducts to be provided with suitable links, levers and quadrants for manual control of volume of air flow. Note: Elliptical VCD gague should be one gauge higher than duct. | C61: Sqmt | D61: =2+1 -> 3 | E61: 7075 | F61: 1623 | G61: =+N($D61)*N(E61) -> 21225 | H61: =+N($D61)*N(F61) -> 4869 | I61: =+SUM(G61:H61) -> 26094
D62: 0 | G62: =+N($D62)*N(E62) -> 0 | H62: =+N($D62)*N(F62) -> 0 | I62: =+SUM(G62:H62) -> 0
A63: 6.3 | B63: Round duct, It should be of 24G ,Note -Duct Dropper of length 100/ 150mm for round diffuser connection to be include | D63: 0 | G63: =+N($D63)*N(E63) -> 0 | H63: =+N($D63)*N(F63) -> 0 | I63: =+SUM(G63:H63) -> 0
B64: 150 mm dia | C64: Rmt | D64: RO | G64: =+N($D64)*N(E64) -> 0 | H64: =+N($D64)*N(F64) -> 0 | I64: =+SUM(G64:H64) -> 0
B65: 200 mm dia | C65: Rmt | D65: RO | G65: =+N($D65)*N(E65) -> 0 | H65: =+N($D65)*N(F65) -> 0 | I65: =+SUM(G65:H65) -> 0
B66: 250 mm dia | C66: Rmt | D66: RO | G66: =+N($D66)*N(E66) -> 0 | H66: =+N($D66)*N(F66) -> 0 | I66: =+SUM(G66:H66) -> 0
B67: 350 mm dia | C67: Rmt | D67: RO | G67: =+N($D67)*N(E67) -> 0 | H67: =+N($D67)*N(F67) -> 0 | I67: =+SUM(G67:H67) -> 0
B68: 400 mm dia | C68: Rmt | D68: RO | G68: =+N($D68)*N(E68) -> 0 | H68: =+N($D68)*N(F68) -> 0 | I68: =+SUM(G68:H68) -> 0
B69: Round VCD -frame shall be made of 20G and blades shall be made of 20G | C69: Sqm | D69: RO | G69: =+N($D69)*N(E69) -> 0 | H69: =+N($D69)*N(F69) -> 0 | I69: =+SUM(G69:H69) -> 0
G70: =+N($D70)*N(E70) -> 0 | H70: =+N($D70)*N(F70) -> 0 | I70: =+SUM(G70:H70) -> 0
A71: 6.4 | B71: SITC of powder coated Extruded Aluminium round supply diffusers with collar dampers in accordance with the approved shop drawings and specifications. | D71: 0 | G71: =+N($D71)*N(E71) -> 0 | H71: =+N($D71)*N(F71) -> 0 | I71: =+SUM(G71:H71) -> 0
B72: 150 mm dia | C72: No | D72: RO | G72: =+N($D72)*N(E72) -> 0 | H72: =+N($D72)*N(F72) -> 0 | I72: =+SUM(G72:H72) -> 0
B73: 200 mm dia | C73: No | D73: RO | G73: =+N($D73)*N(E73) -> 0 | H73: =+N($D73)*N(F73) -> 0 | I73: =+SUM(G73:H73) -> 0
B74: 250 mm dia | C74: No | D74: RO | G74: =+N($D74)*N(E74) -> 0 | H74: =+N($D74)*N(F74) -> 0 | I74: =+SUM(G74:H74) -> 0
B75: 350 mm dia | C75: No | D75: RO | G75: =+N($D75)*N(E75) -> 0 | H75: =+N($D75)*N(F75) -> 0 | I75: =+SUM(G75:H75) -> 0
D76: 0 | G76: =+N($D76)*N(E76) -> 0 | H76: =+N($D76)*N(F76) -> 0 | I76: =+SUM(G76:H76) -> 0
A77: 7 | B77: VOLUME CONTROL DAMPERS AND COLLAR DAMPERS | D77: 0 | G77: =+N($D77)*N(E77) -> 0 | H77: =+N($D77)*N(F77) -> 0 | I77: =+SUM(G77:H77) -> 0
B78: SITC of VCD -thickness of 18 gauge, utilizes aluminium aerofoil blades, incorporates a gear type VCD rated for 120 GSM, and is constructed with a 1.55 mm thick galvanized steel frame and blades. | C78: Sqmt | D78: 5 | E78: 7075 | F78: 1623 | G78: =+N($D78)*N(E78) -> 35375 | H78: =+N($D78)*N(F78) -> 8115 | I78: =+SUM(G78:H78) -> 43490
D79: 0 | G79: =+N($D79)*N(E79) -> 0 | H79: =+N($D79)*N(F79) -> 0 | I79: =+SUM(G79:H79) -> 0
A80: 8 | B80: SITC of MVCD -constructed with an 18-gauge GSS frame and 20-gauge blades. It is equipped with TDF flanges on both sides and features an actuator . The actuator operates on 24 V AC or 230 V AC, is a non-spring return ON/OFF type, and has a torque rating of 5/10 /20 NM as per OEM recomendation sized appropriately for the VCD dimensions. | C80: Sqm | D80: 1 | E80: 9147 | F80: 1623 | G80: =+N($D80)*N(E80) -> 9147 | H80: =+N($D80)*N(F80) -> 1623 | I80: =+SUM(G80:H80) -> 10770
B81: Actuators with control panel ,6 A 3-Pin Socket with plug mounted on PVC Box which has to be fixed to near the Damper for Actuator termination. Socket should be of modular type,3 runs of 2.5 sq.mm HFLS Cu Wire in 19 mm dia GI Conduit for VFD panel to damper of 20m ,4 way TPN MCB DB with 40 A 4 pole RCCB as incomer and 4 nos 10 A SP MCBs as outgoings in sheet enclosure for Motorised Volume control Dampers to be part of | C81: Nos | D81: 1 | E81: 8625 | F81: 1353 | G81: =+N($D81)*N(E81) -> 8625 | H81: =+N($D81)*N(F81) -> 1353 | I81: =+SUM(G81:H81) -> 9978
D82: 0 | G82: =+N($D82)*N(E82) -> 0 | H82: =+N($D82)*N(F82) -> 0 | I82: =+SUM(G82:H82) -> 0
A83: 9 | B83: Supply, installation and adjusting of GSS made fresh motorized volume contol damper with actuators . opposed blades , frame shall be made of 18G and blades shall be made of 20G with prefilters for the louvers in all AHU room | C83: Sqm | D83: RO | G83: =+N($D83)*N(E83) -> 0 | H83: =+N($D83)*N(F83) -> 0 | I83: =+SUM(G83:H83) -> 0
G84: =+N($D84)*N(E84) -> 0 | H84: =+N($D84)*N(F84) -> 0 | I84: =+SUM(G84:H84) -> 0
A85: 10 | B85: SITC of Collar Dampers made of Al. extrusions with black powder coating for Grilles / Diffusers -Collar Dampers or neck damper of opposed blade type made out of Aluminium alloy extrusion with anodised matt black finish (AL.blade thickness 1.0mm, Border thickness-1.3 MM) | C85: Sqm | D85: RO | G85: =+N($D85)*N(E85) -> 0 | H85: =+N($D85)*N(F85) -> 0 | I85: =+SUM(G85:H85) -> 0
D86: 0 | G86: =+N($D86)*N(E86) -> 0 | H86: =+N($D86)*N(F86) -> 0 | I86: =+SUM(G86:H86) -> 0
A87: 11 | B87: SITC of Backdraft dampers -frame shall be made of 18G and blades shall be made of 20G. Gasket shall be provided on the bottom of the blades edges to avoid noise while on operation | C87: Sqmt | D87: 1 | E87: 6209 | F87: 1353 | G87: =+N($D87)*N(E87) -> 6209 | H87: =+N($D87)*N(F87) -> 1353 | I87: =+SUM(G87:H87) -> 7562
D88: 0 | G88: =+N($D88)*N(E88) -> 0 | H88: =+N($D88)*N(F88) -> 0 | I88: =+SUM(G88:H88) -> 0
A89: 12 | B89: SITC of powder coated Extruded Aluminium 4-way diffusers Supply in accordance with the approved shop drawings and specifications. The diffuser Neck size shall be as given below. Outer size shall be as per the F/c grid, Diffuser shall be removable core type, shall have concealed fixing screw. Color code shall be as per architect approval. Supply diffuser with colar damper of opposed blade type made out of Aluminium alloy extrusion with anodised matt black finish (AL.blade thickness 1.0mm, Border thickness-1.3 MM) to be include. | D89: 0 | G89: =+N($D89)*N(E89) -> 0 | H89: =+N($D89)*N(F89) -> 0 | I89: =+SUM(G89:H89) -> 0
A90: =A89+0.1 -> 12.1 | B90: 600 x 600 Outer Size (525x 525 Neck size in mm) | C90: Nos | D90: RO | G90: =+N($D90)*N(E90) -> 0 | H90: =+N($D90)*N(F90) -> 0 | I90: =+SUM(G90:H90) -> 0
A91: =A90+0.1 -> 12.2 | B91: 600 x 600 Outer Size (450 x 450 Neck size in mm) | C91: Nos | D91: RO | G91: =+N($D91)*N(E91) -> 0 | H91: =+N($D91)*N(F91) -> 0 | I91: =+SUM(G91:H91) -> 0
A92: =A91+0.1 -> 12.3 | B92: 600 x 600 Outer Size (375 x 375 Neck size in mm) | C92: Nos | D92: 16 | E92: 2000 | F92: 450 | G92: =+N($D92)*N(E92) -> 32000 | H92: =+N($D92)*N(F92) -> 7200 | I92: =+SUM(G92:H92) -> 39200
A93: =A92+0.1 -> 12.4 | B93: 600 x 600 Outer Size (300x 300 Neck size in mm) | C93: Nos | D93: RO | G93: =+N($D93)*N(E93) -> 0 | H93: =+N($D93)*N(F93) -> 0 | I93: =+SUM(G93:H93) -> 0
A94: =A93+0.1 -> 12.5 | B94: 600 x 600 Outer Size (225 x 225 Neck size in mm) | C94: Nos | D94: RO | G94: =+N($D94)*N(E94) -> 0 | H94: =+N($D94)*N(F94) -> 0 | I94: =+SUM(G94:H94) -> 0
A95: =A94+0.1 -> 12.6 | B95: 600 x 600 Outer Size (150 x 150 Neck size in mm) | C95: Nos | D95: RO | G95: =+N($D95)*N(E95) -> 0 | H95: =+N($D95)*N(F95) -> 0 | I95: =+SUM(G95:H95) -> 0
D96: 0 | G96: =+N($D96)*N(E96) -> 0 | H96: =+N($D96)*N(F96) -> 0 | I96: =+SUM(G96:H96) -> 0
A97: 13 | B97: SITC of powder coated Extruded Aluminium 4-way diffusers Return in accordance with the approved shop drawings and specifications. The diffuser Neck size shall be as given below. Outer size shall be as per the F/c grid, Diffuser shall be removable core type, shall have concealed fixing screw,. Color code shall be as per architect approval. | D97: 0 | G97: =+N($D97)*N(E97) -> 0 | H97: =+N($D97)*N(F97) -> 0 | I97: =+SUM(G97:H97) -> 0
A98: =A97+0.1 -> 13.1 | B98: 600 x 600 Outer Size (525x 525 Neck size in mm) | C98: Nos | D98: RO | G98: =+N($D98)*N(E98) -> 0 | H98: =+N($D98)*N(F98) -> 0 | I98: =+SUM(G98:H98) -> 0
A99: =A98+0.1 -> 13.2 | B99: 600 x 600 Outer Size (450 x 450 Neck size in mm) | C99: Nos | D99: RO | G99: =+N($D99)*N(E99) -> 0 | H99: =+N($D99)*N(F99) -> 0 | I99: =+SUM(G99:H99) -> 0
A100: =A99+0.1 -> 13.3 | B100: 600 x 600 Outer Size (375 x 375 Neck size in mm) | C100: Nos | D100: 16 | E100: 1400 | F100: 300 | G100: =+N($D100)*N(E100) -> 22400 | H100: =+N($D100)*N(F100) -> 4800 | I100: =+SUM(G100:H100) -> 27200
A101: =A100+0.1 -> 13.4 | B101: 600 x 600 Outer Size (300x 300 Neck size in mm) | C101: Nos | D101: RO | G101: =+N($D101)*N(E101) -> 0 | H101: =+N($D101)*N(F101) -> 0 | I101: =+SUM(G101:H101) -> 0
...

Sheet FIRE & SAFETY
A1: PROJECT | B1: PAYTM
A2: SUBJECT | B2: LIFE SAFETY SYSTEM BOQ SUMMARY
A3: DATE | B3: 46113
A4: VERSION | B4: V0
B5: BILL OF QUANTITIES FOR FIRE AND LIFE SAFETY SYSTEMS
A6: Sl.No. | B6: DESCRIPTION | C6: UNIT | D6: QNT | E6: RATE | G6: AMOUNT
E7: Supply | F7: Installation | G7: Supply | H7: Installation | I7: Total
B8: PART-A
A9: I | B9: Analogue Addressable FA System
A10: 1 | B10: Supply Installation Testing and Commissioning of UL 864, 10th Edition and FM-approved 32-bit Microprocessor based Intelligent Addressable Peer-to-Peer networkable 2 Loop Fire Alarm Control Panel. The panel shall accommodate up to 2 nos. of 12V/50AH batteries in its housing and shall have a battery charging capacity of (up to) 2 nos. of 12V/100 AH housed externally, shall have an 8" Color Touch Screen Display to show 8 simultaneous events at a time and at least 10 custom-programmable soft and hard buttons for user-specific programmable functions. Each Detection Loop shall accommodate up to 250 detectors and devices in any flexible combination (suggested to have min. 200 detectors support per loop)and shall accommodate up to 3000 Addresses at 100% capacity in any combination. Scope includes the network card for panel-to-panel integration. Edwards Make Power supply should be tap from emergency UPS | C10: Set | D10: 1 | E10: 238870 | F10: 14219 | G10: =N($D10)*N(E10) -> 238870 | H10: =N($D10)*N(F10) -> 14219 | I10: =SUM(G10:H10) -> 253089
G11: =N($D11)*N(E11) -> 0 | H11: =N($D11)*N(F11) -> 0 | I11: =SUM(G11:H11) -> 0
A12: =+A10+1 -> 2 | B12: Supply Installation Testing and Commissioning of Modbus / BACnet over IP protocol for integrating FA panel with necessary hardware and accessories. | C12: Set | D12: 1 | E12: 148110 | F12: 9479 | G12: =N($D12)*N(E12) -> 148110 | H12: =N($D12)*N(F12) -> 9479 | I12: =SUM(G12:H12) -> 157589
G13: =N($D13)*N(E13) -> 0 | H13: =N($D13)*N(F13) -> 0 | I13: =SUM(G13:H13) -> 0
A14: =+A12+1 -> 3 | B14: Supply Installation Testing and Commissioning of Fire Graphic Software with real time fire system status and system control options. They all interface directly with the system network Gateway. System to be compatible for BMS System. | C14: Set | D14: 0 | G14: =N($D14)*N(E14) -> 0 | H14: =N($D14)*N(F14) -> 0 | I14: =SUM(G14:H14) -> 0
G15: =N($D15)*N(E15) -> 0 | H15: =N($D15)*N(F15) -> 0 | I15: =SUM(G15:H15) -> 0
A16: =+A14+1 -> 4 | B16: Supply Installation Testing and Commissioning of PC with the following configuration. • 8 GB of RAM • SATA hard disk drive • 1TBGB Storage • I7 3GHz Processor • XGA or higher video card PCI-Express, with OpenGL (v4.0 or above) hardware acceleration support, minimum 512 MB RAM • 1280 x 1024 pixel resolution and 65K colors • 10/100/1000 Ethernet Network Interface Card • Windows 10/11 Professional Licensed OS (64-bit) • 21'' Flat Screen Monitor • USB 3.0 • Gigabit TCP/IP Port with 100/1000Mbps network card with antivirus software, MS software with a sound card, mouse, keypad, etc. | C16: Set | D16: RO | G16: =N($D16)*N(E16) -> 0 | H16: =N($D16)*N(F16) -> 0 | I16: =SUM(G16:H16) -> 0
G17: =N($D17)*N(E17) -> 0 | H17: =N($D17)*N(F17) -> 0 | I17: =SUM(G17:H17) -> 0
A18: =+A16+1 -> 5 | B18: Supply Installation Testing and Commissioning of Intelligent Addressable Photoelectric smoke detector with a standard base and junction box. The optical sensor element shall have a sensitivity range of 0.53 to 3.94 %/ft. (1.7 to 12.35 %/m) obscuration, air velocity range from 0 to 4,000 ft./min (0 to 20 m/s), operating temperature range from -20°C to 60°C, and the operating environment from 0 to 49°C, 0 to 93% RH, Non-Condensing. | G18: =N($D18)*N(E18) -> 0 | H18: =N($D18)*N(F18) -> 0 | I18: =SUM(G18:H18) -> 0
A19: a | B19: Above Ceiling Detectors | C19: Nos. | D19: 62 | E19: 3039 | F19: 286 | G19: =N($D19)*N(E19) -> 188418 | H19: =N($D19)*N(F19) -> 17732 | I19: =SUM(G19:H19) -> 206150
A20: b | B20: Below Ceiling Detectors | C20: Nos. | D20: 38 | E20: 2812 | F20: 286 | G20: =N($D20)*N(E20) -> 106856 | H20: =N($D20)*N(F20) -> 10868 | I20: =SUM(G20:H20) -> 117724
A21: =+A18+1 -> 6 | B21: Supply Installation Testing and Commissioning of Intelligent Addressable Multi-Sensor (Optical Smoke + Heat) detector with a standard base and junction box. The optical sensor element shall have multiple selectable sensitivity levels from 0.2% Obs/ft to 3.7% Obs/ft. The ROR detection element shall have a selectable rate of rising setting of 8°C per minute and 11°C per minute (or close to this value not deviating more than 1°C). The fixed temp detection element shall have two selectable settings of 57°C and 68°C (or closer to this value not deviating by 1°C). Multi-sensor detectors shall have a configuration mode that gives separate alarms for smoke detection and heat detection and shall indicate the cause of the alarm (smoke or heat). Also, the multi-sensor shall have a combined configuration mode of smoke and heat detection that gives only one evaluated alarm from a multi-sensor detector in case of a fire event. The detector shall have an operating temperature range from -9°C to 50°C and a humidity tolerance range of up to 95% RH, Non-Condensing. | G21: =N($D21)*N(E21) -> 0 | H21: =N($D21)*N(F21) -> 0 | I21: =SUM(G21:H21) -> 0
A22: a | B22: Above Ceiling Detectors | C22: Nos. | D22: 5 | E22: 3215 | F22: 286 | G22: =N($D22)*N(E22) -> 16075 | H22: =N($D22)*N(F22) -> 1430 | I22: =SUM(G22:H22) -> 17505
A23: b | B23: Below Ceiling Detectors | C23: Nos. | D23: 5 | E23: 2987 | F23: 286 | G23: =N($D23)*N(E23) -> 14935 | H23: =N($D23)*N(F23) -> 1430 | I23: =SUM(G23:H23) -> 16365
A24: c | B24: False Floor Detectors | C24: Nos. | D24: 0 | G24: =N($D24)*N(E24) -> 0 | H24: =N($D24)*N(F24) -> 0 | I24: =SUM(G24:H24) -> 0
G25: =N($D25)*N(E25) -> 0 | H25: =N($D25)*N(F25) -> 0 | I25: =SUM(G25:H25) -> 0
A26: =+A21+1 -> 7 | B26: Supply Installation Testing and Commissioning of Intelligent Addressable Rate of Rising cum Fixed Temperature Heat Detector along with base and junction box. Rate-of-Rise temperature detection element shall have two selectable settings of 8° C and 11° C (or closer to this value not deviating by 1°C) and Fixed temperature sensing shall be independent of rate-of-rise sensing and shall have two selectable settings of 57° C and 68°C (or closer to this value not deviating by 1°C). The detector shall have an operating temperature range from 0°C to 50°C and a humidity tolerance range of up to 95% RH, Non-Condensing. | C26: Nos. | D26: 2 | E26: 3039 | F26: 286 | G26: =N($D26)*N(E26) -> 6078 | H26: =N($D26)*N(F26) -> 572 | I26: =SUM(G26:H26) -> 6650
G27: =N($D27)*N(E27) -> 0 | H27: =N($D27)*N(F27) -> 0 | I27: =SUM(G27:H27) -> 0
A28: =+A26+1 -> 8 | B28: Supply Installation Testing and Commissioning of Analogue Addressable Duct sensor detector with local housing and necessary hardware and accessories. | C28: Nos. | D28: 1 | E28: 10219 | F28: 286 | G28: =N($D28)*N(E28) -> 10219 | H28: =N($D28)*N(F28) -> 286 | I28: =SUM(G28:H28) -> 10505
G29: =N($D29)*N(E29) -> 0 | H29: =N($D29)*N(F29) -> 0 | I29: =SUM(G29:H29) -> 0
A30: =+A28+1 -> 9 | B30: Supply Installation Testing and Commissioning of Response indicator for all detectors located above false ceiling and below false flooring. | C30: Nos. | D30: 55 | E30: 106 | F30: 96 | G30: =N($D30)*N(E30) -> 5830 | H30: =N($D30)*N(F30) -> 5280 | I30: =SUM(G30:H30) -> 11110
G31: =N($D31)*N(E31) -> 0 | H31: =N($D31)*N(F31) -> 0 | I31: =SUM(G31:H31) -> 0
A32: =+A30+1 -> 10 | B32: Supply and Installation of Addressable Single action Manual call point as per OEM (Push/Breakglass/Pull Station) with necessary hardware and accessories. | C32: Nos. | D32: 3 | E32: 3585 | F32: 286 | G32: =N($D32)*N(E32) -> 10755 | H32: =N($D32)*N(F32) -> 858 | I32: =SUM(G32:H32) -> 11613
G33: =N($D33)*N(E33) -> 0 | H33: =N($D33)*N(F33) -> 0 | I33: =SUM(G33:H33) -> 0
A34: =+A32+1 -> 11 | B34: Supply Installation Testing and Commissioning of addressable type Horn / Strobe rated at 82 dBA @ 3m for Audible annunciation and 75cd flashing at 1 Hz for visual indication. | C34: Nos. | D34: =3+2 -> 5 | E34: 5495 | F34: 286 | G34: =N($D34)*N(E34) -> 27475 | H34: =N($D34)*N(F34) -> 1430 | I34: =SUM(G34:H34) -> 28905
G35: =N($D35)*N(E35) -> 0 | H35: =N($D35)*N(F35) -> 0 | I35: =SUM(G35:H35) -> 0
A36: =+A34+1 -> 12 | B36: Supply Installation Testing and Commissioning of addressable fault isolator module for isolating shorted dewired and lose circuits between two successive fault isolators with automatic resetting arrangement to protect the loop from short circuits, the rate shall include GI back box and Cu gland. | C36: Nos. | D36: 6 | E36: 2669 | F36: 286 | G36: =N($D36)*N(E36) -> 16014 | H36: =N($D36)*N(F36) -> 1716 | I36: =SUM(G36:H36) -> 17730
G37: =N($D37)*N(E37) -> 0 | H37: =N($D37)*N(F37) -> 0 | I37: =SUM(G37:H37) -> 0
A38: =+A36+1 -> 13 | B38: Supply Installation Testing and Commissioning of Addressable Control Relay modules for Monitoring/controlling Input or Output. | G38: =N($D38)*N(E38) -> 0 | H38: =N($D38)*N(F38) -> 0 | I38: =SUM(G38:H38) -> 0
B39: - Access control System | G39: =N($D39)*N(E39) -> 0 | H39: =N($D39)*N(F39) -> 0 | I39: =SUM(G39:H39) -> 0
B40: - Integration with Builder fire alarm system | G40: =N($D40)*N(E40) -> 0 | H40: =N($D40)*N(F40) -> 0 | I40: =SUM(G40:H40) -> 0
B41: - PA system | G41: =N($D41)*N(E41) -> 0 | H41: =N($D41)*N(F41) -> 0 | I41: =SUM(G41:H41) -> 0
B42: - Ac Tripping(AHU/DX DUCTABLE SPLIT/DX VRF/PAC) | G42: =N($D42)*N(E42) -> 0 | H42: =N($D42)*N(F42) -> 0 | I42: =SUM(G42:H42) -> 0
B43: - For Fire Curtains / Water curtain | G43: =N($D43)*N(E43) -> 0 | H43: =N($D43)*N(F43) -> 0 | I43: =SUM(G43:H43) -> 0
B44: - For Motorised Fire Dampers/Exhaust/Fresh Air fans | G44: =N($D44)*N(E44) -> 0 | H44: =N($D44)*N(F44) -> 0 | I44: =SUM(G44:H44) -> 0
B45: the rate shall include GI back box and Cu gland | C45: Nos. | D45: 6 | E45: 2669 | F45: 286 | G45: =N($D45)*N(E45) -> 16014 | H45: =N($D45)*N(F45) -> 1716 | I45: =SUM(G45:H45) -> 17730
G46: =N($D46)*N(E46) -> 0 | H46: =N($D46)*N(F46) -> 0 | I46: =SUM(G46:H46) -> 0
A47: =+A38+1 -> 14 | B47: Supply Installation Testing and Commissioning of the Control Module shall be capable of providing SPDT/DPDT contact rated at 24V DC, 2A. The quoted rate shall be with the necessary back box for mounting (for the hooter/strobe). | C47: Nos. | D47: 5 | E47: 2669 | F47: 286 | G47: =N($D47)*N(E47) -> 13345 | H47: =N($D47)*N(F47) -> 1430 | I47: =SUM(G47:H47) -> 14775
G48: =N($D48)*N(E48) -> 0 | H48: =N($D48)*N(F48) -> 0 | I48: =SUM(G48:H48) -> 0
A49: =+A47+1 -> 15 | B49: Supply and Installation of 24DC, 10A power supply for Hooters, the quoted rate shall be with the necessary back box for mounting. | C49: Nos. | D49: 2 | E49: 2086 | F49: 1423 | G49: =N($D49)*N(E49) -> 4172 | H49: =N($D49)*N(F49) -> 2846 | I49: =SUM(G49:H49) -> 7018
G50: =N($D50)*N(E50) -> 0 | H50: =N($D50)*N(F50) -> 0 | I50: =SUM(G50:H50) -> 0
A51: =+A49+1 -> 16 | B51: Supply Installation Testing and Commissioning of Addressable Monitor Module for Sprinkler Flow Switch and WLD with all mounting accessories, complete with MS Powder coated Junction Box for mounting and on Surface, Cable lugs at Ends, cable compression glands, cable tags and Ferruling. | C51: Nos. | D51: 4 | E51: 2669 | F51: 286 | G51: =N($D51)*N(E51) -> 10676 | H51: =N($D51)*N(F51) -> 1144 | I51: =SUM(G51:H51) -> 11820
G52: =N($D52)*N(E52) -> 0 | H52: =N($D52)*N(F52) -> 0 | I52: =SUM(G52:H52) -> 0
A53: =+A51+1 -> 17 | B53: Supply and Laying of 2Cx1.5 sq. mm multistrand copper, FRLS Armoured cable. RED in colour, laid on the surface with GI saddle supports and spacers every 0.3 meters. Complete with GI junction boxes, cable lugs at both ends, cable compression glands, cable tags and ferrule, etc. | C53: Mtrs | D53: 1946 | E53: 101 | F53: 35 | G53: =N($D53)*N(E53) -> 196546 | H53: =N($D53)*N(F53) -> 68110 | I53: =SUM(G53:H53) -> 264656
G54: =N($D54)*N(E54) -> 0 | H54: =N($D54)*N(F54) -> 0 | I54: =SUM(G54:H54) -> 0
A55: =+A53+1 -> 18 | B55: Removing and re-locating of existing builder detectors overlapping with interior partition walls/hvac ducts/raceways with necessary required cabling, hardware and accessories. | C55: Nos | D55: 4 | E55: 0 | F55: 380 | G55: =N($D55)*N(E55) -> 0 | H55: =N($D55)*N(F55) -> 1520 | I55: =SUM(G55:H55) -> 1520
G56: =N($D56)*N(E56) -> 0 | H56: =N($D56)*N(F56) -> 0 | I56: =SUM(G56:H56) -> 0
A57: =+A55+1 -> 19 | B57: Supply and Installation of GI perforated raceways in the ceiling made of 1.6mm thick sheet steel and covered with 1.2mm sheet steel with necessary hardware including supporting with threaded hi-tech rods, junctions, etc. | G57: =N($D57)*N(E57) -> 0 | H57: =N($D57)*N(F57) -> 0 | I57: =SUM(G57:H57) -> 0
A58: a | B58: 200x50mm | C58: Mtrs | D58: 10 | E58: 505 | F58: 86 | G58: =N($D58)*N(E58) -> 5050 | H58: =N($D58)*N(F58) -> 860 | I58: =SUM(G58:H58) -> 5910
A59: b | B59: 100x50mm | C59: Mtrs | D59: 0 | G59: =N($D59)*N(E59) -> 0 | H59: =N($D59)*N(F59) -> 0 | I59: =SUM(G59:H59) -> 0
A60: c | B60: 50x40mm | C60: Mtrs | D60: 0 | G60: =N($D60)*N(E60) -> 0 | H60: =N($D60)*N(F60) -> 0 | I60: =SUM(G60:H60) -> 0
B61: Sub Total for Analogue Addressable FA System | G61: =SUM(G10:G60) -> 1035438 | H61: =SUM(H10:H60) -> 142926 | I61: =SUM(I10:I60) -> 1178364
G62: =N($D62)*N(E62) -> 0 | H62: =N($D62)*N(F62) -> 0 | I62: =SUM(G62:H62) -> 0
A63: II | B63: PUBLIC ADDRESS SYSTEM | G63: =N($D63)*N(E63) -> 0 | H63: =N($D63)*N(F63) -> 0 | I63: =SUM(G63:H63) -> 0
B64: NOTE - Tapping for Workstation & Passage speakers - 6W. Tapping for closed rooms / cabins speakers - 1.5W/3W. | G64: =N($D64)*N(E64) -> 0 | H64: =N($D64)*N(F64) -> 0 | I64: =SUM(G64:H64) -> 0
A65: 1 | B65: Supply Installation Testing and Commissioning of 19U rack for mounting PA system hardware with rigid frame construction, Vented front glass door with a fully vented rear steel door, Top cover with gland plate and single fan cut out, powder coated with black shade with required power distribution with castor wheels for easy maintenance. | C65: Nos | D65: 1 | E65: 21613 | F65: 2703 | G65: =N($D65)*N(E65) -> 21613 | H65: =N($D65)*N(F65) -> 2703 | I65: =SUM(G65:H65) -> 24316
G66: =N($D66)*N(E66) -> 0 | H66: =N($D66)*N(F66) -> 0 | I66: =SUM(G66:H66) -> 0
A67: =+A65+1 -> 2 | B67: Supply Installation Testing and Commissioning of Voice Alarm controller 6/8 Zone with inbuilt Amplifier with a provision of having a Fire Microphone inbuilt in the controller and should have a prerecorded message as 1st level Priority automatically in case of emergency or Fire, Announcing console as 2nd level and music the least (with music zone selector) Alert and Message of Fire Evacuation as per EN54 Standards. Controller to be with the USB option. | C67: Nos | D67: 1 | E67: 232234 | F67: 14219 | G67: =N($D67)*N(E67) -> 232234 | H67: =N($D67)*N(F67) -> 14219 | I67: =SUM(G67:H67) -> 246453
G68: =N($D68)*N(E68) -> 0 | H68: =N($D68)*N(F68) -> 0 | I68: =SUM(G68:H68) -> 0
A69: =+A67+1 -> 3 | B69: Supply Installation Testing and Commissioning of 480 Watts Power Amplifier in a 3U high housing with 70 V / 100 V and 8-ohm outputs, Dual inputs with priority switching, 100 V input for slave operation on 100 V speaker line, Mains, battery back-up, TÜV certified according to IEC 60849 and with necessary channel/mounting support to place the amplifier in the existing rack. | C69: Nos | D69: 1 | E69: 39813 | F69: 4740 | G69: =N($D69)*N(E69) -> 39813 | H69: =N($D69)*N(F69) -> 4740 | I69: =SUM(G69:H69) -> 44553
G70: =N($D70)*N(E70) -> 0 | H70: =N($D70)*N(F70) -> 0 | I70: =SUM(G70:H70) -> 0
A71: =+A69+1 -> 4 | B71: Supply Installation Testing and Commissioning of Gooseneck microphone with keypad for zone selection and necessary accessories. | C71: Nos | D71: 1 | E71: 42656 | F71: 1423 | G71: =N($D71)*N(E71) -> 42656 | H71: =N($D71)*N(F71) -> 1423 | I71: =SUM(G71:H71) -> 44079
G72: =N($D72)*N(E72) -> 0 | H72: =N($D72)*N(F72) -> 0 | I72: =SUM(G72:H72) -> 0
A73: =+A71+1 -> 5 | B73: Supply Installation Testing and Commissioning of 6W Ceiling Recessed Speaker with max SPL1M/1W 96dB. Frequency response of 80Hz-20KHz with a dispersion angle of 160 deg. The speaker should have tappings at 6W/3W/1.5W. Complete with necessary mounting hardware and accessories. | C73: Nos | D73: 40 | E73: 997 | F73: 238 | G73: =N($D73)*N(E73) -> 39880 | H73: =N($D73)*N(F73) -> 9520 | I73: =SUM(G73:H73) -> 49400
G74: =N($D74)*N(E74) -> 0 | H74: =N($D74)*N(F74) -> 0 | I74: =SUM(G74:H74) -> 0
A75: =+A73+1 -> 6 | B75: Supply Installation Testing and Commissioning of 6W Wall mount speaker with max SPL1M/1W 96dB. Frequency response of 160Hz-20KHz. The speaker should have tappings at 6W/3W.complete with necessary mounting hardware and accessories. | C75: Nos | D75: 2 | E75: 1138 | F75: 238 | G75: =N($D75)*N(E75) -> 2276 | H75: =N($D75)*N(F75) -> 476 | I75: =SUM(G75:H75) -> 2752
G76: =N($D76)*N(E76) -> 0 | H76: =N($D76)*N(F76) -> 0 | I76: =SUM(G76:H76) -> 0
A77: =+A75+1 -> 7 | B77: Supply Installation Testing and Commissioning of 6W Ceiling surface mounted Speaker with max SPL1M/1W 96dB. Frequency response of 80Hz-20KHz with a dispersion angle of 160 deg. The speaker should have tappings at 6W/3W/1.5W, complete with necessary mounting hardware and accessories along with the back box. | C77: Nos | D77: 18 | E77: 1234 | F77: 238 | G77: =N($D77)*N(E77) -> 22212 | H77: =N($D77)*N(F77) -> 4284 | I77: =SUM(G77:H77) -> 26496
G78: =N($D78)*N(E78) -> 0 | H78: =N($D78)*N(F78) -> 0 | I78: =SUM(G78:H78) -> 0
A79: =+A77+1 -> 8 | B79: Supply and Laying of 2Cx1 sq. mm multistrand copper, FRLS Armoured cable. BLACK in colour, laid on the surface with GI saddle supports and spacers every 0.3 meters. Complete with GI junction boxes, cable lugs at both ends, cable compression glands, cable tags and ferrule, etc. | C79: Mtrs | D79: 840 | E79: 101 | F79: 35 | G79: =N($D79)*N(E79) -> 84840 | H79: =N($D79)*N(F79) -> 29400 | I79: =SUM(G79:H79) -> 114240
G80: =N($D80)*N(E80) -> 0 | H80: =N($D80)*N(F80) -> 0 | I80: =SUM(G80:H80) -> 0
A81: =+A79+1 -> 9 | B81: Supply and Laying of 100x100mm UPVC cable trough wire manager with cover for dressing up of cables. | C81: Mtrs | D81: 10 | E81: 551 | F81: 86 | G81: =N($D81)*N(E81) -> 5510 | H81: =N($D81)*N(F81) -> 860 | I81: =SUM(G81:H81) -> 6370
B82: Sub Total for PA System | G82: =SUM(G65:G81) -> 491034 | H82: =SUM(H65:H81) -> 67625 | I82: =SUM(I65:I81) -> 558659
G83: =N($D83)*N(E83) -> 0 | H83: =N($D83)*N(F83) -> 0 | I83: =SUM(G83:H83) -> 0
A84: III | B84: Fire Extinguishers | G84: =N($D84)*N(E84) -> 0 | H84: =N($D84)*N(F84) -> 0 | I84: =SUM(G84:H84) -> 0
A85: 1 | B85: Supply and Installation of 4.5kg CO2 type fire extinguisher consisting of welded M.S cylindrical body, squeeze lever discharge valve fitted with pressure indicating gauge internal discharge tube, 2mtr long high-pressure discharge hose, discharge nozzle, suspension bracket conforming to IS: 15683 finished externally with red enamel paint and fixed to the wall with brackets or Floor mounting bracket with four legs complete with internal charge and Fluorescent Sign board, etc. | C85: Nos | D85: 2 | E85: 5119 | F85: 238 | G85: =N($D85)*N(E85) -> 10238 | H85: =N($D85)*N(F85) -> 476 | I85: =SUM(G85:H85) -> 10714
G86: =N($D86)*N(E86) -> 0 | H86: =N($D86)*N(F86) -> 0 | I86: =SUM(G86:H86) -> 0
A87: =+A85+1 -> 2 | B87: Supply and Installation of 6KG ABC Type Fire Extinguisher, Stored Pressure Type, Pressure Gauge, Discharge Time less than 10 Secs, Controllable discharge mechanism, Range minimum 3 Meters, applicable on Class A, B, C and electrically started Fire, Helium Leak Detection Tested, Floor mounting bracket with four legs and Fluorescent Sign board, etc. complete, ISI and EN Approved, confirming to IS: 15683. | C87: Nos | D87: 9 | E87: 2371 | F87: 238 | G87: =N($D87)*N(E87) -> 21339 | H87: =N($D87)*N(F87) -> 2142 | I87: =SUM(G87:H87) -> 23481
G88: =N($D88)*N(E88) -> 0 | H88: =N($D88)*N(F88) -> 0 | I88: =SUM(G88:H88) -> 0
A89: =+A87+1 -> 3 | B89: Supply and Installation of 4 Kg Wet Chemical Stored Pressure Class “K” Kitchen Extinguishers with floor mounting bracket with four legs and Fluorescent Sign board etc. Complete, ISI and EN Approved, confirming to IS: 15683. | C89: Nos | D89: 1 | E89: 2845 | F89: 238 | G89: =N($D89)*N(E89) -> 2845 | H89: =N($D89)*N(F89) -> 238 | I89: =SUM(G89:H89) -> 3083
G90: =N($D90)*N(E90) -> 0 | H90: =N($D90)*N(F90) -> 0 | I90: =SUM(G90:H90) -> 0
A91: =+A89+1 -> 4 | B91: Supply and Installation of Ceiling mounted type clean agent automatic (FE36) fire extinguishers of capacity fitted with an automatic sprinkler valve that shall be calibrated to discharge at an ambient temperature of 68°C. The extinguisher shall be manufactured strictly as per IS standards. The quoted rate shall include necessary supports suitable for ceiling mounting. (For UPS, Battery and Hub rooms) | G91: =N($D91)*N(E91) -> 0 | H91: =N($D91)*N(F91) -> 0 | I91: =SUM(G91:H91) -> 0
A92: a | B92: 5KG | C92: Nos | D92: 5 | E92: 15812 | F92: 949 | G92: =N($D92)*N(E92) -> 79060 | H92: =N($D92)*N(F92) -> 4745 | I92: =SUM(G92:H92) -> 83805
A93: B | B93: 10KG | C93: Nos | D93: RO | G93: =N($D93)*N(E93) -> 0 | H93: =N($D93)*N(F93) -> 0 | I93: =SUM(G93:H93) -> 0
G94: =N($D94)*N(E94) -> 0 | H94: =N($D94)*N(F94) -> 0 | I94: =SUM(G94:H94) -> 0
A95: 5 | B95: Supply, Installation, Testing and Commissioning of Panel proection system,Fire Extinguisher -MMO FIRESPOT 4 kg with Pressure Switch (FK5112) with Heat sensitive tube - 15-20 mtrs with necessary accessories like pressure gauge, Dummy End Cap, Threaded Nipple End and mounting Bracket. (Make - Minimax/ Kanex) | C95: Set | D95: RO | G95: =N($D95)*N(E95) -> 0 | H95: =N($D95)*N(F95) -> 0 | I95: =SUM(G95:H95) -> 0
G96: =N($D96)*N(E96) -> 0 | H96: =N($D96)*N(F96) -> 0 | I96: =SUM(G96:H96) -> 0
B97: Supply and Installation of 2.0kg CO2 type fire extinguisher consisting of welded M.S cylindrical body, squeeze lever discharge valve fitted with pressure indicating gauge internal discharge tube, 2mtr long high-pressure discharge hose, discharge nozzle, suspension bracket conforming to IS: 15683 finished externally with red enamel paint and fixed to the wall with brackets or Floor mounting bracket with four legs complete with internal charge and Fluorescent Sign board, etc. | C97: Nos | D97: 2 | E97: 3319 | F97: 238 | G97: =N($D97)*N(E97) -> 6638 | H97: =N($D97)*N(F97) -> 476 | I97: =SUM(G97:H97) -> 7114
G98: =N($D98)*N(E98) -> 0 | H98: =N($D98)*N(F98) -> 0 | I98: =SUM(G98:H98) -> 0
G99: =N($D99)*N(E99) -> 0 | H99: =N($D99)*N(F99) -> 0 | I99: =SUM(G99:H99) -> 0
B100: Sub Total for Fire Extinguishers | G100: =SUM(G85:G99) -> 120120 | H100: =SUM(H85:H99) -> 8077 | I100: =SUM(I85:I99) -> 128197
...

Sheet ACS & CCTV 
A1: PROJECT | B1: LIFE SAFETY SYSTEM BOQ SUMMARY
A2: SUBJECT | B2: ACCESS CONTROL & CCTV SYSTEM
A3: DATE | B3: 46113
A4: VERSION | B4: V0
A5: Sl.No. | B5: DESCRIPTION | D5: UNIT | E5: QNT | F5: RATE | H5: AMOUNT | K5: Remarks
F6: Supply | G6: Installation | H6: Supply | I6: Installation | J6: Total
B7: PART-B
A8: I | B8: ACCESS CONTROL | C8: Make / Model
A10: 1 | B10: Supply, Installation, Testing & Commissioning of 4 Door & 4 reader Controller (Oryggi 4 door 4 reader controller with encloser & PSU) Intelligent Controller capable of entry & exit control & battery backup to power the controller, EM Locks, Readers, etc. build-in ethernet connection, 32M memory on broad with 300,000 cards capability, 50,000 Log Capacity with TCP IP connectivity. Encloser box for controller Oryggi Controller with Licens | D10: Nos | E10: 3 | F10: 41400 | G10: 1500 | H10: =N($E10)*N(F10) -> 124200 | I10: =N($E10)*N(G10) -> 4500 | J10: =SUM(H10:I10) -> 128700
A11: 1 | B11: Supply, Installation, Testing & Commissioning of 2 Door Intelligent Controller capable of entry & exit control & battery backup to power the controller, EM Locks, Readers, etc. build-in ethernet connection, 32M memory on broad with 300,000 cards capability, 50,000 Log Capacity with TCP IP connectivity. | D11: Nos | E11: 0 | H11: =N($E11)*N(F11) -> 0 | I11: =N($E11)*N(G11) -> 0 | J11: =SUM(H11:I11) -> 0
H12: =N($E12)*N(F12) -> 0 | I12: =N($E12)*N(G12) -> 0 | J12: =SUM(H12:I12) -> 0
A13: 3 | B13: Supply, Installation, Testing & Commissioning of Multi-technology Card Readers as per specification | H13: =N($E13)*N(F13) -> 0 | I13: =N($E13)*N(G13) -> 0 | J13: =SUM(H13:I13) -> 0
B14: The readers shall have the following features:- a) Water resistance, high security, and high durability. b) Mounted directly on metal without affecting performance. c) Suitable for the Wiegand interface. d) Low power consumption. e) Audiovisual indication. f) Internal self-test routine checks and verifies setup configuration. g) Card read time less than .1 sec. h) I Class Smart Card reader (Acs card reader smart I SPR 501) i) Suprema Biometric reader for server room( BIO ENTRY P2) | D14: Nos | E14: 7 | F14: 37375 | G14: 1500 | H14: =N($E14)*N(F14) -> 261625 | I14: =N($E14)*N(G14) -> 10500 | J14: =SUM(H14:I14) -> 272125
H15: =N($E15)*N(F15) -> 0 | I15: =N($E15)*N(G15) -> 0 | J15: =SUM(H15:I15) -> 0
A16: 4 | B16: Supply Installation Testing and Commissioning of Pinpad + Reader with necessary hardware & accessories. | D16: Nos | E16: 1 | F16: 37375 | G16: 1500 | H16: =N($E16)*N(F16) -> 37375 | I16: =N($E16)*N(G16) -> 1500 | J16: =SUM(H16:I16) -> 38875
H17: =N($E17)*N(F17) -> 0 | I17: =N($E17)*N(G17) -> 0 | J17: =SUM(H17:I17) -> 0
A18: 5 | B18: Supply & Installation of Electromagnetic Locks with a holding of 600lbs suitable for single door (L bracket 83014090 Make Bel) | D18: Nos | E18: 3 | F18: 3000 | G18: 500 | H18: =N($E18)*N(F18) -> 9000 | I18: =N($E18)*N(G18) -> 1500 | J18: =SUM(H18:I18) -> 10500
G19: - | H19: =N($E19)*N(F19) -> 0 | I19: =N($E19)*N(G19) -> 0 | J19: =SUM(H19:I19) -> 0
A20: 6 | B20: Supply & Installation of Electromagnetic Locks with a holding for of 600lbs suitable for double door | D20: Nos | E20: 2 | F20: 6000 | G20: 500 | H20: =N($E20)*N(F20) -> 12000 | I20: =N($E20)*N(G20) -> 1000 | J20: =SUM(H20:I20) -> 13000
H21: =N($E21)*N(F21) -> 0 | I21: =N($E21)*N(G21) -> 0 | J21: =SUM(H21:I21) -> 0
A22: 7 | B22: Supply & Installation of Magnetic Contacts - Flush Mounted/ Surface mounted for alarms with necessary hardware & accessories. | D22: Nos | E22: 7 | F22: 450 | G22: 150 | H22: =N($E22)*N(F22) -> 3150 | I22: =N($E22)*N(G22) -> 1050 | J22: =SUM(H22:I22) -> 4200
H23: =N($E23)*N(F23) -> 0 | I23: =N($E23)*N(G23) -> 0 | J23: =SUM(H23:I23) -> 0
A24: 8 | B24: Supply & Installation of buzzer with necessary hardware & accessories. | D24: Nos | E24: 5 | F24: 350 | G24: 150 | H24: =N($E24)*N(F24) -> 1750 | I24: =N($E24)*N(G24) -> 750 | J24: =SUM(H24:I24) -> 2500
H25: =N($E25)*N(F25) -> 0 | I25: =N($E25)*N(G25) -> 0 | J25: =SUM(H25:I25) -> 0
A26: 9 | B26: Supply of Proximity cards of standard size and is thin and flexible. The read ring of the card should be consistent and not affected by body shielding or variable environmental condition. | D26: Nos | E26: 0 | H26: =N($E26)*N(F26) -> 0 | I26: =N($E26)*N(G26) -> 0 | J26: =SUM(H26:I26) -> 0
H27: =N($E27)*N(F27) -> 0 | I27: =N($E27)*N(G27) -> 0 | J27: =SUM(H27:I27) -> 0
A28: 10 | B28: Supply & Installation of Egress switch / Exit Push Button with necessary accessories & hardware. | D28: Nos | E28: 1 | F28: 450 | G28: 200 | H28: =N($E28)*N(F28) -> 450 | I28: =N($E28)*N(G28) -> 200 | J28: =SUM(H28:I28) -> 650
H29: =N($E29)*N(F29) -> 0 | I29: =N($E29)*N(G29) -> 0 | J29: =SUM(H29:I29) -> 0
A30: 11 | B30: Supply & Installation of Emergency Door Release switch with necessary accessories & hardware. | D30: Nos | E30: 5 | F30: 850 | G30: 200 | H30: =N($E30)*N(F30) -> 4250 | I30: =N($E30)*N(G30) -> 1000 | J30: =SUM(H30:I30) -> 5250
H31: =N($E31)*N(F31) -> 0 | I31: =N($E31)*N(G31) -> 0 | J31: =SUM(H31:I31) -> 0
A32: 12 | B32: Supply & Installation of the Panic bar for the Fire exit doors complete with necessary accessories & hardware. | D32: Nos | E32: 0 | H32: =N($E32)*N(F32) -> 0 | I32: =N($E32)*N(G32) -> 0 | J32: =SUM(H32:I32) -> 0
H33: =N($E33)*N(F33) -> 0 | I33: =N($E33)*N(G33) -> 0 | J33: =SUM(H33:I33) -> 0
A34: 14 | B34: Access software - (SPECIFY NO OF USERS) | D34: Nos | E34: 1 | F34: 20700 | G34: 1500 | H34: =N($E34)*N(F34) -> 20700 | I34: =N($E34)*N(G34) -> 1500 | J34: =SUM(H34:I34) -> 22200
H35: =N($E35)*N(F35) -> 0 | I35: =N($E35)*N(G35) -> 0 | J35: =SUM(H35:I35) -> 0
A36: 15 | B36: Supply and Laying of 4 Core x 0.75 sq mm multi-strand, ATC, shielded Cable as per specification | D36: Mtrs | E36: =290+10 -> 300 | F36: 80 | G36: 20 | H36: =N($E36)*N(F36) -> 24000 | I36: =N($E36)*N(G36) -> 6000 | J36: =SUM(H36:I36) -> 30000
H37: =N($E37)*N(F37) -> 0 | I37: =N($E37)*N(G37) -> 0 | J37: =SUM(H37:I37) -> 0
A38: 16 | B38: Supply and Laying of 8 Core x 0.75 sq mm multi-strand, ATC, shielded Cable as per specification | D38: Mtrs | E38: =290+10 -> 300 | F38: 135 | G38: 20 | H38: =N($E38)*N(F38) -> 40500 | I38: =N($E38)*N(G38) -> 6000 | J38: =SUM(H38:I38) -> 46500
H39: =N($E39)*N(F39) -> 0 | I39: =N($E39)*N(G39) -> 0 | J39: =SUM(H39:I39) -> 0
A40: 17 | B40: Supply and Laying of 1" GI Conduits on the wall, columns, cable trays false ceiling etc., with GI spacers, saddles including associated civil works (Purple colour). | D40: Mtrs | E40: =290+10 -> 300 | F40: 60 | G40: 20 | H40: =N($E40)*N(F40) -> 18000 | I40: =N($E40)*N(G40) -> 6000 | J40: =SUM(H40:I40) -> 24000
H41: =N($E41)*N(F41) -> 0 | I41: =N($E41)*N(G41) -> 0 | J41: =SUM(H41:I41) -> 0
A42: 18 | B42: Supply and Laying of perforated raceway of below dimensions with necessary supports for ACS & CCTV works | H42: =N($E42)*N(F42) -> 0 | I42: =N($E42)*N(G42) -> 0 | J42: =SUM(H42:I42) -> 0
A43: a | B43: 200x50mm | D43: Mtrs | E43: 10 | F43: 530 | G43: 120 | H43: =N($E43)*N(F43) -> 5300 | I43: =N($E43)*N(G43) -> 1200 | J43: =SUM(H43:I43) -> 6500
A44: b | B44: 100x50mm | D44: Mtrs | H44: =N($E44)*N(F44) -> 0 | I44: =N($E44)*N(G44) -> 0 | J44: =SUM(H44:I44) -> 0
A45: c | B45: 50x40mm | D45: Mtrs | E45: 0 | H45: =N($E45)*N(F45) -> 0 | I45: =N($E45)*N(G45) -> 0 | J45: =SUM(H45:I45) -> 0
H46: =N($E46)*N(F46) -> 0 | I46: =N($E46)*N(G46) -> 0 | J46: =SUM(H46:I46) -> 0
B47: Sub Total for Access Control System | H47: =SUM(H10:H46) -> 562300 | I47: =SUM(I10:I46) -> 42700 | J47: =SUM(J10:J46) -> 605000
H48: =N($E48)*N(F48) -> 0 | I48: =N($E48)*N(G48) -> 0 | J48: =SUM(H48:I48) -> 0
A49: II | B49: CCTV | H49: =N($E49)*N(F49) -> 0 | I49: =N($E49)*N(G49) -> 0 | J49: =SUM(H49:I49) -> 0
H50: =N($E50)*N(F50) -> 0 | I50: =N($E50)*N(G50) -> 0 | J50: =SUM(H50:I50) -> 0
A51: 1 | B51: Supply, Installation, Testing & Commissioning of Network video recorder with bundled server machine, Preloaded of Enterprises Software & with remote monitoring facilities | H51: =N($E51)*N(F51) -> 0 | I51: =N($E51)*N(G51) -> 0 | J51: =SUM(H51:I51) -> 0
B52: Protoco:TCP/IP, DHCP, SMTP. Power supply source : 240V, 50Hz, AC. Video output : Monitor - A :- 1 BNC, RCA, VGA.: Monitor - B :- 1 BNC (single / multi) Compression : H.264, MPEG-4 & MJPEG on IP cameras Display resolution : 720 x 480 / 720 x 576 (PAL) Motion based Recording OF 70%(Speed/Resolution) Resolution : a) 720p @ 10fps. H.264 format for 30Days HDD Back:: 90 Days Motion based recording, 70% Motion recording per day. | H52: =N($E52)*N(F52) -> 0 | I52: =N($E52)*N(G52) -> 0 | J52: =SUM(H52:I52) -> 0
A53: a | B53: 32 Channel NVR with Hard Disk Make PRAMA | D53: Nos | E53: 1 | F53: 40000 | G53: 3500 | H53: =N($E53)*N(F53) -> 40000 | I53: =N($E53)*N(G53) -> 3500 | J53: =SUM(H53:I53) -> 43500
A54: b | B54: 8 Channel NVR with Hard Disk | D54: Nos | E54: 0 | H54: =N($E54)*N(F54) -> 0 | I54: =N($E54)*N(G54) -> 0 | J54: =SUM(H54:I54) -> 0
H55: =N($E55)*N(F55) -> 0 | I55: =N($E55)*N(G55) -> 0 | J55: =SUM(H55:I55) -> 0
A56: 2 | B56: Supplly, Installation, Testing & Commissioning of IP Fixed IR indoor type dome camera, 3-4 MP Camera with necessary accessories & hardwares.Make PRAMA | D56: Nos | E56: 17 | F56: 4900 | G56: 800 | H56: =N($E56)*N(F56) -> 83300 | I56: =N($E56)*N(G56) -> 13600 | J56: =SUM(H56:I56) -> 96900
H57: =N($E57)*N(F57) -> 0 | I57: =N($E57)*N(G57) -> 0 | J57: =SUM(H57:I57) -> 0
A58: 2 | B58: Supplly, Installation, Testing & Commissioning of IP Fixed IR Outdoor type dome camera, 3-4 MP Camera with necessary accessories & hardwares. | D58: Nos | E58: 0 | H58: =N($E58)*N(F58) -> 0 | I58: =N($E58)*N(G58) -> 0 | J58: =SUM(H58:I58) -> 0
H59: =N($E59)*N(F59) -> 0 | I59: =N($E59)*N(G59) -> 0 | J59: =SUM(H59:I59) -> 0
A60: 3 | B60: Supplly, Installation, Testing & Commissioning of 32 Inch, LED colour monitor suitable for above camers. | D60: Nos | E60: 1 | F60: 15000 | G60: 1500 | H60: =N($E60)*N(F60) -> 15000 | I60: =N($E60)*N(G60) -> 1500 | J60: =SUM(H60:I60) -> 16500
H61: =N($E61)*N(F61) -> 0 | I61: =N($E61)*N(G61) -> 0 | J61: =SUM(H61:I61) -> 0
A62: 4 | B62: Supply, Installation, Testing & Commissioning of POE 24 port switch, 10/100 Base-T Access Layer 2 Switch includes 1 Gigabit combo (SFP/GT) ports and 2 uplink slots providing, With warranty pack. Also vendor to match the POE switch as per cameras requirement. | D62: Nos | E62: 1 | F62: 21250 | G62: 1500 | H62: =N($E62)*N(F62) -> 21250 | I62: =N($E62)*N(G62) -> 1500 | J62: =SUM(H62:I62) -> 22750
H63: =N($E63)*N(F63) -> 0 | I63: =N($E63)*N(G63) -> 0 | J63: =SUM(H63:I63) -> 0
A64: 5 | B64: Supply, Installation, Testing & Commissioning of 24 port patch panel | D64: Nos | E64: 1 | F64: 2200 | G64: 500 | H64: =N($E64)*N(F64) -> 2200 | I64: =N($E64)*N(G64) -> 500 | J64: =SUM(H64:I64) -> 2700
H65: =N($E65)*N(F65) -> 0 | I65: =N($E65)*N(G65) -> 0 | J65: =SUM(H65:I65) -> 0
A66: 6 | B66: Supply & Laying of CAT6 SL Series Patch cords Panel Side | D66: Nos | E66: 17 | F66: 315 | G66: 25 | H66: =N($E66)*N(F66) -> 5355 | I66: =N($E66)*N(G66) -> 425 | J66: =SUM(H66:I66) -> 5780
H67: =N($E67)*N(F67) -> 0 | I67: =N($E67)*N(G67) -> 0 | J67: =SUM(H67:I67) -> 0
A68: 7 | B68: Supply & Laying of CAT6 SL Series Patch cords Camera Side | D68: Nos | E68: 17 | F68: 315 | G68: 25 | H68: =N($E68)*N(F68) -> 5355 | I68: =N($E68)*N(G68) -> 425 | J68: =SUM(H68:I68) -> 5780
H69: =N($E69)*N(F69) -> 0 | I69: =N($E69)*N(G69) -> 0 | J69: =SUM(H69:I69) -> 0
A70: 8 | B70: Supply & Installation of adjustable Camera Pole with powder coating with 1mtr adjustable to 1.5 mtr with suitable base for fixing cameras | D70: Nos | E70: 17 | F70: 850 | G70: 400 | H70: =N($E70)*N(F70) -> 14450 | I70: =N($E70)*N(G70) -> 6800 | J70: =SUM(H70:I70) -> 21250
H71: =N($E71)*N(F71) -> 0 | I71: =N($E71)*N(G71) -> 0 | J71: =SUM(H71:I71) -> 0
A72: 9 | B72: Supply and Laying of 1" GI Conduits, on the wall, columns, cable trays false ceiling etc.,with GI spacers, saddles including associated civil works | D72: Mtrs | E72: 1050 | F72: 60 | G72: 20 | H72: =N($E72)*N(F72) -> 63000 | I72: =N($E72)*N(G72) -> 21000 | J72: =SUM(H72:I72) -> 84000
H73: =N($E73)*N(F73) -> 0 | I73: =N($E73)*N(G73) -> 0 | J73: =SUM(H73:I73) -> 0
A74: 10 | B74: Supplly and laying of cat-6 cable with shilded and braided for connection b/w the camera and NVR and b/w NVR and monitor ( Video signal cable) | D74: Mtrs | E74: 1050 | F74: 46 | G74: 7 | H74: =N($E74)*N(F74) -> 48300 | I74: =N($E74)*N(G74) -> 7350 | J74: =SUM(H74:I74) -> 55650
H75: =N($E75)*N(F75) -> 0 | I75: =N($E75)*N(G75) -> 0 | J75: =SUM(H75:I75) -> 0
A76: =+A74+1 -> 11 | B76: Supplying, installing, testing and commissioning of Glass Break Unit / Emergency Door Release Switch for access control system, break-glass type, wall-mounted (flush / surface as specified), suitable for integration with electromagnetic lock / door controller. The unit shall be provided with resettable glass / key-reset mechanism, LED status indication, and NO/NC dry contacts for fail-safe door release during emergency conditions. | D76: Nos | E76: RO | H76: =N($E76)*N(F76) -> 0 | I76: =N($E76)*N(G76) -> 0 | J76: =SUM(H76:I76) -> 0
H77: =N($E77)*N(F77) -> 0 | I77: =N($E77)*N(G77) -> 0 | J77: =SUM(H77:I77) -> 0
A78: =+A76+1 -> 12 | B78: Supply, installation, testing & commissioning of Dedicated CCTV Recording Server (Rack/Tower type) with minimum Intel Xeon processor, required RAM, RAID supported storage with enterprise-grade HDDs, dual LAN ports, redundant power supply (where required), complete with OS and fully compatible with CCTV VMS software | D78: Nos | E78: 1 | F78: 165000 | G78: 5000 | H78: =N($E78)*N(F78) -> 165000 | I78: =N($E78)*N(G78) -> 5000 | J78: =SUM(H78:I78) -> 170000
H79: =N($E79)*N(F79) -> 0 | I79: =N($E79)*N(G79) -> 0 | J79: =SUM(H79:I79) -> 0
A80: =+A78+1 -> 13 | B80: Supply, installation & configuration of Licensed Video Management Software (VMS) including camera licenses, live view, recording, playback, user management, motion detection, alarm integration and analytics (if applicable), complete in all respects. | D80: Nos | E80: 1 | F80: 25000 | G80: 5000 | H80: =N($E80)*N(F80) -> 25000 | I80: =N($E80)*N(G80) -> 5000 | J80: =SUM(H80:I80) -> 30000
H81: =N($E81)*N(F81) -> 0 | I81: =N($E81)*N(G81) -> 0 | J81: =SUM(H81:I81) -> 0
A82: =+A80+1 -> 14 | B82: Supply & installation of Operator Workstation including CPU, monitor(s), keyboard, mouse and VMS client software for live monitoring and playback | D82: Nos | E82: 1 | F82: 65000 | G82: 2500 | H82: =N($E82)*N(F82) -> 65000 | I82: =N($E82)*N(G82) -> 2500 | J82: =SUM(H82:I82) -> 67500
H83: =N($E83)*N(F83) -> 0 | I83: =N($E83)*N(G83) -> 0 | J83: =SUM(H83:I83) -> 0
A84: =+A82+1 -> 15 | B84: Vendor to integrate the Server based CCTV system with the centralised CCTV system | D84: Job | E84: RO | H84: =N($E84)*N(F84) -> 0 | I84: =N($E84)*N(G84) -> 0 | J84: =SUM(H84:I84) -> 0
H85: =N($E85)*N(F85) -> 0 | I85: =N($E85)*N(G85) -> 0 | J85: =SUM(H85:I85) -> 0
B86: Sub Total for CCTV System | H86: =SUM(H51:H85) -> 553210 | I86: =SUM(I51:I85) -> 69100 | J86: =SUM(J51:J85) -> 622310
B88: TOTAL AMOUNT - Security | H88: =SUM(H10:H87)/2 -> 1115510 | I88: =SUM(I10:I87)/2 -> 111800 | J88: =SUM(J10:J87)/2 -> 1227310
