Workbook
Name \0: #REF!
Name \1: #REF!
Name \a: #REF!
Name \aq: #REF!
Name \b: #REF!
Name \C: #REF!
Name \c1: #REF!
Name \d: #REF!
Name \e: #REF!
Name \f: #REF!
Name \g: #REF!
Name \h: #REF!
Name \i: #REF!
Name \j: #REF!
Name \k: #REF!
Name \kl: #REF!
Name \l: #REF!
Name \m: #REF!
Name \n: #REF!
Name \o: #REF!
Name \P: #REF!
Name \P: #REF!
Name \Q: #REF!
Name \R: #REF!
Name \S: #REF!
Name \U: #REF!
Name \V: #REF!
Name \W: #REF!
Name \x: #REF!
Name \y: #REF!
Name \z: #REF!
Name _: #REF!
Name _???_PriceList2001?2002????_: #REF!
Name _???_PriceList2001?2002???_: #REF!
Name _???_PriceList2002?2001????_: #REF!
Name _???_PriceList2002?2001???_: #REF!
Name __???_PriceList2001?2002????_: #REF!
Name __???_PriceList2001?2002???_: #REF!
Name __???_PriceList2002?2001????_: #REF!
Name __???_PriceList2002?2001???_: #REF!
Name ________: #REF!
Name ___________: #REF!
Name ____________: #REF!
Name ____________________________________________________________________can430: 40.73
Name ____________________________________________________________________can435: 43.3
Name ___________________________________________________________________can430: 40.73
Name ___________________________________________________________________can435: 43.3
Name __________________________________________________________________b111121: #REF!
Name __________________________________________________________________can430: 40.73
Name __________________________________________________________________can435: 43.3
Name __________________________________________________________________Ki1: #REF!
Name __________________________________________________________________Ki2: #REF!
Name __________________________________________________________________MAN1: #REF!
Name __________________________________________________________________PB1: #REF!
Name __________________________________________________________________TB2: #REF!
Name _________________________________________________________________b111121: #REF!
Name _________________________________________________________________bla1: #REF!
Name _________________________________________________________________can430: 40.73
Name _________________________________________________________________can435: 43.3
Name _________________________________________________________________cur1: #REF!

Sheet SUMMARY 
A1: QUOTE SUMMARY
A2: TOTAL AREA (SQ.FT.) | C2: 15000
A3: USD RATE ( AVERAGE) | C3: 90
A4: Master Summary
A6: S.NO. | B6: Description | C6: Revised Amount (In INR)
A8: 1 | B8: C&I | C8: =+'C&I-BOQ '!H251 -> 0
A9: 2 | B9: System Furniture | C9: =+'SYSTEM FURNITURE'!G38 -> 0
A10: 3 | B10: Chair | C10: =+CHAIRS!G26 -> 0
A11: 4 | B11: Carpet | C11: =+'CARPET '!G60 -> 0
A12: 5 | B12: Loose furniture | C12: =+'LOOSE FURNITURE'!F42 -> 0
A13: 6 | B13: Broughtout Items | C13: =+'BROUGHTOUT ITEMS'!G58 -> 0
A14: 7 | B14: Cafe Plumbing work | C14: =+'CAFE PLUMBING WORK'!H46 -> 0
A15: 8 | B15: Electrical Work, Lighting | C15: =+Electrical!F314 -> 0
A16: 9 | B16: HVAC Work | C16: =+HVAC!C6 -> 0
A17: 10 | B17: NETWORKING - Passive | C17: =+Passive!I28 -> 0
A18: 11 | B18: FAS | C18: =+FAS!I25 -> 0
A19: 12 | B19: PAS | C19: =+PAS!I16 -> 0
A20: 13 | B20: Fire exinguishers | C20: =+'Fire Extinguisher'!H9 -> 0
A21: 14 | B21: CCTV | C21: =+CCTV!I17 -> 0
A22: 15 | B22: ACS | C22: =+ACS!I19 -> 0
A23: 16 | B23: Fire Sprinkler | C23: =+'Fire Sprinkler'!I23 -> 0
A24: 17 | B24: Toilet | C24: =+Toilet!F150 -> 0
B26: GRAND TOTAL (Excluding taxes) | C26: =SUM(C8:C25) -> 0
B29: EXCLUSION LIST: -
A30: 1 | B30: ABOVE SUB TOTAL COST IS EXCLUDING TAXES,
A31: 2 | B31: NETWORKING - ACTIVE PART COMPONENTS.
A32: 3 | B32: WHITE GOODS / /SHREDDERS / COMPACTORS/SAFES
A33: 4 | B33: ANY LIASONING ( MUNICIPAL CORPORATION / CFO)
A34: 5 | B34: ELECT. METER
A35: 6 | B35: SHAFT DOOR ( ANY SHUTTERS / DOOR AS ACCESS TO THE SHAFT )
A36: 7 | B36: STAIRCASE & STAIRCASE FIRE EXIT DOORS
A37: 8 | B37: ANY REPAIRS TO EXTERNAL GLAZING .
A38: 9 | B38: AIR CURTAIN
A39: 10 | B39: BUSBAR
A40: 11 | B40: HVAC - HIGH SIDE WORK AND AHU SUPPLY & INSTALLATION, AHU ROOM ACCOSTIC AND PLENUM WORK, STARTER PANEL, VFD SYSTEM.
A41: 12 | B41: UPS
... A46: 17 | B46: TOILET WATERPROOFING
B48: Note:
A49: 1 | B49: Owner/client to provide free of cost electricity/water/security during the due course of site execution works.
A50: 2 | B50: The working shift will be of 12 hours or as required basis of project time lines.
A51: 3 | B51: Elevator to be permitted for lifting of materials from ground level to the floor level.
A52: 4 | B52: Owner/client to provide dedicated area/space for loading/unloading of rawmaterial as well as debris and wastage from the site works.
A53: 5 | B53: Approval from the building for carrying out to the work with intimation of the neighborsand the Local Authorities.
A54: 6 | B54: To avail permission from the building security to permit access to the Labor Team as well as the entry of transportation vehicles supplying raw materials.
A55: 7 | B55: Materials loading & unloading through staircase will be extra and shall be charged on basis of per floor.
A56: 8 | B56: The costing as projected here above shall change in events of any changes are brought on the design or the material makes and or the technical specifications.
A57: 9 | B57: Any changes in the supply cost due to impacts of COVID Pandemic the same may and could have impact accordingly.
A58: 10 | B58: All additional works out of the S.O.W as predefined shall be termed as additional/extra and charged accordingly.
A59: 11 | B59: The Developer / landlord to provide space for the AC Outdoor unit within a maximum of 20 R.M.Ts to maintain the heat load calculations, changes thereto may impact the cost.
A60: 12 | B60: Work Shall be carried out with strict COVID Guidelines and maintaining Safety First as Moto. All required compliances under COVID pandemic considered for.
... A64: 16 | B64: 28% GST on HVAC High side is applicable.
B65: Payment Terms.
A66: 1 | B66: 40% - Advance Payment (Non-recoverable)
A67: 2 | B67: 30% - on completion of Ceiling, wiring and Partition framework.
A68: 3 | B68: 25% - on Furniture delivery .
A69: 4 | B69: 5% - on completion of Project.

Sheet MAKE LIST
A1: LIST OF APPROVED MAKES FOR C&I WORK
A3: Sr. No. | B3: PRODUCT CATEGORIES | C3: APPROVED MAKE/BRAND
A4: 1 | B4: ADHESIVES FOR CARPENTARY WORKS
B5: Rubber based / Glue / Epoxy based adhesives | C5: Fevicol
A6: 2 | B6: ANCHORS & FASTENERS
B7: Mechanical / Chemical Anchors | C7: Hilti
B8: Screws | C8: GSK Or Netfold
A9: 3 | B9: CEILING / PARTITION
B10: Gypsum ceiling systems | C10: Gypsum India / USG Boral
B11: Gypsum Partition systems | C11: Gyproc Gypsum Board
B12: Fire retardant Partition systems | C12: Gyproc Gypsum Board
B13: Grid ceiling system | C13: 0.9NRC/0.7/ 0.5 NRC USG Boral
B14: Axiom Trim | C14: USG Boral
B15: Metal Plain Ceiling | C15: Techno ceiling
B16: Metal Perforated Ceiling | C16: Techno ceiling
B17: Sliding Folding partition systems | C17: OZONE / Doyal Asia
B18: Acoustic Baffle / Screen | C18: Techno ceiling/ Armstrong
A19: 4 | B19: BUILDING MATERIAL
B20: Gypsum Plaster | C20: Gyprock Elite
B21: Construction Blocks | C21: Siporex
B22: Ordinary Portland Cement | C22: ACC/Ultratech
B23: White Cement | C23: JK White
B24: Water Proofing | C24: PIDILITE
B25: Concealed Wall Angle guards | C25: USG Boral
A26: 5 | B26: CEILING/PARTITION ACCESSORIES & COMPONENTS
B27: Jointing Compound for Gypsum Partitions | C27: USG Boral
B28: Paper tapes for Gypsum Partitions | C28: USG Boral
B29: Dry wall top coat for Gypsum Partitions | C29: USG Boral
B30: G.I. Frames & Accessories for modular/false ceilings | C30: USG Boral
B31: Insulation | C31: Rock wool India
B32: Aluminium | C32: Jindal
A33: 6 | B33: FLOORINGS
B34: Entrance Mat/Anti Skid Strip | C34: 3M
B35: Vitrified Tile | C35: NITCO/SOMANY/Kajaria
B36: Marble | C36: Natural Stone
B37: Granite | C37: Natural Stone
B38: Vinyl floors | C38: NFL / LG/Amstrong
B39: Antistatic Vinyl floors | C39: NFL / LG/Amstrong
B40: Cavity floor systems | C40: Unitile / AET
B41: Self levelling Cementitious floors | C41: Ardex /
B42: False Flooring | C42: Flexi / Uni tiles
B43: 1-5 mm epoxy grouts joint fillers for hard floorings | C43: Roff
B44: Integral Water-proofing compound | C44: Pidilite
B45: Ceramic Tile | C45: NITCO/SOMANY/Kajaria
... B49: Plain Acoustic Panels | C49: Techno Acoustic
A50: 7 | B50: WALL FINISHINGS
B51: Ceramic Tile | C51: NITCO/SOMANY/Kajaria
B52: Vitrified Tile | C52: NITCO/SOMANY/Kajaria
B53: Wallpaper | C53: NFL / MARSHALS
B54: Writing lacquered glass | C54: Saint Gobain
B55: Plain Acoustic Panels | C55: Techno Acoustic
A56: 8 | B56: FILMS
B57: Vinyl films | C57: 3M / Crystal D
B58: Frosted films | C58: 3M / Crystal D
A59: 9 | B59: BLINDS & DRAPERY
B60: Roller blinds | C60: Vista / NFL
A61: 10 | B61: HARDWARE
B62: Door Hinges | C62: OZONE / Dorma
B63: Door closers | C63: OZONE / Dorma
B64: Floor springs | C64: OZONE / Dorma
B65: Door Locks | C65: OZONE / Dorma
B66: Pull Handles | C66: OZONE / Dorma
B67: Storage Hinges | C67: OZONE / Dorma
B68: Telescopic Drawer channels | C68: OZONE / Dorma
B69: Kitchen Drawer Baskets | C69: OZONE / Dorma
A70: 11 | B70: BOARDS
B71: Moisture resistant Gypsum Board | C71: Gypsum India /USG Boral
B72: Plain Gypsum Board | C72: Gypsum India /USG Boral
B73: Fire retardant Gypsum Board | C73: Gypsum India /USG Boral
B74: Cement Boards | C74: Everest
B75: Calcium Silicate Board | C75: Ramco- Hilux
B76: Pre- laminated particle board | C76: Archidply /Greenply
B77: Plain particle board | C77: Archidply /Greenply
B78: Marine Ply wood | C78: Archidply /Greenply
B79: Commercial Block board | C79: Archidply /Greenply
B80: Flush doors | C80: Archidply /Greenply
B81: Commercial Ply | C81: Archidply /Greenply
B82: Wooden Flooring | C82: Tarket
... B87: Solid Surface | C87: LG/ Merino
A88: 12 | B88: PAINTING & POLISH WORKS
B89: Emulsion paints | C89: Asian Paint
B90: Plastic paints | C90: Asian Paint
B91: Enamel paint | C91: Asian Paint
B92: Texture Paint
B93: Wall Putty | C93: Birla wallcare Putty
B94: Acrylic Paints | C94: Asian Paint
A95: 13 | B95: SKIRTING AND TRIMS
B96: Aluminium skirting | C96: Bottomline/ Frontline
B97: Aluminium Wall guards | C97: Bottomline/ Frontline,
B98: Aluminium duster Holder | C98: Bottomline/ Frontline,
A99: 14 | B99: FIRE RATED DOORS
B100: Metal fire door | C100: Suha / Shakti Hormann/IGI
A101: 15 | B101: MODULAR GLASS PARTITION AND DOORS
B102: Modular Glass Partition & Doors | C102: OZONE / Dorma
A103: 16 | B103: Carpet Flooring
B104: Carpet Flooring | C104: Interface / Instafloor / Equivalent
A105: 17 | B105: Loose furniture
B106: Loose furniture | C106: Nilkamal/ Estilo/ Amardeep / Equivalent.
A107: 18 | B107: Modular furniture
B108: Modular furniture | C108: HNI / Featherlite / Monsoon / Haworth
...

Sheet C&I-BOQ 
A1: C&I - BOQ
A2: SL.NO. | B2: ITEM | C2: DESCRIPTION | D2: Location | E2: Qty | F2: UNIT | G2: RATE | H2: AMOUNT | I2: Remark
A3: A | B3: Civil Works
A5: 1 | B5: DEMOLITION WORKS | C5: Dismantling and removal of existing partitions( gypsum or glass ), ceiling, flooring, wall finishes, furniture, and MEP items. Including protection of base structure, debris disposal, and handing over the site in clean bare shell condition ready for fit-out. | D5: Complete office | E5: 10750 | F5: Sqft | H5: =+$E5*G5 -> 0
A8: a | B8: REMOVAL OF DEBRIS | C8: All the items in Dismantling / Demolishing shall be cartig away the debris from the site and unloading at a approved location as per statutory rules and regulations.Care shall be taken not to damage other property while carrying dismantling and demolition otherwise cost of damage will be bourne by the contractor.All the safty precautions shall be taken while doing dismantling and demolition job. | D8: Complete office area | E8: 120 | F8: TRIP | H8: =+$E8*G8 -> 0
A10: 2 | B10: MASONRY & CIVIL WORKS
A12: a | B12: SIPHOREX BLOCK WALL CONSTRUCTION | C12: Providing and constructing 4/6/8 inch thick walls of siphorex block in cement mortar of ratio 1:4 and laying of rcc lintel after every 1.5 meter height in 1:2:4 concrete ratio (1unit-cement: 3unit- sand, 6unit- course aggregate); with 2no. Of 6mm diameter mild steel reinforcement & 2 no. Of hoop iron strips 25mm x 1.6mm, painted with anti-corrosive paint ,properly bent and bonded at the end ,inclusive of shuttering, scaffolding, hacking and proper curing etc complete. | D12: Front of Bain Marie, Hand wash & Dish wash Area
A13: i | B13: 6" THK | C13: Specs Same As above line Item a | E13: 819 | F13: Sqft | H13: =+$E13*G13 -> 0
A15: b | B15: CURVED SIPHOREX BLOCK WALL CONSTRUCTION - 6" THK | C15: Providing and constructing 6 inch thick walls of siphorex block in cement mortar of ratio 1:4 and laying of rcc lintel after every 1.5 meter height in 1:2:4 concrete ratio (1unit-cement: 3unit- sand, 6unit- course aggregate); with 2no. Of 6mm diameter mild steel reinforcement & 2 no. Of hoop iron strips 25mm x 1.6mm, painted with anti-corrosive paint ,properly bent and bonded at the end ,inclusive of shuttering, scaffolding, hacking and proper curing etc complete. | F15: Sqft | H15: =+$E15*G15 -> 0
A17: c | B17: LINTEL WORKS | C17: Providing and laying Lintel (4"/6"/8" x 8") (1:1-1/2:3) inclusive of all centering , shuttering , reinforcement and finishing work with complete required material to proper completion of work and to entire satisfaction of Architect. 4"/6"/8" thick | D17: Above door opening
A18: i | B18: 6" THK | C18: Specs Same As above line Item b | E18: 24 | F18: Rft | H18: =+$E18*G18 -> 0
A20: d | B20: PLASTERING | C20: Providing and applying in one coat, 12mm thick plaster on internal surface of RCC / brick/block walls in cement mortar 1:4, finished rough to take on POP punning. Rate shall include for scaffolding, making grooves, sills, pattas curing, surface preparation before the application of plaster, providing galvanized chicken mesh to a width of 150 mm at the junctions of masonry and concrete works including tying in position by using suitable nails / clamps / screws and as directed etc. complete at all levels. The contractor shall make good the grooves, pockets etc. after the scaffolding is removed. (Rate including chicken mesh jali.) | D20: New brick work area | E20: 1638 | F20: Sqft | H20: =+$E20*G20 -> 0
A22: e | B22: PCC FLOORING | C22: Providing & laying plain cement concrete 1:3:6 nominal mix (1 cement :3 coarse sand : 6 graded stone aggregate 25 mm nominal size) of approved quality with all lead & lift below/above the ground level as per drawing including the cost of cement, levelling of surface of concrete with al lead and lift, labour, material as per specifications and directed by Architect up to thickness of 75-100mm. | D22: Complete office area | E22: 11250 | F22: Sqft | H22: =+$E22*G22 -> 0
A24: f | B24: TRENCHING | C24: Trench cutting and Re-filling upto finish levelas required -REMOVING & FILLING OF EXISTING TRENCHES using base of compacted sand filling surfaced with 4" top P.C.C. surfacing ( as per instructions) including levelling & finishing the surface ready for receiving the new floor finish( 1 FEET WIDTH ) | D24: Complete office area | E24: 1850 | F24: Rft | H24: =+$E24*G24 -> 0
A26: g | B26: POP PUNNING | C26: Punning with POP 12mm thick layer of super fine plaster of paris applied over selected existing plastered surface on walls and columns finished smooth, surface prepared by hacking and applying a coat of cement slurry (Rate including Bondit chemical for surface) etc. complete | D26: Over existing walls & Columns were required | E26: 4576 | F26: Sqft | H26: =+$E26*G26 -> 0
A28: A | C28: Total Civil Works | H28: =SUM(H5:H27) -> 0
A30: B | B30: COUNTERS
A31: 1 | B31: PANTRY COUNTER | C31: Providing & fixing Under counter storages for pantry & basin as per drawing . The overall Structure made in 19mm thick BWP ply and approved colour Granite slab on top. Storages finished in 1 mm thick laminate from everywhere except outer back side of storages and also including all SS snap hinges, handles, locks, drawers with smoth closing chanels etc & all necessary hardware as required. PVC lipping on all edges with matching shade, including laminated skirting in approved shade with all hardware, magnetic catchers, tower bolts, etc complete as per detailed drawings. Rate excluding Granite stone work | D31: Pantry Area | E31: 62 | F31: Sqft | H31: =+$E31*G31 -> 0
A33: 1.1 | B33: WASH BASIN COUNTER | C33: Providing & fixing Counter ( 600deepx150-300 facia drop) with appropriate MS framework of counter top finished with BWP ply 19mm thk, including making holes for sink and dust bin including edge polishing around basin and edge moulding as per Drawing and approved sample of moulding. Counter made to recieve stone top/ facia (exclude stone finish / Corian Finish from the cost) | D33: Hand wash Area | E33: 109 | F33: Sqft | H33: =+$E33*G33 -> 0
C35: Counter Top
A36: a | C36: Granite in telephone black / Jet black | D36: Pantry & Wash Basin | E36: 193 | F36: Sqft | H36: =+$E36*G36 -> 0
A38: B | C38: Total for COUNTER Works | H38: =SUM(H31:H37) -> 0
A40: C | B40: FLOORING WORK
A42: 1 | B42: VITRIFIED FLOORING ( 4FT X 2FT) | C42: Providing and Laying Vitrified tiles (1200x600x10mm thk) flooring. Flooring to be laid in cement mortar 1:6 over a cement mortar bedding of avg. thickness upto 25mm as required to level and slopes required, rate included latecrete chemical. The flooring to be done as per design and pattern shown on the drawings inclusive of all joints to be grouted with matching color grout of BAL adhesive or equivalent.All work sites are required to be maintained in a debris-free condition and the Employers/Architects reserve the right to maintain the same, as so required, at the sole risk/cost of the concerned agency. cost to include covering entire flooring with good quality plastic / POP for as many time as required for protection of laid material above and removal before final cleaning handover. Basic Rate - 150/sqft | F42: Sqft | H42: =+$E42*G42 -> 0
A44: 2 | B44: Anti-Skid Handmade Tiles | C44: Providing and laying anti-skid handmade tiles of approved size, color, pattern, and thickness, having natural textured finish for slip resistance and slight variation in tone for a rustic appearance. Tiles to be laid on cement mortar bed of 35–45 mm thickness in 1:6 (cement:sand) ratio, with joints filled using matching grout. Surface to be properly leveled, aligned, and free from lippage. Including curing, cleaning, and all materials, labour, and tools required for complete installation as per approved samples and drawings.. cost to include covering entire flooring with good quality plastic / POP for as many time as required for protection of laid material above and removal before final cleaning handover. Basic Rate - 250/sqft | D44: Caféteria, Store, Hand wash & Dish Wash Area | E44: 5160 | F44: Sqft | H44: =+$E44*G44 -> 0
A46: 3 | B46: Decorative Handmade Tiles | C46: Providing and laying decorative handmade tiles of approved size, color, pattern, and thickness, having natural textured finish for slip resistance and slight variation in tone for a rustic appearance. Tiles to be laid on cement mortar bed of 35–45 mm thickness in 1:6 (cement:sand) ratio, with joints filled using matching grout. Surface to be properly leveled, aligned, and free from lippage. Including curing, cleaning, and all materials, labour, and tools required for complete installation as per approved samples and drawings.. cost to include covering entire flooring with good quality plastic / POP for as many time as required for protection of laid material above and removal before final cleaning handover. Basic Rate - 325/sqft | D46: High Seating Area, Bain Marie area & Pantry Area | E46: 3235 | F46: Sqft | H46: =+$E46*G46 -> 0
A48: 4 | B48: PLYWOOD RAISED FLOORING (150mm) | C48: Providing and Fixing PLYWOOD RAISED FLOORING (150MM) made out of MS section 50x50mm - Framework covered with 25mm thk block board finished with approved laminated wooden flooring as shown in details. Quoted rate includes all hardware, MS framing,block board, Laminated wooden flooring,adhesive,corner profile,skirting, covering with bubble sheet till handing over. etc. Mode of measurements; actual plan area to be measured & paid in this item,no additional cost payable for verticals - Finishwith 1mm thk laminate | D48: Misc. | E48: 860 | F48: Sqft | H48: =+$E48*G48 -> 0
A50: 5 | B50: LAMINATED WOODEN FLOORING | C50: Providing and fixing Laminated wooden flooring 10mm thk with underlay plastic and 4mm foam sheet laying. | D50: Café | E50: 618 | F50: Sqft | H50: =+$E50*G50 -> 0
A52: 6 | B52: ANTISTATIC FALSE FLOORING | C52: Providing & fixing stringer based raised access floor of approved make metal cladded system finished in Anti-Static laminate of approved shade consisting of : Panel Construction: Panels of size 600 mm X 600 mm are manufactured from pressed form corrosion resistant galvanized steel. The above hollow panel shall have an infill of light weight cementatious material. The entire panel shall be coated with epoxy coating on the exposed surface. Pedestal construction shall be all steel construction, zinc plated and consisting of anti vibration head cap with cruciform up stands and four panel locating studs, positively clipped to the steel top plate . Pedestal shall be screwed to floor. Uniformly distributed load shall be 12 kN/m2 Concentrate point load : 4.0 kN over 25 sqmm. Floor void should be 300 mm minimum from underside of raised floor pan to finish slab. Provision should made for satisfactory earthing for all floor tiles. ( Height-300mm) | D52: Hub Room | E52: 150 | F52: Sqft | H52: =+$E52*G52 -> 0
A54: 7 | B54: TRANSITION PROFILE | C54: Fabricating and fixing of SS transition profile at the junction of hard/soft flooring as per Architect's approval and design - Bottomline make | D54: Joint of hard and carpet flooring | E54: 55 | F54: RFt | H54: =+$E54*G54 -> 0
A56: 8 | B56: SKIRTING & DADO
A57: a | B57: ALUMINUM SKIRTING | C57: Providing and fixing Aluminum skirting of 50 mm of approved make with rubber beading fixed on screwing slot on partitions and walls etc. all complete as per architects instructions. There shall be 12 mm thk commercial Ply backing as approved by the architect. The rate to be inclusive of all accessories required for fixing of skirting complete. | D57: Complete office area | E57: 2110 | F57: Rft | H57: =+$E57*G57 -> 0
A59: b | B59: VITRIFIED TILE DADO CLADDING | C59: Providing and laying in position as per approved sample porcelain /ceramic /vitreous tiles (without warpage of approved make, shade, shape and colour) of size 600x300mm on walls laid on 12 mm thick cement mortar 1:3 ( 1 cement : 3 course sand ) the rate shall be inclusive of necessary preparation, 2mm spacer groove matching with floor tiles , cleaning, grouting open joints with epoxy grouts bal grout etc. complete as per drawing and Designer Instruction. | D59: Pantry, Hand Wash, Dish Wash | E59: 720 | F59: Sqft | H59: =+$E59*G59 -> 0
A61: c | B61: VIRTICAL MOSIAC TILE CLADDING | C61: Providing and fixing Kit Kat (finger mosaic) tiles of approved make, factory-mounted on mesh sheets of size 300×300 mm (or equivalent), comprising strips approx. 20×145 mm, thickness 6–9 mm, in required color, shade and finish, fixed with suitable tile adhesive, including cutting, grouting, finishing, and all complete. | D61: Café Columns | E61: 394 | F61: Sqft | H61: =+$E61*G61 -> 0
A63: d | B63: ALUMINIUM SECTIONS U/H/L/T/Flat PROFILE | C63: Supply & Installation of approved size & shape of aluminium transition section in black colour at the top & bottom of the Writing board & Fabric paneling as per the detail drawings complete and approval of Designer/PM (Sizes varies from 6mm to 50mm) | D63: complete office area | E63: 1540 | F63: Rft | H63: =+$E63*G63 -> 0
A65: C | C65: Total Flooring Works | H65: =SUM(H41:H64) -> 0
A67: D | B67: CEILING WORKS
A68: 1 | B68: GYPSUM CEILING | C68: Providing and fixing in position multi level GYPSUM board false-ceiling suspended on G.I. frame work in design as shown in the drawing. The G.I. frame work consist of Perimeter channel of size 27mm x 0.5mm. Intermediate channel of size 45mm x 0.5mm thick. Ceiling section of 0.5mm thickness. 12.5mm thick tapered edge gypsum plaster board fixed to ceiling channel with 25mm dry wall screws at 230mm centers Jointed and finished with requisite filler, paper tape, finisher and primer suitable for Gypsum plaster boards. Rate to include making necessary cut-outs/openings for light fittings. This item includes all vertical drops, niches in ceiling etc. Gypsum board to be of Boral / India Gypsum. | D68: Café, Cabins, Conference Room & MD cabin | E68: 6062 | F68: Sqft | H68: =+$E68*G68 -> 0
A70: 2 | B70: COVE CEILING IN GYPSUM | C70: Providing and Fixing Gypsum board cove ceiling as per detail drawing and direction of the architects. With provision and cutouts for fixing light fittings, cable, conduits etc running internally, AC grill fixing etc. 100mm front facia and 200mm back facia Mode of measurements:- Running meter Length, No wastage to be added | D70: MD Cabin, All Cabins & Conference Room | E70: 435 | F70: Rft | H70: =+$E70*G70 -> 0
A72: 3 | B72: MODULAR FALSE CEILING (600MM X 600MM) 0.5 NRC | C72: Providing & Fixing of Mineral Fibre Acoustical Suspended Ceiling System with Bevelled Tegular Edge Tiles With 15mm Silhouette GRID. The tiles should have Humidity Resistance (RH) of 99%, Light Reflectance <85%, Thermal Conductivity k = 0.052 - 0.057 w/m K, Colour White, Fire Performance UK Class 0 / Class 1 (BS 476 pt - 6 &7) in module size as specified by the architects , suitable for Green Building application, with Recycled content of 63%. 0.5 NRC of Tile. The tile shall be laid on Silhouette profile grid system with 15mm white flanges incorporating a 6mm central reveal in white/black colour and with a web height of 45mm and a load carrying capacity of minimum 15.68 Kgs/M2 & pull out strength of 100Kgs. Silhouette, Main Runners & Cross Tees to have mitred ends & “birdsmouth” notches to provide mitred cruciform junctions. The T Sections have a Galvanizing of 90 grams per M2 and need to be installed with Proprietary Suspension system. The Tile & Grid system used together should carry a 10 year warranty. | D72: 5 pax, 4 pax, 8 pax, Store, Above Bain Marie, Hand Wash & Dish Wash | E72: 2363 | F72: Sqft | H72: =+$E72*G72 -> 0
A74: 4 | B74: ACOUSTIC FEATURE CEILING | C74: Providing and installing suspended acoustic feature ceiling in curved / concentric circular design using approved acoustic panels on metal framework, including cutting, shaping, supports, and integration of lighting fixtures, complete as per drawings and specifications, with uniform spacing of 150–300 mm between adjacent circular bands or as approved. 9mm thick acoustic panel used. | D74: Discussion Area | E74: 750 | F74: Sqft | H74: =+$E74*G74 -> 0
A76: 5 | B76: CNC CUT METAL FEATURE CEILING | C76: Providing, fabricating, and installing suspended CNC-cut metal feature ceiling panels of approved pattern and finish, formed in curved / free-flowing shapes with a vertical drop of 450 mm, using perforated metal sheets fixed to a concealed MS/GI framework. The work includes cutting, bending, edge finishing, supports, hangers, and integration with lighting services, complete as per drawings and specifications. | D76: Waiting Lounge | E76: 650 | F76: Sqft | H76: =+$E76*G76 -> 0
A78: 6 | B78: GYPSUM DESIGNER CEILING | C78: Providing and installing suspended feature ceiling in curved / organic shape using 12.5 mm thick gypsum board fixed on a concealed GI metal framework, including forming of central circular cut-out, smooth curves, edge finishing, joint treatment, and preparation for paint, with a vertical drop/depth of 300–450 mm from the structural slab or as per drawings. The work includes supports, hangers, cutting, shaping, and integration of lighting fixtures, complete as per specifications. | D78: Workstation area | E78: 670 | F78: Sqft | H78: =+$E78*G78 -> 0
A80: 7 | B80: MDF FOR DECORATIVE LIGHTS | C80: MDF with Paint support for Decorative Light Fixtures and Speakers only as per Project Manager Instructions. Rate shall be inclusive of Approved Paint and necessary supports from ceiling & Provisions and cutout for lights U Type Size - 100 mm x 100 mm Mode of Measurement: Running meter measured for payment. | D80: Cabins & MD Cabin | E80: 340 | F80: Rft | H80: =+$E80*G80 -> 0
A82: 8 | B82: DECORATIVE WOODEN CEILING | C82: Providing and fixing Size - 75mm x 150mm wooden battens with approved Venner finish ceiling made of including framing, all fixing hardware, accessories, making cove, cut out for light fixtures and any other incidentals which may require to secure to false ceiling and to accomplish the work in all respect as per detail drawings and as directed & approved by architect. Rate quoted to include provision of lights and all cut-outs required for light fixtures and other services cut-outs complete as directed by Architect. Mode of Measurement: Running meter area to be measured for payment. Size - 75 mm x 150mm | D82: Conference Room | E82: 150 | F82: Rft | H82: =+$E82*G82 -> 0
A84: 9 | B84: METAL BAFFLE CEILING IN WOODEN FINISH | C84: Supplying & Installation of Aluminium Baffle ceilings of size 100mm x 50mm x 0.5mm thick @ 150mm clear spacing as per drawing. Rate shall include the cost of proprietary suspension system, Connectors, End caps, Hanging brackets, threaded rods etc. Supply & installation to be done as per manufacturer's specification. Finish:Wooden finish of approved shade. Necessary supports to be given from true ceiling. To have necessary powder coated MS box section / threaded rod support to be taken from true ceiling as per details. Cost shall include the necessary scaffolding Mode of Measurement : Measurement to be along the horizontal surface or plan area of the ceiling. Supply and installation of approved equivalent make baffle ceiling of size 100 x 50 mm placed at 150 mm center to center of the following components and specifications : 1.Carrier made of 0.50 mm GI , powder coated to matching baffle color or black as directed by the engineer / architect .Baffle to have arrangement to fix, hang and lock the baffles of required sizes and at required intervals . The size of punched carrier would be 35x20x35mm bent channel with holes for suspension and fixing secondary channel . 2.The baffles would be made of Aluminium profiles of 0.50 mm TCT, U shaped bent f 100 mm height and 50 mm bottom width. The top edge will have a flange of 4 mm to fix in the carrier profile. These profiles would be polyester powder coated 60 micron to the approved shade . baffel are Armstrong make. 3.Suspension ..The carriers would be placed at every 1200 mm ( maximum ) and suspended by means of a secondary angle / channel fixed to the carrier at every 900 to 1200 mm and this secondary member in turn would be suspended by means of a 3 mm wire and level adjustment butterfly clip...fixed to the slab by means of a 6 mm diam., dash fastener . "The baffle as well as the runner will have their respective connector at their ends to attach to the next profile respectively . " quoted rate includes fixing of required as a frame/supports etc | D84: Misc. | E84: 710 | F84: Sqft | H84: =+$E84*G84 -> 0
A86: 10 | B86: LAMINATED CEILING | C86: Providing and Fixing Wooden ceiling made out of 2" X 1 /2"sal wood frame work with c/c 600 mm distance cladded with 19 mm thk commercial ply from one sides, finish in 1.0 mm thk Laminate to all exposed surface with provision for fixing light fixtures. ac grills, spakers , projectors etc. as per detailed drawing given by the Architect. | D86: Misc. | E86: 555 | F86: Sqft | H86: =+$E86*G86 -> 0
A88: 11 | B88: WOODEN FRAME FOR CASSETE AC. | C88: Providing & fixing of framing in 19mm thk ply with wooden support from main ceiling for AC cassettes units. All exposed frame work to be finished in laminate in level with the gypsum / modular tile ceiling. (Avg size of wooden framing: 1200mm x 1200mm) | D88: Complete office | E88: 19 | F88: No's | H88: =+$E88*G88 -> 0
A90: 12 | B90: ACOUSTIC DESIGNER CEILING | C90: Providing & Fixing in position, DESIGNER Acoustical Ceiling made out of sandwich of 9mm thk Accoustic panels with over all 18mm thick as per approved design and details with SS wire hanger fitting adustable. Shapes are as per veiws. | D90: 8 pax & Café | E90: 618 | F90: Sqft | H90: =+$E90*G90 -> 0
... A102: 18 | B102: READY MADE TYPE TRAP DOORS. | C102: Providing and fixing Ready made type Access Panel of Horizon make Acess panel or approved equivalent make Sizes: 550mm x 550mm Material & Installing procedure shall be as per Manufacturers instructions manual. | D102: Complete office area | E102: 40 | F102: No's | H102: =+$E102*G102 -> 0
A104: D | C104: Total Ceiling Works | H104: =SUM(H68:H103) -> 0
A106: E | B106: PARTITION WORKS
A108: 1 | B108: FULL GLAZED PARTITIONS-CLEAR 10 MM GLASS - 2700mm High | C108: Supply and Installation of Modular Aluminium single glazed partitioning frame (75mm x 25mm) as top channel, wall starter, \(45mm x 25mm)bottom channel. Partition frame Dimension – 45mm x 25mm. Finish – Anodized Silver finish OR Midnight black. Glass to glass butt joint with I,L,T joint respective finish.Glass type- 10mm thickness toughened glass. Acoustic performance STC 28 to 32 dB. Make : Dorma / Geze | D108: Conference room, MD Cabin, Vendor meeting & Cabin 02 | E108: 565 | F108: Sqft | H108: =+$E108*G108 -> 0
A110: 2 | B110: CURVED GLAZED PARTITION - CLEAR 10 MM GLASS | C110: Providing and fixing curved toughened glass partition using 10 mm thick clear glass, machine-polished and bent to required radius, including aluminium framework, floor & ceiling channels, SS fittings (patch fittings, clamps, hinges, handles, etc.), gaskets and silicone sealing, complete with all materials, labor, fixing, alignment, and finishing as per approved drawings and specifications; measured in sqm. | D110: 5 pax, 8 pax, cabins & 4 pax | E110: 397 | F110: Sqft | H110: =+$E110*G110 -> 0
A112: 3 | B112: 100mm THICK DOUBLE SKIN GYPSUM BOARD FINISH PARTITIONS WITH GI FRAMEWORK AND INFILL OF 50MM THICK ROCKWOOL. | C112: Providing and fixing of GI Frame 48 mm C Stud (0.5 mm thk having one flange of 34mm and another flange of 36mm made of GI Steel) placed at 610 mm centre to centre in 50 mm Floor and ceiling Channel (0.5 mm thk have equal flanges of 32mm made of GI steel), which is anchored to the floor and ceiling using suitable anchor fasteners at 600 c/c in centre line. Stud and floor channel are crimped together using crimping tool. Framework to be secured to wall surface/column surface closely structural support using screw. rawl plug as per details. channel of 48 mm width (0.5 mm thk having two flanges of 40 mm each) has to be provided at the horizontal joints of the two boards screw fixed to the studs using metal to metal flat head screws.All steel sections to be marked with gypsteel which is a registered trademark of bpb igl and hologram. At all locations where services are penetrating the partition above false ceiling to have additional GI frame work around the duct/cable tray/pipe and the gaps between the frame work and service to be filled with silicon sealant as directed.Should make provision for all electrical/networking boxes and to provide 30mm dia cut-outs as required. Electrical/Network boxes /other services to be provided at desired height and location as indicated. Rate including Gypshera make GI Chanel system. | D112: 5 pax, 8 pax, Cabins, Coference Room & store room | E112: 4370 | F112: Sqft | H112: =+$E112*G112 -> 0
C113: Rate including 50mm thick rock wool of approved make of density 48kg/m³ , suitably affixed to partition framework using Gyproc Holding Clips, where necessary GI binding wire / duct tape to be used.
C114: Rate including Two layers of tapered edge 2X12.5 mm thk Gypsum Board is screw fixed with drywall screws of 25mm and 35mm at 600 mm at centre and 300 mm at periphery of wall to either side of GI framework on both sides. The boards are to be fixed vertically to the framework with joints staggered to avoid leakage through joints. Finally square and tapered edges of the boards are to be joined and finished so as to have a flush look which includes filling and finishing with Pro fill Jointing Compound, Joint Paper tape or Fibre Tape (as per recommended practices of Saint- Gobain Gyproc India).All exposed edges / corners/ grooves to have proprietary corner / edge bead sections/channels as per Architect's instructions.
A116: 4 | B116: SLIDING FOLDING PARTITION SOLID - STC -45DB (Modwall/Equivalent make) | C116: Providing & fixing Sliding folding partition finished with both side laminate/Accoustic panel/Back painted glass/ Fabric panel/ mdf painted panel finish as shown in details Overhead Track System - Specifically casted hardwearing fire resistant heavy duty steel or alumimium track to suit the necessary stacking requirement. Intersection design shall prevent carrier wheels from dropping into track slot. Heavy duty multi-directional roller carrier to facilitate excellent panel movement through curved and straight track section. "Panel Configuration - Panels are custom built to suit the specified requirement. Each panel thickness is 100mm maximum; width is 1200mm respectively, which shall conform to the manufacturer's standard. Individual panel is reinforced with welded steel frame and both sides of the outer surface are mounted with 15mm MDF. Internal structure is built with steel mechanism incorporating superior performance Top and Bottom retractable sound seals device. Internal space/ cavities are filled with not less than 80km M³ thick rock wool. " "Acoustic Sound Seal System - With built in superior retractable Top and Bottom seals consist of extruded aluminum channel anodized with rubber seal laminated and is operated by handle via jacking lock system with spring loaded telescoping rods. Vertical seals of each panel are comprised of deep tongue and grove type extruded aluminum laminated with rubber seal. " No Bottom track is required in our Acoustic System Top and Bottom seals do not contact the track and floor during panel movement. When sound seals are compressed, it gives up to 2000 Newtons per panel pressure and position the panel in solid stability with Top and Bottom seals compressed against track and floor with tight acoustical seals including adjustable telescopic panel "Panel Surface - Shall be bare finish 15mm MDF. However, it can accommodate any decorative designs like Accoustic panels, Backpainted glass, Laminate surface, wall fabrics, painting and etc (by others). " Acoustic Sound Rating of operable wall partition with high acoustical performance should provide sound attenuation of 46Db to 52DB average Weight - of each panel shall be average 4 kg per sq.ft depending on panel size. "Application and Operation - shall consist of a series of individual flat wall panels manually operated and permits stacking flexibility at center or remote side stacking. " Quoted rate includes cost of above ceiling frame,supporting structure,laminate/Accoustic panel/Back painted glass/ Fabric panel/ mdf painted panel finish panel from both sides, etc, Mode of measurements; only one side actual visible area to be measured & paid in this item, | D116: Misc. | E116: 255 | F116: Sqft | H116: =+$E116*G116 -> 0
A118: =A116+1 -> 5 | B118: DESIGNER PARTITION | C118: Providing and fixing 25mmx25mmx2mm MS powder quoated section framework as per details drawing and GI wire Mesh fixing as per the veiws with black paint Finish . Above ceiling partition is including in the quoted rate. Mode of measurement is only front elevation, one side only.Powder coated should be 40 to 50 Microns. | D118: Disussion Area & Pantry Area | E118: 312 | F118: Sqft | H118: =+$E118*G118 -> 0
A120: 6 | B120: CURVED GYPSUM PARTITION | C120: Frame: Providing and fixing of Gypsum Partition framing consist of 25mm x 50mm x 1.2mm thick extruded aluminium box section framework at spacing not exceeding 600mm both ways as per details. Aluminum box sections to be secured to each other with 25 x 25 mm aluminum cleats screwed with sheet metal screws Framework to be secured to wall surface/column surface using wood screw with wooden/pvc rawel plug as per details.Please note that horizontal frame members at floor level, skirting level and false ceiling level to be formed of 50mm x 50mm x 1.2mm aluminum extruded box section as per details. Infill: Providing & fixing Acoustic insulation to G.I. frame partition of 50mm thick Polyster Wool of approved make of density 48kg/m³ affixed to partition framework using where necessary GI binding wire, duct tape as indicated in the drawing. Cladding: P/F Skin type of single layers of 12.5 mm thk tapered edge gypsum board (IS-2095/1982) in line and level screw fixed with 25mm drywall screws @ 300mm c/c with staggered joints to avoid through joints and finished with proprietory supplied jointing tape and compound as per manufacturer's specification. Joints to be sand papered to achieve a smooth and seamless finish. Cost of skinning to include making of necessary cutouts for Electrical / AC ducting other conduiting and outlets. MOM: Visible Length x Height | D120: Above curver glass partition & Discussion Area | E120: 723 | F120: Sqft | H120: =+$E120*G120 -> 0
A122: E | C122: Total of Partition Works | H122: =SUM(H107:H121) -> 0
A124: F | B124: DOORS
A126: 2 | B126: SINGLE LEAF METAL 2 HR FIRE RATED DOOR (1050X2700) | C126: Providing and fixing in position Fire Rated Metal door with pressed steel frame and shutter as per manufacturer’s details and as mentioned in the drawings including fixing ironmongery etc ofapproved make make. This includes Fire rated vision panel of 1 ft x 1ft providing and fixing brush steel finished iron mongery like Ball bearing Hinges, Mortise Locks, Vedic Handles, Push Plates, Bolts, Door Closer etc. Vedic make as indicated in the detail drawings and all surfaces of doors shall be finished with 2 coats of Fire rating paint over a coat of primer to achieve the fire rating as indicated in the detail drawings. | D126: Hub Room | E126: 1 | F126: nos | H126: =+$E126*G126 -> 0
C127: The door finished Fire retardant polish, steel pressed shutter with 2 Hour Fire rating of Single Shutter and vision panel. Complete as per design and instructions of the Designers.
C128: Complete as per instruction of the Designer's . Vendor need to provide shope drawing before procuring the material
A130: 3 | B130: SINGLE LEAF GLAZED STYLE DOOR 900X2700MM | C130: Shutter : 12mm thk Toughened Glass Frame : 45 x 25mm black/silver powder coated aluminium door frame with data patti. Door Handle :H-type handle of 300*25mm 1-set considered. Door Closer: Door closure with hold open TS72 Lockset : Dead-lock with both sides key considered Hinges:4No's SS ball bearing Hinges Make :- Dorma Rate to include necessary ply support finished with approved paint at the junction of false ceiling / solid partition as per detail. | D130: All Enclosed Cabins | E130: 10 | F130: nos | H130: =+$E130*G130 -> 0
A132: 6 | B132: DOUBLE LEAF GLAZED STYLE DOOR (1800x2700MM) | C132: Shutter : 12mm thk Toughened Glass - double leaf Frame : 45 x 25mm black/silver powder coated aluminium door frame with data patti. Door Handle :H-type handle of 300*25mm 2-set considered. Door Closer: Door closure with hold open TS72 - 2 set. Lockset : Dead-lock with both sides key considered Hinges:4No's SS ball bearing Hinges for each shutter. Make :- Dorma Rate to include necessary ply support finished with approved paint at the junction of false ceiling / solid partition as per detail. | D132: Passage Area | E132: 1 | F132: nos | H132: =+$E132*G132 -> 0
A134: 7 | B134: SINGLE LEAF SOLID CORE FLUSH DOOR - without VISION PANEL -SIZE 1050x2700mm | C134: Shutter : 40mm thk Solid core flush door with vision panel and shutter to be cladded with 1mm thk Laminate on both sides Frame : 105 x 25mm black/silver powder coated aluminium door frame with data patti. Door Handle :H-type handle of 300*25mm 1-set considered. Door Closer: Door closure with hold open TS72 Lockset : Dead-lock with both sides key considered Hinges:4No's SS ball bearing Hinges Make :- Dorma Rate to include necessary ply support finished with approved paint at the junction of false ceiling / solid partition as per detail. | D134: Dish Wash & Store Room | E134: 2 | F134: nos | H134: =+$E134*G134 -> 0
A136: F | C136: Total of Doors /Windows | H136: =SUM(H125:H135) -> 0
A138: G | B138: CARPENTRY WORKS
A140: 1 | B140: POD SEATING 2 SEATER WITH CUSIONING AND WORKING TOP | C140: Providing & fixing of 2 seater pod seating with cusioning and working Top made in 18mm thk comm ply and finished in 10mm thk approved accoustic paneling laminate finish working top and cusion for seating as per the finalized design and veiws. Size as per drwaings. | D140: Café | E140: 2 | F140: No's | H140: =+$E140*G140 -> 0
A142: 2 | B142: POD SEATING 4 SEATER WITH CUSIONING AND WORKING TOP | C142: Providing & fixing of 4 seater pod seating with cusioning and working Top made in 18mm thk comm ply and finished in 10mm thk approved accoustic paneling laminate finish working top and cusion for seating as per the finalized design and veiws. Size as per drwaings. (Rate including factory made upolstery Fabric Finishes) | D142: Café | E142: 2 | F142: No's | H142: =+$E142*G142 -> 0
A144: 3 | B144: FULL HEIGHT STORAGES | C144: Providing and fixing full height storages as per details, fabricated out of 19mm commercial ply finished in 1.0mm thk approved laminate externally & internally.Average depth of the storage will be 450 MM. Shelves also to be made of 19mm thk. commercial ply & finished inlaminate. All exposed edges of ply shall be covered with lipping Patti of laminate of required size. Cost of the storage units to be inclusive of pre-approved handles, SS hinges, tower bolts, ball catches, locks and all necessary hardware all complete as per drawing and detail and as per the instructions of the Designer. | D144: Pantry Area | E144: 257 | F144: Sqft | H144: =+$E144*G144 -> 0
A146: 4 | B146: LOW HEIGHT STORAGES | C146: Providing and fixing Low height storages as per details, fabricated out of 19mm commercial ply finished in 1.0mm thk approved laminate externally & internally.Average depth of the storage will be 400MM. Shelves also to be made of 19mm thk. commercial ply & finished inlaminate. All exposed edges of ply shall be covered with lipping Patti of laminate of required size. Cost of the storage units to be inclusive of pre-approved handles, SS hinges, tower bolts, ball catches, locks and all necessary hardware all complete as per drawing and detail and as per the instructions of the Designer. Rate should also include top with planters. | D146: MD Cabin & Workstation area | E146: 269 | F146: Sqft | H146: =+$E146*G146 -> 0
A148: =A146+1 -> 5 | B148: OVER HEAD STORAGE | C148: Providing and fixing over head storages of 750 mm height as per details, fabricated out of 19mm commercial ply finished in 1.0mm thk approved laminate externally & internally.Average depth of the storage will be 400 MM. Shelves also to be made of 19mm thk. commercial ply & finished inlaminate. All exposed edges of ply shall be covered with lipping Patti of laminate of required size. Cost of the storage units to be inclusive of pre-approved handles, SS hinges, tower bolts, ball catches, locks and all necessary hardware all complete as per drawing and detail and as per the instructions of the Designer. | D148: Pantry Area | E148: 50 | F148: Sqft | H148: =+$E148*G148 -> 0
A150: 6 | B150: OPEN SHELF STORAGE | C150: Providing and fixing open shelf storage made of 19 mm thick plywood, finished with 1.0 mm laminate on all exposed surfaces, including edge banding, necessary supports, hardware, and complete installation as per approved design. | D150: MD Cabins & Cabins | E150: 298 | F150: Sqft | H150: =+$E150*G150 -> 0
A152: =+A150+1 -> 7 | B152: CIRCULAR SEATING | C152: Providing & fixing of circular seating made in 18mm thk comm ply and finished in 1mm laminate as per the finalized design. The seating to have cushioning on top and Back up to 1200mm high etc. as per design and details. | D152: Misc. | E152: 15 | F152: Rft | H152: =+$E152*G152 -> 0
A154: =A152+1 -> 8 | B154: LINEAR SEATING WITH CUSHIONING BACK AND SEAT | C154: Providing & fixing of Linear seating made in 18mm thk comm ply and finished in 1mm laminate as per the finalized design. The seating to have cushioning on top and back as per design and details..(Rate including factory made upolstery Fabric Finishes) | D154: Waiting Lounge | E154: 38 | F154: Rft. | H154: =+$E154*G154 -> 0
A156: =A154+1 -> 9 | B156: CURVE SEATING WITH BACK AND SEAT CUSHIONING UP TO HIGH 1200MM. | C156: Providing & fixing of curve seating made in 18mm thk comm ply and finished in 1mm laminate as per the finalized design. The seating to have cushioning on top and Back up to 1200mm high etc. as per design and details. Quoted Rates including the rate of Planter box.(Rate including factory made upolstery Fabric Finishes) | D156: Discussion Area & Café | E156: 67 | F156: Rft | H156: =+$E156*G156 -> 0
A158: G | C158: Total of Carpentry Works | H158: =SUM(H139:H157) -> 0
A160: H | B160: PANELLING & BOXING
A161: 1 | B161: PLYWOOD PANELING. | C161: Supplying and fixing 12 mm thick plywood paneling over existing galvanized iron (GI) metal framework, properly prepared and leveled for mounting TV. The plywood shall be of approved quality, smooth-finished, and free from defects. The work includes cutting, shaping, and securely fixing the plywood panels to the GI frame with appropriate fasteners and adhesives to ensure a rigid and stable surface capable of supporting TV weight. | D161: 5 pax, 4 pax & Conference Room | E161: 163 | F161: Sqft | H161: =+$E161*G161 -> 0
A163: 2 | B163: VERTICAL GYPSUM BOXING | C163: Providing and installing vertical gypsum board boxing over the existing gypsum false ceiling using 12.5 mm thick gypsum boards fixed on a concealed GI metal framework. The work includes fabrication of vertical GI studs and channels, cutting and fixing of gypsum boards, joint treatment with tape and compound, sanding, and preparation for painting. The boxing shall be true to line, rigid, and finished smooth as per drawings and specifications. All necessary supports, hangers, fasteners, and accessories for a complete and durable installation are included. | D163: Above Café & Workstation ceiling & Glazing side | E163: 3964 | F163: Sqft | H163: =+$E163*G163 -> 0
A165: 3 | B165: FULTED PANEL PANELING | C165: Providing and fixing of wooden slats/ Fluted panelling formed of HDF panels wall panel of size 125mm width, 18mm thick & 1800 mm height as per details. To have necessary cutout provisions for electrical switch, hardwares etc. | D165: Bain Marie front wall | E165: 595 | F165: Sqft | H165: =+$E165*G165 -> 0
A167: 4 | B167: PLY BOXING WITH LAMINATE FINISH | C167: Providing and fixing ply boxing with laminate finish made over existing GI framework. The GI frame shall comprise vertical and horizontal members at 600 mm c/c. The framework shall be cladded with 12 mm thick commercial plywood and finished with 1 mm thick approved shade and colour laminate as per detail drawings. Measurement for payment shall be only for elevation area. | D167: Cabins, 4 pax, Conference Room & 5 pax | E167: 2648 | F167: Sqft | H167: =+$E167*G167 -> 0
A169: 5 | B169: GYPSUM BOXING WITH COVE FOR LIGHTS. | C169: Providing and fixing Gypsum boxing with cove for lights made out of GI section section of size 48mm X 48 mm X 0.5mm comprising of vertical and horizontal at 600 mm c / c. Frame work cladded with 12mm thk Gypsum board as per detail drawing. mode of measurement only elevation area should be measured and paid. | D169: Waiting Lounge | E169: 253 | F169: Sqft | H169: =+$E169*G169 -> 0
A171: 6 | B171: PELMETS-TYPE-A . (FOR ROLLER BLINDS) | C171: Providing and fixing of Pelmet for vertical blinds formed out of 19mm thk ply with 1mm thk approved laminate for top and 12mm for sides with laminate finish. The pelmet shall be in 'L' shape and shall be 250mm + 150mm in size.The rate quoted shall be including cost of wooden support, Pelmet to the fixed to the ceiling with salwood support etc., Complete as per drawing. | D171: Glazing side area | E171: 850 | F171: Rft | H171: =+$E171*G171 -> 0
A173: 7 | B173: BACK PAINTED GLASS PANELING | C173: Providing and fixing 8mm thick lacquered glass in panel sizes as indicated with all edges machine polished and the panel fitted on to wall /partition, glass to be fixed on to the existing Plywood with compatible neutral cure silicone sealant and 3m tape( GE Winsil/Dow corning), in workmanlike manner, as per design and detail. glass should be saint gobain make | D173: Cabins & Conference Room | E173: 455 | F173: Sqft | H173: =+$E173*G173 -> 0
A175: 8 | B175: ACOSTICAL PANELLING - GROOVED | C175: Providing and installing Acoustical panels of 12mm thick V groove of approved make with the details mentioned below on the existing surface, 12mm ridge(groove) & to be fixed with necessary adhesives on existing partition / wall surfaces as per details and LOW VOC. Cost to include antitermite treatment / borer treatment for salwood / plywoodwith adhesive .Composition : 100% PET (50%-60% Recycled) Dimensions : 1220x2440mm (+/-2mm)Thickness :(+/-7%)12mm, Sound Absorption : 0.35-0.85 NRC (Subject tomounting conditions)based on the thickness (without airgap)- as per the design requirements of Architect . Generic Technical Specifications of Acoustical panels of 12mm thick of approved make is as mentioned below "Acoustic Panels is made of 100% PET fiber, bonded using heat instead of traditional chemical binders. PET is naturally resistant to fire, moisture, vermin, insects, mould and bacteria, elimina ting the need for any chemical additives. These can be installed as bare panels or if required as fabric wrapped panels. Technical Specification Core: 100% Polyester Fiber Thickness- 12mm, Maximum dimensions: L-2.44m, W-1.22m Density Kg/ m2 ( +/- 10%) 9mm-200Kg ; 12mm-190 Kg ; 25mm : 120Kg ; Edges: Square / Bevelled / Mitre Warranty: Warranted against workmanship and manufacturing defects for 2 years from date of purchase Fire Rating: Class ""A"" and Class ""B"" as per ASTM E-84 Tunnel Test Mounting Method : Glued to the wall with or without air gap using adhesive." Rate to include wastage. | D175: Cabins | E175: 1150 | F175: Sqft | H175: =+$E175*G175 -> 0
A177: 9 | B177: DISPLAY UNIT WITH BOXING. (OPEN DISPLAY) | C177: Providing and fixing Display Unit boxing with back drop made out of 19mm thk commercial plywood boxing of 400mm deep with laminate finish as per design and details. | D177: Discussion Area | E177: 242 | F177: Sqft | H177: =+$E177*G177 -> 0
A179: 10 | B179: MDF WITH PU POLISH | C179: Supply and fix 12mm MDF panels over existing GI frame, joints filled and sanded, finished with high-gloss PU polish, including surface preparation and labour. Rate including of making groves as per the design. | D179: MD Cabin, 8 pax & Conference Room | E179: 1185 | F179: Sqft | H179: =+$E179*G179 -> 0
A181: 11 | B181: MARBLE CLADDING | C181: Providing and laying 16mm thk approved Marble of first quality including cutting to any shape and set in minimum 12 mm thk white cement and sand mortar of 1:3 backing pointing , laid to proper line and level flush including cement floating of joints,polishing and cleaning , filling the joints with white cement mixed with matching colour pigment complete as directed in position without the use of chips or under pinning of any sort. Care shall be taken to match the grains as directed. Further the stones shall be secured to the backing by means of necessary pins, cramps & dowels. consealed services to be complete before finishing with the cladding. Mode of measurements : Sqft area front elevation. | D181: MD cabin | E181: 132 | F181: Sqft | H181: =+$E181*G181 -> 0
A183: 12 | B183: CNC CUT METAL CLADDING WITH BACK LIGHTING | C183: Providing and fixing MS perforated sheet panelling over column, made from 1.2–1.6 mm thick sheet with MS box section framework, including concealed LED back-lighting, wiring, drivers, and all accessories, finished with powder coating/PU paint, complete in all respects as per approved design and drawings. | D183: Waiting lounge | E183: 135 | F183: Sqft | H183: =+$E183*G183 -> 0
A185: 13 | B185: 18MM PLY SKIN | C185: Providing and fixing 18mm thk Ply skin as per design and details. | D185: Misc. | E185: 353 | F185: Sqft | H185: =+$E185*G185 -> 0
A187: =A185+1 -> 14 | B187: 12MM PLY SKIN | C187: Providing and fixing 12mm ply skin as per design and details. | D187: Misc. | E187: 243 | F187: Sqft | H187: =+$E187*G187 -> 0
A189: =A187+1 -> 15 | B189: 12MM GYPSUM SKIN | C189: Providing and fixing 12mm Gypsum skin as per design and details. | D189: Misc. | E189: 548 | F189: Sqft | H189: =+$E189*G189 -> 0
A191: =A189+1 -> 16 | B191: 12MM BWP PLY SKIN | C191: Providing and fixing 12mm bwp ply skin as per design and details. | F191: Sqft | H191: =+$E191*G191 -> 0
A193: =A191+1 -> 17 | B193: 12MM FLEXI PLY SKIN | C193: Providing and fixing 12mm Flexi ply skin as per design and details. | D193: Misc. | E193: 548 | F193: Sqft | H193: =+$E193*G193 -> 0
A195: =A193+1 -> 18 | B195: 1MM THK LAMINATE SKIN | C195: Providing and fixing 1mm thk laminate skin as per design and details. | D195: Misc. | E195: 1015 | F195: Sqft | H195: =+$E195*G195 -> 0
A197: H | C197: Total of Ply Panelling & Ply Boxing Works | H197: =SUM(H161:H196) -> 0
...

Sheet SYSTEM FURNITURE
A1: SYSTEM FURNITURE - BOQ
A2: S.No. | B2: Item Name | C2: Description | D2: Unit | E2: TOTAL | F2: Rate | G2: Amount | H2: Remarks
A4: 1 | B4: LINEAR STAFF | C4: SIZE:- 1200X650X 750 | D4: Nos | E4: 24 | G4: =E4*F4 -> 0
B5: WORKSTATION | C5: TABLE TOP :- 25mm thick PLPB E1 board with 2mm thick PVCedge banding finish with as per approved laminate color.
C6: LEGS :- 4X040 /50X50 powder coated straight leg finish with as per approved shade. Powder coating (AkzoNobel 60-80 Microns) are connected to Legs with Brackets for table support. The open table base should be assembled from the main beams, and end legs.
C7: BEAM :- 40mm x 40mm CRC square pipe with powder coated finish as per
C8: approved shade provided with die casted brackets to support top.
C9: MAIN SCREEN (400HT) :- Fabric Pin-up supported on table top with brackets.RETURN SCREEN (400HT) :- 30 mm fabric screen supported on table top with brackets. PASSAGE SIDE - 30 mm SCREEN HANG PANEL
C10: FLAPPER :- Wire management would be accessed by aluminium fliptops having soft closure with 3D cutouts for wire accessibility on the countertop which are 450mm(W) x 150mm(D) to access all the face plates comfortably.
C11: WIRE CARRIER :- Powder coated wire carrier to be provided for arranging
C12: wires for electricity & data.
C13: RISER LEG :- Powder coated wire riser to be provided for raising wires form floor. CENTER MODESTY (450HT) :- 18mm thick PLPB board with 2mm thick PVCedge banding finish with as per approved laminate color. Haworth - Make
A15: 2 | B15: LINEAR HEIGHT ADJUSTABLE TABLE | C15: LINEAR HEIGHT ADJUSTABLE TABLE -3 STAGE HAT System: HEIGHT ADJUSTABLE TABLE SIZE 1500LX 750DX1200HT Specification : Haworth - Make Table top : 25mm thick Pre-laminate particle board E1 norms finished with with 2mm pvc edge banding with Reversewaterfall Edge Considered . Screen 400ht From FFL -30mm Al screen with Soft Board Tile considered . Retaurn Side -30mm Al Screen with fabric Tile considered . Under-structure : Supported on ms powder coated motorized Height adjustable understructure. Wiremanagement: 450mm flipup with 175ht cable dump & vertebra and ms cable tray with vertical wire entry cover for wire taken through floor level Specifications of Height Adjustment mechanism - 3 stage 1)Motor : Dual Motor 2)Programmable Memory : 4 Preset memory 3)Max load (Capacity) : 100 Kg 4)Push load : 1600N (2 x 800N) 5)Speed : 36mm/s 6)Power type : DC 7)Decibel(db) : <50dBDuty Cycle 8)Height Range : 650-1200mm 9)Anti-collision Feature | D15: Nos | E15: 21 | G15: =+E15*F15 -> 0
A17: 3 | B17: PRELAM PEDESTAL | C17: Prelam Pedestal BBF [E1 Grade] 2D+1F Pedestal @ 400x450x621mm HT. on Castors. Top,Carcass&Fasia : 18mm Prelam Partical Board With PVC Lipping. Handle : Side chamfer handle With top cousining | D17: Nos | E17: 45 | G17: =+E17*F17 -> 0
C19: MEETING TABLE
A21: 1 | B21: 12 PAX | C21: 4050X1500X750 | D21: Nos | E21: 1 | G21: =E21*F21 -> 0
C22: Table top: Corian finish top with 6mm thick Under-structure: Supported on One Side MS powdercoated Switch 40 x 40 Angular Leg with supporting beams. Wire management: 450 mm Aluminium flipup with soft closure and provision to mount switches and sockets on MS Cable Dump & Wire Entry Cover For Wire Uptaking FFL. Haworth - MAke
A23: 2 | B23: 8 PAX | C23: 2700X1200X750 mm ht | D23: Nos | E23: 1 | G23: =E23*F23 -> 0
C24: Table top: Corian finish top with 6mm thick Under-structure: Supported on One Side MS powdercoated Switch 40 x 40 Angular Leg with supporting beams. Wire management: 450 mm Aluminium flipup with soft closure and provision to mount switches and sockets on MS Cable Dump & Wire Entry Cover For Wire Uptaking FFL. Haworth - MAke
A25: 3 | B25: 5 PAX | C25: 1800X1200X750 mm ht | D25: Nos | E25: 1 | G25: =E25*F25 -> 0
C26: Table top: 25 mm thick Pre-laminate particle board E1 norms finished with 2mm pvc edge band Finish . Under-structure: Supported on One Side MS powdercoated Switch 40 x 40 Angular Leg with supporting beams. Wire management: 450 mm Aluminium flipup with soft closure and provision to mount switches and sockets on MS Cable Dump & Wire Entry Cover For Wire Uptaking FFL. Haworth - MAke
A27: 4 | B27: 4 PAX | C27: 1050mm Dia.X750 mm | D27: Nos | E27: 2 | G27: =E27*F27 -> 0
C28: Table top: 25 mm thick Pre-laminate particle board E1 norms finished with 2mm pvc edge band Finish . Under-structure: Supported on One Side MS powdercoated Switch 40 x 40 Angular Leg with supporting beams. Wire management: 450 mm Aluminium flipup with soft closure and provision to mount switches and sockets on MS Cable Dump & Wire Entry Cover For Wire Uptaking FFL. Haworth - MAke
A30: 5 | B30: CABINS TABLE | C30: CABIN TABLES WITH Side Table Cum Storage
C31: Main Table Size :- 1500L x 750D x 750H Side Storage Table Size :- 1500L x 300D x 750H Description: Table Top: 25mm thick Pre-laminate particle board finished with 2mm PVC Edge Banding. Under Structure: Supported on MS Powder Coated Enrich Legs and Supporting MS beams. Modesty Panel : Prelaminated (PLT) modesty panel of 450mm ht on Main and Ailse side of cabin table. Wire Management: 350mm Aluminium Flip Up and provision to mount swicthes and sockets on PVC cable dump and Vertical wire entry cover for wire uptake from floor to cable dump. Side Storage : (Openable Shutter) The structure is made out of 18mm thick pre-laminated boards (PLT). The shelves are made out of 18mm(PLT), which are adjustable in height. The shutters are made out of 18mm(PLT), and fitted by hinges. Finger groove handles, locking unit and levelers are considered. Haworth - MAke | D31: Nos | E31: 4 | G31: =+E31*F31 -> 0
A33: 6 | B33: MD CABINS TABLE | C33: CABIN TABLES WITH Side Table Cum Storage
C34: Main Table Size :- 2100L x 750D x 750H Side Storage Table Size :- 1500L x 300D x 750H Description: Table Top: Corian finish top with 6mm thick Under Structure: Supported on MS Powder Coated Enrich Legs and Supporting MS beams. Modesty Panel : Prelaminated (PLT) modesty panel of 450mm ht on Main and Ailse side of cabin table. Wire Management: 350mm Aluminium Flip Up and provision to mount swicthes and sockets on PVC cable dump and Vertical wire entry cover for wire uptake from floor to cable dump. Side Storage : (Openable Shutter) The structure is made out of 18mm thick pre-laminated boards (PLT). The shelves are made out of 18mm(PLT), which are adjustable in height. The shutters are made out of 18mm(PLT), and fitted by hinges. Finger groove handles, locking unit and levelers are considered. Haworth - MAke | D34: Nos | E34: 1 | G34: =+E34*F34 -> 0
A36: 7 | B36: Metal Lockers | C36: Supply and installation fo metal numeric locker of side 400*450*450 | D36: Nos | E36: 75 | G36: =+E36*F36 -> 0
C38: Total without Taxes | F38: Total | G38: =SUM(G3:G36) -> 0

Sheet CHAIRS
B1: CHAIRS - BOQ
A2: Sr.No. | B2: Description | C2: Location | D2: Qty. | E2: Unit | F2: Rate | G2: Amount
A3: B | B3: CHAIRS
A5: 1 | B5: WORK STATIONS CHAIRS
B6: Medium Back Mesh Chair * AN 70 Mesh * Self Calibrating Multilock Mechanism * Adjustable Lumbar Support * One Way Adjustable Arms (Height) * Nylon Base * Fabric Upholstered Cushion Seat | D6: =SUM(D7:D10) -> 58 | E6: Nos. | G6: =$D6*F6 -> 0
C7: Workstation Area | D7: 45
C8: 8 pax | D8: 8
C9: 5 pax | D9: 5
A11: 2 | B11: MD CABIN HEAD CHAIR
B12: * Leatherette • High Back Chair • Seat & Back Leatherette • Multilock with Knee tilt Mechanism • Aluminum Fixed Arms • Aluminum Base with 60mm castors. | C12: MD room | D12: 1 | E12: Nos. | G12: =$D12*F12 -> 0
A14: 3 | B14: MD CABIN VISITOR CHAIR
B15: *-LEATHERETTE * Seat & Back Artificial Leatherette ( Medium) * Multilock Synchro Mechanism * Chrome Base (Steel) with 60mm Castors. | C15: MD room visitor chair | D15: 3 | E15: Nos. | G15: =$D15*F15 -> 0
A17: 4 | B17: CABIN HEAD CHAIR
B18: * LEATHERETTE * Seat & Back Artificial Leatherette (High) * Multilock Synchro Mechanism * Chrome Base (Steel) with 60mm Castors. | D18: =SUM(D19) -> 4 | E18: Nos. | G18: =$D18*F18 -> 0
C19: Cabin Head Chair | D19: 4
A21: 4 | B21: CABIN VISITOR CHAIR
B22: * Fabric * Seat & Back Fabric ( Medium) * Multilock Synchro Mechanism * Chrome Base (Steel) with 60mm Castors. | D22: =SUM(D23:D24) -> 16 | E22: Nos. | G22: =$D22*F22 -> 0
C23: Cabin Visitor chair | D23: =2*4 -> 8
C24: 4 pax | D24: =2*4 -> 8
B26: TOTAL OF CHAIRS | G26: =SUM(G6:G25) -> 0

Sheet CARPET 
A3: Note:-
B4: * | D4: The quoted rates should be exclusive of GST & it would be extra as applicable.
B5: * | D5: The quoted rates should be F.O.R at site including all freight,packaging, installation etc.
B6: * | D6: It will be the vendors responsibility to hand-over the Carpet to clients/owner free of defects.
B7: * | D7: Any material found to be defective shall be replaced free of cost.
B8: * | D8: Vendor shall rectify all snags before handing over of the completed project.
B9: * | D9: Storing, safe guarding of the supplied material shall be the scope of the vendor till handing over.
B10: * | D10: Availability of material & timelines be confirmed along with submission of bids.
B11: * | D11: Before placing the final order, Quantities to be strictly rechecked with the latest approved layout from client/architect.
A12: CARPET - BILL OF QUANTITIES
A13: SL.NO | D13: DESCRIPTION
A14: I | D14: Carpet : ( Tiles)
D15: Providing, supplying & installing carpet in the specified areas as per patterns specifications as below :
A16: - | D16: Style | F16: Laser Cut , “ Free Form ” Carpet Tile
D17: Construction | F17: Multi Hi / Lo Loop
D18: Pile Fibre | F18: nexlon™ Premium Solution Dyed Nylon with Stain and Soil Resist Technology
D19: Tufted Machine Gauge | F19: 1/10 gauge
D20: Pile Height | F20: 5.0~3.0mm
D21: Total Thickness | F21: 8.9 mm max
D22: Tile size | F22: As per design and selection (450x450mm, 600x600mm, 800x800mm, 1000x1000mm, 1200x200mm)
D23: Total Weight | F23: 6250 gm/m2
D24: Wear Warranty | F24: Lifetime – product is warranted not to lose more than 10% pile fibre by weight in normal commercial use
D25: Colour Fastness | F25: 15 Year Warranty ASTM 16-04. Grade 4 – Little or no change
D26: Static Electricity | F26: Permanent Lifetime Protection – less than 2.0kv
D27: Stain Resistance | F27: nexlon™ Stain Shield Treatment
D28: Soil Resistance | F28: nexlon™ Soil Guard Treatment
... D31: Installation | F31: Pressure Sensitive Adhesive
A32: - | D32: Sustainability | F32: All yarns used are Solution dyed to minimise use of water and exclude any effluent production.
D33: ISO | F33: ISO 14001 and ISO 9001
D34: CRI Label | F34: CRI Green Label Plus Certified for Indoor Air Quality
D35: EPD | F35: Environmental Product Declaration (EPD) by UL
D36: v.HPD | F36: Health Product Declaration (HPD) Third Party verified by U.S. GreenCircle Certified
D37: Fire rating | F37: Fire Rating EN 13501 Cfl s1
A38: - | D38: Wear Rating | F38: Wear Rating EN1307 Class 33
D39: Auns
A40: 2 | D40: Adhesive system
D41: approved adhesive-VOC free
D42: Installation method
A43: - | D43: Direct stick method using water base approved adhesive applied to 100% of the backing surface
A44: - | D44: Completed carpet to be smooth and free of bubbles, puckers and other defects
A46: 3 | D46: Cost to include plastic covering protection after installation not less than 100microns thickness , all handling and transportation .
A48: 4 | D48: Layout- Physical Site measurements should be carried out by the vendor as per final layout plan in advance to confirm quantities of carpet required before releasing the PO.
A49: 4 | B49: Code as per Drg. | C49: PARTICULARS | D49: UNIT | E49: Total QTY | F49: UNIT RATE IN INR (Supply+Install) | G49: AMOUNT IN INR
A51: 1 | C51: Base Carpet - Workstation area Auns - 18-20 Basic Rate - 215/sqft | D51: Sqft | E51: 2410 | G51: =+F51*$E51 -> 0
A52: 2 | C52: Base Carpet - Workstation Passage area Auns - 18-20 Basic Rate - 195/sqft | D52: Sqft | E52: 915 | G52: =+F52*$E52 -> 0
A53: 3 | C53: Base Carpet - Discussion area Auns - 18-20 Basic Rate - 215/sqft | D53: Sqft | E53: 299 | G53: =+F53*$E53 -> 0
A54: 4 | C54: Base Carpet - Waiting Lounge Auns - 18-20 Basic Rate - 215/sqft | D54: Sqft | E54: 272 | G54: =+F54*$E54 -> 0
A55: 5 | C55: Base Carpet - Conference Room & MD Cabin Auns - 20-25 Basic Rate - 265/sqft | D55: Sqft | E55: 654 | G55: =+F55*$E55 -> 0
A56: 6 | C56: Base Carpet - Enclosed Meeting Rooms Auns - 20-25 Basic Rate - 225/sqft | D56: Sqft | E56: 1536 | G56: =+F56*$E56 -> 0
C60: TOTAL FOR SUPPLY & INSTALLATION OF CARPET TILES | G60: =SUM(G51:G59) -> 0
A63: * Prices should be including custom duty etc.
A64: * Prices should be inclusive of transportation and installation.
A65: * Carpet pattern / Colour / Shade to be strictly as per Client / Architect approval.
A66: * Cost to include complete installation, cleaning & after installation till handover.
A67: * Cost also to be included 2 nos. hot extraction valid till 1 year from the installation of carpets

Sheet LOOSE FURNITURE
A1: LOOSE FURNITURE
A3: S.No | B3: Description | C3: Qty. | D3: Unit | E3: Rate | F3: Total | G3: Remarks
A5: A | B5: DISCUSSION AREA & WORKSTATION AREA
A7: 1 | B7: Lounge Chairs | C7: 2 | D7: Nos | F7: =C7*E7 -> 0 | G7: As per Drawing
A8: 2 | B8: Center Coffee Round Tables - 1100mm Dia. | C8: 1 | D8: Nos | F8: =C8*E8 -> 0 | G8: As per Drawing
A9: 3 | B9: Puffys | C9: 12 | D9: Nos | F9: =C9*E9 -> 0 | G9: As per Drawing
A11: B | B11: WAITING LOUNGE AREA
A13: 1 | B13: Lounge Chairs | C13: 2 | D13: Nos | F13: =C13*E13 -> 0 | G13: As per Drawing
A14: 2 | B14: Center Coffee Round Tables - 550mm Dia. | C14: 2 | D14: Nos | F14: =C14*E14 -> 0 | G14: As per Drawing
A15: 3 | B15: Puffys | C15: 5 | D15: Nos | F15: =C15*E15 -> 0 | G15: As per Drawing
A17: C | B17: MD CABIN
A19: 1 | B19: Lounge Chairs | C19: 2 | D19: Nos | F19: =C19*E19 -> 0 | G19: As per Drawing
A20: 2 | B20: Center Coffee Round Tables - 550mm Dia. | C20: 2 | D20: Nos | F20: =C20*E20 -> 0 | G20: As per Drawing
A21: 3 | B21: Two Seater Sofa | C21: 1 | D21: Nos | F21: =C21*E21 -> 0 | G21: As per Drawing
A22: 4 | B22: Singler Seater Sofa | C22: 1 | D22: Nos | F22: =C22*E22 -> 0 | G22: As per Drawing
A24: C | B24: CAFETERIA & COLLAB AREA
A26: 1 | B26: TABLE TOP : Table top to be made of 25mm plywood finished with approved shade of laminate and edges to be finished with 2mm thick PVC edge banding matching to the laminate shade.
B27: UNDERSTRUCTURE : Legs to be made of 40mm x 40mm x 1.6mm MS tube finished with approved shade of powder coating.
A28: 1.1 | B28: Café Tables : 2050 X 900 X 750mm - 6 Pax | C28: 16 | D28: Nos | F28: =C28*E28 -> 0 | G28: As per Drawing
A29: 1.2 | B29: Café Tables : 2700 X 900 X 750mm - 8 Pax | C29: 3 | D29: Nos | F29: =C29*E29 -> 0 | G29: As per Drawing
A30: 1.3 | B30: Café Round Table : 900 X 750 mm - 4 Pax | C30: 8 | D30: Nos | F30: =C30*E30 -> 0 | G30: As per Drawing
A31: 1.4 | B31: Café Round Table : 800 X 750 mm - 2 Pax | C31: 4 | D31: Nos | F31: =C31*E31 -> 0 | G31: As per Drawing
A32: 1.5 | B32: Café Round Table : 950 X 750 mm - 3 Pax | C32: 2 | D32: Nos | F32: =C32*E32 -> 0 | G32: As per Drawing
A33: 1.6 | B33: Café High Running Table : 450mm depth | C33: 24 | D33: Rft | F33: =C33*E33 -> 0 | G33: As per Drawing
A34: 1.4 | B34: Café Chair | C34: 166 | D34: Nos | F34: =C34*E34 -> 0 | G34: As per Drawing
B35: Providing and placing premium café chairs with solid hardwood / powder-coated metal frame, upholstered seat and back using high-density foam and approved fabric/leatherette/leather. Finished with melamine/PU polish for wood or powder coating for metal in approved shade.
A36: 1.5 | B36: High Table : 3150 X 1050 X 1250 mm - 10 Pax | C36: 1 | D36: Nos | F36: =C36*E36 -> 0 | G36: As per Drawing
B37: TABLE TOP : Table top to be made of 18mm thick granite with proper finish. UNDERSTRUCTURE : Legs to be made of 40mm x 40mm x 1.6mm MS tube finished with approved shade of powder coating.
A38: 1.6 | B38: High Table : 3400 X 1000 X 1250 mm - 12 Pax | C38: 2 | D38: Nos | F38: =C38*E38 -> 0 | G38: As per Drawing
B39: TABLE TOP : Table top to be made of 18mm thick granite with proper finish. UNDERSTRUCTURE : Legs to be made of 40mm x 40mm x 1.6mm MS tube finished with approved shade of powder coating.
A40: 1.7 | B40: High Stools | C40: 31 | D40: Nos | F40: =C40*E40 -> 0 | G40: As per Drawing
B41: Providing and placing premium café high chairs with solid hardwood / powder-coated metal frame, upholstered seat and back using high-density foam and approved fabric/leatherette/leather. Finished with melamine/PU polish for wood or powder coating for metal in approved shade.
B42: TOTAL OF LOOSE FURNITURE ITEMS | F42: =SUM(F4:F40) -> 0

Sheet BROUGHTOUT ITEMS
A1: Sr.No. | B1: Description | C1: Location | D1: Qty. | E1: Unit | F1: Rate | G1: Amount | H1: Remarks
A2: D | B2: BROUGHT OUT FURNITURE
A4: 1 | B4: Sick Room Single Bed with Mattress | E4: Nos | G4: =$D4*F4 -> 0
B5: Angle iron support shall be at equal distance. Strips in angle iron frame gap between two strips not more than 50mm of 25x1.0mm minimum.Head bow and foot bow pipe. Head bow/Foot bow pipe support in width wise , one in each side. Height of the head bow from support pipe –300mm.Height of the foot bow from support pipe
A7: 2 | B7: Supply and installation of chair for Lactation room | E7: Nos. | G7: =D7*F7 -> 0
A9: 3 | B9: METAL LOCKER 1 NOS -400X450X300 MM HT (1- Tower 1200X450X1850 MM HT =18 nos) & ( 1- Tower 900X450X1850 MM = 12 nos) | E9: Nos. | G9: =D9*F9 -> 0
A11: 4 | B11: CHESS TABLE WITH CHAIRS | E11: Nos. | G11: =D11*F11 -> 0
B12: Supply and Installation of Chess Table with chairs
A14: 5 | B14: CARROM TABLE WITH STAND AND CHAIRS | E14: Nos. | G14: =D14*F14 -> 0
B15: Supply and Installation of Carrom Table with stand and chairs
A17: =A14+1 -> 6 | B17: AIR Hockey Table (2100x1200mm) - Xpeed | E17: Nos. | G17: =D17*F17 -> 0
B18: Supply and Installation of Air hockey Table
A20: =A17+1 -> 7 | B20: Foose Ball (1800x1200mm) - Signature Pro | E20: Nos. | G20: =D20*F20 -> 0
B21: Supply and Installation of Foose ball Table
A23: 8 | B23: TABLE TENIS | E23: Nos. | G23: =D23*F23 -> 0
B24: Supply and Installation of Table Tenis
A26: 9 | B26: POOL Table | E26: Nos. | G26: =D26*F26 -> 0
B27: Supply and installation of Pool Table
A29: 10 | B29: FRIDGE | D29: 1 | E29: Nos. | G29: =D29*F29 -> 0
B30: Supply and Installation of Fridge of make Elanpro ECG 515 Single Door Refrigerator
A32: =A29+1 -> 11 | B32: WATER Purifier / Dispenser | C32: Pantry Area | D32: 2 | E32: Nos. | G32: =D32*F32 -> 0
B33: Supply and Installation of WAE VAR 150 Drinking Water Stations 400 Mm(W) X 1470 Mm (H) X 647 Mm(D) Ss 304 With Frp Dispensing Construct, Galvanized Iron Powder Coated, 5 Stage Purification @ 50 Litres Per Hour with Kent Elite 2 Plus Purifier
A35: =A32+1 -> 12 | B35: MICROWAVE | D35: 1 | E35: nos. | G35: =D35*F35 -> 0
B36: Supply and Installation of LG All In One 28 Litres Convection Microwave Oven (Charcoal Lighting Heater, MJEN286UI, Black)
A38: 13 | B38: MONITOR STAND | E38: nos. | G38: =D38*F38 -> 0
B39: Supply and Installation of Providing & Fixing Monitor stand single arm
A41: 14 | B41: DISH WASHER | E41: nos. | G41: =D41*F41 -> 0
B42: Supply and Installation of IFB Make (Hood Type)
A44: 15 | B44: Bainmerry - S.S. Drop In Five Container Hot Bain Marie water based Size : 2950 x 660 x 240 | D44: 4 | E44: nos. | G44: =D44*F44 -> 0
A46: 16 | B46: Induction Live Counter Top | E46: nos. | G46: =D46*F46 -> 0
A48: 17 | B48: Commercial Sandwich Grillers | D48: 1 | E48: nos. | G48: =D48*F48 -> 0
A50: 18 | B50: DUST BINS - Café | D50: 2 | E50: nos. | G50: =D50*F50 -> 0
B51: SUPPLY OF SS SWING BIN - SS 202 ECONOMY GRADE SIZE 12"X28" - 50L GRAPHICS PRINT
A53: 19 | B53: DUST BINS - Kitchen | D53: 2 | E53: nos. | G53: =D53*F53 -> 0
B54: SUPPLY OF SS SOLID OPEN BIN - SS 202 ECONOMY GRADE SIZE 12"X28" - 50L SUPPLY OF SS WASTE OPEN CHUTE - SS 304 GRADE 1.2MM THICK - 250MM INNER DIA X 300MM OUTER DIA X 100MM RAISING
A56: 20 | B56: High speed Hand drier – café handwash area | C56: Handwash - café. | D56: 2 | E56: nos. | G56: =D56*F56 -> 0
B58: TOTAL OF BROUGHT OUT FURNITURE ITEMS | G58: =SUM(G3:G57) -> 0

Sheet CAFE PLUMBING WORK
A1: Sl. No. | C1: DESCRIPTION | D1: MAKE | E1: UNIT | F1: QTY | G1: RATE | H1: Total Amount | I1: REMARKS
A3: 1 | B3: 995479 | C3: SS SINK - SINGLE BOWL - NIRALI MAKE | D3: Nirali
C4: Single bowl SS sink Single Bowl with drain board - Supply & fixing of sink with all accessories, necessary supports and sealing the edges with Sealant. Provision for fixing 32mm Dia waste coupling and bottle trap to be given. model - nirali elegance medium Note : Cost to include for Faucet, waste coupling, angle cock, inlet connection pipe, bottle trap & waste coupling. | E4: Nos. | F4: 1 | H4: =+F4*G4 -> 0
A6: 2 | C6: WASH BASIN | D6: Jaquar | E6: Nos. | F6: 10 | H6: =+F6*G6 -> 0
C7: Supply and Installing washbasin (INCLUDING piller cock, basin mixer, waste coupling, bottle trap , angle cock and supports for fixing) for Handwash of approved make & model - JAQUAR
C9: T O T A L - PART I | H9: =SUM(H3:H8) -> 0
A11: II | B11: 995479 | C11: INTERNAL SEWERAGE SYSTEM - SOIL, WASTE, VENT, PIPES
C12: Please note all the pipes should be low noise pipes
A13: 1 | C13: Supply and fixing, of PVC soil, waste and vent pipes (SWR) confirming to IS13592 : 1990, type B with rubber ring (confirming to IS 5382) 6kg/sqcm with solvent joint inclusive of all necessary specials like bends, tees, offsets, doorbends, junctions, screw type caps with rubber rings for cleanout pipe ends, etc., suspended under floor slabs/fixed on walls or on pipe racks in shafts. All suspenders, saddles, pipe packs are to be quoted separately under relevant items.( Inclusive of verticals & horizontals at Internal Toilets ) ,
C15: 75mm dia , | D15: Astral / Ajay / Ashirwad | E15: Rmt | F15: 35 | H15: =+F15*G15 -> 0
C16: 110mm dia | D16: Astral / Ajay / Ashirwad | E16: Rmt | F16: 25 | H16: =+F16*G16 -> 0
A18: 2 | C18: Supply and fixing, of PVC pressure pipes (6Kg/sqcm) confirming to IS 4985 for waste connection from wash basin, kitchen sinks to floor trap, antisyphonage/vent pipe with solvent cement joints, including all the fittings, suspended under floor slabs/concealed in wall etc, the work shall include wall chase and making good the same in cement mortar. All suspenders, saddles , pipe packs are to be quoted separately under relevant items.
C19: 40mm dia (I.D.) | E19: Rmt | F19: 45 | H19: =+F19*G19 -> 0
C20: 50mm dia (I.D.) | E20: Rmt | F20: 35 | H20: =+F20*G20 -> 0
A23: 4 | C23: Supplying, installing,testing and commissioning pipe clean outs fabricated from heavy duty PVC pipe for waste and soil lines for effective maintenance, laid at the dead end side of header pipe pluged and opening type ., complete
C24: 75mm dia | E24: Nos | F24: 15 | H24: =+F24*G24 -> 0
A26: 7 | C26: Supply and fixing, of MS slotted angle iron brackets, MS threaded hangers and supports with necessary drilling holes to suit the insertion of pipe clamps, as per approved fabrication drawings, for supporting soil, waste and rain water pipes and water supply pipes in shafts with suitable MS clamps, bolts, anchor bolts nuts and washers fixed on shaft walls and suspended under floors. The quoted rate shall include painting all steel members with one coat of primer and two coats of enamel paint etc complete. | E26: Kgs. | F26: 8 | H26: =+F26*G26 -> 0
C27: T O T A L - PART II | H27: =SUM(H13:H26) -> 0
A29: III | B29: 995479 | C29: INTERNAL WATER SUPPLY SYSTEM
C30: Please note all the pipes should be low noise pipes
A31: 1 | C31: Supplying, installing, fixing, jointing, testing and commissioning of approved make Chlorinated Polyvinyl Chloride pipes (CPVC) SDR.11 pipes confirming to ASTM standards with necessary fittings, and above 50mm dia pipe fitting shall be schedule 40 ASTM IPS. The fittings and specials such as tees, elbows,couplers, bends, enlargers etc.,m with CPVC brass threaded combination / transition specials such as male adapters brass threaded female adapters, brass FPT Tee, Brass FPT elbow etc., where connection with metal is to be made including necessary drilling holes, chasing walls and making the same good in cement martor 1:1 restore the same original condition neately as directed by the Engineer in-charge.Joints to be made with CPVC solvent cement up to 50mm dia as per ASTM D-2846 and above 50mm dia primer P-70, and solvent confirming to ASTM F-4931 / 724 (internal piping)
C32: c) 25 mm dia | D32: Astral / Ajay / Ashirwad | E32: Rmt | F32: 25 | H32: =+F32*G32 -> 0
C33: d) 32 mm dia | D33: Astral / Ajay / Ashirwad | E33: Rmt | F33: 30 | H33: =+F33*G33 -> 0
A35: 2 | C35: Supplying, and fixing, GM ball valves conforming to IS 1703 with necessary connecting fittings like flanges, nuts and bolts etc., complete.
C36: 25 mm dia (Screwed ends) | D36: NVR / Zoloto / DRP/SANT | E36: Nos. | F36: 1 | H36: =+F36*G36 -> 0
C37: 32 mm dia (Screwed ends) | D37: NVR / Zoloto / DRP/SANT | E37: Nos. | F37: 1 | H37: =+F37*G37 -> 0
A39: 3 | C39: Supplying, and fixing, GM non return valves conforming to IS 1703 with necessary connecting fittings like flanges, nuts and bolts etc., complete. Dia of 40mm | D39: NVR / Zoloto / DRP/SANT | E39: Nos. | F39: 2 | H39: =+F39*G39 -> 0
A41: 5 | C41: Supplying, installing, testing and commissioning of GI Class C Pipe heavy grade with threaded fittngs for hot water supply confirming to ASTM standard including all GI fittings like tees, elbows, bends, unions, coupling, reducer tees, collars, etc. Also insulation for hot water pipes. Insulation of GI Pipe with Elastomeric tube for insulation with 9mm thick Class O material The work shall include making holes, including chasing in solid block masonry walls with groove cutting machine to required width and depth, making opening in walls, , making good the walls and bores in CC or CM 1:3 as applicable clearing the debris, grouting of concealed pipes, MS hooks for fixing pipes and making good the walls and floors.
C42: a) 20 mm dia | D42: Tata / Jindal (Hissar) / apollo | E42: Rmt | F42: 35 | H42: =+F42*G42 -> 0
C44: T O T A L - PART III | H44: =SUM(H31:H43) -> 0
C46: Grand Total ( I + II + III ) | H46: =+H9+H27+H44 -> 0

Sheet Electrical
A3: BOQ For Electrical Work
A4: Sr. Nos | B4: Description | C4: Qty. | D4: Unit | E4: Rate | F4: Amount
A6: 1 | B6: Supply, Installation, Testing, Commissioning of MAIN L.T & HVAC PANEL - MCCB INCOMER AND MCCB / MCB OUTGOING. with fire suppression systems | C6: 1 | D6: Nos | F6: =C6*E6 -> 0
A8: 2 | B8: Supply, Installation, Testing, Commissioning of UPS POWER O/P PANEL - with fire suppression systems | C8: 1 | D8: Nos | F8: =C8*E8 -> 0
A10: A | B10: DISTRIBUTION BOARDS
B11: Supply, installation, testing, tagging, (Circuit numbering) and commissioning of following IP43,double door readymade recessed type MCB, DB, fabricated out of CRCA sheet and painted with powdercoating process OR made out of scratch proof polycarbonate body, and concealed in wall or on surface with necessary frame complete as required.
A12: 1.1 | B12: MAIN DB | C12: 0 | D12: Set | F12: =C12*E12 -> 0
B13: 8way , VTPN MCB Double Door DB
B14: Incomer :-
B15: 160A TPN MCCB, 25KA : 1Nos
B16: Outgoing :-
B17: 63A TP MCB, 10KA : 3Nos.
B18: 40A TP MCB, 10KA : 3Nos.
B19: 32A TP MCB, 10KA : 1Nos.
B20: 25A SP MCB, 10KA : 3Nos.
A22: 1.2 | B22: UPS OUTPUT MAIN DB | C22: 0 | D22: Set | F22: =C22*E22 -> 0
B23: 4way , VTPN MCB Double Door DB
B24: Incomer :-
B25: 63A TPN MCB, 10KA : 1Nos
B26: Outgoing :-
B27: 63A TP MCB, 10KA : 2Nos.
B28: 40A TP MCB, 10KA : 1Nos.
B29: 25A SP MCB, 10KA : 3Nos.
A31: 1.2 | B31: LIGHTING DISTRIBUTION BOARD (LPDB) | C31: 1 | D31: Set | F31: =C31*E31 -> 0
B32: FLEXI TIER DB DOUBLE DOOR 4 TIER 32 MODULE
B33: Incomer :-
B34: 40A TPN MCB, 10KA : 1Nos
B35: 25A/30mA DP RCCB : 3Nos
B36: Outgoing :-
B37: 6/32A SP MCB, 10KA : 18Nos.
A39: 1.3 | B39: RAW POWER DISTRIBUTION BOARD (RPDB) | C39: 1 | D39: Set | F39: =C39*E39 -> 0
B40: FLEXI TIER DB DOUBLE DOOR 4 TIER 56 MODULE
B41: Incomer :-
B42: 40A TPN MCB, 10KA : 1Nos
B43: 25A/30mA DP RCCB : 3Nos
B44: Outgoing :-
B45: 6/32A SP MCB, 10KA : 30Nos.
A47: 1.4 | B47: UPS DISTRIBUTION BOARD (UDB) | C47: 1 | D47: Set | F47: =C47*E47 -> 0
B48: FLEXI TIER DB DOUBLE DOOR 4 TIER 56 MODULE
B49: Incomer :-
B50: 63A TPN MCB, 10KA D CURVE : 1Nos
B51: 40A DP RCCB 100MA : 3Nos
B52: Outgoing :-
B53: 6/32A SP MCB, 10KA D CURVE : 30Nos.
A55: 1.5 | B55: HVAC INDOOR UNIT DISTRIBUTION BOARD (ACDB)VAV | C55: 1 | D55: Set | F55: =C55*E55 -> 0
B56: FLEXI TIER DB DOUBLE DOOR 4 TIER 32 MODULE
B57: Incomer :-
B58: 40A TPN MCB, 10KA : 1Nos
B59: 25A/100mA DP RCCB : 3Nos
B60: Outgoing :-
B61: 6/32A SP MCB, 10KA : 18Nos.
A63: 1.6 | B63: EMERGENCY LIGHTING DISTRIBUTION BOARD (ELDB) | C63: 1 | D63: Set | F63: =C63*E63 -> 0
B64: 12way , SPN MCB Double Door DB
B65: Incoming :-
B66: 1. 25A DP MCB, 10KA : 1Nos
B67: 2. 25A DP,30mA RCCB : 1Nos
B68: Outgoing :-
B69: 1. 6/10 A SP MCB, 10KA : 8Nos.
A71: 1.7 | B71: SERVER DISTRIBUTION BOARD | C71: 2 | D71: Set | F71: =C71*E71 -> 0
B72: 12way , SPN MCB Double Door DB
B73: Incoming :-
B74: 1. 40A DP MCB, 10KA : 1Nos
B75: 2. 40A RCCB 30MA : 1Nos
B76: Outgoing :-
B77: 1. 6/10 A SP MCB, 10KA : 8Nos.
A79: 1.8 | B79: HVAC Encluser Box for near Outdoor unit | C79: 5 | D79: Set | F79: =C79*E79 -> 0
B80: 1. 63A TPN ELMCB with IP65 box.
A82: B | B82: L.T. CABLES & END TERMINATIONS
A83: 1 | B83: M V CABLES
B84: Supply and laying of 1.1 KV grade PVC insulated, inner sheath PVC tapped extruded outer sheath PVC GI strip/round armoured, solid aluminium/Copper conductor power cable conforming to IS 1554 / Part –I with latest amendments fixed on wall / column slab etc.
A86: 1.1 | B86: 3C X 4 sq mm Cu Armoured Cable | C86: 60 | D86: Mtrs | F86: =C86*E86 -> 0
A87: 1.2 | B87: 3C X 6 sq mm Cu Armoured Cable | C87: 120 | D87: Mtrs | F87: =C87*E87 -> 0
A88: 1.3 | B88: 3C X 10 sq mm Cu Armoured Cable | C88: 0 | D88: Mtrs | F88: =C88*E88 -> 0
A89: 1.4 | B89: 4C X 4 sq mm Cu Armoured Cable | C89: 0 | D89: Mtrs | F89: =C89*E89 -> 0
A90: 1.5 | B90: 4C X 6 sq mm Cu Armoured Cable | C90: 0 | D90: Mtrs | F90: =C90*E90 -> 0
A91: 1.6 | B91: 4C X 10 sq mm Cu Armoured Cable | C91: 72 | D91: Mtrs | F91: =C91*E91 -> 0
A92: 1.7 | B92: 4C X 16 sq mm Cu Armoured Cable | C92: 0 | D92: Mtrs | F92: =C92*E92 -> 0
A93: 1.8 | B93: 4C x 10Sq.mm Alu.Armoured Cable | C93: 120 | D93: Mtrs | F93: =C93*E93 -> 0
A94: 1.9 | B94: 4C x 16Sq.mm Alu.Armoured Cable | C94: 120 | D94: Mtrs | F94: =C94*E94 -> 0
A95: 2 | B95: 4C x 25Sq.mm Alu.Armoured Cable | C95: 360 | D95: Mtrs | F95: =C95*E95 -> 0
A96: 2.1 | B96: 3.5C x 35Sq.mm Alu.Armoured Cable | C96: 0 | D96: Mtrs | F96: =C96*E96 -> 0
A97: 2.2 | B97: 3.5C x 50Sq.mm Alu.Armoured Cable | C97: 0 | D97: Mtrs | F97: =C97*E97 -> 0
... A104: 2.9 | B104: 3.5C x 300Sq.mm Alu.Armoured Cable | C104: 0 | D104: Mtrs | F104: =C104*E104 -> 0
B105: UN-ARMOURED FLEXIBLE CABLES
A106: 3 | B106: 1C X 185 sq mm Cu unarmoured Cable | C106: 0 | D106: Mtrs | F106: =C106*E106 -> 0
A107: 3.1 | B107: 1C X 150 sq mm Cu unarmoured Cable | C107: 0 | D107: Mtrs | F107: =C107*E107 -> 0
A108: 3.1 | B108: 1C X 120 sq mm Cu unarmoured Cable | C108: 0 | D108: Mtrs | F108: =C108*E108 -> 0
A109: 3.2 | B109: 1C X 95 sq mm Cu unarmoured Cable | C109: 0 | D109: Mtrs | F109: =C109*E109 -> 0
A110: 3.3 | B110: 1C X 70 sq mm Cu unarmoured Cable | C110: 0 | D110: Mtrs | F110: =C110*E110 -> 0
A111: 3.4 | B111: 1C X 50 sq mm Cu unarmoured Cable | C111: 0 | D111: Mtrs | F111: =C111*E111 -> 0
A112: 3.5 | B112: 1C X 35 sq mm Cu unarmoured Cable | C112: 0 | D112: Mtrs | F112: =C112*E112 -> 0
A113: 3.6 | B113: 1C X 25 sq mm Cu unarmoured Cable | C113: 120 | D113: Mtrs | F113: =C113*E113 -> 0
A114: 3.7 | B114: 1C X 16 sq mm Cu unarmoured Cable | C114: 0 | D114: Mtrs | F114: =C114*E114 -> 0
A115: 3.8 | B115: 1C X 10 sq mm Cu unarmoured Cable | C115: 0 | D115: Mtrs | F115: =C115*E115 -> 0
A116: 3.9 | B116: 1C X 6 sq mm Cu unarmoured Cable | C116: 360 | D116: Mtrs | F116: =C116*E116 -> 0
A117: 4 | B117: 1C X 4 sq mm Cu unarmoured Cable | C117: 120 | D117: Mtrs | F117: =C117*E117 -> 0
A119: 2 | B119: End Joining of Cables
B120: EndTermination:Supplying and making end terminal joints to the following 1.1 KV grade PVC insulated armoured overall sheathed copper / aluminium conductor XLPE cables, using nickle plated single compression brass cable glands, copper compression type cable sockets , PVC insulating tapes, etc.:
A122: 1.1 | B122: 3C X 4 sq mm Cu Armoured Cable | C122: 3 | D122: Nos | F122: =C122*E122 -> 0
A123: 1.2 | B123: 3C X 6 sq mm Cu Armoured Cable | C123: 5 | D123: Nos | F123: =C123*E123 -> 0
...

Sheet HVAC
A1: Sr. No. | B1: SUMMERY SHEET | C1: Amount
A2: Part A | B2: VRF SYSTEM (High side Supply part) | C2: =F43 -> 0
A3: Part B | B3: Low Side ancillary SITC Work | C3: =F97 -> 0
A4: Part C | B4: Fresh air for VRV System | C4: =F116 -> 0
A5: Part D | B5: Toilet Ventilation | C5: =F151 -> 0
B6: SUB TOTAL PART A+B | C6: =SUM(C2:F5) -> 0
B7: GST EXTRA @ 18 %
A8: HVAC | E8: ECO GREEN
A9: Sr. No | B9: Description | C9: Total Qty | D9: UM | E9: Supply Rate | F9: Supply Amount
A10: A | B10: VRF SYSTEM (High side Supply part)
A11: 1 | B11: Outdoor Units (with 410 A Gas)
B12: Supply of Out Door Units suitable for VRF System Outdoor units suitable for the following capacities :
A13: =A11+0.1 -> 1.1 | B13: 28HP Outdoor Units | C13: 3 | D13: Nos. | F13: =C13*E13 -> 0
A14: =A13+0.1 -> 1.2 | B14: 16HP Outdoor Units | C14: 1 | D14: Nos. | F14: =C14*E14 -> 0
A16: 2 | B16: VRF Indoor Comapct Cassettes Type Unit
A17: =A16+0.1 -> 2.1 | B17: 1.5 TR Compact Cassette Units | C17: 1 | D17: Nos. | F17: =C17*E17 -> 0
A18: =A17+0.1 -> 2.2 | B18: 1.3 TR Compact Cassette Units | C18: 4 | D18: Nos. | F18: =C18*E18 -> 0
A19: =A18+0.1 -> 2.3 | B19: 1.0 TR Compact Cassette Units | C19: 2 | D19: Nos. | F19: =C19*E19 -> 0
A20: =A19+0.1 -> 2.4 | B20: 0.8 TR Compact Cassette Units | C20: 3 | D20: Nos. | F20: =C20*E20 -> 0
A22: 3 | B22: VRF Indoor Large Cassettes Type Unit
A23: =A22+0.1 -> 3.1 | B23: 3.2 TR Cassette Units | C23: 8 | D23: Nos. | F23: =C23*E23 -> 0
A24: =A23+0.1 -> 3.2 | B24: 2.8 TR Cassette Units | C24: 12 | D24: Nos. | F24: =C24*E24 -> 0
A25: =A24+0.1 -> 3.3 | B25: 2.0 TR Cassette Units | C25: 3 | D25: Nos. | F25: =C25*E25 -> 0
A27: 4 | B27: VRF Indoor One Way Cassettes Type Unit
A28: =A27+0.1 -> 4.1 | B28: 2.0 TR Cassette Units | C28: 1 | D28: Nos. | F28: =C28*E28 -> 0
A30: 5 | B30: VRF Indoor Hiwall Type Unit
A31: =A30+0.1 -> 5.1 | B31: 1.3 TR Cassette Units | C31: 1 | D31: Nos. | F31: =C31*E31 -> 0
A33: 6 | B33: Supply of Dx hiwall units.
A34: =A33+0.1 -> 6.1 | B34: 1.0 TR Hi-wall Units Server Room (1W+ 1S) | C34: 1 | D34: Nos. | F34: =C34*E34 -> 0
A36: 7 | B36: Supply of Centralized Controller, Remote Controllers
A37: =A36+0.1 -> 7.1 | B37: Cordless Remote For Cassette, Hiwall Indoor Units | C37: 35 | D37: Nos. | F37: =C37*E37 -> 0
A38: =A37+0.1 -> 7.2 | B38: Centrallized Wifi Controller | C38: 1 | D38: Nos. | F38: =C38*E38 -> 0
A40: 8 | B40: REFNET/Y JOINTS
A41: =A40+0.1 -> 8.1 | B41: Refnet for Indoor unit | C41: 34 | D41: Nos. | F41: =C41*E41 -> 0
A42: =A41+0.1 -> 8.2 | B42: Refnet for Outdoor unit | C42: 3 | D42: Nos. | F42: =C42*E42 -> 0
B43: SUB TOTAL WITHOUT TAX | F43: =SUM(F13:F42) -> 0
A45: B | B45: LOW SIDE ANCILLARY SITC WOTK | C45: Total Qty | D45: UM | E45: Supply Rate | F45: Supply Amount
A47: 1 | B47: Installation of outdoor units (Loading unloading, Lifting shifting, Alignment with all ancillary material)
A48: =A47+0.1 -> 1.1 | B48: 28HP Outdoor Units | C48: 3 | D48: Nos. | F48: =C48*E48 -> 0
A49: =A48+0.1 -> 1.2 | B49: 16HP Outdoor Units | C49: 1 | D49: Nos. | F49: =C49*E49 -> 0
A51: 2 | B51: Installation , Testing & Commisining of VRF Indoor units with ancillary material
A52: =A51+0.1 -> 2.1 | B52: 1.5 TR Compact Cassette Units | C52: 1 | D52: Nos. | F52: =C52*E52 -> 0
A53: =A52+0.1 -> 2.2 | B53: 1.3 TR Compact Cassette Units | C53: 4 | D53: Nos. | F53: =C53*E53 -> 0
A54: =A53+0.1 -> 2.3 | B54: 1.0 TR Compact Cassette Units | C54: 2 | D54: Nos. | F54: =C54*E54 -> 0
A55: =A54+0.1 -> 2.4 | B55: 0.8 TR Compact Cassette Units | C55: 3 | D55: Nos. | F55: =C55*E55 -> 0
A56: =A55+0.1 -> 2.5 | B56: 3.2 TR Cassette Units | C56: 8 | D56: Nos. | F56: =C56*E56 -> 0
A57: =A56+0.1 -> 2.6 | B57: 2.8 TR Cassette Units | C57: 12 | D57: Nos. | F57: =C57*E57 -> 0
A58: =A57+0.1 -> 2.7 | B58: 2.0 TR Cassette Units | C58: 3 | D58: Nos. | F58: =C58*E58 -> 0
A59: =A58+0.1 -> 2.8 | B59: 2.0 TR Cassette Units | C59: 1 | D59: Nos. | F59: =C59*E59 -> 0
A60: =A59+0.1 -> 2.9 | B60: 1.3 TR Cassette Units | C60: 1 | D60: Nos. | F60: =C60*E60 -> 0
A62: 3 | B62: Installation,testing and Commissioning Dx hiwall units type (indoor+outdoor)
A63: =A62+0.1 -> 3.1 | B63: 1.0 TR Hi-wall Units Server Room (1W+ 1S) | C63: 1 | D63: Nos. | F63: =C63*E63 -> 0
A65: 4 | B65: Installation of Centralized Controller, Remote Controllers & Refnet Joints
A66: =A65+0.1 -> 4.1 | B66: Installation of Indoor units refnet with proper support & nitrile insualtion | C66: =C41 -> 34 | D66: Nos | F66: =C66*E66 -> 0
A67: =A66+0.1 -> 4.2 | B67: Installation of Outdoor units refnet with proper support & nitrile insulation | C67: =C42 -> 3 | D67: Nos | F67: =C67*E67 -> 0
A68: =A67+0.1 -> 4.3 | B68: Installation, testing & commissioning of CRC Controller | C68: =C38 -> 1 | D68: Nos | F68: =C68*E68 -> 0
A70: 5 | B70: Referigent Copper Piping With Tubular insulation
A71: =A70+0.1 -> 5.1 | B71: All Refrigerant Piping & RefJoints along with 19 mm& 13 mm closed cell nitrile rubber | C71: 255 | D71: Rmt | F71: =C71*E71 -> 0
A73: 6 | B73: Condensing drain water piping with 6mm tubular nitrile rubber Insulation
A74: =A73+0.1 -> 6.1 | B74: 25mm dia | C74: 50 | D74: Rmt | F74: =C74*E74 -> 0
A75: =A74+0.1 -> 6.2 | B75: 32mm dia | C75: 80 | D75: Rmt | F75: =C75*E75 -> 0
A76: =A75+0.1 -> 6.3 | B76: 40mm dia | C76: 65 | D76: Rmt | F76: =C76*E76 -> 0
A78: 7 | B78: Installation Testing and commissioning of electrical cabling
A79: =A78+0.1 -> 7.1 | B79: Communication Cable for VRF system : 2C x 0,75 sq.mm Cu. Shielded control cabling | C79: 320 | D79: Rmt | F79: =C79*E79 -> 0
A80: =A79+0.1 -> 7.2 | B80: Power to Indoor Units: With 6A MCB and 1RMT per IDU of Flexible Copper Cable of suitable size.(3 core .1.5 sqmm shilded copper cable) with conduits, required lugs, clamps, supprots, screws, complete. | C80: R/O | D80: Rmt | F80: 0
A81: =A80+0.1 -> 7.3 | B81: MCB with IP65 Protection for VRF ODU at nearest location within 1 RMT | C81: R/O | D81: Nos | F81: 0
A83: 8 | B83: MS Framework for ODU Units:
A84: =A83+0.1 -> 8.1 | B84: MS C Chaneel & Angle ( with 2 coat of red oxide anti rust paint & black pianted) - MS base frame /platform for outdoor units as mentioned above complete with vibration isolation pads, supports, hangers, railing, brackets etc. FOR VRV ODU UNITS | C84: 4 | D84: Nos | F84: =C84*E84 -> 0
A86: 9 | B86: Testing & Commissioning
A87: =A86+0.1 -> 9.1 | B87: Pressure Testing, Nitrogen flushing & Gas charging R-410 For VRF units | C87: 4 | D87: Nos | F87: =C87*E87 -> 0
A89: 10 | B89: STAND BY UNIT-DX INVERTER HI WALL UNIT
A90: =A89+0.1 -> 10.1 | B90: Interconnecting copper refrigerant pipe work insulated with 12.5.0 mm / 6.0 mm Nitrile Rubber Sleeves as per the standards | C90: 10 | D90: Rmt | F90: =C90*E90 -> 0
A91: =A90+0.1 -> 10.2 | B91: Control Cabling between IDU and ODU | C91: 12 | D91: Rmt | F91: =C91*E91 -> 0
A92: =A91+0.1 -> 10.3 | B92: L-Type Framework for Dx Hiwall Units | C92: 1 | D92: Nos | F92: =C92*E92 -> 0
A93: =A92+0.1 -> 10.4 | B93: Condensate Drain Pump for Hiwall Units | C93: R/O | D93: Nos | F93: 0
A94: =A93+0.1 -> 10.5 | B94: Testing & Commisioning of Hiwall Inddor unit | C94: 1 | D94: Nos | F94: =C94*E94 -> 0
A95: =A94+0.1 -> 10.6 | B95: Sequentional Timer for DX HW units | C95: 1 | D95: Nos | F95: =C95*E95 -> 0
B97: SUB TOTAL WITHOUT TAX | F97: =SUM(F47:F96) -> 0
A99: C | B99: FRESH AIR VENTILATION FOR VRV SYSTEM
A100: 11 | B100: Supply, Installation, Testing & Commissioning of Cabinet Fans with Filter
A101: =A100+0.1 -> 11.1 | B101: 1000 CFM | C101: 2 | D101: Nos | F101: =C101*E101 -> 0
A103: 12 | B103: Supply, Installation, Testing & Commissioning of GI Ducting | C103: 50 | D103: Sq.Mtr | F103: =C103*E103 -> 0
A105: 13 | B105: Supply, Installation, Testing & Commissioning of Canvas connection | C105: 4 | D105: Nos | F105: =C105*E105 -> 0
A107: 14 | B107: Manual Volume control damper-
A108: =A107+0.1 -> 14.1 | B108: Supply, installation and testing of AL construction of 18G opposed blade volume control dampers within ducts to be provided with suitable links, levers and quadrants for manual control of volume of air flow. | C108: 1 | D108: Sq.Mtr | F108: =C108*E108 -> 0
A110: 15 | B110: Supply, installation, testing & commissioning of flexible duct | C110: 40 | D110: Rmt | F110: =C110*E110 -> 0
A112: 16 | B112: Supply, installation of MS bracket with threaded rod for ceiling mounted fan ( FE+EX) installation work | C112: 2 | D112: Nos | F112: =C112*E112 -> 0
A114: 17 | B114: Cowl Piece
A115: =A114+0.1 -> 17.1 | B115: Supply, Installing, testing and comissioning of cowl piece with bird screen | C115: 2 | D115: Nos | F115: =C115*E115 -> 0
B116: SUB TOTAL WITHOUT TAX | F116: =SUM(F100:F115) -> 0
A118: D | B118: Toilet Ventilation
A119: 18 | B119: Supply, Installation, Testing & Commissioning of Exhaust Air Inline /Cabinet Fan withot Filters
A120: =A119+0.1 -> 18.1 | B120: 1400 CFM For Cafe | C120: 1 | D120: Nos | F120: =C120*E120 -> 0
A121: =A120+0.1 -> 18.2 | B121: 500 CFM For Gents Toilet | C121: 1 | D121: Nos | F121: =C121*E121 -> 0
A122: =A121+0.1 -> 18.3 | B122: 300 CFM For Ladies Toilet | C122: 1 | D122: Nos | F122: =C122*E122 -> 0
A124: 19 | B124: Supply, Installation, Testing & Commissioning of Fresh Air inline/Cabinet Fan With Filters
A125: =A124+0.1 -> 19.1 | B125: 1200 CFM For Cafe | C125: 1 | D125: Nos | F125: =C125*E125 -> 0
A126: =A125+0.1 -> 19.2 | B126: 400 CFM For Gents Toilet | C126: 1 | D126: Nos | F126: =C126*E126 -> 0
A127: =A126+0.1 -> 19.3 | B127: 200 CFM For Ladies Toilet | C127: 1 | D127: Nos | F127: =C127*E127 -> 0
A129: 20 | B129: SITC of GI Ducting (120 GSM) Site Fabricated with Duct Mate Flanges as per SMACNA. Standards
...

Sheet Summary
A1: Master Summary
A2: S.NO. | B2: Description | C2: Amount (In INR)
E3: Summary | F3: Make
A4: 1 | B4: NETWORKING - Passive | C4: =+Passive!I28 -> 0 | E4: PASSIVE | F4: Commscope Netconnect
A5: 2 | B5: CCTV | C5: =+CCTV!I17 -> 0 | E5: CCTV | F5: CP Plus
A6: 3 | B6: Access Control System | C6: =+ACS!I19 -> 0 | E6: ACS | F6: Essl
A7: 4 | B7: FAS | C7: =+FAS!I25 -> 0 | E7: FAS | F7: Ravel
A8: 5 | B8: PAS | C8: =+PAS!I16 -> 0 | E8: PAS | F8: Bosch+Ahuja
A9: 6 | B9: Fire exinguishers | C9: =+'Fire Extinguisher'!H9 -> 0 | E9: Fire Extinguishers | F9: Safex/ Excellent
B11: GRAND TOTAL (Excluding taxes) | C11: =SUM(C4:C9) -> 0 | F11: Total

Sheet Passive
B2: Passive
A3: Sr.No | B3: Description (cable average 50m per node)(Total nodes 150) | C3: Part Code | D3: UOM | E3: Qty | F3: Supply Rate | G3: Installation Rate | H3: Supply Amount | I3: Installation Amount
B4: Passive Network Data
A6: 1 | B6: 4 Pair UTP Cat 6a Cable | C6: Commscope | D6: 305m/Box | E6: 32 | H6: =F6*E6 -> 0 | I6: =SUM(G6*E6) -> 0
A7: 2 | B7: UTP CAT 6a I/O User End & Data End | C7: Commscope | D7: NOS | E7: 375 | H7: =F7*E7 -> 0 | I7: =SUM(G7*E7) -> 0
A8: 3 | B8: Single\Dual Port FACEPLATE | C8: Commscope | D8: NOS | E8: 132 | H8: =F8*E8 -> 0 | I8: =SUM(G8*E8) -> 0
A9: 4 | B9: Quad Port FACEPLATE | C9: Commscope | D9: NOS | E9: 0 | H9: =F9*E9 -> 0 | I9: =SUM(G9*E9) -> 0
A10: 5 | B10: CAT 6a UTP PATCH CORD 2M - USER END & RACK END | C10: Commscope | D10: NOS | E10: 375 | H10: =F10*E10 -> 0 | I10: =SUM(G10*E10) -> 0
A11: 6 | B11: CAT 6a 24 Port Unloaded Patch Panel | C11: Commscope | D11: NOS | E11: 9 | H11: =F11*E11 -> 0 | I11: =SUM(G11*E11) -> 0
A12: 7 | B12: CAT 6a UTP PATCH CORD 2M -UPLINK | C12: Commscope | D12: NOS | E12: 9 | H12: =F12*E12 -> 0 | I12: =SUM(G12*E12) -> 0
B13: Fiber Uplink MDF to IDF
A14: 1 | B14: OFC Multimode Mode OM4-12F armoured cable (APPROX QTY) | C14: Commscope | D14: RMT | E14: 255 | H14: =F14*E14 -> 0 | I14: =SUM(G14*E14) -> 0
A15: 2 | B15: 24 port Loaded LIU with splice trey/Adaptors with all accessories | C15: Commscope | D15: NOS | E15: 2 | H15: =F15*E15 -> 0 | I15: =SUM(G15*E15) -> 0
A16: 3 | B16: LC to LC Ofc fiber patch cords -SMF-OS2-DPX-LCLC-3MTR | C16: Commscope | D16: NOS | E16: 24 | H16: =F16*E16 -> 0 | I16: =SUM(G16*E16) -> 0
A17: 4 | B17: Splicing of LC pigtails | C17: Commscope | D17: NOS | E17: 24 | H17: =F17*E17 -> 0 | I17: =SUM(G17*E17) -> 0
B18: Rack Components
A19: 1 | B19: 42 U 800x1000 | C19: Netrack | D19: Nos | E19: 1 | H19: =F19*E19 -> 0 | I19: =SUM(G19*E19) -> 0
A20: 2 | B20: Server /IT Rack mount power distribution unit, 1Ph, 230V, 16A, 50/60Hz, 2U standard with 6 X Indian Round Pin 5/15A, Inlet Plug type 16A Indian Round Pin, 16A MCB - PDU Rating 3.6KVA/Side feed-1.5Mt/ Black | C20: Netrack | D20: Nos | E20: 2 | H20: =F20*E20 -> 0 | I20: =SUM(G20*E20) -> 0
A21: 3 | B21: 2U Horizontal Cable manager Chnl on Front | C21: Netrack | D21: Nos | E21: 9 | H21: =F21*E21 -> 0 | I21: =SUM(G21*E21) -> 0
A22: 4 | B22: Mounting Hardware/OR/Pk-20 | C22: STD | D22: Nos | E22: 20 | H22: =F22*E22 -> 0 | I22: =SUM(G22*E22) -> 0
A23: 5 | B23: Rack Dressing Charges | C23: STD | D23: Nos | E23: 1 | H23: =F23*E23 -> 0 | I23: =SUM(G23*E23) -> 0
B24: Testing & Certification
A25: 1 | B25: Cable Segrigation/Bunching /Dressing/Feruling/Termination of Infomration outlets Both Side (User side & Rack side)/ complete Rack dressing/ Jack panel and Faceplate Labling/ LAN testing (Using Lan Tester)/Patch cord labling and Dressing/ Fluke Testing & Certification | C25: Job | D25: Nos | E25: 150 | H25: =F25*E25 -> 0 | I25: =SUM(G25*E25) -> 0
A26: 2 | B26: Project Management Charges | C26: Job | D26: Nos | E26: 1 | H26: =F26*E26 -> 0 | I26: =SUM(G26*E26) -> 0
B27: Total | H27: =SUM(H6:H26,) -> 0 | I27: =SUM(I6:I26,) -> 0
B28: Grand Total | I28: =H27+I27 -> 0

Sheet CCTV
A2: CCTV - NVR - CP Plus
A3: Sr.No | B3: Descirption | C3: Part Code | D3: UOM | E3: Qty | F3: Supply Rate | G3: Installation Rate | H3: Supply Price | I3: Installation Price
A5: 1 | B5: Dome Camera - 2 MP | C5: CP-UNC-DA21L3C-Q | D5: Nos | E5: 16 | H5: =F5*E5 -> 0 | I5: =SUM(G5*E5) -> 0
A6: 2 | B6: 24 Port POE Switch | C6: D-Link DGS-1100-24PV2 | D6: Nos | E6: 1 | H6: =F6*E6 -> 0 | I6: =SUM(G6*E6) -> 0
A7: 3 | B7: 32 Channel NVR 4 Slot | C7: CP-UNR-4K5324-V3 | D7: Nos | E7: 1 | H7: =F7*E7 -> 0 | I7: =SUM(G7*E7) -> 0
A8: 4 | B8: 10 TB Hardisk Drive for NVR | C8: SEGATE | D8: Nos | E8: 2 | H8: =F8*E8 -> 0 | I8: =SUM(G8*E8) -> 0
A9: 5 | B9: Camera Stand | C9: STD | D9: Nos | E9: 16 | H9: =F9*E9 -> 0 | I9: =SUM(G9*E9) -> 0
A10: 6 | B10: PVC Back Box | C10: STD | D10: Nos | E10: 16 | H10: =F10*E10 -> 0 | I10: =SUM(G10*E10) -> 0
A11: 7 | B11: 27" LCD Screen for CCTV Monitoring | C11: Samsung | D11: Nos | E11: 1 | H11: =F11*E11 -> 0 | I11: =SUM(G11*E11) -> 0
A12: 8 | B12: Testing & Certification | D12: Nos | E12: 1 | H12: =F12*E12 -> 0 | I12: =SUM(G12*E12) -> 0
A13: 9 | B13: Conduit & Saddle | C13: STD | D13: MTR | E13: 1050 | H13: =F13*E13 -> 0 | I13: =SUM(G13*E13) -> 0
B16: Total | H16: =SUM(H4:H13) -> 0 | I16: =SUM(I4:I13) -> 0
B17: Grand Total | I17: =SUM(H16:I16) -> 0

Sheet ACS
B1: ACS - ESSL
A2: Sr.No | B2: Description | C2: Part Code | D2: UOM | E2: Qty | F2: Supply Rate | G2: Installation Rate | H2: Supply Amount | I2: Installation Amount
A3: 1 | B3: 4 Door Controller | C3: C3-400 | D3: Nos | E3: 1 | H3: =F3*E3 -> 0 | I3: =SUM(G3*E3) -> 0
A4: 2 | B4: Entry Reader - ( Facial + RFID) | C4: FACE - AIFACE MAGNUM LITE eSSL | D4: Nos | E4: 1 | H4: =F4*E4 -> 0 | I4: =SUM(G4*E4) -> 0
A5: 3 | B5: Exit Reader - ( Facial + RFID) | C5: FACE - AIFACE MAGNUM LITE eSSL | D5: Nos | E5: 1 | H5: =F5*E5 -> 0 | I5: =SUM(G5*E5) -> 0
A6: 4 | B6: Entry Reader - (RFID+Biometric) | C6: Essl Fr1200 | D6: Nos | E6: 2 | H6: =F6*E6 -> 0 | I6: =SUM(G6*E6) -> 0
A7: 5 | B7: Exit Reader - (RFID+Biometric) | C7: Essl Fr1200 | D7: Nos | E7: 2 | H7: =F7*E7 -> 0 | I7: =SUM(G7*E7) -> 0
A8: 6 | B8: Push Button | C8: HF-S86 | D8: Nos | E8: 3 | H8: =F8*E8 -> 0 | I8: =SUM(G8*E8) -> 0
A9: 7 | B9: Single Leaf EM LOCK | C9: ESSL | D9: Nos | E9: 1 | H9: =F9*E9 -> 0 | I9: =SUM(G9*E9) -> 0
A10: 8 | B10: Double Leaf EM LOCK | C10: ESSL | D10: Nos | E10: 2 | H10: =F10*E10 -> 0 | I10: =SUM(G10*E10) -> 0
A11: 9 | B11: U or L Bracket HI FOCUS 280 | C11: HI FOCUS 280 | D11: Nos | E11: 3 | H11: =F11*E11 -> 0 | I11: =SUM(G11*E11) -> 0
A12: 10 | B12: 8core 0.75 sq.mm Shielded, PVC Sheathed Copper Flexible Cable with 1.6mm thick, 25mm MS conduit. | C12: Polycab | D12: MTR | E12: 375 | H12: =F12*E12 -> 0 | I12: =SUM(G12*E12) -> 0
A13: 11 | B13: 4core 0.75 sq.mm Shielded, PVC Sheathed Copper Flexible Cable with 1.6mm thick, 25mm MS conduit. | C13: Polycab | D13: MTR | E13: 375 | H13: =F13*E13 -> 0 | I13: =SUM(G13*E13) -> 0
A14: 12 | B14: 2core 0.75sq.mm Shielded, PVC Sheathed Copper Flexible Cable with 1.6mm thick, 25mm MS conduit. | C14: Polycab | D14: MTR | E14: 188 | H14: =F14*E14 -> 0 | I14: =SUM(G14*E14) -> 0
... A17: 15 | B17: Testing & Certification | C17: Job | D17: Nos | E17: 1 | H17: =F17*E17 -> 0 | I17: =SUM(G17*E17) -> 0
B18: Total | H18: =SUM(H3:H17) -> 0 | I18: =SUM(I3:I17) -> 0
B19: Grand Total | I19: =SUM(G18:I18) -> 0

Sheet FAS
A1: Sr.No | B1: PARTICULARS. | C1: SIZE/MAKE. | D1: UNIT. | E1: QTY. | F1: Supply Rate | G1: Installation Rate | H1: Supply Amount | I1: Installation Amount
B3: FIRE ALARM SYSTEM ( RAVEL)
A4: 1 | B4: 8 LOOP ADDRESSABLE FIRE CONTROL PANEL Microprocessor designed to meet all requirements of IS – 2189,indication for open, short , sounder fault , power supply fault , battery low, fault buzzer mute facility, space for SMF batteries, compact stylish design, user friendly controls,With 24V battery backup(Exide Make), UL& CE approved | C4: Ravel | D4: Nos | E4: 1 | H4: =F4*E4 -> 0 | I4: =SUM(G4*E4) -> 0
A5: 2 | B5: Photoelectric type smoke detector (Addressable) BFC Plug in type optical smoke detector placed above false ceiling, with red lamp type for indication,LPCB,Vds, UL& CE approved | C5: Ravel | D5: Nos | E5: 35 | H5: =F5*E5 -> 0 | I5: =SUM(G5*E5) -> 0
A6: 3 | B6: Photoelectric type smoke detector (Addressable) AFC Plug in type optical smoke detector placed above false ceiling, with red lamp type for indication,LPCB,Vds, UL& CE approved | C6: Ravel | D6: Nos | E6: 35 | H6: =F6*E6 -> 0 | I6: =SUM(G6*E6) -> 0
A7: 4 | B7: Photoelectric type Heat Detector (Addressable) BFC Plug in type optical heat detector placed above/Below false ceiling, with red lamp type for indication,LPCB,Vds, UL& CE approved | C7: Ravel | D7: Nos | E7: 5 | H7: =F7*E7 -> 0 | I7: =SUM(G7*E7) -> 0
A8: 5 | B8: Response Indicator | C8: Ravel | D8: Nos | E8: 40 | H8: =F8*E8 -> 0 | I8: =SUM(G8*E8) -> 0
A9: 6 | B9: Loop Sounder (Addressable) Fire alarm hooter cum strob having an audible range of 25mtrs.,10~30 VDC, <32 mA current rating,LPCB,Vds, UL& CE approved | C9: Ravel | D9: Nos | E9: 5 | H9: =F9*E9 -> 0 | I9: =SUM(G9*E9) -> 0
A10: 7 | B10: Manual Call Point (Addressable) Manual Call Point i(Break glass)to initiate audio visual alarm .,LPCB,Vds, UL& CE approved | C10: Ravel | D10: Nos | E10: 5 | H10: =F10*E10 -> 0 | I10: =SUM(G10*E10) -> 0
A11: 8 | B11: CABLING FOR THE SYSTEM : 2c x 1.5 sqmm FRLS Armoured Cable in RED Colour | C11: Polycab | D11: Mts | E11: 985 | H11: =F11*E11 -> 0 | I11: =SUM(G11*E11) -> 0
A12: 9 | B12: Control Module | C12: Ravel | D12: Nos | E12: 5 | H12: =F12*E12 -> 0 | I12: =SUM(G12*E12) -> 0
A13: 10 | B13: Control Relay Module | C13: Ravel | D13: Nos | E13: 5 | H13: =F13*E13 -> 0 | I13: =SUM(G13*E13) -> 0
A14: 10 | B14: Monitor Module | C14: Ravel | D14: Nos | E14: 5 | H14: =F14*E14 -> 0 | I14: =SUM(G14*E14) -> 0
A15: 11 | B15: Isolator Module | C15: Ravel | D15: Nos | E15: 7 | H15: =F15*E15 -> 0 | I15: =SUM(G15*E15) -> 0
... A23: 19 | B23: Testing & Certification | C23: Job | D23: Nos | E23: 1 | H23: =F23*E23 -> 0 | I23: =SUM(G23*E23) -> 0
A24: TOTAL | H24: =SUM(H5:H23) -> 0 | I24: =SUM(I5:I23) -> 0
B25: Grand Total | I25: =SUM(H24:I24) -> 0

Sheet PAS
A1: Public Address System
A2: Sr.No | B2: Description | C2: SIZE/MAKE. | D2: UNIT. | E2: QTY | F2: SUPPLY RATE | G2: INSTALLATION RATE | H2: SUPPLY AMOUNT | I2: INSTALLATION AMOUNT
A3: 1 | B3: CEILING SPEAKER UNIT 6" with RMS in Watts 6 Watt, Frequency Response 120 HZ to 15 KHZ, Line Matching Transformer 100 / 70 V, & wall mounting fitting accessories. BOSLBD8352 | C3: Bosch | D3: Nos | E3: 35 | H3: =F3*E3 -> 0 | I3: =SUM(G3*E3) -> 0
A4: 2 | B4: GOOD SENSITIVITY MICROPHONE with accessories (Ahuja AWM-630VG Wireless PA Microphones) | C4: Ahuja | D4: Nos | E4: 1 | H4: =F4*E4 -> 0 | I4: =SUM(G4*E4) -> 0
A5: 3 | B5: VOLUME CONTROL AT-20 | C5: Ahuja | D5: Nos | E5: 1 | H5: =F5*E5 -> 0 | I5: =SUM(G5*E5) -> 0
A6: 4 | B6: MERAKI's Alarm Trigger Interface | C6: Ahuja | D6: Nos | E6: 1 | H6: =F6*E6 -> 0 | I6: =SUM(G6*E6) -> 0
A7: 5 | B7: Mono Cable (5m) | C7: Ahuja | D7: Nos | E7: 1 | H7: =F7*E7 -> 0 | I7: =SUM(G7*E7) -> 0
A8: 6 | B8: 32 GB Micro SD Card | C8: Ahuja | D8: Nos | E8: 1 | H8: =F8*E8 -> 0 | I8: =SUM(G8*E8) -> 0
A9: 7 | B9: Bosch 240 Watt Amplifier PLE‑1ME240‑3IN | C9: Bosch | D9: Nos | E9: 1 | H9: =F9*E9 -> 0 | I9: =SUM(G9*E9) -> 0
A10: 8 | B10: CABLING FOR THE SYSTEM : 2c x 0.75 sqmm FRLS Armoured Cable in RED Colour | C10: Polycab / RR | D10: Mtr | E10: 450 | H10: =F10*E10 -> 0 | I10: =SUM(G10*E10) -> 0
A11: 9 | B11: MS - Powder coateated Box- 250x200mm | C11: STD | D11: Nos | E11: 35 | H11: =F11*E11 -> 0 | I11: =SUM(G11*E11) -> 0
A12: 10 | B12: Saddles for PA Cable | C12: STD | D12: Nos | E12: 1050 | H12: =F12*E12 -> 0 | I12: =SUM(G12*E12) -> 0
A13: 11 | B13: Hardware Material (Screw , Rawl plug etc) | C13: STD | D13: Nos | E13: 1 | H13: =F13*E13 -> 0 | I13: =SUM(G13*E13) -> 0
A14: 12 | B14: Testing & Certification | C14: Job | D14: Nos | E14: 1 | H14: =F14*E14 -> 0 | I14: =SUM(G14*E14) -> 0
B15: Total | H15: =SUM(H3:H14) -> 0 | I15: =SUM(I3:I14) -> 0
B16: Grand Total | I16: =H15+I15 -> 0

Sheet Fire Extinguisher
A1: PORTABLE FIRE EXTINGUISHERS
A2: Sr.No | B2: Description | C2: UoM | D2: Qty | E2: Supply Rate | F2: Installation Rate | G2: Supply Price | H2: Installation Price
A4: 1 | B4: 4.5 Kg CO2 type Fire Extinguisher ISI marked confirming to IS:15683. . Complete with delivery hose horn, squeeze grip release valve, locking arrangement, operation manual and floor stand, sigange and service tag. | C4: Nos. | D4: 3 | G4: =IFERROR(IF(D4="","",D4*E4),"") -> 0 | H4: =IFERROR(IF(D4="","",D4*F4),"") -> 0
A5: 2 | B5: 6kg Powder Fire Extinguisher (Stored Pressure type) duly ISI marked conforming to IS: 15683:2006, with IS 14609 ISI marked ABC powder complete with squeeze grip release valve, discharge pipe, locking arrangement, pressure gauge, operation manual and floor stand, signage and service tag. | C5: Nos. | D5: 20 | G5: =IFERROR(IF(D5="","",D5*E5),"") -> 0 | H5: =IFERROR(IF(D5="","",D5*F5),"") -> 0
A6: 3 | B6: Ceiling suspended Clean Agent Gas DuPont FE 36 , 5kG Stored Pressure Type, Pressure Gauge, Automatic Discharge Mechanism on temperature rise, Discharge time less than 8secs, Applicable on A,B,C and Electrically started fire, provided with sprinkler bulb of 68 degree with the coverage area not less than 12 sq.mt confirming to IS standard. The cost should include all necessary fixing supports and service tag. | C6: Nos. | D6: 3 | G6: =IFERROR(IF(D6="","",D6*E6),"") -> 0 | H6: =IFERROR(IF(D6="","",D6*F6),"") -> 0
A7: 4 | B7: Ceiling suspended Clean Agent Gas DuPont FE 36 , 10kG Stored Pressure Type, Pressure Gauge, Automatic Discharge Mechanism on temperature rise, Discharge time less than 8secs, Applicable on A,B,C and Electrically started fire, provided with sprinkler bulb of 68 degree with the coverage area not less than 12 sq.mt confirming to IS standard. The cost should include all necessary fixing supports and service tag. | C7: Nos. | D7: 0 | G7: =IFERROR(IF(D7="","",D7*E7),"") -> 0 | H7: =IFERROR(IF(D7="","",D7*F7),"") -> 0
B8: SUB TOTAL | G8: =SUM(G3:G7) -> 0 | H8: =SUM(H3:H7) -> 0
B9: TOTAL | H9: =SUM(H8+G8) -> 0

Sheet Fire Sprinkler
A1: Sl. No. | B1: Description | C1: Unit | D1: Qty | E1: Supply Rate | F1: Installation Rate | G1: Supply Amount | H1: Installation Amount | I1: Total Amount
A2: A | B2: AUTOMATIC SPRINKLER SYSTEM
A3: 1 | B3: Supply, Installation, Testing & Commissioning and jointing including testing GI Class "C " Pipes conforming to IS: 1239 including cutting, welded (all type) joints as per detailed specifications and providing suitable flanges wherever required complete with necessary fittings viz bends, tees, reducers etc. required including fixing the pipes on wall/ ceiling/ beam/ floor with suitable hangers, clamps and Providing two coats of synthetic enamel paint of approved shade over a coat of primer. All joints upto 50mm should be socket welded and above 50 mm butt weld. Prior to application of primer the surface should be cleaned for any dirt, rusts, rough substance etc. as per the approval of the Project Manager. The pipe of following sizes complete. (All types of welded joints).
A4: a | B4: 100 mm dia | C4: RM | D4: 95 | G4: =E4*D4 -> 0 | H4: =F4*D4 -> 0 | I4: =H4+G4 -> 0
A5: b | B5: 50 mm dia | C5: RM | D5: 118 | G5: =E5*D5 -> 0 | H5: =F5*D5 -> 0 | I5: =H5+G5 -> 0
A6: c | B6: 40 mm dia | C6: RM | D6: 132 | G6: =E6*D6 -> 0 | H6: =F6*D6 -> 0 | I6: =H6+G6 -> 0
A7: d | B7: 32 mm dia | C7: RM | D7: 95 | G7: =E7*D7 -> 0 | H7: =F7*D7 -> 0 | I7: =H7+G7 -> 0
A8: e | B8: 25 mm dia | C8: RM | D8: 125 | G8: =E8*D8 -> 0 | H8: =F8*D8 -> 0 | I8: =H8+G8 -> 0
A9: 2 | B9: Supply, Installation, Testing & Commissioning of 15mm gunmetal sprinkler head with quartzoid bulb and set to operate at specified temperature pendent/ upright/ side wall as per the location indicated on the drawings. sprinklers 68 degree C FOC/UL/FM approved complete with socket nipple, adaptor etc. Sprinkler bulb temperature of operation shall be 68 deg. C
A10: a | B10: Pendent type in brass chrome finish. | C10: Nos | D10: 116 | G10: =E10*D10 -> 0 | H10: =F10*D10 -> 0 | I10: =H10+G10 -> 0
A11: b | B11: Upright type in brass chrome finish. | C11: Nos | D11: 30 | G11: =E11*D11 -> 0 | H11: =F11*D11 -> 0 | I11: =H11+G11 -> 0
A12: 7 | B12: Supply, Installation, Testing & Commissioning of sprinkler drops 1/2” X 1500mm as per NFPA 13, i3r & 130, as well as UL 1474 standards minimum bending radius is 3” (76mm) stainless steel corrugated flexline made with AISI 304 and 3i6l. Braided flexible sprinkler drops wrapped with AISI 304 wire. Tube connectors made of brass, edam packing in the connector to prevent leakage and withstand high pressure.
A13: a | B13: 1000mm length | C13: Nos | D13: 30 | G13: =E13*D13 -> 0 | H13: =F13*D13 -> 0 | I13: =H13+G13 -> 0
A14: 8 | B14: Supply, Installation, Testing & Commissioning of 25 mm dia brass inspecting & testing valve. | C14: Nos | D14: 1 | G14: =E14*D14 -> 0 | H14: =F14*D14 -> 0 | I14: =H14+G14 -> 0
A15: 9 | B15: Supply, Installation, Testing & Commissioning of electrically operated flow indicating switches in sprinkler branch line on each zone of each floor (Wiring from switches to panel and staircase pressurization not included) | C15: Nos | D15: 1 | G15: =E15*D15 -> 0 | H15: =F15*D15 -> 0 | I15: =H15+G15 -> 0
A16: 10 | B16: Supply, Installation, Testing & Commissioning of single acting air release valve with screwed inlet 25 mm dia. | C16: Nos | D16: 1 | G16: =E16*D16 -> 0 | H16: =F16*D16 -> 0 | I16: =H16+G16 -> 0
A17: 11 | B17: Supply, Installation, Testing & Commissioning of dial type pressure gauge with Isolation cock and chromium plated copper pipe on main header.
B18: Dial diameter 100mm
B19: calibration 0-10kg/sq.cm | C19: Nos | D19: 1 | G19: =E19*D19 -> 0 | H19: =F19*D19 -> 0 | I19: =H19+G19 -> 0
A20: 12 | B20: Supplying and installing cast iron Butterfly valves PN 1.6 with potential free contacts tamper switch & cabling upto fire alarm panel as an supervisory control complete with both sides including flanges on receiving pipes with nuts, bolts, 1.5mm thick compressed asbestos gasket insertion as required
A21: a | B21: 100 mm dia | C21: Nos | D21: 1 | G21: =E21*D21 -> 0 | H21: =F21*D21 -> 0 | I21: =H21+G21 -> 0
B23: TOTAL 'A' CARRIED OVER TO SUMMARY | I23: =SUM(I2:I22) -> 0

Sheet Toilet
A1: TOILETS - FINISHING WORKS - BOQ.
A2: S.N. | B2: Description | C2: Unit | D2: Qty. | E2: Rate | F2: Amount
A3: A | B3: CIVIL & INTERIORS
A5: 1 | B5: DEMOLITION AND DISMENTALING
A6: 1.1 | B6: REMOVING OF WALL'S/WALL TILES/ PLASTER'S/FLOOR TILES ETC.
B7: Removing of wall's, Wall tiles, Plaster's, Floor Tiles etc and carting away the debris at siad locations in the same primises. | C7: Sqm | F7: =D7*E7 -> 0
A9: 1.3 | B9: REMOVAL OF FALSE CEILING
B10: Demolishing of existing partition and gypsum ceiling work on site as directed and carting away of the debris outside the campus limits,(or, as so mutually agreed upon); rate to include all leads and lift. | C10: Sqm | F10: =D10*E10 -> 0
A12: 1.4 | B12: REMOVING OF BASIN COUNTER
B13: Removing basin counter with below carcase and carting away the debris at siad locations in the same primises. | C13: Rmt. | F13: =D13*E13 -> 0
A15: 1.6 | B15: REMOVING OF EXISTING CUBICALS
B16: Removing Existing cubicals handing over to client and carting away the debris at siad locations in the same primises. | C16: Nos | F16: =D16*E16 -> 0
A18: 1.7 | B18: REMOVING OF TOILET ACCESSARIES AND HANDED OVER TO CLIENT
B19: Removing Toilet accessaries and handed over to client and carting away the debris at site locations in the same primises. | C19: Ls. | F19: =D19*E19 -> 0
A21: 1.8 | B21: REMOVAL OF DEBRIS.
B22: All the items in Dismantling / Demolishing shall be cartig away the debris from the site and unloading at a approved location as per statutory rules and regulations.Care shall be taken not to damage other property while carrying dismantling and demolition otherwise cost of damage will be bourne by the contractor.All the safty precautions shall be taken while doing dismantling and demolition job. | C22: TRIP | F22: =E22*D22 -> 0
A24: 1.9 | B24: REMOVING OF CEILING FIX FIXTURES.
B25: Removing of ceiling with fix fixtures such as light fixtures and sprinkler | C25: Ls. | F25: =E25*D25 -> 0
A27: 1.1 | B27: Deep cleaning the Gents and Ladies Toilet
B28: Deep cleaning of the Gents and Ladies Toilet | C28: Ls. | D28: 2 | F28: =E28*D28 -> 0
A30: 2 | B30: FLOORING/CLADDING
A31: 1.1 | B31: FLOOR TILES
B32: Providing and Laying, after selecting uniform colour and size 600 x 600 mm, 8 to 10 mm thk. Full bodied vitrified tiles (matt) fully rectified technical material in Flooring laid with 2 mm spacer and Stain Free Epoxy grout (Latapoxy SP 100) from MYK Laticrete of approved shade. The Tiles will be laid using adhesive of Bal / Laticrete of adequate thickness laid over an even bed of adequate thickness of cement mortar 1:4 (1cement:4coarse sand) minimum 20mm thk. Item rate includes cost of plaster bedding and grout making holes / cutouts for floor trap all other accessories as required. (make Morbilino/Nitco/Somany/equivalent.) | C32: Sqm | D32: 62 | F32: =D32*E32 -> 0
A34: 1.2 | B34: COUNTER WORK
B35: Providing & fixing Counter ( 600deepx150-300 facia drop) with appropriate MS framework of counter top finished with BWP ply 19mm thk, including making holes for sink and dust bin including edge polishing around basin and edge moulding as per Drawing and approved sample of moulding. Counter made to recieve stone top/ facia (exclude stone finish / Corian Finish from the cost) | C35: Sqm | D35: 5 | F35: =D35*E35 -> 0
A36: 1.3 | B36: Granite Top on Counter
B37: Providing and fixing of 19 mm thick pre-polished granite on the wash basin counter top. | C37: Sqm | D37: 3.5 | F37: =D37*E37 -> 0
A39: 1.4 | B39: Providing and fixing of 19 mm thick prepolished granite verticle/horizontal cladding upto 200 mm | C39: Rmt | F39: =D39*E39 -> 0
A41: 1.7 | B41: TILES CLADDING
B42: Vitrified Tile Wall Cladding: Providing and fixing Vitrified tile cladding in Toilet of size 600x600mm. Make Nitco/kajaria/ Somany | C42: Sqm | D42: 145 | F42: =D42*E42 -> 0
A44: 2 | B44: CEILING
A45: 2.1 | B45: Gypsum Ceiling
B46: Providing and fixing in position multi level GYPSUM board false-ceiling suspended on G.I. frame work in design as shown in the drawing. The G.I. frame work consist of Perimeter channel of size 27mm x 0.5mm. Intermediate channel of size 45mm x 0.5mm thick. Ceiling section of 0.5mm thickness. 12.5mm thick tapered edge gypsum plaster board fixed to ceiling channel with 25mm dry wall screws at 230mm centers Jointed and finished with requisite filler, paper tape, finisher and primer suitable for Gypsum plaster boards. Rate to include making necessary cut-outs/openings for light fittings. This item includes all vertical drops, niches in ceiling etc. Gypsum board and finishing putty will be Gypsum India/USG. | C46: Sqm | D46: 13 | F46: =D46*E46 -> 0
A47: 2.2 | B47: COVE WORK
B48: Providing and fixing cove upto 200mm wide of following hts finished with 3 coats of emulsion paint on the edges of Gypsum Ceiling with or without light as per locations. Cost is without painting)
A49: 2.2b | B49: 150 mm ht | C49: RMT | D49: 35 | F49: =D49*E49 -> 0
A51: 2.3 | B51: PERFORATED METAL MESH CEILING
B52: Providing & Fixing of Alluminium lay in Standard Mesh (2.5mm diameter – 16% open area) metal ceiling consisting of 600x600mm Lay in tiles of pre coated aluminium in 0.5 mm thickness in Global white color Soundtex acoustical fleece hot pressed to the back of the tile to be laid on plain grid systems with color and white/black reveal white having rotary stitching on the Main Runner, 1200 mm & 600 mm Cross Tees. The tiles would have NRC of 0.70, Fire Performance of Class A2-s1.d0 as per EN13501 standard in module size of 600 X 600mm, suitable for Green Building application, with Recycled content of 25%. Suspension system for grid to be of make Armstrong or Techno or equivalent.The tile shall be laid on grid system with 15mm white flanges incorporating a 6mm central reveal in white/black color and with a web height of 45mm and a load carrying capacity of minimum 15.68 Kgs/M. Main Runners & Cross Tees to have mitered ends & “birds mouth” notches to provide mitered cruciform junctions. The T Sections have a Galvanizing of 90 grams per M2 with pull out strength of 100 Kgs.
A53: 2.3a | B53: SIZE :- 600x600mm | C53: Sqm | D53: 475 | F53: =D53*E53 -> 0
A55: 3 | B55: PARTITION & PANELLING
A56: 3.1 | B56: 12mm THK BWP PLY Paneling.
B57: P/F 12mm thk HDHMR BOARD Mirror boxing, Led Strip Lighting behind the mirror.This boxing would be fixed to the blockwork with rough wood battens and enough anchoring is to be provided to take the weight of the mirror. (Wall Paneling as per 3D Veiw.) | C57: Sqm | D57: 7.5 | F57: =D57*E57 -> 0
A58: 3.2a | B58: TOILET MIRROR OVER THE COUNTER
B59: Providing and fixing 6mm thick Mirror Panels fixed with mirror-compatible double sided adhesive tapes (3M make mirror tape) or with mirror-compatible adhesive (Use only neutral binding agents such as Alkoxy silicone or Oxime silicone) as per the manufacturer's recommendation over a 6mm ply fixed to boxing as described in 3.1 above . | C59: Sqm | D59: 7.5 | F59: =D59*E59 -> 0
A61: 5 | B61: FINISHING
A62: 5.1 | B62: POP PUNNING
B63: P/A 12.5 mm thick P.O.P. Punning on the Existing / Proposed walls with/ without horizontal grooves to create a smooth surface. | C63: Sqm | D63: 77.5 | F63: =D63*E63 -> 0
A64: 5.1 | B64: ACRYLIC EMULSION PAINT
B65: Providing and applying 2 to 3 coats (as approved by architect/consultant) of 100% washable, antifungal, antibacterial and stain resistant paint over a coat of primer. The paint to be of approved shade, complete as per manufacturers specifications, drawing & as directed by the Engineer-in-charge. Suggested Make: Dulux Professional Solitaire Stain Resistant or equivalent. | C65: Sqm | D65: 77.5 | F65: =D65*E65 -> 0
A67: 6.3 | B67: WATER PROOFING WORKS - chemical waterproofing.
B68: Three coats of tapecrete - first layer of tapecrete to be @0.253kg/sqm,in proportion of 2:1(2 parts of cement and 1 part of tapecrete), the second & third layer to be @ 0.126kg/sqm in 2:1:1.5 and 2:1:1each admixed with grey cement over a coat of neat cement slurry admixed with chemical CH - 9 to a total thickness of not less than 4mm after preparation of the surface etc. including a protective layer of 12mm thick plaster in 1:4 mortar with coarse sand and application of epoxy based putty at junctions and corners , around pipes and other outlets etc. prior to application of final coat of tapecrete. Allow for necessary curing and drying time for each coat, providing proper bonding keys in coats where required and necessary curing. Tapecrete shall be polymer modified cementitious emulsion. The work shall be carried out by specialized agency broadly as outlined above and shall carry guarantee against leakage, sepage, sweating and other defects for 10 years. Item to include making gola as per PMC instructions. | C68: Sqm | F68: =D68*E68 -> 0
A70: 7 | B70: MISCELLANEOUS WORK
A71: 7.1 | B71: URINAL PARTITION
B72: P/F 19mm thk Granite Urinal Partition Size: 1200x450mm | C72: NOS | D72: 5 | F72: =D72*E72 -> 0
A73: 7.2 | B73: TOILET CUBICAL PARTITIONS AND DOORS.
B74: Toilet cubicles- Providing and fixing modular partitions for toilet cubicles made of 12mm thick compact laminate using stainless steel profiles of 304 grade polished in 400 grains. Profiles of approx size 60x60mm.The partition to stop at 150mm above FFL. Height of the partition to be 2200mm. Cost to be inclusive of door of width 750mm of the same specifications as per the cubicle partitions. Accessories to be finished with door stopper (cubicle mounted), thumb turn with occupancy indicator, 'U' channel, adjustable legs, 3 nos gravity self closing hinges, screws, plugs, and double robe hook etc all complete. Size - 1550mm X 1000mm X2150mm H Note :- Greenlam Cubical Consider | C74: NOS | D74: 6 | F74: =D74*E74 -> 0
B76: TOTAL AMOUNT | F76: =SUM(F5:F75) -> 0
A78: B | B78: PLUMBING WORK
A80: 1 | B80: SANITARY FIXTURES
A81: 1.1 | B81: Supply, fixing, testing and commissioning white vitreous china wall hung European type WC with 'P' trap straight/offset type flexible single body push fit type WC - Connection socket with lip seal and body made of PP with C.P. bolts, nuts, C.I. chair or other hanging arrangement, with solid bakelite seat and slow falling cover, C.P. brass hinges rubber buffers with accessories,C.I/M.S. brackets painted with two coats of enamel paint of approved shade over a coat of primer. C.P. brass screws, including cutting and making good the wall and floors wherever required. (Make : Hindware/Jaguar make) | C81: Each | D81: 7 | F81: =D81*E81 -> 0
A83: 1.2 | B83: Supply and fixing of concealed flush valve (Make : Hindware/Jaguar make) | C83: Each | D83: =+D81 -> 7 | F83: =D83*E83 -> 0
A85: 1.3 | B85: Providing and Fixing Wash basin Under counter /over the counter mounting, specially fabricated brackets painted white with waste coupling, C.P. wall flange and rubber adopter for waste connection complete, including cutting and making good the walls wherever required. (Make : Hindware/Jaguar make) | C85: Each | D85: 5 | F85: =D85*E85 -> 0
A87: 1.4 | B87: Providing and fixing of Sensor tap on wash basin with S.S braided flexible connector, nuts and washers including cutting hole complete. in all respects. (Make : Hindware/Jaguar make) | C87: Each | D87: =+D85 -> 5 | F87: =D87*E87 -> 0
A89: 1.5 | B89: Providing, fixing, testing & commissioning vitreous china flat back urinal large (semistall) of size 610x410x380 mm or eqv. size with C.I. hangers, C.P. 15mm Spreader, 32mm dia C.P. brass domical waste, 32 mm dia cast Bottle Trap including connection pipe to wall with C.P flange complete including cutting and making good the walls and floors wherever required. (Make : Hindware/Jaguar make) | C89: Each | D89: 5 | F89: =D89*E89 -> 0
A91: 1.6 | B91: Providing and Fixing of low noise Urinal flush valve touch-free infrared flushing device battery operated (9V) and/or mains operated (9V) with isolating valve which includes roughing in set for electronic actuation and Urinal Control finishing set. Roughing in set should comprises - plastic construction casing with cleaning cover; pre-assembled water path with isolating valve, sealing plug, cleaning cover and Urinal Control finishing set should comprises mounting frame with electronic module, front panel with sensor, 230V, 50Hz Power supply unit with mains plug, solenoid valve with pre-filter, diagnostic lamps, adjustment range, flushing time seconds adjustable, capable of operating with pressurized supply (Make : Hindware/Jaguar make) | C91: Each | D91: =+D89 -> 5 | F91: =D91*E91 -> 0
A93: 1.7 | B93: Providing and fixing of health spray with pressure reducing solution which can tolerate water pressure up to 10 bar flow pressure and outlet pressure of 2 bar with metal hose and holder in Polished Chrome (Make : Hindware/Jaguar make) | C93: Each | D93: =+D81 -> 7 | F93: =D93*E93 -> 0
A95: 1.8 | B95: Providing and Fixing of ABS BODY liquid soap dispenser horizontal filled with liquid soap (one time) including cutting and making good the walls, wherever required (Make : Euronics, Model : ES16SA) | C95: Each | D95: 3 | F95: =D95*E95 -> 0
A97: 1.9 | B97: Providing and Fixing Paper Towel Dispensers with capacity of 3 Packets or as per make (Make : Euronics, Model : EP23) With ABS Body | C97: Each | D97: 3 | F97: =D97*E97 -> 0
A99: 1.1 | B99: Providing C.P brass toilet paper holder with stainless steel roller complete, including cutting and making good the walls where required. (Make : Hindware) | C99: Each | D99: =+D81 -> 7 | F99: =D99*E99 -> 0
A101: 1.11 | B101: Provide and fixing of Set of SS Grab Bars and Grap Rails for Handicapped Toilet (Make : Euronics, Model : EGRS02, EGR01-600 mm) and EGR04 | C101: Set | D101: 1 | F101: =D101*E101 -> 0
A103: 1.12 | B103: Providing and Fixing ABS Body hand drier (Automatic Sensor Type) to be operated with 220 volts, single phase, with fully hygienic condition, with all accessories including cutting and making good the walls, wherever required. | C103: Each | D103: 3 | F103: =D103*E103 -> 0
A105: 1.13 | B105: Providing and Fixing C.P cast brass double coat hook fixed to wooden / PVC cleats with C.P. brass screws (Make : Euronics, Model : EC02) | C105: Each | D105: =+D81 -> 7 | F105: =D105*E105 -> 0
A107: 1.14 | B107: Supply and fixing of approved make jaquar make angle valve | C107: Each | D107: 12 | F107: =D107*E107 -> 0
A109: 1.15 | B109: Supply and fixing of Nahani trap | C109: Each | D109: 15 | F109: =D109*E109 -> 0
A111: 1.16 | B111: Supply and placing of dustbin size 10 x 14 inch | C111: Each | F111: =D111*E111 -> 0
A113: (II) | B113: SOIL, WASTE, VENT PIPES & FITTINGS
A115: 1 | B115: Supply and fixing, of PVC soil, waste and vent pipes (SWR) confirming to IS13592 : 1990, type B with rubber ring (confirming to IS 5382) 6kg/sqcm with solvent joint inclusive of all necessary specials like bends, tees, offsets, doorbends, junctions, screw type caps with rubber rings for cleanout pipe ends, etc., suspended under floor slabs/fixed on walls or on pipe racks in shafts including all kind of supports with drilling of holes, wall chasing, etc.
A117: a) | B117: 100 mm dia | C117: RM | D117: 35 | F117: =D117*E117 -> 0
A118: b) | B118: 75 mm dia | C118: RM | D118: 25 | F118: =D118*E118 -> 0
A120: 2 | B120: Providing & Fixing PVC (SWR) Multi/P- trap (as per requirement) along with inlet hopper of GI/CI for indirect waste connections of self cleaning design with multiple inlet connections of 40/50 mm dia and outlet of 100 mm with a clear intact water seal of 50 mm complete in accordance to EN 877 (last edition) including EN 681-1 for rubber gaskets. This includes the cost of cutting,jointing, fixing and making good the same complete as per direction of Engineer in Charge. | C120: Each
A122: 3 | B122: Providing and fixing Heavy class SS grating of approved design including setting in floor with cement motor to match with floor finish as per architect requirement suitable for waster F.D. & F.T.
A124: a) | B124: 125 mm x 125 mm | C124: Each | D124: 10 | F124: =D124*E124 -> 0
A125: b) | B125: 150 mm x 150 mm | C125: Each | D125: 12 | F125: =D125*E125 -> 0
A127: (III) | B127: WATER SUPPLY SYSTEM (Internal )
A129: 1 | B129: Providing and fixing CPVC (Chlorinated Poly Vinyl Chloride) water supply pipes with pipe as per CTS SDR 11 (operating pressure - 7 Bar @ 82 Deg C and 28 Bar @ 23 Deg C)for pipes from 1/2 Inch to 2 Inch. Schedule 40 Pipe to be used from 2-1/2 Inch to 6 Inch. Pipes shall be joined using solvent welded CPVC fittings i.e. Tees, Elbows, Couplers, Unions, Reducers, brushings etc. including transition fittings (connection between CPVC & metal pipe/GI) i.e. Brass Adaptors (both Male & Female threaded) conforming to ASTM D-2846. ASTM F441 with only CPVC solvent cement conforming to ASTM F-493.
B130: Fixing/supporting the pipes & fittings at wall/ceiling level supported by galvanized clamps, hangers etc, as per specification. CPVC pipe sleeves suitable higher size shall be provided wherever the pipes are crossing the fire rated walls / floors slab and sealing the sleeves with glass wool in between and fire sealant compound at either end all as per Project Manager's / Consultant requirement. All termination points for installation of faucets shall have brass termination fittings. Installation shall be to as per Technical Manual of manufacturer of pipes & fittings.(Cost including maximum of 7.5x7.5cm chasing in wall and floors for the pipe and making good the same.)
A132: a) | B132: 15 mm dia | C132: Meter | D132: 45 | F132: =D132*E132 -> 0
A133: b) | B133: 20 mm dia | C133: Meter | D133: 35 | F133: =D133*E133 -> 0
A134: c) | B134: 25 mm dia | C134: Meter | D134: 25 | F134: =D134*E134 -> 0
A135: d) | B135: 32 mm dia | C135: Meter | D135: 20 | F135: =D135*E135 -> 0
A137: 4 | B137: Providing and fixing forged brass lever operated ball valve of full flow with forged brass ball (Machined to mirror smooth finsh with hard chrome plated) and spindle with setting and gland of superior quality having minimum working pressure of 10 kg/cm2 etc. complete in all respect.
A139: a) | B139: 15mm dia | C139: Each | D139: 4 | F139: =D139*E139 -> 0
A140: b) | B140: 20 mm dia | C140: Each | D140: 2 | F140: =D140*E140 -> 0
A141: c) | B141: 25 mm dia | C141: Each | F141: =D141*E141 -> 0
A142: d) | B142: 32mm dia | C142: Each | F142: =D142*E142 -> 0
A143: e) | B143: 40mm dia | C143: Each | F143: =D143*E143 -> 0
A145: B | B145: ELECTRICAL WORK
A146: 1 | B146: Removal and reinstallation of all existing electrical light fixtures will be carried out as per the 3D design presentation. No new light fixtures or cabling are included; if required, they will be charged at standard market rates. | C146: LS / Toilet | F146: =D146*E146 -> 0
B148: TOTAL AMOUNT | F148: =SUM(F80:F147) -> 0
B150: Total for Toilet Work (Excluding Taxes) | F150: =SUM(F148,F76,) -> 0
