Workbook

Sheet HVAC SUMMARY
A1: PROJECT | B1: TS-T2- WEX - BANGLORE
A2: SUB | B2: SUMMARY
A3: Sl. No. | B3: DESCRIPTION | C3: Amount
C4: Supply | D4: Installation | E4: Total
B5: LOW SIDE WORK
A6: C | B6: INSTALLATION OF CHW AHU , FCU & PIPING WORK | C6: ='HVAC LOW SIDE '!I73 -> 0 | D6: ='HVAC LOW SIDE '!J73 -> 0 | E6: =SUM(C6:D6) -> 0
A7: D | B7: SHEET METAL WORK & AIR TERMINATION | C7: ='HVAC LOW SIDE '!I233 -> 0 | D7: ='HVAC LOW SIDE '!J233 -> 0 | E7: =SUM(C7:D7) -> 0
A8: E | B8: INSULATION WORK | C8: ='HVAC LOW SIDE '!I244 -> 0 | D8: ='HVAC LOW SIDE '!J244 -> 0 | E8: =SUM(C8:D8) -> 0
A9: F | B9: TOTAL OF VRF WORK | C9: ='HVAC LOW SIDE '!I354 -> 0 | D9: ='HVAC LOW SIDE '!J354 -> 0 | E9: =SUM(C9:D9) -> 0
A10: G | B10: ELECTRICAL WORK | C10: ='HVAC LOW SIDE '!I378 -> 0 | D10: ='HVAC LOW SIDE '!J378 -> 0 | E10: =SUM(C10:D10) -> 0
A11: H | B11: TOTAL OF VAV WORKS -01 | C11: ='HVAC LOW SIDE '!I412 -> 0 | D11: ='HVAC LOW SIDE '!J412 -> 0 | E11: =SUM(C11:D11) -> 0
A12: I | B12: TOTAL OF VAV WORKS -02 | C12: ='HVAC LOW SIDE '!I432 -> 0 | D12: ='HVAC LOW SIDE '!J432 -> 0 | E12: =SUM(C12:D12) -> 0
B14: TOTAL HVAC OF LOW SIDE WORK | C14: =SUM(C6:C13) -> 0 | D14: =SUM(D6:D13) -> 0 | E14: =SUM(E6:E13) -> 0
B16: GST @18% | C16: =C14*18% -> 0 | D16: =D14*18% -> 0 | E16: =E14*18% -> 0
B18: GRAND TOTAL WITH GST ( LOW SIDE WORK) | C18: =SUM(C14:C17) -> 0 | D18: =SUM(D14:D17) -> 0 | E18: =SUM(E14:E17) -> 0

Sheet HVAC LOW SIDE 
A1: PROJECT | B1: TS-T2 - WEX- BANGLORE
A2: Sl. No. | B2: DESCRIPTION | C2: Office | D2: COMMON AREA | E2: TOTAL | F2: Unit | G2: Rate | I2: AMOUNT
C3: QTY | G3: SUPPLY | H3: INSTALLATION | I3: SUPPLY | J3: INSTALLATION
A4: A | B4: CHW AHU /CASSETTE/HIWALL & PIPING WORKS
A6: 1 | B6: Installation, testing & commissioning of Floor mounted AHU (Double Skin) as per specification
B7: Fan section with DIDW type centrifugal impeller with the motor shall be permanent magnet external rotor motor with integrated electronics and suitable for continuous operation, Chilled water coils of copper tube and aluminum fins construction section with six rows deep having 12-13 FPI with coil face velocity of 500 FPM, Filter section with synthetic fiber filters in corrugated shape rated for filter face velocity 500 FPM Prefilter, & MERV 13 Rating filters.IE-3 motor (inside AHU casing), , spring mounted vibration Isolators, Limit Switch, Emergency Light, UV Emitter section with UVC Lamps, Guard for Inspection Door. AHU motor should be minimum IE3 grade along with the necessary controller hosed in a panel. The internal wiring between the limit switches,without UV lamp & interlock to be part of AHU vendor scope. Fan Vendor should also provide the BacNet card for each AHU for BMS integration.
B8: The air-handling units shall be as per specifications with extruded aluminum framework having panels with outer pre-plasticised 0.6mm G.I / Galvalume sheets & inner plain 0.6mm GI / Galvalume sheet having injected 23- 25 mm PUF of 38 -kg/Cum density in between. The drain pan shall be of 18 G SS with 13mm thick nitrile rubber insulation. The frame for AHU shall be extruded aluminum. The entire AHU shall be mounted on GI base of min 70mm.
B9: Drain pan: 1.2 mm thick SS304 with 25mm Nitrile rubber sandwiched. Provide 40 mm SS threaded drain nipple.
B10: Dampers: Al. anodized low leakage aerofoil.
B11: Filter section: With Prefilter , Non-Combustible Filter, access doors filters in extruded al. box type frames with gasket arrangements around filter frames. This should include one set of commissioning filters
B12: Coil Section: Cu coils with hydrophilic coated al. fins,6 Row coil , CHW COIL
B13: Fan section: Centrifugal fans with access doors on both sides, inspection windows, limit switch to shut off fan on door opening, Emergency Light,UV Emitter section with UVC Lamp, VFD Starter Panel & cabling from control to fans shall be scope of HVAC VENDOR.
B14: Drive: IE-3 motor
B15: Vibration Isolators: For fans and mounting arrangements - Rust resistant spring
B16: Flexible connectors: Non flammable, weather and fungus proof
B17: FLOOR MOUNTED ESP-40 mm | E17: =C17+D17 -> 0 | I17: =+N($E17)*N(G17) -> 0 | J17: =+N($E17)*N(H17) -> 0
A18: 1.1 | B18: 16000 CFM with VFD & bypass starter | E18: =C18+D18 -> 0 | F18: Nos | I18: =+N($E18)*N(G18) -> 0 | J18: =+N($E18)*N(H18) -> 0
A19: 1.2 | B19: 12000 CFM with bypass starter | E19: =C19+D19 -> 0 | F19: Nos | I19: =+N($E19)*N(G19) -> 0 | J19: =+N($E19)*N(H19) -> 0
E20: =C20+D20 -> 0 | I20: =+N($E20)*N(G20) -> 0 | J20: =+N($E20)*N(H20) -> 0
A21: 1.3 | B21: CEILING SUSPENDED AHU ESP 25 mm | E21: =C21+D21 -> 0 | I21: =+N($E21)*N(G21) -> 0 | J21: =+N($E21)*N(H21) -> 0
B22: 12000 CFM with starter Panel | E22: =C22+D22 -> 0 | F22: Nos | I22: =+N($E22)*N(G22) -> 0 | J22: =+N($E22)*N(H22) -> 0
E23: =C23+D23 -> 0 | I23: =+N($E23)*N(G23) -> 0 | J23: =+N($E23)*N(H23) -> 0
E24: =C24+D24 -> 0 | I24: =+N($E24)*N(G24) -> 0 | J24: =+N($E24)*N(H24) -> 0
A25: 1.4 | B25: CEILING SUSPENDED AHU ESP 20 mm | E25: =C25+D25 -> 0 | I25: =+N($E25)*N(G25) -> 0 | J25: =+N($E25)*N(H25) -> 0
B26: 4400 CFM/20.0 TR with starter Panel | E26: =C26+D26 -> 0 | F26: Nos | I26: =+N($E26)*N(G26) -> 0 | J26: =+N($E26)*N(H26) -> 0
E27: =C27+D27 -> 0 | I27: =+N($E27)*N(G27) -> 0 | J27: =+N($E27)*N(H27) -> 0
A28: 1.3 | B28: DECORATIVE WALL MOUNTED FAN COIL UNITS | E28: =C28+D28 -> 0 | I28: =+N($E28)*N(G28) -> 0 | J28: =+N($E28)*N(H28) -> 0
B29: Installation, Testing, Commissioning of Decorative High Wall Mounted type Chilled Water based Fan Coil Units with energy efficient 3 speed motor, ABS plastic decorative casing, Low noise fan-motor combination, Synthetic washable filter, Semi Circular Chilled Water Cooling Coil & aluminium fins with corrossion resistant coating blue or golden, minimum 13 FPI, Copper tubes minimum 7mm dia, multi step design Coil section with minimum 2 Rows, an in-built factory fitted 2 way On/ Off control valve of minimum PN16 rating duly connected and wired, with combination of pair of brass ball valve with "Y" strainer set fixed outside FCU, flexible pipe/hose with required couplings to fit CHW field In/Out piping; All piping are to be insulated with closed cell elastomeric rubber insulation. Unit shall be equipped with self diagnostic function, temperature display and supplied with Digital Display type cordless remote with 3 speed fan switch & Temp Edit facility & Digital Temp Display, supplied with relevant power supply cable from nearest point to to FCU as required. Inbuilt BMS provision in the units, no additional equipments should be required for Backnet IP connectivity | E29: =C29+D29 -> 0 | I29: =+N($E29)*N(G29) -> 0 | J29: =+N($E29)*N(H29) -> 0
B30: 2.0 TR (Hub room & IT Room) | E30: =C30+D30 -> 0 | F30: Nos | I30: =+N($E30)*N(G30) -> 0 | J30: =+N($E30)*N(H30) -> 0
B31: 1.6 TR (UPS room) | E31: =C31+D31 -> 0 | F31: Nos | I31: =+N($E31)*N(G31) -> 0 | J31: =+N($E31)*N(H31) -> 0
B32: 1.0 TR (Battery room) | E32: =C32+D32 -> 0 | F32: Nos | I32: =+N($E32)*N(G32) -> 0 | J32: =+N($E32)*N(H32) -> 0
B33: 1.0 TR (IT STORE room ) | E33: =C33+D33 -> 0 | F33: Nos | I33: =+N($E33)*N(G33) -> 0 | J33: =+N($E33)*N(H33) -> 0
E34: =C34+D34 -> 0 | I34: =+N($E34)*N(G34) -> 0 | J34: =+N($E34)*N(H34) -> 0
A35: 1.4 | B35: HIGH STATIC DUCT FAN COIL UNIT ( FCU ) | E35: =C35+D35 -> 0 | I35: =+N($E35)*N(G35) -> 0 | J35: =+N($E35)*N(H35) -> 0
B36: Supply, installation, testing and commissioning of ceiling concealed type High Static Duct type Fan Coil Units, Eurovent Certified, single skin, draw through type with minimum 3 speed fan motor, minimum 3 row chilled water coil, with Al fins with corrossion resistant coating blue or gold, metallic centrifugal blower, washable filter minimum 20 micron, insulated enclosed double skin drain tray, hanging rods and accessories, copper piping connections, etc. of the following capacities. Starter panel with necessary controls, incoming cable from starter panel to unit, connected with Pressure Independent Control cum Balancing Valve DN25, with minimum 24V Modulating Actuators IP54 with 0-10VDC control, Digital Thermostat with Modbus connectivity, Fire retardant canvass connections with GI powdercoated finish angle flanges on both sides, etc. Additional auxillary tray should accommodate all valves as per the specifications and approved drawings. The external static pressure shall be as per specifictions below. he unit shall have provision for complete control and monitoring over BMS using Modbus/ Bacnet protocol, additional items and controllers if required shall also be provided. | E36: =C36+D36 -> 0 | I36: =+N($E36)*N(G36) -> 0 | J36: =+N($E36)*N(H36) -> 0
B37: 3.0 TR ( Server Room) | E37: =C37+D37 -> 0 | F37: Nos | I37: =+N($E37)*N(G37) -> 0 | J37: =+N($E37)*N(H37) -> 0
E38: =C38+D38 -> 0 | I38: =+N($E38)*N(G38) -> 0 | J38: =+N($E38)*N(H38) -> 0
A39: 2 | B39: Insulated chilled water piping, MS heavy duty 'C' Class (as per IS 1239 - Part I 2004) complete with bends, elbows, tees, vibration isolators, hangers, full round PU / rubber supports insulated with 25mm Thick Nitrile Rubber Insulation with 7 mil Cloth Pipe thickness: 6.3 mm thick for 200 - 250 dia pipes 8 mm thick for 300 - 350 dia pipes 10 mm thick for 400 - 600 dia pipes 12 mm thick for 650 - 1000 dia pipes Insulation thickness exposed to sun - 75 mm | E39: =C39+D39 -> 0 | I39: =+N($E39)*N(G39) -> 0 | J39: =+N($E39)*N(H39) -> 0
A40: 2.1 | B40: 80mm dia | E40: =C40+D40 -> 0 | F40: Rmt | I40: =+N($E40)*N(G40) -> 0 | J40: =+N($E40)*N(H40) -> 0
A41: 2.2 | B41: 50mm dia | E41: =C41+D41 -> 0 | F41: Rmt | I41: =+N($E41)*N(G41) -> 0 | J41: =+N($E41)*N(H41) -> 0
A42: 2.3 | B42: 32mm dia | E42: =C42+D42 -> 0 | F42: Rmt | I42: =+N($E42)*N(G42) -> 0 | J42: =+N($E42)*N(H42) -> 0
A43: 2.4 | B43: 25mm dia | E43: =C43+D43 -> 0 | F43: Rmt | I43: =+N($E43)*N(G43) -> 0 | J43: =+N($E43)*N(H43) -> 0
E44: =C44+D44 -> 0 | I44: =+N($E44)*N(G44) -> 0 | J44: =+N($E44)*N(H44) -> 0
A45: 3 | B45: Supply, Installation, Testing and commissioning of AHU Manifold including all valves and accessories | E45: =C45+D45 -> 0 | I45: =+N($E45)*N(G45) -> 0 | J45: =+N($E45)*N(H45) -> 0
A46: 3.1 | B46: 80mm dia | E46: =C46+D46 -> 0 | F46: Nos | I46: =+N($E46)*N(G46) -> 0 | J46: =+N($E46)*N(H46) -> 0
A47: 3.2 | B47: 50mm dia | E47: =C47+D47 -> 0 | F47: Nos | I47: =+N($E47)*N(G47) -> 0 | J47: =+N($E47)*N(H47) -> 0
A48: 3.3 | B48: 40mm dia | E48: =C48+D48 -> 0 | F48: Nos | I48: =+N($E48)*N(G48) -> 0 | J48: =+N($E48)*N(H48) -> 0
A49: 3.4 | B49: 32mm dia | E49: =C49+D49 -> 0 | F49: Nos | I49: =+N($E49)*N(G49) -> 0 | J49: =+N($E49)*N(H49) -> 0
A50: 3.5 | B50: 25mm dia | E50: =C50+D50 -> 0 | F50: Nos | I50: =+N($E50)*N(G50) -> 0 | J50: =+N($E50)*N(H50) -> 0
E51: =C51+D51 -> 0 | I51: =+N($E51)*N(G51) -> 0 | J51: =+N($E51)*N(H51) -> 0
A52: 4 | B52: Supply, Installation, Testing and commissioning of Insulated Butterfly Valves with flanges, gaskets, bolts etc. | E52: =C52+D52 -> 0 | I52: =+N($E52)*N(G52) -> 0 | J52: =+N($E52)*N(H52) -> 0
A53: 4.1 | B53: 80mm dia | E53: =C53+D53 -> 0 | F53: Nos | I53: =+N($E53)*N(G53) -> 0 | J53: =+N($E53)*N(H53) -> 0
A54: 4.2 | B54: 50mm dia | E54: =C54+D54 -> 0 | F54: Nos | I54: =+N($E54)*N(G54) -> 0 | J54: =+N($E54)*N(H54) -> 0
A55: 4.3 | B55: 40mm dia | E55: =C55+D55 -> 0 | F55: Nos | I55: =+N($E55)*N(G55) -> 0 | J55: =+N($E55)*N(H55) -> 0
A56: 4.4 | B56: 32mm dia | E56: =C56+D56 -> 0 | F56: Nos | I56: =+N($E56)*N(G56) -> 0 | J56: =+N($E56)*N(H56) -> 0
A57: 4.5 | B57: 25mm dia | E57: =C57+D57 -> 0 | F57: Nos | I57: =+N($E57)*N(G57) -> 0 | J57: =+N($E57)*N(H57) -> 0
E58: =C58+D58 -> 0 | I58: =+N($E58)*N(G58) -> 0 | J58: =+N($E58)*N(H58) -> 0
A59: 5 | B59: Supply, Installation, Testing and commissioning of Insulated balancing type control-cum-balancing valves complete with flanges measuring ports etc. | E59: =C59+D59 -> 0 | I59: =+N($E59)*N(G59) -> 0 | J59: =+N($E59)*N(H59) -> 0
A60: 5.1 | B60: 50mm dia | E60: =C60+D60 -> 0 | F60: Nos | I60: =+N($E60)*N(G60) -> 0 | J60: =+N($E60)*N(H60) -> 0
A61: 5.2 | B61: 40mm dia | E61: =C61+D61 -> 0 | F61: Nos | I61: =+N($E61)*N(G61) -> 0 | J61: =+N($E61)*N(H61) -> 0
A62: 5.3 | B62: 32mm dia | E62: =C62+D62 -> 0 | F62: Nos | I62: =+N($E62)*N(G62) -> 0 | J62: =+N($E62)*N(H62) -> 0
A63: 5.4 | B63: 25mm dia | E63: =C63+D63 -> 0 | F63: Nos | I63: =+N($E63)*N(G63) -> 0 | J63: =+N($E63)*N(H63) -> 0
E64: =C64+D64 -> 0 | I64: =+N($E64)*N(G64) -> 0 | J64: =+N($E64)*N(H64) -> 0
E65: =C65+D65 -> 0 | I65: =+N($E65)*N(G65) -> 0 | J65: =+N($E65)*N(H65) -> 0
A66: 6 | B66: Supply, Installation, Testing and commissioning of I BTU meter with all necessary flanges etc Complete with PIPE SPOOL piece. | E66: =C66+D66 -> 0 | I66: =+N($E66)*N(G66) -> 0 | J66: =+N($E66)*N(H66) -> 0
A67: 6.1 | B67: 80mm dia | E67: =C67+D67 -> 0 | F67: Nos | I67: =+N($E67)*N(G67) -> 0 | J67: =+N($E67)*N(H67) -> 0
A68: 6.2 | B68: 50mm dia | E68: =C68+D68 -> 0 | F68: Nos | I68: =+N($E68)*N(G68) -> 0 | J68: =+N($E68)*N(H68) -> 0
A69: 6.3 | B69: 32mm dia | E69: =C69+D69 -> 0 | F69: Nos | I69: =+N($E69)*N(G69) -> 0 | J69: =+N($E69)*N(H69) -> 0
A70: 6.4 | B70: 25mm dia | E70: =C70+D70 -> 0 | F70: Nos | I70: =+N($E70)*N(G70) -> 0 | J70: =+N($E70)*N(H70) -> 0
E71: =C71+D71 -> 0 | I71: =+N($E71)*N(G71) -> 0 | J71: =+N($E71)*N(H71) -> 0
E72: =C72+D72 -> 0 | I72: =+N($E72)*N(G72) -> 0 | J72: =+N($E72)*N(H72) -> 0
B73: Total of CHW AHU /CASSETTE/HIWALL & PIPING WORKS | I73: =SUM(I5:I72) -> 0 | J73: =SUM(J5:J72) -> 0
A75: B | B75: SHEET METAL WORK & AIR TERMINATION | E75: =C75+D75 -> 0
E76: =C76+D76 -> 0
A77: 1 | B77: DUCTING , INSULATION WORKS & AIR TERMINALS | E77: =C77+D77 -> 0
B78: Rectangular Duct : Galvanizing shall be Class VIII – light coating of zinc, nominal 120 gsm / sqm surface area and Lock Forming Quality prime material alongwith mill test certificates. In addition, if deemed necessary, samples of raw material, selected at random by owner’s site representative shall be subject to approval and tested for thickness and zinc coating at contractor’s expense. | E78: =C78+D78 -> 0
B79: All duct construction and installation shall be in accordance with SMACNA standards. In addition ducts shall be factory fabricated utilizing the following machines to provide the requisite quality of ducts. | E79: =C79+D79 -> 0
B80: The ducts shall be provided with Stiffner rods & Guide vanes for the ducts more than 800 mm | E80: =C80+D80 -> 0
B81: All ducts shall be fabricated and installed in workmanlike manner, conforming to relevant SMACNA codes. | E81: =C81+D81 -> 0
B82: The Duct shall be supported with specified Supports at regular intervalas as mentioned in the technical specifications. The sheet metal ducting running inside AHU Rooms& near AHU rooms should be supported with special acoustic hangers to avoid transmission of vibaration from AHU Room to adjacent sensitive areas. The insulation executed on the ducts inside the AHU Room shall be further finished with fiber glass cloth for mechanical protection.(To ensure the air tightness, all ducts shall be checked with Smoke Test after completion of installation but before applying insulation) | E82: =C82+D82 -> 0 | I82: =+N($E82)*N(G82) -> 0 | J82: =+N($E82)*N(H82) -> 0
A83: 1.1 | B83: 24 gauge galvanized sheet steel TDF flanges (0.63mm) (0-750mm) | C83: 65 | D83: 40 | E83: =C83+D83 -> 105 | F83: Sqm | I83: =+N($E83)*N(G83) -> 0 | J83: =+N($E83)*N(H83) -> 0
A84: 1.2 | B84: 22 gauge galvanized sheet steel /TDF flanges(0.80mm) (751-1200mm) | C84: 65 | D84: 40 | E84: =C84+D84 -> 105 | F84: Sqm | I84: =+N($E84)*N(G84) -> 0 | J84: =+N($E84)*N(H84) -> 0
A85: 1.3 | B85: 20 gauge galvanized sheet steel /TDF flanges(1.00mm)(1201-1800mm) | C85: 90 | D85: 25 | E85: =C85+D85 -> 115 | F85: Sqm | I85: =+N($E85)*N(G85) -> 0 | J85: =+N($E85)*N(H85) -> 0
E86: =C86+D86 -> 0
E87: =C87+D87 -> 0 | I87: =+N($E87)*N(G87) -> 0 | J87: =+N($E87)*N(H87) -> 0
A88: 2 | B88: Supply & applying of spray painting for exposed rectangular & Elliptical ducts(colour will be confirmed by PMC/ARCH at later date) -2 coats of primer to be considered as first level. Further based on finalized color one set of painting to be done. And final coat to be applied, including support painting. | C88: 350 | D88: 25 | E88: =C88+D88 -> 375 | F88: Sqm | I88: =+N($E88)*N(G88) -> 0 | J88: =+N($E88)*N(H88) -> 0
E89: =C89+D89 -> 0 | I89: =+N($E89)*N(G89) -> 0 | J89: =+N($E89)*N(H89) -> 0
A90: 3 | B90: FACTORY FABRICATED POWDER COATED SPIRAL ELLIPTICAL/OVAL DUCTS | E90: =C90+D90 -> 0 | I90: =+N($E90)*N(G90) -> 0 | J90: =+N($E90)*N(H90) -> 0
B91: ELLIPTICAL / SPIRAL OVAL DUCTS (internal 9mm thick thermal insulation to be considered cost. Insulation should be done at factory for all elliptical ducts).All ducts should be supported with wire supports & painted inline with duct colour . Supports should be provide within 2m distance .All ducts should be supplied with primer & without any patches & damages | E91: =C91+D91 -> 0 | I91: =+N($E91)*N(G91) -> 0 | J91: =+N($E91)*N(H91) -> 0
B92: Please note that all elliptical duct should be delivered to the site with zinc cromate primer & required H frames for the elliptical duct connections, cost should be included in the same ducting cost. C ring should be with 18 G only. | E92: =C92+D92 -> 0 | I92: =+N($E92)*N(G92) -> 0 | J92: =+N($E92)*N(H92) -> 0
A93: 3.1 | B93: 24 gauge galvanized sheet steel (0.63mm) (0"-24") | C93: 150 | D93: 25 | E93: =C93+D93 -> 175 | F93: Sqmt | I93: =+N($E93)*N(G93) -> 0 | J93: =+N($E93)*N(H93) -> 0
A94: 3.2 | B94: 22 gauge galvanized sheet steel (0.8mm) (25"-48") | C94: 150 | E94: =C94+D94 -> 150 | F94: Sqmt | I94: =+N($E94)*N(G94) -> 0 | J94: =+N($E94)*N(H94) -> 0
A95: 3.3 | B95: 20 gauge galvanized sheet steel (1.0 mm) (49"-70") | C95: 50 | E95: =C95+D95 -> 50 | F95: Sqmt | I95: =+N($E95)*N(G95) -> 0 | J95: =+N($E95)*N(H95) -> 0
E96: =C96+D96 -> 0 | I96: =+N($E96)*N(G96) -> 0 | J96: =+N($E96)*N(H96) -> 0
A97: 4 | B97: Supply & Installation of double skin plenum of 40-45mm thick with puf insulation (factory fabricated ) of following sizes -Plenum Mouth Size to be cordinated with final Shop drawings for number of openings . Also scope covers for supply and fixing of double reinforced fire rated canvass. The scope also includes necessary hanging arrangements for plenum boxes,plenum cutouts as per HVAC layout . Color of plenum to match to nearest color of AHU body .Density of PUF 40+/-2 Kg/Cum. Note Quoted rate includes MS 50x50x6 mm angular support for plenum with suspension from dia 10mm threaded rods | C97: 50 | E97: =C97+D97 -> 50 | F97: Sqm | I97: =+N($E97)*N(G97) -> 0 | J97: =+N($E97)*N(H97) -> 0
E98: =C98+D98 -> 0 | I98: =+N($E98)*N(G98) -> 0 | J98: =+N($E98)*N(H98) -> 0
A99: 5 | B99: Sound Attenuators for Supply air Duct & Return | C99: 23 | D99: 8 | F99: Sqm | I99: =+N($E99)*N(G99) -> 0 | J99: =+N($E99)*N(H99) -> 0
B100: Sound Attenuators of dissipative type to be provided on the supply & Return air duct entering the AHU Room,Sound attenuator qty shall be on surface area basis. | E100: =C100+D100 -> 0 | I100: =+N($E100)*N(G100) -> 0 | J100: =+N($E100)*N(H100) -> 0
B101: Sound Attenuators shall consist of outer casing, sound absorbing material and internal baffles, splitters and supports as expalined in the technical specifications. | E101: =C101+D101 -> 0 | I101: =+N($E101)*N(G101) -> 0 | J101: =+N($E101)*N(H101) -> 0
B102: Casing shall be of galavanised steel of not less than 20G in thickness. Casings shall be tested to 150mmwg and shall show no leakage or distortion in this condition. | E102: =C102+D102 -> 0 | I102: =+N($E102)*N(G102) -> 0 | J102: =+N($E102)*N(H102) -> 0
...
