Workbook

Sheet Master - Summary
A1: PROJECT : DHL - Chennai | D1: Project Area in SFT | E1: 70000
A2: BOQ : MEP
A3: SL. NO | B3: ITEM DESCRIPTION | C3: TOTAL AMOUNT (INR) | D3: RATE / SFT | E3: REMARKS
A5: 1 | B5: HVAC | C5: ='Summary - HVAC'!C18 -> 26373771 | D5: =C5/E$1 -> 376.76815
A6: =A5+1 -> 2 | B6: Electrical | C6: ='Summary - Electrical'!C9 -> 0 | D6: =C6/E$1 -> 0
A7: =A6+1 -> 3 | B7: ELV | C7: ='ELV Summary'!C11 -> 0 | D7: =C7/E$1 -> 0
A8: =A7+1 -> 4 | B8: Networking | C8: =Networking!F61 -> 0 | D8: =C8/E$1 -> 0
A9: 5 | B9: Plumbing & Fire Fighting | C9: ='Summary - Plumbing & Fire Fight'!C11 -> 0 | D9: =C9/E$1 -> 0
A10: 6 | B10: BMS | C10: =BMS!I95 -> 0 | D10: =C10/E$1 -> 0
B12: GRAND TOTAL | C12: =SUM(C5:C11) -> 26373771 | D12: =C12/E$1 -> 376.76815

Sheet Summary - HVAC
A1: PROJECT : DHL - Chennai
A2: HVAC SUMMARY
A3: S.NO. | B3: ITEM DESCRIPTION | C3: AMOUNT(INR) | D3: REMARKS
A5: 1 | B5: =HVAC!B5 -> EQUIPMENTS | C5: =HVAC!F22 -> 943750
A6: 2 | B6: =HVAC!B24 -> CO2 & FLUSHING | C6: =HVAC!F67 -> 96880
A7: 3 | B7: =HVAC!B69 -> PIPING & ACCESSERIES | C7: =HVAC!F107 -> 944040
A8: 4 | B8: =HVAC!B109 -> DUCTING & AIR TERMINAL WORKS | C8: =HVAC!F193 -> 9271260.7
A9: 5 | B9: =HVAC!B195 -> INSULATION | C9: =HVAC!F215 -> 1672720
A10: 6 | B10: =HVAC!B217 -> VFD & Starter Panel | C10: =HVAC!F234 -> 171000
A11: 7 | B11: =HVAC!B236 -> EQUIPMENT | C11: =HVAC!F293 -> 3390912
A12: 8 | B12: =HVAC!B295 -> PIPING | C12: =HVAC!F341 -> 1311060
A13: 9 | B13: =HVAC!B343 -> ELECTRICAL WORKS | C13: =HVAC!F427 -> 335230
A14: 10 | B14: =HVAC!B429 -> VAV BOXES WORKS | C14: =HVAC!F483 -> 3235250
A15: 11 | B15: =HVAC!B485 -> HYDROGEN EXHAUST | C15: =HVAC!F577 -> 159350
A16: 12 | B16: FAHU System | C16: ='FAHU System'!I50 -> 4842318
B18: GRAND TOTAL | C18: =SUM(C5:C16) -> 26373771

Sheet HVAC
A1: PROJECT : DHL - Chennai
A2: SUBJECT : HVAC
A3: SL.NO | B3: ITEM DESCRIPTION | C3: UNIT | D3: QTY | E3: RATE (INR) | F3: AMOUNT (INR)
A5: 1 | B5: EQUIPMENTS
A7: =A5+0.01 -> 1.01 | B7: AIR HANDLING UNITS FLOOR MOUNTED OR CEILING SUSPENDED
B8: Supply, installation, testing and commissioning of factory fabricated Double Skinned Chilled Water Air- handling unit floor mounted (Horizontal / Vertical to suit site) or ceiling suspended horizontal type, fabricated out of extruded aluminium section with 0.6mm pre-plasticized / pre-coated Galvanised steel sheet outside & 0.6 mm plain Galvanised steel sheet inside with EC Plug Fans IE5 type motor, 4/6/8 Row cooling coil made of Aluminium finned Copper tube with coil section of copper header and MS adaptor, filter section with filters as mentioned below,UV section of 200 mm in length complete with UV lamps, polished stainless steel drain pan made out of 20 G sheet duly insulated. Drain pan insulation shall be minimum 19mm closed cell nitrile.The AHU panels shall be insulated with 48 mm thick & 48 Kg/m³ density PU foam. The maximum permissible sound pressure level of the AHU shall not exceed 50-60 dbA measured at 1.5 m from AHU surface for the recommended range of operation.The motor & fan assembly shall be mounted on Aluminium extruded section only. The complete AHU shall conform to standard specification. AHU shall be supplied with commissioning filter of both type wherever applicable as specified above which shall be replaced with actual pre and esp filters. The capacity of Air-handlers shall be as follows. Mixing box with aluminium volume control dampers for return air and fresh air complete as per specifications and drawings.
B9: The AHU panel shall be insulated with 48 mm thick injected fire retardent PUF of density 40+/-2 Kg/m³ . Marine light with limit switch shall be provided . The complete AHU shall conform to standard spec.The face velocity across cooling / heating coil, filters should not exceed 500 FPM. The capacities of airhandling shall be as follows, All paint shall be Low VOS as per IGBC
B10: The polished stainless steel drain pan of 1.25 mm (18 G) thick duly insulated with 13 mm thick nitrile rubber under cooling coil shall be provided. Motor & belt drive package/ direct driven arrangement, belt guard etc for belt driven blower without face and bypass dampers.
B11: NOTE (1) The Air velocity across the filter should not be more then 500 FPM. (2) CSU- Ceiling Suspended Units | FM- Floor Mounted (3) All CSU shall be provided with drain Pumps (4) All AHUs shall be with S.A damper. (5) Chilled water coil should have inlet and outlet temperature as 6.7°C & 12.2°C respectively. (6) Suitable Rubber bellow required for chilled water pipes to avoid the direct contact . (7) All fans should be AMCA certified. (8) All AHUs shall be provided with EC Plug Fan & ESP filter (Electrostatic Precipiator) of suitable capacity
B13: CSU AHU -2000 CFM, 5.0 TR with 50mm S.P. with MERV-7 filters, with 4 row deep cooling Coil. | C13: Nos | D13: 6 | E13: 150000 | F13: =E13*D13 -> 900000
A15: =A7+0.01 -> 1.02 | B15: Electronic Thermostat BMS compatible
B16: Supply of Electronic Heating and Cooling Thermostat (AC 220 V and DC 24 V) with LCD display with necessary control cabling for AHUs & FCUs complete as required. The thermostat shall have provision of setting of space temperature and display of the same, fixing of suitable transformer complete with interconnecting wiring between 2 way modulating valve and thermostat.
B17: Supply, Installation & Testing Temperature control with Wiring complete as required for AHU's. All Thermostats for Summer/Winter System of AHUs/ CSUs Shall be Heat Cool with change over. | C17: Nos | D17: 6 | E17: 4200 | F17: =E17*D17 -> 25200
A19: =A15+0.01 -> 1.03 | B19: FLEXIBLE CANVASS CONNECTIONS
B20: Supply, Installation, Testing of 125mm deep antivibration flexible joints at the outlet of air handling units/inline fans. Flexible connections shall be constructed using imported fire retardant fabric with extruded aluminium frame/flange on both sides of approved make. | C20: RMT | D20: 7 | E20: 2650 | F20: =E20*D20 -> 18550
B22: TOTAL ITEM NO. 1 (EQUIPMENT) | F22: =SUM(F5:F21) -> 943750
A24: 2 | B24: CO2 & FLUSHING
A26: =A24+0.01 -> 2.01 | B26: CO2 SENSOR for rooms with display
B27: SITC of CO2 Sensor for rooms only with display with (WiFi Enable/BMS Compatible) | C27: Nos | D27: 6 | E27: 11980 | F27: =E27*D27 -> 71880
A29: =A26+0.01 -> 2.02 | B29: INDOOR AIR QUALITY MONITOR WITHOUT DISPLAY
B30: Supply, Installation, Testing & commissioning of IAQ Monitor to measure the levels of PM 2.5, VOCs, CO2, Temperature, Humidity on a real time basis. The IAQ Monitor shall be RS485 enabled and should be capable of getting connected with Wi-Fi. Units should have dedicated data browse i.e. sim card etc. The Monitor should be capable of sending the indoor air quality information on display Screen/Mobile/Workstation as per Client's requirement. The Monitor should indicate the quality of air through changing the colours as per the NAAQS standards and should meet the WELL building standards. The monitor should be a 3 tier architecture including sensor Hardware, secure cloud infrastructure, monitoring apps including dashboard, android/IOS. Quoted price shall be inclusive of all necessary arrangement as required to make the unit proper functional. (LED Screen not included.) Quoted shall also be inclusive of individual network arrangement as required for monitoring/integration. Note: The System should provide Soft Assistance in form of Notifications and Alerts for Periodic Preventive Maintenance. | C30: Nos
A32: 2.03 | B32: Central Air Cleaner for AHUs
B33: Electrically Charged Filter Supply, Installtion, Testing & Commissioning of hybrid Air purification for ceiling suspended Ductable indoor units and AHU The air purification system should be suitable suitable to reduce harmful pollutants like particulate matter (PMx), PM 2.5, allergens, smoke, bacteria, pathogens etc. based on below principle technology viz; Impingement, Polarization and Agglomeration for passive air purification. It should be a slim structured unit specifically designed for integration in Return Air path of ceiling suspended indoor units and AHUs. EAC shall be equivalent to Merv-14 or Higher efficiency for AHU and Ductable Units with low pressure drop. It should have 3x working principles and it should be aluminum based or powder coated steel casing and should be self-contained. The EAC shall have UL certified core components. The units shall meet ANSI/ASHRAE 52.2/ISO16890 standards and have valid test report to verify filtration efficiency. The Supplier shall carry UL2998 certificate for testing against Zero Ozone Emission either as Whole unit or included components. The filter shall be capable of effectively reducing haze particles, smoke, mold spores, and airborne bacteria, and shall be supported by test reports from NABL-accredited laboratories verifying its performance. The Electronic Air Cleaner shall be GreenPro certified by CII–IGBC (Confederation of Indian Industry – Indian Green Building Council to support ECBC compliance by ensuring energy-efficient operation, low pressure drop, and improved indoor air quality . The test report for pressure drop need to be submitted for passive air purification and the same shall be demonstrated at site."
B34: Electronic filters should consist of an Internet of Things (IoT) based Smart Filtration option employing a 3-Tier Architecture. This architecture would serve to identify pressure drops across the filter, indicating when a cleaning & replacement is necessary due to clogged filters.
B35: Vendor to study local ambient air data and quality of air before proposing & finalizing air cleaner. Unit should be suitable to meet all IAQ parameters i.e. PM 2.5, PM-10 etc. as per ASHRAE/ANSI/ NEA & OSHA etc.
B36: Technical submittals with supported catalog shall be submitted for approval prior to procurement. Quoted price shall be inclusive of all necessary arrangement as required for fixing of filter section within AHU and control wiring etc.
A37: a | B37: 12600 CFM Floor Mounted AHU | C37: Nos
A38: b | B38: 12150 CFM Floor Mounted AHU | C38: Nos
A39: c | B39: 11700 CFM Floor Mounted AHU | C39: Nos
A40: d | B40: 10350 CFM Floor Mounted AHU | C40: Nos
A41: e | B41: 2000 CFM Ceiling Suspended AHU | C41: Nos
A43: 2.04 | B43: Active Purification System (BIO POLAR IONISER)
B44: The Active Air Purification system should consist of Supply, Installation, Testing and commissioning of Bipolar Ionisation System. The Bipolar Ionisation System must be a combination of Tube Based Model and Needle Point Model (Needle Point should have Nitinol (nickel titanium) Needles) and Carbon Fibre Brush Model, System should produce positive and negative ions for creating a Bio Climate rich in ions and hence neutralising harmful pollutants including pathogens, Volatile Organic Compounds and Particulate Matter. Product should have UL 867 and UL 2998 certification (for zero ozone emission). The OEM shall have Efficacy test report on COVID from any Internationally/Nationally recognised Laboratory. The technology shall also have UL 2043 for Fire and Smoke safety certificate , ISO 16000 for safety against any Organic Byproduct and CSA C22.2#187 , CARB certification.
B45: Manufacturers shall provide Test report from Internationally/Nationally recognized Lab for proven efficacy on below pathogens with minimum kill rates for the following pathogens given the allotted time and in a space condition: a) SARS-CoV-2 (COVID-19) Human Strain b) MS2 Bacteriophage (Surrogates COVID-19) c) Omicron Variant of SARS-CoV-2 d) H1N1 e) Total Bacterial Count Reduction rate of more than 90% from NABL Accredited Lab f) Yeas & Mold/Total fungal count Reduction rate of more than 90% from NABL Accredited Lab
B46: Total Nos. of ionisers shall be as per air quantity distributed in individual duct drawn from main plenum/ AHUs in approved shop drawing.
A47: a | B47: 12600 CFM Floor Mounted AHU | C47: Nos
A48: b | B48: 12150 CFM Floor Mounted AHU | C48: Nos
A49: c | B49: 11700 CFM Floor Mounted AHU | C49: Nos
A50: d | B50: 10350 CFM Floor Mounted AHU | C50: Nos
A51: e | B51: 2000 CFM Ceiling Suspended AHU | C51: Nos
A53: 2.05 | B53: UVGI LAMP
B54: Supply, installation, testing and commissioning of the UVGI unit to be fitted upstream portion of Chilled Water coil (for Cooling Coil Treatment & to Improve Indoor Air Quality ) with Reflector, lamp status display, audio-visual lamp failure alarm , lamp lifetime counter, lamp replacement reminder & SS stand.UVGI System shall be designed with scientifically. UVGI system for disinfection shall utilize high output UV lamp not less then 250 nm wavelength. The reflector shall "Dish Antenna” Shape to utilize 100% of UV & it MOC will be Anodized Aluminum. The electrical control system should utilize high frequency electronic ballasts and provide efficiency of more then 90%. System shall have a Dry Contacts or A 4-20 mA output shall also be provided for BMS compatibility. Control Power panel with necessary wiring & cabling to UVGI system upto 15 Mtr.length shall be inclusive in the cost. UL 2998 certified, USFDA and ASME certified. The UVGI System shall consist of UV lamps, LED control box with UV sensors, BMS integration and realtime lamp monitoring. UVGI system shall be provided for following AHUS for Air capacities as mentioned below respectively
A55: a | B55: 12600 CFM Floor Mounted AHU | C55: Nos
A56: b | B56: 12150 CFM Floor Mounted AHU | C56: Nos
A57: c | B57: 11700 CFM Floor Mounted AHU | C57: Nos
A58: d | B58: 10350 CFM Floor Mounted AHU | C58: Nos
A59: e | B59: 2000 CFM Ceiling Suspended AHU | C59: Nos
A61: 2.06 | B61: AIR QUALITY TESTING
B62: Air Quality testing by an ISO/IEC 17025 certified lab for LEEDv4.1 (Minimum 6 air samples per floor). Samples to checked pre occupancy and post occupancy Carrying out detailed outside Indoor air test (as per IAQ standard) for the occupied spaces. The following parameters (but not limited to) shall be tested - Temperature, Relative Humidity, Total Bacterial Count, Total Fungal Count, Respirable suspended particulate matter PM10, Respirable suspended particulate matter PM2.5, Carbon Dioxide, Carbon Monoxide, Total volatile organic compounds, Formaldehyde, Ozone, Sulphur Dioxide, Nitrogen Dioxide, Ammonia, Hydrogen Sulfide.Vendor to furnish a quality report showing results/concentration of all parameters. Results noted needs to be compared with IAQ Standard limits.IAQ parameters should not exceed the standards after running the purifier Equipment's. | C62: Nos
A64: 2.07 | B64: BUILDING FLUSHING
B65: Upon completion of construction including the installation of woodwork, doors, acoustic tiles, tiles, paint, carpet, movable furnishings, and other interior finishes a building air flush must be performed. This should occur only after all interior work has been completed and the building is ready for occupancy. The flush-out must be carried out while maintaining an indoor temperature of at least 60°F and a relative humidity of no more than 60%. A total air volume of 14,000 CFM per square foot of floor area must be supplied during the process. An external fan section need to be brought in specifically for this purpose, should be used to conduct the flush-out. This fan must be equipped with a MERV 8 (EU5) filter. Additionally, all doors and windows must remain open throughout the flush-out period to allow pollutants to be effectively exhausted from the building.This entire process must be conducted in accordance with LEED flush-out requirements. | C65: Lot | D65: 1 | E65: 25000 | F65: =E65*D65 -> 25000
B67: TOTAL ITEM NO. 2 (CO2 & FLUSHING) | F67: =SUM(F26:F66) -> 96880
A69: 3 | B69: PIPING & ACCESSERIES
A71: 3.1 | B71: M.S. CHILLED WATER PIPING
B72: Supply, Installation, Testing and Commissioning of following nominal sizes of M.S. E.R.W. tube (black steel) heavy class Chilled water piping (with necessary clamps, vibration isolators and fitttings but excluding valves, strainers, gauges) duly insulated with 25mm/32mm thick closed cell elastomeric insulation in tubing form Class O as per specifications and drawings covered with a layer of 120 gm/sqm polythene sheet (vapour barrier) and finally applying 0.5mm aluminum sheet cladding complete with type 3, grade I roofing felt strip (as per IS:1322 as amended upto date) at the joints repairing of damage to building etc. as per specifications and as required. (Gripple Wire & Hangers can be used at site for support) The following insulation thickness shall be followed : a) pipes size upto 150 mm-32 mm insulation thickness b) pipes size upto 200 mm to 300 mm-50 mm insulation thickness c) pipes size above 300 mm-75 mm insulation thickness Adheshiv shall be slected as per IGBC guidlines
B73: Note:- The pipes size 150 mm & below shall be M.S. `C' class as per IS:1239 and pipes size above 150 mm shall be black steel pipe heavy class as per IS:3589, from minimum 6.0 mm thick M.S. sheet for pipes from 200mm dia upto 400 mm dia.
A74: a | B74: 32 MM | C74: RMT
A75: b | B75: 40 MM | C75: RMT | D75: 420 | E75: 1280 | F75: =E75*D75 -> 537600
A76: c | B76: 50 MM | C76: RMT
B77: Note:- Actucal qty as per site
A79: 3.02 | B79: BUTTERFLY VALVE
B80: Supply, installation, testing and commi-ssioning of butterfly valves along with flanges as per specifications and drawings. (PN-16)
A81: a | B81: 32 MM | C81: Nos
A82: b | B82: 40 MM | C82: Nos | D82: 12 | E82: 2700 | F82: =E82*D82 -> 32400
A83: c | B83: 50 MM | C83: Nos
A85: 3.03 | B85: PIBC VALVE FOR AHU
B86: Supply, installation, testing and commi-ssioning of PIBC Valves with CI body SS disc nitrile rubber seal & O - ring & PN 16 pressure rating, confirm to BS 5155, IS 13095, with IP-55 actuator, capable of accepting up to 24 VAC and upto 20mA electric signal and providing similar transduced feed back output to control system as required & as specified.
B87: The valve actuator shall be electronic type with brushless DC motor. The actuator's angle of rotation shall be 900. It shall be without any limit switches and shall be overload proof. It shall have an indicator to indicate the position and push-button to disengage the gear train for manual operation. All related electrical connection and accessories required shall be inclusive.
A88: a | B88: 32mm Dia, Maximum | C88: Nos
A89: b | B89: 40mm Dia, Maximum | C89: Nos | D89: 6 | E89: 42840 | F89: =E89*D89 -> 257040
A90: c | B90: 50mm Dia, Maximum | C90: Nos
A92: 3.04 | B92: Y-STRAINER
B93: Supply, installation, testing and commi-ssioning of Y - strainer along with flanges connection complete as per specifications and drawings. (PN-16)
A94: a | B94: 32mm Dia, Maximum | C94: Nos
A95: b | B95: 40 MM | C95: Nos | D95: 6 | E95: 3400 | F95: =E95*D95 -> 20400
A96: c | B96: 50 MM | C96: Nos
A98: 3.05 | B98: PRESSURE GUAGE
B99: Pressure Gauge 6" Dial ( 0 To 6 Kg/CM2 ) with approved ball valve. Industrial type pressure gauges with SS syphon, gun metal / brass valves complete as required | C99: Nos | D99: 12 | E99: 3400 | F99: =E99*D99 -> 40800
A101: 3.06 | B101: THERMOMETERS WITH THERMOWELL
B102: Providing and fixing thermometer Mercury filled V form type complete as per speci-fications and drawings. | C102: Nos | D102: 12 | E102: 3400 | F102: =E102*D102 -> 40800
A104: 3.07 | B104: AUTOMATIC AIR VENTS
B105: Providing and fixing auto airvent purging valve complete as per specification and drawings. | C105: Nos | D105: 6 | E105: 2500 | F105: =E105*D105 -> 15000
B107: TOTAL ITEM NO. 3 (PIPING & ACCESSERIES) | F107: =SUM(F71:F106) -> 944040
A109: 4 | B109: DUCTING & AIR TERMINAL WORKS
A111: 4.01 | B111: FACTORY FABRICATED DUCTING
B112: Supply hollow partial pieces, Assembling, installation, testing and commissioning of 120 GSM G.S.S. metal ducting & as per ISI specifications & tender drawings. The price shall include with rolamate / TDF Corner flanges with nut bolt, cleat for clamping, self adhesive gasket / sealent (neoprene gasket) & supports Wire Rope Hangers or as per Duct size standard manufacturer etc. (Gripple Wire & Hangers can be used at site for support)
A113: a | B113: 24 G (0.60 mm) - 1 mm to 750 mm | C113: SqM | D113: 565 | E113: 1185 | F113: =E113*D113 -> 669525
A114: b | B114: 22 G (0.80 mm) - 751 mm to 1500 mm | C114: SqM | D114: 96 | E114: 1346 | F114: =E114*D114 -> 129216
A115: c | B115: 20 G (1.0 mm) - 1501 mm to 2250 mm | C115: SqM | D115: 10 | E115: 1591 | F115: =E115*D115 -> 15910
A116: d | B116: 18 G (1.2 mm) - 2250 mm to Above & Plenum | C116: SqM | D116: 200 | E116: 1787 | F116: =E116*D116 -> 357400
A118: 4.02 | B118: SITE FABRICATED DUCTING
B119: Supply GSS sheets, fabricate ducting at site, installation, testing and commissioning of 120 GSM G.S.S. metal ducting & as per ISI specifications & tender drawings. The price shall include with rolamate / TDF Corner flanges with nut bolt, cleat for clamping, self adhesive gasket / sealent (neoprene gasket) & supportsWire Rope Hangers etc. (Gripple Wire & Hangers can be used at site for support)
A120: a | B120: 24 G (0.60 mm) - 1 mm to 750 mm | C120: SqM | D120: 56 | E120: 1185 | F120: =E120*D120 -> 66360
A121: b | B121: 22 G (0.80 mm) - 751 mm to 1500 mm | C121: SqM | D121: 10 | E121: 1346 | F121: =E121*D121 -> 13460
A122: c | B122: 20 G (1.0 mm) - 1501 mm to 2250 mm | C122: SqM | D122: 5 | E122: 1591 | F122: =E122*D122 -> 7955
A123: d | B123: 18 G (1.2 mm) - 2250 mm to Above | C123: SqM | D123: 20 | E123: 1787 | F123: =E123*D123 -> 35740
A125: 4.03 | B125: Flat Oval Spiral Duct
B126: Supply hollow partial pieces, Assembling, installation, testing and commissioning of G.S.S. metal ducting & as per ISI specifications & tender drawings. The price shall include with rolamate / TDF Corner flanges with nut bolt, cleat for clamping, self adhesive gasket / sealent (neoprene gasket) & supports (GI Threaded Rod & Chilly clamp (Thickness & Width shall be as per manufacturere Standard) by or Wire Rope Hangers etc. (Gripple Wire & Hangers can be used at site for support)
B127: With 13 mm thick internal insulation as per the approved make list
A128: a | B128: 24 G (0.60 mm) | C128: SqM
...

Sheet FAHU System
A1: PROJECT : DHL - Chennai
A2: SUBJECT : FAHU System
A3: SL.NO | B3: ITEM DESCRIPTION | C3: UNIT | D3: QTY | E3: SUPPLY RATE (INR) | F3: INSTALLATION RATE (INR) | G3: SUPPLY AMOUNT (INR) | H3: INSTALLATION AMOUNT (INR) | I3: TOTAL AMOUNT (INR)
A6: 1 | B6: Part A
A8: 1.01 | B8: Treated Fresh Air Handling Units VRF Compatible
B9: SITC of Factory built and Site assembled Vertically floor mounted TFA.DX type double skin air handing units complete with
B10: Double skin construction : Inner skin 0.8 mm GI and outer skin 0.8 mm thk precoated GI. Thickness of insulation- 45 mm CFC free PUF injected with density of 40+/-42 kg/cum.
B11: Frame work: Thermal break aluminium profile with thermal barrier & Coving.
B12: Unit Base ; Heavy Duty GSS
B13: Drain pan : 18 G stainless steel duly insulated with 12 mm thick nitrile rubber (Armacell Class O Only)
B14: 8 row deep DX cooling coil – Multiple distributors. (Coil Surface area ≤ 500 FPM)
B15: Fan Section: DIDW Backward curve centrifugal fan, EFF-2 motor, (The Fan Section to be provided with double glass view window, light fixtures and Limit switch), Screen protection door, fire proof double canvass connections (Fungal Resistant and Lint free).
B16: SA section with manual gear operated SA damper.
A17: a | B17: VERTICAL FLOOR MOUNTED 1580 CFM @ 50 mm WG (EXTERNAL STATIC PRESSURE), (TFA-01) | C17: Nos | D17: 6 | E17: 60840 | F17: 7500 | G17: =+E17*D17 -> 365040 | H17: =+D17*F17 -> 45000 | I17: =H17+G17 -> 410040 | J17: QUOTED FOR 5.5TR VRF TFA INDOOR UNIT
A19: 1.02 | B19: Supply, installation, commissioning and testing of imported Air - cooled type VRF system with Inveter DC Twin Rotary with enviroment friendly green Refrigerant R-410A. (Supply of Variable Refrigerant Volume / Flow Out Door package consisting of high efficiency scroll type compressors, condensers, fans, control panels etc. The Compressor installed in the Outdoor Unit shall be equipped with Invertor Controller, and capable of changing the rotating speed to follow variations in cooling. The outdoor unit shall be with all necessary safety devices such as high pressure switch, low pressure switch, fuse, crankcase heater, fusible plug, over current protection for invertor and short recycling guard timer. All Outdoor Units shall have necessary Anti-corrosive treatments complete with all necessary valves, accessories and supports.)
B20: Outdoor Units
B21: 10 HP (Top Discharge) | C21: Nos | D21: 6 | E21: 301560 | F21: 10000 | G21: =+E21*D21 -> 1809360 | H21: =+D21*F21 -> 60000 | I21: =H21+G21 -> 1869360
A23: 2 | B23: PART -B : Low Side Works
A25: 2.01 | B25: All refrigerant Soft/Hard drawn copper piping interconnecting Refrigerant Copper piping between Indoor & Outdoor units covered with Nitrile Rubber Insulation
A26: a | B26: Gas Line - 19 mm thick Insulation | C26: Rmt | D26: 91 | E26: 1358 | F26: 280 | G26: =+E26*D26 -> 123578 | H26: =+D26*F26 -> 25480 | I26: =H26+G26 -> 149058
A27: b | B27: Liquid Line - 13 mm thick Insulation | C27: Rmt | D27: 91 | E27: 550 | F27: 240 | G27: =+E27*D27 -> 50050 | H27: =+D27*F27 -> 21840 | I27: =H27+G27 -> 71890
A29: 2.02 | B29: All communication / control cabling works between all indoor and outdoors units. | C29: Rmt | D29: 183 | E29: 113 | F29: 26 | G29: =+E29*D29 -> 20679 | H29: =+D29*F29 -> 4758 | I29: =H29+G29 -> 25437
A31: 2.03 | B31: PVC Drain piping for the units with insultion | C31: Rmt | D31: 91 | E31: 60 | F31: 20 | G31: =+E31*D31 -> 5460 | H31: =+D31*F31 -> 1820 | I31: =H31+G31 -> 7280
A33: 2.04 | B33: UV coating on exposed ref. pipe | C33: Rmt | D33: 183 | E33: 250 | F33: 50 | G33: =+E33*D33 -> 45750 | H33: =+D33*F33 -> 9150 | I33: =H33+G33 -> 54900
A35: 2.05 | B35: MS stand painted with two coats of red oxide and two coats of enamel paint. | C35: Nos | D35: 6 | E35: 6000 | F35: 500 | G35: =+E35*D35 -> 36000 | H35: =+D35*F35 -> 3000 | I35: =H35+G35 -> 39000
A37: 2.06 | B37: Electrical Panel with Voltage Scanner for preventig of Under voltage/over volta ge/single phasing/phase reverse. | C37: Nos | D37: 1 | E37: 80000 | F37: 2500 | G37: =+E37*D37 -> 80000 | H37: =+D37*F37 -> 2500 | I37: =H37+G37 -> 82500
A39: 2.07 | B39: Control cabling between panel and VRF units. | C39: Rmt | D39: 274 | E39: 837 | F39: 30 | G39: =+E39*D39 -> 229338 | H39: =+D39*F39 -> 8220 | I39: =H39+G39 -> 237558
A41: 2.08 | B41: GSS Ducting Work-24 G | C41: Sqm | D41: 883 | E41: 945 | F41: 240 | G41: =D41*E41 -> 834435 | H41: =F41*D41 -> 211920 | I41: =H41+G41 -> 1046355
A43: 2.09 | B43: Thermal insulation of ducting with fire retardant closed cell nitrile rubber (Class-O) insulation with aluminum foil. 19 mm thick. | C43: Sqm | D43: 1059 | E43: 520 | F43: 160 | G43: =+E43*D43 -> 550680 | H43: =+D43*F43 -> 169440 | I43: =H43+G43 -> 720120
A45: 2.1 | B45: UP coating of exposed duct | C45: Sqm | D45: 139 | E45: 240 | F45: 120 | G45: =+E45*D45 -> 33360 | H45: =+D45*F45 -> 16680 | I45: =H45+G45 -> 50040
A47: 2.11 | B47: Supply air grille with VCD | C47: Sqm | D47: 6 | E47: 9630 | F47: 3500 | G47: =+E47*D47 -> 57780 | H47: =+D47*F47 -> 21000 | I47: =H47+G47 -> 78780
B48: The frame and blades shall be of high quality extuded aluminium construction with the advantages of corrosion resistance and rigidity. Louvered type core shall be fxed to the frame with aluminium pins loaded with steel springs. Core can be easily removable and interchangeable to allow for maximum fexibility in installation, maintenance and damper adjustment. Damper shall be fxed rigidly to the frame by aluminium rivets. Fixing by spring clips as option. Damper blades shall be separated from its frame by nylon bushes. Opposed blade damper shall be screw operated from the face opening of the diffuser after removing the internal core
B50: GRAND TOTAL | G50: =SUM(G11:G49) -> 4241510 | H50: =SUM(H11:H49) -> 600808 | I50: =SUM(I11:I49) -> 4842318

Sheet Summary - Electrical
A1: PROJECT : DHL - Chennai
A2: ELECTRICAL SUMMARY
A3: SR. NO. | B3: ITEM DESCRIPTION | C3: AMOUNT (INR) | D3: REMARKS
A5: 1 | B5: Electrical Works | C5: ='Electrical Work'!F437 -> 0
A6: 2 | B6: Lighting Works | C6: ='Light Fixture'!L26 -> 0
A7: 3 | B7: UPS & Batteries | C7: ='UPS & Batteries'!F72 -> 0
B9: GRAND TOTAL | C9: =SUM(C5:C8) -> 0

Sheet Electrical Work
A1: PROJECT : DHL - Chennai
A2: SUBJECT : Electrical Work
A3: SL.NO | B3: ITEM DESCRIPTION | C3: UNIT | D3: QTY | E3: SUPPLY & INSTALLATION RATE (INR) | F3: TOTAL AMOUNT (INR)
A5: 1 | B5: PANEL & DBs
A7: =A5+0.01 -> 1.01 | B7: Supply, Installation, testing & commissioning of LT switchboards compartmental cubicle type freestanding with appropriate cable entries, front operating, front maintained wherever required complete with base frame etc. as required and as per IS 8623, Technical specifications & Single line diagram. Panels shall be CPRI approved & NFPA 70E complied, fabricated out of 14 / 16 SWG CRCA sheet, and surface treated with phosphating seven tank process and duly powder coated with RAL 9016. NOTE:- 1)TEST AT MANUFACTURERS WORK All routine tests specified in IEC 61439-1 & 2: • HV test • IR Test before & after HV Test • Primary/Secondary injection tests 2) ALL FLOOR MOUNTED PANEL SHALL BE TYPE TESTED AS PER THE IEC61439 - 1 & 2 - Following 13 type tests to be carried and certified by OEMs - a) Strength of material and parts, b) Degree of protection of enclosures, c) Clearances and creepage distances, d) Effective continuity between parts and PE, e) Effectiveness of the ASSEMBLY for external faults, f) Incorporating of apparatus Internal electrical circuits and connections, g) Terminals for external conductors, h) Power frequency withstand voltage, i) Impulse withstand voltage, j) Temperature rise limits, k) Short - circuit withstand strength, l) EMC, m) Mechanical operation. 3) Vendor to consider testing guidelines as per IEC61439 and testing refer the technical specification section A4. 4) Vendor to consider the LOTO (Lock Out Tag Out) Arrangement for all the panels/DB's. 5)Vendor to submit the GA drawings along with offer. 6)Electrical design shall include fully rated (for available fault current) equipment. 7)Provision shall be top/bottom entries to be considered with aluminum gland plate of 3 mm thickness. 8)Provision for Door earthing to be considered. 9) Refer SLD. Ref no BLK/SLD/01
B8: i) All MCCBS shall be with Extended type Front door operating handle, Phase Spreaders & Phase Barriers.
B9: ii) Metering CT's burden & accuracy class will be as per the SLD.
B10: iii)CT's shall be "CAST RESIN" type .
B11: iv)MCCB's up to and including 200 Amp shall be with adjustable thermal-magnetic release for over current and short circuit protection with EFR on CBCT. MCCB 250 amp and above shall be with Microprocessor based release for over current, instantaneous, short circuit protection and earth fault protection(LSIG). All MCCBs with Thermal Magnetic Protection will be adjustable from 70-100 %.
B12: v) All indication lights shall be LED type.
B13: vi) All meter shall be "DIGITAL" type with LCD display.
B14: vii) Breaking Capacity of all MCCB's are Ics Service Breaking Capacity
B15: viii) Degree of Protection shall be IP:42 for indoor panel & IP:65 for outdoor panel
B16: ix) Panel Manufacturer should have authorization from International Certifying agency or Indian government lab for manufacturing LT switchboards as per IEC 61439.
B17: x) "R,Y,B,ON,OFF,TRIP " Indicating lamp shall be provided for all 3 phase MCCB incoming and outgoing feeders.
B18: xi) Control SP MCB's of 2A Rating shall be provided for each metering circuit.
B19: xii) 30% spare control terminal to be provided.
... B24: All panels to have provision for panele fire speration tubing, routing and required cutouts
A26: a | B26: UPS INPUT PANEL | C26: Nos | D26: 1 | F26: =D26*E26 -> 0
B27: Main Incomer - 2 x 250 Amp 4P MCCB (36 KA)
B28: Metering & Indication - Multi Function Meter (PM 5000) with suitable size of CT and 3 Nos. phase indicating lamp
B29: Provide TVSS 40kA. class-II
B30: Provide CBCT with 1-10A ELR
B31: Buscoupler - 1 x250 Amp 4P MCCB (50 KA)
B32: Busbars -300 Amp TPN Al
B33: Outgoings :
B34: 3x 200 A TPN MCCB (36 KA)
B35: 4x 100 A TPN MCCB (36 KA)
B36: 3x 63A TPN MCCB (36 KA)
B37: 1x 63A TPN MCB (10 KA)
A38: b | B38: SDB- L&P | C38: Nos | D38: 1 | F38: =D38*E38 -> 0
B39: Main Incomer -2x 250 Amp 4P MCCB (36 KA)
B40: Metering & Indication - Multi Function Meter (PM 2130) with suitable size of CT and 3 Nos. phase indicating lamp
B41: Provide TVSS 40kA. class-II
B42: Provide CBCT with 1-10A ELR
B43: Busbars - 300 Amp TPN Al
B44: Buscoupler - 1 x 250 Amp 4P MCCB (50 KA) with mechanical interlocking 3 lock + 2keys
B45: Outgoings :
B46: 2x 100 A TPN MCCB (36 KA)
B47: 2x 100 A TPN MCCB (36 KA) with KWH
B48: 2 x 40 A FP MCB (10 KA) wth KWH
B49: Sub Incomer- for Power- 100Amp 4 Pole MCCB 25KA with KWH Meter and indicating lamp.
B50: Busbars - 150 Amp TPN Al
... B55: 4 x 40 A FP MCB (10 KA)
A56: c | B56: SDB- L&P | C56: Nos | D56: 1 | F56: =D56*E56 -> 0
B57: Main Incomer -2x 250 Amp 4P MCCB (36 KA)
B58: Metering & Indication - Multi Function Meter (PM 2130) with suitable size of CT and 3 Nos. phase indicating lamp
B59: Provide TVSS 40kA. class-II
B60: Provide CBCT with 1-10A ELR
B61: Busbars - 300 Amp TPN Al
B62: Buscoupler - 1 x 250 Amp 4P MCCB (50 KA) with mechanical interlocking 3 lock + 2keys
B63: Outgoings :
B64: 2 x 63 A FP MCB (10 KA)
B65: 2 x 40 A FP MCB (10 KA)
B66: 1x 100 A TPN MCCB (36 KA) with KWH
B67: 2 x 40 A FP MCB (10 KA) wth KWH
B68: Sub Incomer- for Power- 100Amp 4 Pole MCCB 25KA with KWH Meter and indicating lamp.
... B73: 4 x 40 A FP MCB (10 KA)
A74: d | B74: UPS O/P panel -1 | C74: Nos | D74: 1 | F74: =D74*E74 -> 0
B75: Main Incomer - 1x200 Amp TP+2N MCCB (36 KA)
B76: Main Incomer - 1x200 Amp FP MCCB (36 KA) with Pad LOCK
B77: Metering & Indication - Multi Function Meter (PM 5000) with suitable size of CT and 3 Nos. phase indicating lamp for each incomer
B78: Provide TVSS 40kA. class-II
B79: Provide CBCT with 1-10A ELR
B80: Busbars - 300 Amp TP+2N Cu
B81: Outgoings :
B82: 1 x 200 A FP MCCB (25 KA)
B83: 1 x 100 A FP MCCB (25 KA)
B84: 11 x 63A FP MCB (10 KA)
B85: 4 x 40 A DP MCB (10 KA)
A86: e | B86: SDB- UPS-2 | C86: Nos | D86: 1 | F86: =D86*E86 -> 0
B87: Main Incomer - 1x200 Amp TP+2N MCCB (36 KA)
B88: Metering & Indication - Multi Function Meter (PM 5000) with suitable size of CT and 3 Nos. phase indicating lamp for each incomer
B89: Provide TVSS 40kA. class-II
B90: Provide CBCT with 1-10A ELR
B91: Busbars - 300 Amp TP+2N Cu
B92: Outgoings :
B93: 1 x 200 A FP MCCB (25 KA)
B94: 1 x 100 A FP MCCB (25 KA)
B95: 12 x 63A FP MCB (10 KA)
B96: 5x 40 A DP MCB (10 KA)
A97: f | B97: SDB- Server | C97: Nos | D97: 0 | F97: =D97*E97 -> 0
B98: Main Incomer - 1x100Amp TP+2N MCCB (25 KA)
B99: Metering & Indication - Multi Function Meter (PM 5000) with suitable size of CT and 3 Nos. phase indicating lamp for each incomer
B100: Provide TVSS 40kA. class-II
B101: Provide CBCT with 1-10A ELR
B102: Busbars - 200 Amp TP+2N Cu
B103: Outgoings :
B104: 5 x 63A FP MCB (10 KA)
B105: 1x 63 A DP MCB (10 KA)
A106: g | B106: SDB- Em Lighting | C106: Nos | D106: 1 | F106: =D106*E106 -> 0
B107: Main Incomer - 1x100Amp DP MCB (10 KA)
B108: Metering & Indication - Multi Function Meter with suitable size of CT and 3 Nos. phase indicating lamp for each incomer
B109: Busbars - 200 Amp TP+2N Cu
B110: Outgoings :
B111: 6x40 A DP MCB (10 KA)
A113: h | B113: Supply, installation, testing and commissioning of sheet metal enclosed Manual Maintenance bypass panel , consisting of 1 No. 200 Amp TP+2N MCCB (36KA) incomer and 2 nos 200 Amps 4 pole MCCB Bus coupler and out going with 300 Amps copper Bus bar the bus coupler should be with pad lock as per the SLD , the cost shall include on/ off indicating lamp as per the SLD. The design of panel shall be as approved by consultant . | C113: Nos | D113: 2 | F113: =D113*E113 -> 0
A115: i | B115: Supply, installation, testing and commissioning of sheet metal enclosed Manual Maintenance bypass panel , consisting of 1 No. 100 Amp TP+2N MCCB (36KA) incomer and 2 nos 100 Amps 4 pole MCCB Bus coupler and out going with 300 Amps copper Bus bar the bus coupler should be with pad lock as per the SLD , the cost shall include on/ off indicating lamp as per the SLD. The design of panel shall be as approved by consultant . | C115: Nos | D115: 0 | F115: =D115*E115 -> 0
A117: =A7+0.01 -> 1.02 | B117: Supply, Installation, Testing & Commissioning of Following MCCB /MCB with all standard accessories in MS fabricated enclosure having padlock . It should have termination box for appropriate size of cables on both the sides. With All Standard Accessories In MS Enclosure With Sets Of Phase Indicating Lamps.
A118: a | B118: 100 Amp FP MCCB 25 kA in IP 55 Metal Enclosure. | C118: Nos | D118: 4 | F118: =D118*E118 -> 0
...

Sheet Light Fixture
A1: PROJECT : DHL - Chennai
A2: SUBJECT : Light Fixture
A3: SL.NO | B3: LIGHT TYPE AS PER DRAWING | C3: ITEM DESCRIPTION | D3: REF. IMAGE | E3: LOCATION | F3: UNIT | G3: QTY | H3: SUPPLY RATE(INR) | I3: INSTALLATION RATE (INR) | J3: SUPPLY AMOUNT (INR) | K3: INSTALLATION AMOUNT (INR) | L3: TOTAL AMOUNT (INR)
C4: Supply, Installation, Testing and Commissioning of Light fixtures and lamps with all accessories, fixing on the wall / ceiling/false ceiling with wooden blocks, screws ,hardware's ,suspended chain hooks as required as per the site conditions (including the earthing of fixture)
C5: Note : All light fixtures should have CRI < 80, luminaire System efficacy of >110 lm/watt, PF >0.95, CCT 5000K, Anti glare diffuser. It is proposed to achieve USGBC LEED Gold Certification for this Project. Vendor to go through the LEED documents & comply to the requirement in reference to this BOQ & Specification.
A6: 1 | B6: DOWNLIGHT | C6: Recessed LED Downlighter ,made up of pressure die cast aluminum housing with high efficiency PS diffuser, LED Used shall be SMD type and fixture should have minimum efficacy at System level 120 lumens/watt with Minimum system Lumens 1200 , CCT of 4000K (SDCM<=5), CRI Ra >=80, PF >0.9, an Operating working temp range - 0°C < Ta < 45°C & operating Voltage Range of 160-270 V AC. Minimum Internal Surge Protection 2.5KV. Manufacturer shall have inhouse lab approved by NABL or ministry of science of govt of India. LM 79 and LM80 reports need to be submitted from a NABL/UL accredited lab to verify above parameters. Both the fixture and Driver should have separate BIS approval. | E6: Cabins, Washroom & Meeting Rooms, Support Areas | F6: Nos. | G6: 335 | J6: =H6*G6 -> 0 | K6: =I6*G6 -> 0 | L6: =K6+J6 -> 0
A7: 2 | B7: HANGING CYLINDER LIGHT | C7: Supply of Suspended Cylinderical Downlight, 1000 lm, Having CCT option of 4000K, SDCM<5, CRI≥80, Efficacy ≥100lm/W, Surge 2.5kV internal, THD ≤10% (At Full Load), pf ≥0.9. The luminaire housing shall be Extruded aluminum housing, White/Black finish , Product Dia 55mm, Height 150mm. The product should have beam angle option of 40° beam angle. The operating volateg range shall be 140-270V. The product shall be Class B serviceability. Manufacturer shall have inhouse lab approved by NABL or ministry of science of govt of India. LM 79 and LM80 reports need to be submitted from a NABL/UL accredited lab to verify above parameters. Both the fixture and Driver should have separate BIS approval. | E7: Workstation Areas | F7: Nos. | G7: 290 | J7: =H7*G7 -> 0 | K7: =I7*G7 -> 0 | L7: =K7+J7 -> 0
A8: 3 | B8: 2 X 2 PANEL LIGHT | C8: Supply of recessed mounted 2X2 LED panel ,made of CRCA housing with high efficiency PS Diffuser. LED Used shall be SMD type and fixture should have minimum efficacy at System level >=100 lumens/watt with Minimum system Lumens 3600 & Max , Life of fixture : 50000 burning Hrs. @ L70B50 Lumen maintenance,CCT-4000K/5700K/6500K, (SDCM<=5), CRI Ra >=80, THD<10%, PF >0.95, an operating Voltage Range of 140 - 270 VAC.Minimum Internal Surge Protection 3.0KV & IP20/IK02 protection, Manufacturer shall have inhouse lab approved by NABL or ministry of science of govt of India. LM 79 and LM80 reports need to be submitted from a NABL/UL accredited lab to verify above parameters. Both the fixture and Driver should have separate BIS approval . | E8: Store & Support Room & Critical Room | F8: Nos. | G8: 60 | J8: =H8*G8 -> 0 | K8: =I8*G8 -> 0 | L8: =K8+J8 -> 0
A9: 4 | B9: LINEAR LIGHT 1500mm | C9: Supply of continues Suspended 5ft slim Linear LED made of extruded Aluminium with white/black powder coaed finish with high efficiency Opal Diffuser.The luminaire shall have a width of not more than 50mm(± 3mm), and shall be available in multiple lengths. LED Used shall be SMD type with approx system Lumens 2750 (+-10%) & efficacy 100lm/W, Life of fixture : 50000 burning Hrs. @ L70B50 Lumen maintenance, CCT of 4000K (SDCM<=5), CRI 80, PF ≥0.95, THD≤ 10%, an Operating working temp range - 0°C < Ta < 45°C & operating Voltage Range of 140-270 V AC having Class - I protection & serviceability of Class B. Minimum Internal Surge Protection 3.5kV. The manufacturer shall submit the following reports before supply of material for approvals LM79 issued by NABL accredited lab, LM80 issued by LED manufacturer, | E9: Linear Workstations | F9: Nos. | G9: 182 | J9: =H9*G9 -> 0 | K9: =I9*G9 -> 0 | L9: =K9+J9 -> 0
A10: 5 | B10: SUSPENDED HANGING LIGHT | C10: Suspended Curvilinear Slim 50mm Flushed Flat Micro prismatic Diffuser 50mm height x 1000mm length. Fixture to be made of extrusion Aluminum housing white/Black powder coating. LED Used shall be SMD type with Minimum system Lumens 1800 Lumen with System efficacy >100lm/W, UGR<19 Life of fixture : 50000 burning Hrs. @ L70B50 Lumen maintenance, CCT of 400k.(SDCM<=5), CRI 80, an Operating working temp range - 0°C < Ta < 45°C & operating Voltage Range of 140-270 V AC. Minimum Internal Surge Protection 4KV. Current Ripple necessarily <10%.Luminaire with Ingress & IK protection Rating of of IP20 & IK02.The driver shall be compliant to IEC61347-2-13, IEC62384 & IEC6100-3-2. Driver should be D4I Certified & compliant to DALI Part 251/252/253 with Rated input voltage range 202-254, Power factor 0.99%, efficiency of ≥ 91% Output current ripple LF<4%. The driver & Luminaire shall be BIS registered.The driver & Luminaire shall be BIS registered. The driver shall be designed for continuous operation of minimum 12-15Hrs a day. The luminaire driver shall be of the same make/manufacturer as that of LED luminaires. Luminaire manufacturer must have In-house NABL accredited lab in India to conduct LM79, Type test as per IS10322, "FAT" before dispatch as per IS 10322 & IK Test. The successful bidder must submit the NABL accreditation certificate for Luminaire manufacturer along with before supply of LED Luminaires for approval. Successful bidder shall submit the following reports before supply of material for approvals LM79 issued by NABL accredited lab, LM80 issued by LED manufacturer, Type Test Certificate for luminaire as issued by NABL accredited lab, IK Test Report issued by NABL accredited lab, RoHS compliance issued by LED luminaire manufacturer, BIS certificate for LED. | E10: Passage & 120 degree Workstations, Collab, Breakout Areas | F10: RMT | G10: =980 -> 980 | J10: =H10*G10 -> 0 | K10: =I10*G10 -> 0 | L10: =K10+J10 -> 0
A11: 6 | B11: SURFACE PROFILE LED LIGHT ( 20 nos) | C11: Supply of continues surface Linear LED made of extruded Aluminium with white/black powder coaed finish with high efficiency Opal Diffuser.The luminaire shall have a width of not more than 50mm(± 3mm), and shall be available in multiple lengths. LED Used shall be SMD type with approx system Lumens 2200 (+-10%) & efficacy 100lm/W, Life of fixture : 50000 burning Hrs. @ L70B50 Lumen maintenance, CCT of 4000K (SDCM<=5), CRI 80, PF ≥0.95, THD≤ 10%, an Operating working temp range - 0°C < Ta < 45°C & operating Voltage Range of 140-270 V AC having Class - I protection & serviceability of Class B. Minimum Internal Surge Protection 3.5kV. The manufacturer shall submit the following reports before supply of material for approvals LM79 issued by NABL accredited lab, LM80 issued by LED manufacturer, | E11: Cabins, Command Centre, Training Room | F11: RMT | G11: 252 | J11: =H11*G11 -> 0 | K11: =I11*G11 -> 0 | L11: =K11+J11 -> 0
A12: 7 | B12: SUSPENDED PROFILE LED LIGHT ( 7 nos) | C12: Supply of continues Suspended 4ft slim Linear LED made of extruded Aluminium with white/black powder coaed finish with high efficiency Opal Diffuser.The luminaire shall have a width of not more than 50mm(± 3mm), and shall be available in multiple lengths. LED Used shall be SMD type with approx system Lumens 2200 (+-10%) & efficacy 100lm/W, Life of fixture : 50000 burning Hrs. @ L70B50 Lumen maintenance, CCT of 4000K (SDCM<=5), CRI 80, PF ≥0.95, THD≤ 10%, an Operating working temp range - 0°C < Ta < 45°C & operating Voltage Range of 140-270 V AC having Class - I protection & serviceability of Class B. Minimum Internal Surge Protection 3.5kV. The manufacturer shall submit the following reports before supply of material for approvals LM79 issued by NABL accredited lab, LM80 issued by LED manufacturer, | E12: Meeting Room 6PAX | F12: RMT | G12: =15.6*4 -> 62.4 | J12: =H12*G12 -> 0 | K12: =I12*G12 -> 0 | L12: =K12+J12 -> 0
A13: 8 | B13: PENDANT LIGHT | C13: Tense pendant hanging light set of 4 700mm Dia – 1 Qty 600mm Dia – 2 Qty 450mm Dia – 1 Qty" | E13: Reception | F13: Nos. | G13: 1 | J13: =H13*G13 -> 0 | K13: =I13*G13 -> 0 | L13: =K13+J13 -> 0
A14: 9 | B14: DECORATIVE LIGHT - 4PAX MEETING ROOM | C14: Rectangular ribbon suspended linear light with curved edges, black body, size – 1200 x 1200 mm, with 20 W/mtr, CRI < 80, luminaire system efficacy of >110 lm/watt, with flicker-free DALI dimmable driver. | E14: Meeting Room 4PAX | F14: Nos. | G14: 1 | J14: =H14*G14 -> 0 | K14: =I14*G14 -> 0 | L14: =K14+J14 -> 0
A15: 10 | B15: DECORATIVE LIGHT - BREAKOUT AREA, RECEPTION | C15: Rectangular linear light with curved edges, black body, size – 2700 x 2100 mm, continuous rectangular shape with 1 driver for every 4 mtr, CRI < 80, luminaire system efficacy of >110 lm/watt, with flicker-free DALI dimmable driver. | E15: Reception, Breakout Area | F15: Nos. | G15: 9 | J15: =H15*G15 -> 0 | K15: =I15*G15 -> 0 | L15: =K15+J15 -> 0
A16: 11 | B16: DECORATIVE LIGHT - BREAKOUT AREA | C16: Rectangular linear light with curved edges, black body, size – 3900 x 2400 mm, continuous rectangular shape with 1 driver for every 4 mtr, CRI < 80, luminaire system efficacy of >110 lm/watt, with flicker-free DALI dimmable driver. | E16: Breakout Area | F16: Nos. | G16: 2 | J16: =H16*G16 -> 0 | K16: =I16*G16 -> 0 | L16: =K16+J16 -> 0
A17: 12 | B17: DECORATIVE LIGHT - BOARDROOM | C17: Custom linear light, black body, size – 5800 x 1850 mm. | E17: Boardroom | F17: Nos. | G17: 1 | J17: =H17*G17 -> 0 | K17: =I17*G17 -> 0 | L17: =K17+J17 -> 0
A18: 13 | B18: DECORATIVE LIGHT - INTERVIEW ROOM | C18: Hanging decorative light | E18: Interview Room | F18: Nos. | G18: 2 | J18: =H18*G18 -> 0 | K18: =I18*G18 -> 0 | L18: =K18+J18 -> 0
A19: 14 | B19: DECORATIVE LIGHT - ULD | C19: ULD – decorative light | E19: ULD | F19: Nos. | G19: 2 | J19: =H19*G19 -> 0 | K19: =I19*G19 -> 0 | L19: =K19+J19 -> 0
A20: 15 | B20: DECORATIVE LIGHT - MEETING ROOMS | C20: Rectangular linear light with edges, black body | E20: Meeting Rooms - 4/8/12PAX | F20: RMT | G20: 325 | J20: =H20*G20 -> 0 | K20: =I20*G20 -> 0 | L20: =K20+J20 -> 0
A21: 16 | B21: DECORATIVE LIGHT - BREAKOUT AREA | C21: Hanging light | E21: Breakout Area | F21: Nos. | G21: 15 | J21: =H21*G21 -> 0 | K21: =I21*G21 -> 0 | L21: =K21+J21 -> 0
A22: 17 | B22: INDIRECT LIGHT - WASHROOM, PANTRY | C22: Indirect LED light | E22: Washroom, Pantry | F22: RMT | G22: 310 | J22: =H22*G22 -> 0 | K22: =I22*G22 -> 0 | L22: =K22+J22 -> 0
A23: 18 | C23: Supplying, installing, testing and commissioning of suitable size of dimmer panel for 10 Nos. circuit with 6 to 8 Nos light fixture on each circuit 2000W light load, complete as required | F23: Nos. | G23: 4 | J23: =H23*G23 -> 0 | K23: =I23*G23 -> 0 | L23: =K23+J23 -> 0
A24: 19 | C24: DALLI Ballast for dimmer panel | F24: Nos. | G24: 30 | J24: =H24*G24 -> 0 | K24: =I24*G24 -> 0 | L24: =K24+J24 -> 0
A25: 20 | C25: SITC for Meeting room , touch switch all all fixing accessries complete as required. | F25: Nos. | G25: 18 | J25: =H25*G25 -> 0 | K25: =I25*G25 -> 0 | L25: =K25+J25 -> 0
C26: GRAND TOTAL | L26: =SUM(L6:L25) -> 0

Sheet UPS & Batteries
A1: PROJECT : DHL - Chennai
A2: SUBJECT : UPS & Batteries
A3: BILL OF QUANTITIES FOR UPS & BATTERIES SYSTEM
A4: Note 1: Rate should be inclusive of getting RESISTIVE 20 kW load at site & required connection with UPS set for 110% load testing as stipulated in specifications. Entire cost is to be born by Vendors .The cost of leads from Basement floor for load bank to the UPS room, Load bank etc to be borne by vendor. UPS vendor to retain load bank and load bank attendant for minimum seven days at site till the completion of testing.
A5: Note 2: To conduct factory and site load test for UPS & ISOLATION TRANSFORMER as per requirement as stated in the tender specification including sufficient sized load bank in order to perform load sharing and full load testing as required. For factory & test to & fro travel, lodging & boarding expenditure of 2person for Complete duration of Factory Testing.
A6: Note 3: For each item the specification attached to be referred. Any deviation can be filled in the specification sheet.
A7: Note 4 : All UPS are to be installed on 10th floor in Clients UPS Room. Floor UPS vendor to include the necessary lifting cost of UPS ,Battery racks ,Batteries & all other equipments, cables, termination kits, panels etc upto 10th floor in Clients UPS Room.
A8: Note 5 : UPS Vendor to study UPS Room Layout drawings & to confirm the room sizes. Also Confirm on the Cable tray sizing & routing for Battery cables. For Any changes in Battery Breaker Location, Vendor to revise the cable Tray layout & Submit the same along with tender. Cable Tray is in the scope of Eectrical Contractor.
A9: Note 6 : UPS Vendor to Study Site & Confirm Horizontal & Vertical Transportation of UPS upto UPS Room without Dismantling any component after Factory Testing is Conducted. The Lift may not be available for vertical transportation . Vendor to make all constructional damages good which occured to any part of the building during transportation.
A10: Note 7 : During integrated system testing UPS vendor to appoint two service engineers for entire tenure of IST alongwith required tools,tackles and power analysers.
A11: Note 8 : factory test to & fro travel, lodging & boarding expenditure of three person for Complete Duration of Factory Testing.
A12: SL.NO | B12: ITEM DESCRIPTION | C12: UNIT | D12: QTY | E12: RATE (INR) | F12: AMOUNT (INR) | G12: REMARK
B14: Note : Vendor to consider below items for BMS Connectivity : (Also refer UPS Specification)
A15: a | B15: Serial communication in the form of MODBUS / IP chained between all UPS & one output given including all software integration. Cabling for Daisy chaining to be considered.
A16: b | B16: Minimum Five nos of Hardwire Potential free contacts of all & critical Alarms for each UPS to be extended to BMS.The PFC terminals to be wired up to a ABS IP54 junction box with Elmex terminals ( both Junction box and terminals included by UPS vendor) for further extension by BMS vendor.
A17: c | B17: 1 no of NO + 1 no. of NC Aux. Contact to be Provided with I/P , Battery , BYPASSS , OUTPUT Breakers, Battery breaker switch outside the battery room etc.
A18: d | B18: SNMP CARD & Network card
A19: e | B19: Parallel redundant Kit
A20: f | B20: Load Bus Synchronising Kit
A21: g | B21: Temperature sensors
A23: 1 | B23: SITC of 30 KVA, 3 Phase Input 3 Phase Output Conventional UPS System with inbuilt isolation transformer High Efficiency, Low Input Current Harmonic Distortion of < 3 % and High Input Power Factor of > 0.99. Batteries for 30 kVA UPS back up time will be 15minutes each . The battery room shall be maintained at 25 deg C and UPS vendor to consider the rating accordingly. Cost to be inclusive of Batter Rack as per drawing. Each UPS to have one strings of batteries. VRLA Batteries for 30 kVA UPS considering 30 kVA as load .The UPS back up time will be 15 minutes each for 30 kVA load. The battery room will be maintained at 25 deg C and UPS vendor to consider the rating accordingly . Cost to be inclusive of Battery Rack where in battery monitoring system will be part of battery rack wherein battery IR , Current , Temperature & voltage will be monitored at real time . Warranty 2 years on Batteries. 450 mm(H) Base Frame to consider for Battery Rack matching with false flooring Battery sizing parameters:At full KVA rating,0.9 PF,10% ageing factor. Declaration will be submitted along with offer from respective battery manufacturer for battery back up calculation stating valid for end of life. | C23: Nos. | D23: 0 | F23: =E23*D23 -> 0
B24: Three Phase Input: 415V AC 3PH 4 wire, +20%, -40% 50HZ +/- 5HZ
B25: Rectifier technology: IGBT Based Rectifier
B26: Input P.F.: >0.99
B27: Input Current Harmonics: <3% | F27: =E27
B28: Three Phase output: 415V AC +/- 1%, 3Ph, 4 wire, 50HZ +/- 0.01% (Async mode)
B29: Inverter Technology: PWM IGBT
B30: High overall efficiency: 96.5% | F30: =E30
B31: M.S. Rack (Open type) with battery MCCB , interlinks & UPS to battery cable | F31: =E31
B32: Warranty 1 years on UPS | F32: =E32
B33: Network card | F33: =E33
B34: Temperature sensors | F34: =E34
F35: =E35
A36: 2 | B36: SITC of 120 KVA, 3 Phase Input 3 Phase Output Conventional UPS System with inbuilt isolation transformer High Efficiency, Low Input Current Harmonic Distortion of < 3 % and High Input Power Factor of > 0.99. Batteries for 30 kVA UPS back up time will be 15minutes each . The battery room shall be maintained at 25 deg C and UPS vendor to consider the rating accordingly. Cost to be inclusive of Batter Rack as per drawing. Each UPS to have one strings of batteries. VRLA Batteries for 120 kVA UPS considering 120 kVA as load .The UPS back up time will be 15 minutes each for 120 kVA load. The battery room will be maintained at 25 deg C and UPS vendor to consider the rating accordingly . Cost to be inclusive of Battery Rack where in battery monitoring system will be part of battery rack wherein battery IR , Current , Temperature & voltage will be monitored at real time . Warranty 2 years on Batteries. 450 mm(H) Base Frame to consider for Battery Rack matching with false flooring Battery sizing parameters:At full KVA rating,0.9 PF,10% ageing factor. Declaration will be submitted along with offer from respective battery manufacturer for battery back up calculation stating valid for end of life. | C36: Nos. | D36: 2 | F36: =E36*D36 -> 0
B37: Three Phase Input: 415V AC 3PH 4 wire, +20%, -40% 50HZ +/- 5HZ
B38: Rectifier technology: IGBT Based Rectifier
B39: Input P.F.: >0.99
B40: Input Current Harmonics: <3% | F40: =E40
B41: Three Phase output: 415V AC +/- 1%, 3Ph, 4 wire, 50HZ +/- 0.01% (Async mode)
B42: Inverter Technology: PWM IGBT
B43: High overall efficiency: 96.5% | F43: =E43
B44: M.S. Rack (Open type) with battery MCCB , interlinks & UPS to battery cable | F44: =E44
B45: Warranty 1 years on UPS | F45: =E45
B46: Network card | F46: =E46
B47: Temperature sensors | F47: =E47
A49: 3 | B49: SITC of 15 KVA, 3 Phase Input 1 Phase Output Monolithic inverter System with High Efficiency, Low Input Current Harmonic Distortion of < 3 % and High Input Power Factor of > 0.99. 450 mm Base Frame to consider for UPS VRLA Batteries for 15 kVA UPS considering 15 kVA as load .The UPS back up time will be 90 minutes each for 15 kVA load. The battery room will be maintained at 25 deg C and UPS vendor to consider the rating accordingly . Cost to be inclusive of Battery Rack where in battery monitoring system will be part of battery rack wherein battery IR , Current , Temperature & voltage will be monitored at real time . Warranty 2 years on Batteries. 450 mm Base Frame to consider for Battery Rack matching with false flooring Battery sizing parameters:At full KVA rating,0.9 PF,10% ageing factor. Declaration will be submitted along with offer from respective battery manufacturer for battery back up calculation stating valid for end of life. | C49: Nos. | D49: 1 | F49: =E49
A51: 4 | B51: Site Testing cost for all UPS as mentioned 1x120 KVA, 1 x 30kVA, 1 x 15kVA | C51: Lot | D51: 1 | F51: =E51*D51 -> 0
B52: Visual Inspection ( Physical Check UP)
B53: Functional Test
B54: Regulation Test on No Load, 25 % , 50% , 75% , 100 %. & 100% UNBALANCE LOAD ( Parameters required - I/P %THD Voltage & Current (Input harmonic (ordinals 1 to 21). Wave form) , I/P Power Factor ,Efficiency etc. )
B55: Load Transfer Test for 100 % Balance & 100 % Unbalance Load on BYPASS & MAINTENANCE BYPASS (Wave Form)
B56: Transient Response on Step Load at 50 % Load & 100 % Load ( Waveform )
B57: Heat Run Test on Each UPS at Full Load ( 8 Hours)
B58: Battery Autonomy Tests
B59: System Failure Mode Tests
B60: Over Load Test 110% - 30 min., 125% - 10 min. & 150 % - 1 min
B61: dBA Level Test ( At 1 Meter ) on Full Load
B62: Temperature measurement by Thermal Scanning for battery , UPS capacitors etc. ( THERMOGRAPHY with Thermal Images )
B63: After completion of three months from the date of commissioning , UPS vendor to carry out harmonics test at Input of UPS as well as Output of UPS with power analysers and data loggers to be kept for 24 hours & detailed report to be summitted.
... B70: Note : Site engineers and load bank to be available at site till complition of testing. Vendor to allow pricing for carrying out the detailed Factory /Site Testing & Commissioning based on the specification attached herewith.
B72: GRAND TOTAL | F72: =SUM(F14:F70) -> 0

Sheet ELV Summary
A1: PROJECT : DHL - Chennai
A2: SUBJECT: | B2: ELV SUMMARY
A3: SR. NO. | B3: ITEM DESCRIPTION | C3: AMOUNT (INR) | D3: REMARKS
E4: `
A5: 1 | B5: FA&PA | C5: ='FA&PA'!F74 -> 0
A6: 2 | B6: Water Leak Detection | C6: ='Water Leak Detection'!F17 -> 0
A7: 3 | B7: Rodent | C7: =Rodent!F13 -> 0
A8: 4 | B8: Exit Signage | C8: ='Exit Signage'!F14 -> 0
A9: 5 | B9: Vesda | C9: =Vesda!F28 -> 0
B11: GRAND TOTAL | C11: =SUM(C5:C10) -> 0

Sheet FA&PA
A1: PROJECT : DHL - Chennai
A2: SUBJECT : FA&PA
A3: SL.NO | B3: ITEM DESCRIPTION | C3: UNIT | D3: QTY | E3: SUPPLY & INSTALLATION
E4: RATE (INR) | F4: AMOUNT (INR)
B6: INTELLIGENT ADDRESSABLE FIRE ALARM AND EVACUATION SYSTEM
B7: The Panel shall be suitable for BMS connectivity. Provide bacnet card for BMS integration.
B8: The Builder Main Fire Panel shall have 2 way communication with Main Fire Panel. In case of fire signal all the access control doors shall deactivate.
B9: The access control doors will get de activated for people evacuation
B10: Emergency evacuation message will pass through public address system automatically
B11: Dampers will get deactivated through the modules to close the air movement.
B12: The Flow switch shall be monitored on our Fire Panel.
B13: Supply, Installation, Testing and Commissioning of the following:
A15: 1 | B15: UL listed & FM Approved Intelligent Addressable Rate of Rise Heat detectors with blinking LED and standard base, being capable of addressed electronically. Manual Addressing Detector shall have Automatic device mapping capability. | C15: Nos | D15: 20 | F15: =E15*D15 -> 0
A17: 2 | B17: UL listed & FM Approved Intelligent Addressable Smoke detector, optical type with blinking LED and standard base, being capable of addressed electronically. Manual Addressing. Detector shall have Automatic device mapping capability. | C17: Nos | D17: 350 | F17: =E17*D17 -> 0
A19: 3 | B19: UL listed & FM Approved Intelligent Addressable Smoke detector, optical type with blinking LED and being capable of addressed electronically with Sounder Base. Manual Addressing Detector shall have Automatic device mapping capability. | C19: Nos | D19: 70 | F19: =E19*D19 -> 0
A21: 4 | B21: UL listed & FM Approved Intelligent Addressable Multi-Criteria smoke cum Heat detector, optical type with blinking LED and standard base, being capable of addressed electronically. Manual Addressing. Detector shall have Automatic device mapping capability. | C21: Nos | D21: 0 | F21: =E21*D21 -> 0
A23: 5 | B23: Response Indicator | C23: Nos | D23: 105 | F23: =E23*D23 -> 0
A25: 6 | B25: UL Listed & FM Approved Intelligent Addressable Double action manual pull station, capable of being addressed electronically. Manual Addressing, it shall have Automatic device mapping capability complete as required.and as per specifications.The MCP should be with double pole manual break glass for breaking glass and fire status . | C25: Nos | D25: 14 | F25: =E25*D25 -> 0
A27: 7 | B27: UL Listed & FM Approved Fire Alarm Hooter (sound output of minimum 90 dB upto a distance of 30 meters) cum Strobe (Selectable 15, 30, 75, or 110 cd), made Addressable with the help of Intelligent Addressable Signal Module (cost of the Module to be included), module capable of being addressed electronically. Manual Addressing, with seperate power supply arrangement complete as required. Module shall have Automatic device mapping capability. | C27: Nos | D27: 14 | F27: =E27*D27 -> 0
A29: 8 | B29: UL Listed & FM Approved Addressable control module complete as required for switching ON of smoke extraction fans / Pressurisation Fans etc. and switching off AHU' s, capable of being addressed electronically. Manual Addressing complete as required.and as per specifications. It shall have Automatic device mapping capability. | C29: Nos | D29: 25 | F29: =E29*D29 -> 0
A31: 9 | B31: UL Listed & FM Approved Addressable Monitor module complete as required for monitoring flow switches/ interface with any third party equipment capable of being addressed electronically. Manual Addressing , complete as required.and as per specifications. It shall have Automatic device mapping capability. | C31: Nos | D31: 30 | F31: =E31*D31 -> 0
A33: 10 | B33: UL Listed & FM Approved Addressable Fault Isolator module complete as required for determining the short in a circuit and separating the segment having the short capable of being addressed electronically. Manual Addressing, complete as required.and as per specifications. It shall have Automatic device mapping capability. | C33: Nos | D33: 20 | F33: =E33*D33 -> 0
A35: 11 | B35: UL Listed & FM Approved 2W High Fidelity (520 Hz) Ceiling Mounted speaker with capacity to have 2 watt tapping, working at 84dB compatible with amplifier complete as required. | C35: Nos | D35: 96 | F35: =E35*D35 -> 0
A37: 12 | B37: UL Listed & FM Approved 2W High Fidelity (520 Hz) Wall/Surface Mounted speaker and 2 watt tapping, working at 84dB compatible with amplifier complete as required.Provide circular back boxes for the above speakers | C37: Nos | D37: 35 | F37: =E37*D37 -> 0
... A43: 15 | B43: UL Listed Telephone handset for fire fighters telephone system with suitable enclosure. | C43: Nos | D43: 2 | F43: =E43*D43 -> 0
A45: 16 | B45: Microprocessor based Multi-loop, True Peer-to-Peer Networkable Addressable Fire Alarm Control Panel with minimum 600 characters LCD display, 4000 event plus 1000 alarm log history events, QWERTY keypad for programming. The panel should be equipped with sufficient numbers of loops considering 20% spare capacity in each loop. Each loop shall have a capacity of minimum 300 analog addressable devices. The panel shall work in degrade mode in case of CPU failure, Products not having this feature may offer Redundant CPU. Four access levels, flash EPROM, 240 volts AC power supply, automatic battery charger, 24 volts sealed lead acid batteries sufficient for 24 hours normal working and 30 mins in alarm condition. The panel shall be complete with Integrated 8 channel Digital Voice Evacuation System Controller capable of broadcasting Evacuation Messages on same peer-to-peer Network. The system shall be equipped with necessary Digital Audio Amplifier capable of processing one of 8 audio channels and amplifiers as per the speakers requirement at 70.7 VRMS output along with necessary enclosures. The DAA shall be fully monitored for fault and alarm reporting. The proposed Digital Amplifiers shall not be rail mounted / dependant on Fire Panel CPU for operation. Failure of Fire Panel CPU shall not result in failure of Amplifier operation. The Digital Amplifier Loop shall have N+1 Redundancy concept to avoid chances of failure. The Fire Fighters Telephone System shall be capable of having minimum 20 Telephones on conference. The panel shall have a built in power supply and battery charger along with maintenance free 24 AH, 2 x 12 volt SMF Lead acid batteries capable of running for a minimum of 8 hours with battery charger complete as required. The panel should have a plug in Microphone for important manual messaging if required.
A46: a | B46: 16 Loop Panel | C46: Nos | D46: 0 | F46: =E46*D46 -> 0
A47: b | B47: 8 Loop Panel | C47: Nos | D47: 0 | F47: =E47*D47 -> 0
A48: c | B48: 6 Loop Panel | C48: Nos | D48: 1 | F48: =E48*D48 -> 0
B50: it shall also include the following :
B51: The FACP shall contain all equipment required for all audio control, 100 W amplifier telephone system control, signalling and supervisory functions. This includes speaker zone indication, telephone circuit indication and control, digital voice units, microphone and main telephone handset. The amplifier rating shall be as per the speakers quantities
B52: Function: The EVAC system equipment shall perform following functions:
B53: Operate as a two-way emergency telephone system control center.
B54: Audibly and visually annunciate the active or trouble condition of every speaker circuit and telephone circuit.
B55: Audibly and visually annunciate any trouble condition of tone generators and digital voice units required for normal operation of the system.
B56: Provide automatic, digitally-recorded voice messages and tones which may be field-programmed through the microphone.
B57: Suitable nos. of Digital Audio Amplifier ( 100 Watts each ) capable of processing One of 8 audio channels at 70.7 VRMS output along with necessary enclosures. The Digital Audio Amplifier shall be fully monitored for fault and alarm reporting. The proposed Digital Audio Amplifiers shall (be Wall/Panel Mounted) not be rail mounted / dependant on Fire Panel CPU for operation. Failure of Fire Panel CPU shall not result in failure of Amplifier operation. rate of the same shall be included in above fire panel item. The Amplifier size shall be 20% extra.
B58: Necessary Integration Facility with BMS for following functions:-
B59: Alarm, Trouble condition, Supervisory alerts to BMS
B60: Share Graphics of Security, Fire and HVAC
B61: Web Interface
A63: 17 | B63: UL Listed Fire Alarm Graphic Software for Monitoring & Control along with compatible computer system. | C63: Nos | D63: 1 | F63: =E63*D63 -> 0
A65: 18 | B65: UL Listed & FM Approved Repeater Panel with 960 Character LCD Display complete as required. | C65: Nos | D65: 1 | F65: =E65*D65 -> 0
A67: 19 | B67: Supply & laying of following grade with copper conductor armoured FIRE SURVIVAL cable with XLPE insulation as per IEC-60502:2004 Part-1 (Armoured), Retain circuit integrity as per BS-6387 CWZ, BSEN 50200, BS-8434. (armoured), (Resistance to fire at 950º C for 3 hours), as per specifications in cable trays, clamped including anchor fastners to wall with suitable clamps, saddles fixing bolts,2 MS cable glands for each detector back box, complete in all respect as required as per specifications.(Red Colour)
A68: a. | B68: 2 core x 1.5 sq. mm | C68: RMT | D68: 8500 | F68: =E68*D68 -> 0
A70: 20 | B70: Providing and fixing in position 1.2mm thick M.S. circular outlet boxes for housing smoke detectors/heat detectors on the true Ceiling complete with all fixing accessories as required | C70: Nos | D70: 150 | F70: =E70*D70 -> 0
A72: 21 | B72: 4 x 1.5 sq mm PVC sheathed copper conductor 1100 volts grade flexible FRLS wires of approved make in concealed or surface mounted existing 25 mm dia MS conduit including fixing, supporting, saddling & flexible conduit etc complete in all respect. | C72: RMT | D72: 0 | F72: =E72*D72 -> 0
B74: GRAND TOTAL | F74: =SUM(F15:F73) -> 0

Sheet Water Leak Detection
A1: PROJECT : DHL - Chennai
A2: SUBJECT : Water Leak Detection
A3: SL.NO | B3: ITEM DESCRIPTION | C3: UNIT | D3: QTY | E3: SUPPLY & INSTALLATION
E4: RATE (INR) | F4: AMOUNT (INR)
A6: 1 | B6: Supply Installation, Testing and comissioning of Conventional Water Leak Detection Panel, The Panel should be complete with Power Supply units for Hooter mounted outside each critical room. | C6: Nos. | D6: 4 | F6: =E6*D6 -> 0
A8: 2 | B8: Supply Installation, Testing and comissioning of Sensor interface module. Mounted on false floor pedestal with sutable clamp. Note:- SIM should be able to provide PF Contact for FAS/BMS Integration. | C8: Nos. | D8: 4 | F8: =E8*D8 -> 0
A10: 3 | B10: Supply Installation, Testing and comissioning of "UL Listed" WLD Digital sensing cable : Cable shall have Jacket on top to avoid false alarm, Hold Down Clips with adhesive backs, cable connectors, end termination plugs etc.
A11: a | B11: 15 Mtrs. Length | C11: Nos. | D11: 6 | F11: =E11*D11 -> 0
A13: 4 | B13: Supply Installation, Testing and comissioning of Communication Cable for networking between WLD Serial Interface Modules and Panel : (Beldon 8723 or Equivalent as ratified by the WLD OEM) Typical Specs : FRLS 1 Twisted Pair x 1.5 mm2, Multistrand Copper conductor, (Armoured or flexible in GI Conduit including the conduit), Black in Colour, Shielded individually with Al-Mylar Tape, and 0.5 mm2 Drain wire. Complete with GI Junction Boxes, lugs, cable compression glands, cable tags and Ferruling. | C13: Mtr | D13: 60 | F13: =E13*D13 -> 0
A15: 5 | B15: Supply Installation, Testing and comissioning of Hooter cum strobe for WLD system complete with required accessories. Location - Outside each critical room | C15: Nos. | D15: 4 | F15: =E15*D15 -> 0
B17: GRAND TOTAL | F17: =SUM(F6:F16) -> 0

Sheet Rodent
A1: PROJECT : DHL - Chennai
A2: SUBJECT : Rodent
A3: SL.NO | B3: ITEM DESCRIPTION | C3: UNIT | D3: QTY | E3: SUPPLY & INSTALLATION
E4: RATE (INR) | F4: AMOUNT (INR)
B6: Supply, Installation & Commissioning of Rodent Systems.
A7: 1 | B7: Supply Installation, Testing and comissioning of Main Panel wall mounting type with facility to connect 24 satellites in one zone. | C7: Nos | D7: 4 | F7: =E7*D7 -> 0
A9: 2 | B9: Supply Installation, Testing and comissioning of Transducer Satellite Stations capable of Emitting Ultrasonic sound of frequencies 20 Khz and higher, with blinking LED Indication & shall capable to covering area of 500 Sq.ft. complete with required mounting accessories. | C9: Nos | D9: 40 | F9: =E9*D9 -> 0
A11: 3 | B11: Supply Installation of FRLS 1 pair Armoured 14/40 SWG Specially coated wire, PVC sheathed Cable on surface with hot dip GI Saddels and spacers at evry 0.3 meter. | C11: Mtrs | D11: 280 | F11: =E11*D11 -> 0
B13: GRAND TOTAL | F13: =SUM(F6:F12) -> 0

Sheet Exit Signage
A1: PROJECT : DHL - Chennai
A2: SUBJECT : Exit Signage
A3: SL.NO | B3: ITEM DESCRIPTION | C3: UNIT | D3: QTY | E3: SUPPLY & INSTALLATION
E4: RATE (INR) | F4: AMOUNT (INR)
B6: Note : Vendor to visit the construction site, understanding the building, structure, beams, roofs, ceiling etc., for the benefit of quoting completely on several perspectives such as mobilisation, Logistics, storage, Instalation, Support systems to the I beams Purlins etc.,
B7: Note: It is proposed to achieve LEED Gold Certification for this building. Vendor to go through the LEED documents & comply to the requirement in reference to this BOQ & Specification.
A9: 1 | B9: Supply, Installation, Testing and Commissioning of Self contained Emergency Exit Signages comprising of following :
A10: a | B10: Supply Installation Testing and comissioning of FLUSH MOUNT DUAL SIDED, Maintained 3 Watt LED, FIRE Exit luminaires, Sheet metal Body, Painted to RAL 9010, Pictogram 280 (I) X 130(W), with spring supports, Legend with clear acrylic/engraved pattern to be fully compliant with requirements of designed and installed to meet the fire and safety code of practice & the respective EN 60598-2-22 and the system designed in compliance with EN50171, EN50272-2, EN50172, and EN1838 standards EN Standards, IP 20 with NiCad 2 x 1.2V Battery Backup for 90 Minutes operation in following formats as per Layouts : Right Arrow, Left Arrow, Down Arrow, Both sides etc. Input Supply : 220 V AC ±10% | C10: Nos | D10: 36 | F10: =E10*D10 -> 0
A12: b | B12: Supply Installation Testing and comissioning of SURFACE MOUNT SINGLE SIDED, Maintained 3 Watt LED, FIRE Exit luminaires, Sheet metal Body, Painted to RAL 9010, Pictogram 280 (I) X 130(W), Legend with clear acrylic/engraved pattern to be fully compliant with requirements of designed and installed to meet the fire and safety code of practice & the respective EN 60598-2-22 and the system designed in compliance with EN50171, EN50272-2, EN50172, and EN1838 standards EN Standards, IP 20 with NiCad 2 x 1.2V Battery Backup for 90 Minutes operation in following formats as per Layouts : Right Arrow, Left Arrow, Down Arrow, Both sides etc. Input Supply : 220 V AC ±10% | C12: Nos | D12: 20 | F12: =E12*D12 -> 0
B14: GRAND TOTAL | F14: =SUM(F10:F13) -> 0

Sheet Vesda
A1: PROJECT : DHL - Chennai
A2: SUBJECT : Vesda
A3: SL.NO | B3: ITEM DESCRIPTION | C3: UNIT | D3: QTY | E3: SUPPLY & INSTALLATION
E4: RATE (INR) | F4: AMOUNT (INR)
B6: VESDA ASPIRATING SMOKE DETECTION SYSTEM
B7: For Hub Rooma and server rooms.
B8: 1. Should be BMS Compatible
B9: 2. Modbus and interface card over RS485 output to be provided
B10: 3. Termination of cables in the respective device
B11: Make : Honeywell /Xtralis
A12: 1 | B12: Supply, installation, testing and commissioning of the following VESDA (Very Early Smoke Detection and Alarm System).
B13: The Panels Shall be BMS comptable.
B14: Supply, installation, testing and commissioning of UL & FM certified Laser-Based Absolute Smoke Detection system with single pipe inlet aspiration detector for Up to 500 m2 (5000 sq. ft.) coverage; 50m linear pipe & 30m branched pipe; Wide sensitivity range; 3 alarm levels; High efficiency aspirator; Clean air barrier optics protection; Easy to replace air filter; 3 relays; AutoLearn; Referencing; Event log. Alarm Threshold Setting Range: (0.005%–20% obs/m) & Instant Fault Finder. The cost should includes power supply unit for the controller VESDA Model Similar to VLF 500 [Vendor to selct the model as per room dimension given with sampling holes to be consider for room & false floor & also return air path] | C14: Nos. | D14: 4 | F14: =E14*D14 -> 0
A16: 2 | B16: Power supply unit for above detector | C16: Nos. | D16: 4 | F16: =E16*D16 -> 0
A18: 3 | B18: Aspiration tubes UPVC | C18: RM | D18: 50 | F18: =E18*D18 -> 0
A20: 4 | B20: Capillary tubes | C20: Nos. | D20: 16 | F20: =E20*D20 -> 0
A22: 5 | B22: Air termination ( Nozzles) | C22: Nos. | D22: 32 | F22: =E22*D22 -> 0
A24: 6 | B24: Electronic Hooter | C24: Nos | D24: 4 | F24: =E24*D24 -> 0
A26: 7 | B26: Supply and surface laying of 2 c x 1.5 sq mm armoured copper cable | C26: RM | D26: 60 | F26: =E26*D26 -> 0
B28: GRAND TOTAL | F28: =SUM(F14:F27) -> 0

Sheet Networking
A1: PROJECT : DHL CHENNAI
A2: BOQ : Networking
A3: SL.NO | B3: ITEM DESCRIPTION | C3: UNIT | D3: QTY | E3: RATE (INR) | F3: Amount(INR)
A5: Supply Components-DATA Nodes-Cat6
A7: 1 | B7: Cat 6 UTP Mounting Cord,7 ft, Color Light Blue for User ends | C7: Nos. | D7: 1986 | F7: =E7*D7 -> 0
A8: 2 | B8: 1-port face plate of size 3x3 with shutter, Color White | C8: Nos. | D8: 25 | F8: =E8*D8 -> 0
A9: 3 | B9: 2-port face plate of size 3x3 with Shutter, Color White | C9: Nos. | D9: 914 | F9: =E9*D9 -> 0
A10: 4 | B10: 4-port face plate of size 3x3 with Shutter, Color White | C10: Nos. | D10: 69 | F10: =E10*D10 -> 0
A11: 5 | B11: Cat 6 UTP Information Outlets, Color Blue for User ends | C11: Nos. | D11: 1986 | F11: =E11*D11 -> 0
A12: 6 | B12: 4-Pair, Cat6, UTP Cable (305 mt. Roll) | C12: Roll | D12: 359 | F12: =E12*D12 -> 0
A13: 7 | B13: Patch Panel, unloaded, 24-port -Angular Data | C13: Nos. | D13: 83 | F13: =E13*D13 -> 0
A14: 8 | B14: Cat 6 UTP Information Outelts,Color Blue for Rack ends | C14: Nos. | D14: 1992 | F14: =E14*D14 -> 0
A15: 9 | B15: Cat 6 UTP Mounting Cord, 7 ft, Color Light Blue Rack end | C15: Roll | D15: 1986 | F15: =E15*D15 -> 0
A17: Supply Components-Fiber Cable & Fiber Accessories--2Runs x 6Core Fiber MM
A19: 1 | B19: 6-Core MM 50/125 micron OM4 Armoured Fiber Cable, LSZH | C19: Mtr | D19: 250 | F19: =E19*D19 -> 0
A20: 2 | B20: High Density 1U Sliding fiber Splice Panel, accepts (4) G2 modules, providing up to 48 duplex LC ports, accepts splice wallets, | C20: Nos | D20: 0 | F20: =E20*D20 -> 0
A21: 3 | B21: 360G2 Cartridge, 12-LC-LS-AQ-Pigtails, LazrSPEED, Aqua w/Pigtails | C21: Nos | D21: 0 | F21: =E21*D21 -> 0
A22: 4 | B22: RoloSplice Kit E/W 2 Fusion Splice Trays, for 1U Shelf | C22: Nos | D22: 0 | F22: =E22*D22 -> 0
A23: 5 | B23: Blank Panel | C23: Nos | D23: 0 | F23: =E23*D23 -> 0
A24: 6 | B24: LC-LC Style MM 50/125 micron Duplex OM4 Patch Cord, 3 Meter | C24: Nos | D24: 0 | F24: =E24*D24 -> 0
A25: 7 | B25: LC-LC Style MM 50/125 micron Duplex OM4 Patch Cord, 5 Meter | C25: Nos | D25: 0 | F25: =E25*D25 -> 0
A27: Supply Components-Network Rack & Accessories
A29: 1 | B29: 42U Rack/Powder Coated | C29: Nos | D29: 6 | F29: =E29*D29 -> 0
A30: 2 | B30: High Density Vertical Cable Organiser/8 inch/Front & Back | C30: Nos | D30: 14 | F30: =E30*D30 -> 0
A31: 3 | B31: Run-Way Kit-20Inch | C31: Nos | D31: 7 | F31: =E31*D31 -> 0
A32: 4 | B32: Mounting Hardware/OR/Pk-20 | C32: Nos | D32: 5 | F32: =E32*D32 -> 0
A33: 5 | B33: IT Rack mount power distribution unit, 1Ph, 230V, 16A, 50/60Hz, 2U standard with 6 X Indian Round Pin 5/15A, Inlet Plug type 16A Indian Round Pin, 16A MCB - | C33: Nos | D33: 14 | F33: =E33*D33 -> 0
A35: Supply Components-Misc Items for Cabling
A37: 1 | B37: Copper Consumables items Ferrule Tube for UTP cables, Bubble Wrap arounds for securing cables,,Cable Ties,Velcro Tie etc | C37: LS | D37: 1 | F37: =E37*D37 -> 0
A39: Installation /Services for-Cabling Components
A41: 1 | B41: Laying of CAT6 UTP Cables in Raceway/Conduits | C41: Mtr | D41: 109495 | F41: =E41*D41 -> 0
A42: 2 | B42: Cat6 UTP Cable Identification, Ferruling with Cylinderical ferrule both end | C42: Nos | D42: 1986 | F42: =E42*D42 -> 0
A43: 3 | B43: Termination of Cat6 Information Outlet at User end | C43: Nos | D43: 1986 | F43: =E43*D43 -> 0
A44: 4 | B44: Installation of Face Plate Including labelling | C44: Nos | D44: 1008 | F44: =E44*D44 -> 0
A45: 5 | B45: Fixing of 24 Port Jack Panel in rack including labeling | C45: Nos | D45: 83 | F45: =E45*D45 -> 0
A46: 6 | B46: Termination of Cat6 Information Outlet at Panel end | C46: Nos | D46: 1986 | F46: =E46*D46 -> 0
A47: 7 | B47: Copper Patch Cord Labelling & Dressing at Rack end | C47: Nos | D47: 1986 | F47: =E47*D47 -> 0
A48: 8 | B48: Testing of Data Nodes with Fluke Meter | C48: Nos | D48: 1986 | F48: =E48*D48 -> 0
A49: 9 | B49: Installation of 45/42U network Rack with all the accessories | C49: Nos | D49: 6 | F49: =E49*D49 -> 0
A50: 10 | B50: Documentation of Copper work | C50: Nos | D50: 1986 | F50: =E50*D50 -> 0
A51: 11 | B51: Certification of Copper work | C51: Nos | D51: 1986 | F51: =E51*D51 -> 0
A52: 12 | B52: Project Management includes supervisions Charges | C52: Nos | D52: 1986 | F52: =E52*D52 -> 0
A54: Fiber Services
A56: 13 | B56: Laying of Fiber Cable | C56: Mtr | D56: 250 | F56: =E56*D56 -> 0
A57: 14 | B57: Installation of Fiber LIU | C57: Nos | D57: 0 | F57: =E57*D57 -> 0
A58: 15 | B58: Splicing of Fiber Core | C58: Core | D58: 12 | F58: =E58*D58 -> 0
A59: 16 | B59: Testing of Fiber Core with Fluke Meter | C59: Core | D59: 12 | F59: =E59*D59 -> 0
B61: GRAND TOTAL | F61: =SUM(F7:F59) -> 0

Sheet DHL 7F NDL 
A1: DHL 7th FLOOR Chennai
A3: SL.NO | B3: LOCATION | C3: QTY. | D3: DATA D1 | E3: DATA D2 | F3: TOTAL DATA D1 | G3: TOTAL DATA D2 | H3: DUPLEX PLATE | I3: QUAD PLATE
A4: 1 | B4: LINER WORKSTATION | C4: 290 | D4: 1 | E4: 1 | F4: =D4*C4 -> 290 | G4: =E4*C4 -> 290 | H4: =F4 -> 290
A5: 2 | B5: 120 DG. WORKSTATION | C5: 486 | D5: 1 | E5: 1 | F5: =D5*C5 -> 486 | G5: =E5*C5 -> 486 | H5: =F5 -> 486
A6: 3 | B6: RECEPTION | C6: 2 | D6: 1 | E6: 1 | F6: =D6*C6 -> 2 | G6: =E6*C6 -> 2 | H6: =F6 -> 2
A7: 4 | B7: CABIN ROOM | C7: 20 | D7: 1 | E7: 1 | F7: =D7*C7 -> 20 | G7: =E7*C7 -> 20 | I7: 20
A8: 4 | B8: PHONE BOOTH | C8: 16 | D8: 1 | E8: 1 | F8: =D8*C8 -> 16 | G8: =E8*C8 -> 16 | I8: 16
A9: 4 | B9: 4PAX MEETING ROOM | C9: 6 | D9: 1 | E9: 1 | F9: =D9*C9 -> 6 | G9: =E9*C9 -> 6 | I9: 6
A10: 5 | B10: 6PAX MEETING ROOM | C10: 7 | D10: 2 | E10: 2 | F10: =D10*C10 -> 14 | G10: =E10*C10 -> 14 | I10: 7
A11: 6 | B11: 8PAX MEETING ROOM | C11: 6 | D11: 2 | E11: 2 | F11: =D11*C11 -> 12 | G11: =E11*C11 -> 12 | H11: =F11 -> 12
A12: 7 | B12: 14 PAX CONFERENCE ROOM | C12: 1 | D12: 9 | E12: 9 | F12: =D12*C12 -> 9 | G12: =E12*C12 -> 9 | H12: 2 | I12: 4
A13: 8 | B13: COMAND CENTER | C13: 6 | D13: 1 | E13: 1 | F13: =D13*C13 -> 6 | G13: =E13*C13 -> 6 | H13: 2 | I13: 4
A14: 9 | B14: LAB | C14: 4 | D14: 1 | E14: 1 | F14: =D14*C14 -> 4 | G14: =E14*C14 -> 4 | H14: 2 | I14: 4
A15: 10 | B15: BMS ROOM | C15: 1 | D15: 1 | E15: 1 | F15: =D15*C15 -> 1 | G15: =E15*C15 -> 1 | H15: =F15 -> 1
A16: 11 | B16: IDF ROOM | C16: 3 | D16: 1 | E16: 1 | F16: =D16*C16 -> 3 | G16: =E16*C16 -> 3 | H16: =F16 -> 3
A17: 12 | B17: BATTERY ROOM | C17: 1 | D17: 1 | E17: 1 | F17: =D17*C17 -> 1 | G17: =E17*C17 -> 1 | H17: =F17 -> 1
A18: 13 | B18: ELECTERICAL ROOM | C18: 2 | D18: 1 | E18: 1 | F18: =D18*C18 -> 2 | G18: =E18*C18 -> 2 | H18: =F18 -> 2
A19: 14 | B19: NURSING ROOM | C19: 2 | D19: 1 | E19: 1 | F19: =D19*C19 -> 2 | G19: =E19*C19 -> 2 | H19: =F19 -> 2
A20: 15 | B20: TB ROOM | C20: 3 | D20: 1 | E20: 1 | F20: =D20*C20 -> 3 | G20: =E20*C20 -> 3 | H20: =F20 -> 3
A21: 16 | B21: 50 SEATER TRAINING ROOM | C21: 1 | D21: 10 | E21: 10 | F21: =D21*C21 -> 10 | G21: =E21*C21 -> 10 | H21: 2 | I21: 4
A22: 17 | B22: STORE ROOM | C22: 1 | D22: 1 | E22: 1 | F22: =D22*C22 -> 1 | G22: =E22*C22 -> 1 | H22: =F22 -> 1
A23: 18 | B23: 50 SEATER TRAINING ROOM | C23: 1 | D23: 10 | E23: 10 | F23: =D23*C23 -> 10 | G23: =E23*C23 -> 10 | H23: 8 | I23: 4
A24: 19 | B24: PANTRY | C24: 2 | D24: 1 | E24: 1 | F24: =D24*C24 -> 2 | G24: =E24*C24 -> 2 | H24: =F24 -> 2
A25: 20 | B25: JANITOR ROOM | C25: 1 | D25: 1 | E25: 1 | F25: =D25*C25 -> 1 | G25: =E25*C25 -> 1 | H25: =F25 -> 1
A26: 21 | B26: ULD BHOOT | C26: 1 | D26: 1 | E26: 1 | F26: =D26*C26 -> 1 | G26: =E26*C26 -> 1 | H26: =F26 -> 1
A27: 22 | B27: COLLAB | C27: 1 | D27: 1 | E27: 1 | F27: =D27*C27 -> 1 | G27: =E27*C27 -> 1 | H27: =F27 -> 1
A28: 23 | B28: WIFI | C28: 50 | D28: 1 | E28: 1 | F28: =D28*C28 -> 50 | G28: =E28*C28 -> 50 | H28: =F28 -> 50
A29: 24 | B29: AV AND SECURITY SYSTEM | C29: 40 | D29: 1 | E29: 1 | F29: =D29*C29 -> 40 | G29: =E29*C29 -> 40 | H29: =F29 -> 40
B31: TOTAL :- | F31: =SUM(F4:F29) -> 993 | G31: =SUM(G4:G29) -> 993 | H31: =SUM(H4:H29) -> 914 | I31: =SUM(I4:I29) -> 69

Sheet Summary - Plumbing & Fire Fight
A1: PROJECT : DHL - Chennai
A2: SUBJECT : Plumbing & Fire Fighting
A3: SR. NO. | B3: ITEM DESCRIPTION | C3: AMOUNT (INR) | D3: REMARKS
A5: 1 | B5: Plumbing | C5: =Plumbing!F126 -> 0
A6: 2 | B6: Wet Sprinkler System | C6: ='Wet Sprinkler System'!F85 -> 0
A7: 3 | B7: Fire Extinguishers | C7: ='Fire Extinguishers'!F20 -> 0
A8: 4 | B8: FK-5-1-12 | C8: ='FK-5-1-12'!L38 -> 0
A9: 5 | B9: Fire Curtain | C9: ='Fire Curtain'!F19 -> 0
B11: GRAND TOTAL | C11: =SUM(C5:C9) -> 0

Sheet Plumbing
A1: PROJECT : DHL - Chennai
A2: SUBJECT : Plumbing
A3: SL.NO | B3: ITEM DESCRIPTION | C3: UNIT | D3: QTY | E3: SUPPLY & INSTALLATION
E4: RATE (INR) | F4: AMOUNT (INR)
A6: 1 | B6: SOIL, WASTE AND VENT PIPES AND FITTINGS
A8: =A6+0.01 -> 1.01 | B8: Providing, jointing and fixing UPVC Soil, Waste and Vent System ( For Toilet)
B9: The work shall be done as per technical specifications and in general shall include:
B10: Material: UPVC pipes and fittings (moulded as well as fabricated) conforming to IS : 13592 - Type B
B11: Fittings shall include all standard moulded as well as fabricated fittings like bends, tees, Y-tees, crosses, boss connections, access pieces, saddle pieces, cleanouts, adaptors for connections to other materials, plugs, reducers, cowls, offsets and other specials
B12: Jointing: Pushfit rubber ring jointing technique in general. Solvent cement joints may be provided for fittings and specials which are not manufactured with pushfit rubber joints
B13: Installation, Testing and Commissioning: The installation shall be complete in all respects including cutting chases / holes in walls, slabs, excavation, refilling and disposal of surplus earth where required and making good, etc
B14: M.S Supports: All vertical and suspended horizontal pipework shall be fixed on MS brackets and hangers with U-clamps made from 10 mm dia galvanised steel rod complete with nuts and washers. Cost for MS structural work for supports shall be included in the rates
B15: Conctere Encasing ( In case of Sunken Floor/ burried pipes): The pipes and fittings shall be encased with 75 mm thick cement concrete ( 1:2:4) all around
B16: Making Good the Structure Crossongs: For all horozontal and vertical crossings of building structure ( slabs, walls, beams, coloumn etc), the space between pipe and the structure shall be made good and water tight with concrete. The annular space between the pipe and the sleeves shall be sealed (upto a minimum depth 25 mm) with fire resistant acrylic based sealent of approved make and quality.
B17: a) 75 mm dia | C17: M | D17: 100 | F17: =E17*D17 -> 0
B18: b) 110 mm dia | C18: M | D18: 30 | F18: =E18*D18 -> 0
A20: =A8+0.01 -> 1.02 | B20: Providing & fixing UPVC soil, waste, vent pipework comprising UPVC pipe conforming to IS :4985-1983 and of required class as specified below and fittings (moulded as well as fabricated) like elbows, bends, reducers, threaded tail pieces, caps and and other specials. jointing with cement solvent, chasing, cutting and making good the walls, complete in all respects including testing of complete installation.
B21: a) 40 mm dia 6 kg/cm2 ( Class III ) | C21: M | D21: 95 | F21: =E21*D21 -> 0
B22: b) 50 mm dia 6 kg/cm2 ( Class III ) | C22: M | D22: 30 | F22: =E22*D22 -> 0
B23: c) 63 mm dia 6 kg/cm2 ( Class III ) | C23: M | D23: 10 | F23: =E23*D23 -> 0
A25: =A20+0.01 -> 1.03 | B25: Providing and fixing of UPVC Floor Traps formed out of bore 'P' trap with 50 mm water seal, setting in 1:2:4 mix cement concrete block or clamping to the wall or suspending with the ceiling including cutting and making good the walls and floors wherever required.
B26: a) 110 mm inlet and 75 mm outlet | C26: No. | D26: 5 | F26: =E26*D26 -> 0
A28: =A25+0.01 -> 1.04 | B28: Providing and fixing PVC floor trap EXTENTION PIECE formed out of 110 mm pipe with multiple side inlets formed with saddle pieces, suitable for 40, 50 and 63 mm dia side connections as per standard detail. | C28: No. | D28: 95 | F28: =E28*D28 -> 0
A30: =A28+0.01 -> 1.05 | B30: Providing and fixing floor drain points formed out of 63x 50 mm dia UPVC elbow with suitable extension piece, fitted with 75 mm dia nickel bronze grating and frame, embedded in floor, all complete. | C30: No. | D30: 2 | F30: =E30*D30 -> 0
A32: =A30+0.01 -> 1.06 | B32: Providing and fixing screwed down type nickel bronze alloy cast floor cleanout/ CO with opening arrangements for soil / waste pipe and other necessary fittings inlcuding jointing, all complete as per standard detail.
B33: a) for 75 mm dia pipe | C33: No. | D33: 10 | F33: =E33*D33 -> 0
B34: b) for 110 mm dia pipe | C34: No. | D34: 0 | F34: =E34*D34 -> 0
A36: =A32+0.01 -> 1.07 | B36: Providing and fixing 120 mm dia round stainless steel rotate lock type grating with frame and ABS Plastic cockroach trap, embedded in floor, all complete of following make or equal approved
B37: Make : ATGT, China/Neer
B38: Model: PD 3128 | C38: No. | D38: 95 | F38: =E38*D38 -> 0
A40: =A36+0.01 -> 1.08 | B40: Making connection with existing Soil and Waste pipework. The work includes loosening / removing the existing lead joints, rotating the direction of the existing tees, bends etc. so as to connect with new branch lines from the toilets, redoing the joints with 'sealent', testing, commissioning all complete. Any pipe piece, fittings etc. required to make the connection shall be measured in Item No. 2.1 | C40: No. | D40: 5 | F40: =E40*D40 -> 0
A42: =A40+0.01 -> 1.09 | B42: P/Fixing straight /offset type Macfit single body push fit type WC pan connector with factory supplied spring loaded seal guard of McAlpine, UK with integral single mould sealing fins made of flexible EVA body, including bush/adaptor for use with C.I. Pipe as supplied with the pan connector (if required). | C42: No. | D42: 66 | F42: =E42*D42 -> 0
A44: =A42+0.01 -> 1.1 | B44: Making core cutting in slab of following size using core cutter machine as specified in the drawing. The annular space shall be sealed with adhesive material aand making water proof after installation of pipe, complete in all respect. Note: The approval for core cutting shall be taken from the Client/Structural consultant before core cutting.
B45: a) 90/100 mm dia | C45: No. | D45: 0 | F45: =E45*D45 -> 0
B46: b) 150 mm dia | C46: No. | D46: 5 | F46: =E46*D46 -> 0
A48: =A44+0.01 -> 1.11 | B48: Sealing core cutting in slab of following size using adhesive material aand making water proof after installation of pipe, complete in all respect.
B49: a) 90/100 mm dia | C49: No. | D49: 0 | F49: =E49*D49 -> 0
B50: b) 150 mm dia | C50: No. | D50: 5 | F50: =E50*D50 -> 0
A52: =A48+0.01 -> 1.12 | B52: Providing, installing, testing and commissioning of Grease Separator having grease storage capacity of 9 litre and total iquid holding capacity of 34.3 litre , all as per standard design and including making connections with scullery sink
B53: Make : SFA Paris ( Marketed by flowmech Pumps)
B54: Model: PP 40 | C54: No. | D54: 0 | F54: =E54*D54 -> 0
A56: =A52+0.01 -> 1.13 | B56: Providing, installing, testing and commissioning of package sump unit with built-in submersible drainage pump, nonreturn valve, all as per standard design and including making connections with scullery sink/wash bsain
B57: Make : SFA, Paris ( Marketed by flowmech Pumps)
B58: Model: Sanispeed | C58: No. | D58: 0 | F58: =E58*D58 -> 0
B61: TOTAL FOR "Soil, Waste & Vent Pipework" carried over to SUMMARY | F61: =SUM(F17:F60) -> 0
A63: 2 | B63: WATER SUPPLY PIPE WORK
A65: =A63+0.01 -> 2.01 | B65: Providing and fixing in position CPVC pipes conforming to IS: 15778:2007 (Grade SDR-11) with all fittings, brass threaded adaptors and specials, solvent cement/threaded jointing, effecting proper connections, cutting chases in walls and floors and making good (including making connection with existing pipework), Note: Pipe work in shafts, ceiling voids and terrace shall be supported/ fixed on MS structural supports with U-clamps complete with nuts and washers.Cost for MS structural work for supports shall be included in the rates all complete. ( Pipework inside the toilets and pantry etc) Note : 1) Solvent Cement shall be of make and grade as specified by the manufacturer of CPVC piping system. 2) The entire CPVC piping system shall be installed, connected with exiting pipework, tested and commissioned following the recommendation of the manufacturer.
B66: a) 1/2" N.D.(SDR 11 Rated ) | C66: M | D66: 0 | F66: =E66*D66 -> 0
B67: b) 3/4" N.D.(SDR 11 Rated ) | C67: M | D67: =925+35 -> 960 | F67: =E67*D67 -> 0
B68: c) 1" N.D. (SDR 11 Rated ) | C68: M | D68: 125 | F68: =E68*D68 -> 0
B69: d) 1 1/4" N.D. (SDR 11 Rated ) | C69: M | D69: 45 | F69: =E69*D69 -> 0
B70: e) 1 12" N.D. (SDR 11 Rated ) | C70: M | D70: 65 | F70: =E70*D70 -> 0
B71: f) 2" N.D. (SDR 11 Rated ) | C71: M | D71: 35 | F71: =E71*D71 -> 0
B72: g) 2 1/2" N.D. (SDR 11 Rated ) | C72: M | D72: 15 | F72: =E72*D72 -> 0
A74: =A65+0.01 -> 2.02 | B74: Providing and fixing of nickel plated brass/ nonferrous alloy fullyway ball valve ( minimum working pressure of 20 bar ) with operating handle of approved make.( Note: Existing isolating valve shall be used for making connection with new pipework)
B75: a) 15 mm dia | C75: No. | D75: 0 | F75: =E75*D75 -> 0
B76: b) 20 mm dia | C76: No. | D76: 40 | F76: =E76*D76 -> 0
B77: c) 25 mm dia | C77: No. | D77: 4 | F77: =E77*D77 -> 0
B78: d) 32 mm dia | C78: No. | D78: 2 | F78: =E78*D78 -> 0
B79: e) 40 mm dia | C79: No. | D79: 4 | F79: =E79*D79 -> 0
B80: f) 50 mm dia | C80: No. | D80: 8 | F80: =E80*D80 -> 0
A82: =A74+0.01 -> 2.03 | B82: Providing and fixing screwed end Wafer type check valve (non return valve) of Class PN 10, having stainless steel body and disc, trim and spring of approved make. all complete.
B83: a) 32 mm dia | C83: No. | D83: 0 | F83: =E83*D83 -> 0
A85: =A82+0.01 -> 2.04 | B85: Providing and fixing insulation to hot water piping with closed cell chemically cross-linked polyethylene ( XLPE) preformed pipe sleeves of specified wall thickness using propriety adhesive and self adhesive tapes, all as per the manufacturer's specifications. (For exposed water pipes in plumbing shaft and on terrace)
B86: a) 15 mm dia - 9 mm thickness | C86: M | D86: 0 | F86: =E86*D86 -> 0
B87: b) 20 mm dia - 9 mm thickness | C87: M | D87: 35 | F87: =E87*D87 -> 0
A89: =A85+0.01 -> 2.05 | B89: Making connection with existing water supply pipes with all fittings, specials & clamps effecting proper connections, cutting chases in walls and floors and making good, including painting with two coats of anti-corrosive bitumanistic paint on buried and concealed pipework and with two coats enamel paint of approved quality and shade over a coat of zinc chromate primer on exposed pipework. (Internal Work). Any pipe piece, fittings etc. required to make the connection shall be measured in Item No. 3.1
B90: a) 15 mm dia | C90: No. | D90: 0 | F90: =E90*D90 -> 0
B91: b) 20 mm dia | C91: No. | D91: 40 | F91: =E91*D91 -> 0
B92: c) 25 mm dia | C92: No. | D92: 4 | F92: =E92*D92 -> 0
B93: d) 32 mm dia | C93: No. | D93: 2 | F93: =E93*D93 -> 0
B94: e) 40 mm dia | C94: No. | D94: 4 | F94: =E94*D94 -> 0
B95: f) 40 mm dia | C95: No. | D95: 8 | F95: =E95*D95 -> 0
A97: =A89+0.01 -> 2.06 | B97: Supplying, installing, testing and commissioning of Electromagnetic Water Meter Sandwich / Flanged ends ( and necessary bolt & nuts with complete Wiring and Cabling work (compatible to bms system)
B98: Make :UPC
B99: a) 15mm DIA Water Meter | C99: No. | D99: 0 | F99: =E99*D99 -> 0
B100: b) 20mm DIA Water Meter | C100: No. | D100: 0 | F100: =E100*D100 -> 0
B101: c) 25mm DIA Water Meter | C101: No. | D101: 0 | F101: =E101*D101 -> 0
B102: d) 32mm DIA Water Meter | C102: No. | D102: 0 | F102: =E102*D102 -> 0
B103: e) 40mm DIA Water Meter | C103: No. | D103: 0 | F103: =E103*D103 -> 0
B104: f) 50mm DIA Water Meter | C104: No. | D104: 0 | F104: =E104*D104 -> 0
B105: g) 65mm DIA Water Meter | C105: No. | D105: 0 | F105: =E105*D105 -> 0
A107: =A97+0.01 -> 2.07 | B107: Under Counter R.O Unit ( Kitchen area): Providing, installing, testing and commissioning Packaged type R.O system based water treatment system, capable of producing 50LPH of portable water meeting the requirements as per standard and having storage capacity 25 litre. suitable for Two taps ,The system shall be complete with housing, Pre-Treatment Units, Membranes Flushing / Cleaning System pH Correction System, Disinfection System, TDS modulator, Water Transfer & Booster Pump, Buffer Tank, complete instrumentation for automation and monitoring, Rotameters, Pressure Gauges, TDS Mudulator, interconnecting pipework, electrical cabling and switchgear, all complete . The skid/supporting system shall be inclusive in the quoted rate Basic Rate: 60500/-
B108: The unit shall be suitable for the following expected raw water characterstics: Raw Water Characterstic pH Value: 6.5 - 8.5 Total Hardness : upto 300 mg/litre Dissolved Solids: upto1000 mg/litre
B109: Suggested Makes:
B110: a) Wa Corp Hyundai India Ltd./Oasis | C110: No. | D110: 4 | F110: =E110*D110 -> 0
A112: =A107+0.01 -> 2.08 | B112: Providing, Fixting, Testing and Commissioing Infrared sensor touchless faucet system for filtered drinking water. Tarnish and scratch free resistant the SINGLE TAP SENSOR TAP WITH 3 OUTLET ( for chilled, hot and ambient temp.water dispensing Tap suitable to fill pet water bottel 1ltr. comes single dispensing with LED UVC and anti bacterial tubing. ( Sink and Drip tray inclusive) and under counter Hydropac Calssic Unit with 10L Hot/10L Cold and online interface of ambient temp water. Power Consumption- 370 W Voltage Supply-230 V AC/50 Hz Ambient temperature- 4-32 deg C Chilled water temp- 5-10 deg C Hot water temp- max 80 deg C Flow pressure: min. 0.5 bar / recommended 1 – 5 bar Minimum recommended pressure 2.0 bar Basic Rate: 175000/- | C112: No. | D112: 4 | F112: =E112*D112 -> 0
B113: a) Wa Corp Hyundai India Ltd./Oasis
A115: =A112+0.01 -> 2.09 | B115: R.O Tower Unit: Providing, Fixting, Testing and Commissioing Floor Mounted Package RO Membrane Based Drinking Water Generation System with built-in Hot and Cold Water Storage
B116: Type: Packaged Type complete with micron filter, carbon filter cartridges and RO membranes, UF membranes all in engineering plastic housings, high pressure pump, pressurised storage vessel, disinfection unit, auto flush, TDS Mudulator, auto controls, interconnecting micro tubing, cabling etc and complete supporing/ fixing arrangement Basic Rate: 140000/-
B117: The unit shall be suitable for the following expected raw water characterstics: Raw Water Characterstic pH Value: 6.5 - 8.5 Total Hardness : upto 300 mg/litre Dissolved Solids: upto1000 mg/litre
B119: R.O Water Generation Capacity: As mentioned Below
B120: Cold- 40 L; Ambeint - 85 Hot- 5 L
B121: a) Capacity: 100 LPH Capacity with three sensor taps (CHA)
B122: Make: WAE/Oasis | C122: No. | D122: 4 | F122: =E122*D122 -> 0
B124: TOTAL of "Water Supply" carried over to SUMMARY | F124: =SUM(F66:F123) -> 0
B126: GRAND TOTAL | F126: =SUM(F61+F124) -> 0

Sheet Wet Sprinkler System
A1: PROJECT : DHL - Chennai
A2: SUBJECT : Wet Sprinkler System
A3: SL.NO | B3: ITEM DESCRIPTION | C3: UNIT | D3: QTY | E3: SUPPLY & INSTALLATION
E4: RATE (INR) | F4: AMOUNT (INR)
B6: Note: Vendor has to prepare necessary drawings for approval, documentation, fill up government forms, as required for the statutory authority certification (Fire NOC Certification). The statutory associated government fee for this certification & inspection, will be paid by the client.
B7: Note : Vendor to visit the construction site, understanding the building, structure, beams, roofs, ceiling etc., for the benefit of quoting completely on several perspectives such as mobilisation, Logistics, storage, Instalation, Support systems to the I beams Purlins etc.,
B8: Note: It is proposed to achieve USGBC LEED Gold Certification for this building. Vendor to go through the LEED documents & comply to the requirement in reference to this BOQ & Specification.
A9: 1 | B9: Providing, laying, jointing, testing and commissioning pipework for Sprinkler System including making connection with existing pipework, fixing of pipework on walls, beams, slabs, columns etc. with M. S. supports (duly painted), adjustable hangers,wedge nut support complete in all respects.
B10: Material: G.I. pipe Class 'C' conforming to IS:1239 for pipes upto 150 mm dia and IS:3589-1991 for pipes above 150 mm dia.
B11: Fittings: Ductile Iron Fittings (FM Approved) Screwed end Upto 50 mm dia pipes and Ductile Iron ( FM Approved) Groove Fittings (FM Approved) for pipes 65mm dia and above. Rigid & Flexible Coupling shall be installed whever required Note: No welding is allowed in the pipes unless approved by the Engineer in Charge for areas where Grooving is not possible. The coupling should not require any torque while tightening and approved as per FM Guidelines. The Gasket in the Rigid Coupling should be Grade E EPDM Type A. The Grooving in the pipes should be done by the compatible Grooving Machine approved by the manufacturer of grooved fittings.
B12: Painting: Pipework shall be painting with two coats of enamel paint of fire red shade over a coat of primer.
B13: Firestops: For all horozontal and vertical crossings of building structure ( slabs, walls, beams, coloumn etc) pvc pipe sleeves of dia atleast 30 mm more than the dia of the pipe to be passed through shall be fixed in the building structure, the space buitween the the sleeve and the structure shall be made good. The annular space between the pipe and the sleeves shall be sealed (upto a minimum depth 25 mm) with fire resistant acrylic based sealent of approved make and quality.
B14: Vendor shall submit all the Manufacturing and Test certificates with the delivery of pipes at site.
A15: a | B15: 150mm dia ISI | C15: Mtrs | D15: 160 | F15: =E15*D15 -> 0
A16: b | B16: 100mm dia ISI | C16: Mtrs | D16: 125 | F16: =E16*D16 -> 0
A17: c | B17: 80mm dia ISI | C17: Mtrs | D17: 105 | F17: =E17*D17 -> 0
A18: d | B18: 65mm dia ISI | C18: Mtrs | D18: 270 | F18: =E18*D18 -> 0
A19: e | B19: 50mm dia ISI | C19: Mtrs | D19: 360 | F19: =E19*D19 -> 0
A20: f | B20: 40mm dia ISI | C20: Mtrs | D20: 165 | F20: =E20*D20 -> 0
A21: g | B21: 32mm dia ISI | C21: Mtrs | D21: 220 | F21: =E21*D21 -> 0
A22: h | B22: 25mm dia ISI | C22: Mtrs | D22: 1800 | F22: =E22*D22 -> 0
B23: ISI MARKED
A25: 2 | B25: Supply Installation testing & comissioning of Concealed type, Bulb type sprinkler with Fusible coverplate of 15 NB, 68 deg.with heat activated, Quick Response, powder coated plate. | C25: Nos | D25: 20 | F25: =E25*D25 -> 0
B26: UL/FM Approved
A28: 3.1 | B28: Supply Installation testing & comissioning of Pendant type sprinkler of 15 NB, Quartzoid bulb type 68 deg.Quick Response, with adjustable escutcheon plate in SS 304. | C28: Nos | D28: 435 | F28: =E28*D28 -> 0
B29: UL/FM Approved
A31: 3.2 | B31: Remove, Reinstallation, Testing of Existing Upright Sprinklers. | C31: Nos | D31: 0 | F31: =E31*D31 -> 0
A33: 4.1 | B33: Supply Installation testing & comissioning of Upright type sprinkler of 15 NB, Quartzoid bulb type 68 deg, Quick Response, with SS 304 sprinkler guard if required. | C33: Nos | D33: 700 | F33: =E33*D33 -> 0
B34: UL/FM Approved
A36: 4.2 | B36: Remove, Reinstallation, Testing of Existing Pendant Sprinklers. | C36: Nos | D36: 0 | F36: =E36*D36 -> 0
A38: 5 | B38: Supply Installation testing & comissioning of Side Wall sprinklerof 15 NB, 68 deg. Quick Response, with heat activated black powder coated plate. | C38: Nos | D38: 200 | F38: =E38*D38 -> 0
B39: UL/FM Approved
A41: 6 | B41: Supply Installation testing of Orifice Plate 6 mm Thick SS 316 shall be fitted in flanges at the sprinkler header tapoff point to Main Riser.
A42: 6.1 | B42: - Size 150 NB. | C42: Nos | D42: 0 | F42: =E42*D42 -> 0
A43: 6.2 | B43: - Size 100 NB. | C43: Nos | D43: 0 | F43: =E43*D43 -> 0
A45: 7 | B45: Supply Installation testing of Sprinkler Flexible drop pipes of 25mm diameter of SS Braided Corrugated SS Tubing to with stand 16 Bar pressure with welded reducer on one end to directly accommodate sprinkler & female check nut on the other end to connect to the branch pipe with supports complete with required accessories to fix on the False ceiling with adjustable SS bar and clamps. Note : Wherever Sprinklers are located below the ducts, the Vendor shall provide Victaulic AB11 / AB12 or equivalent type threaded rod bracket to fit the sprinkler below the Duct. ( Space below duct is only 100mm) OR with UL Listed FlexDrops with integral short Radius Elbow to ensure low profile fitting below the Duct.
A46: 7.1 | B46: 1000 mm long | C46: Nos | D46: 55 | F46: =E46*D46 -> 0
A47: 7.2 | B47: 1200 mm long | C47: Nos | D47: 100 | F47: =E47*D47 -> 0
A48: 7.3 | B48: 1500 mm long | C48: Nos | D48: 300 | F48: =E48*D48 -> 0
B49: UL/FM Approved
B51: Remove, Reinstallation, Testing of Existing Sprinkler Flexible drop pipes | C51: Nos | D51: 0 | F51: =E51*D51 -> 0
A53: 8 | B53: Providing and fixing of Sprinkler Hard drop pipes made of 25 NB GI Pipe with socket weld fittings with welded reducer on one end to directly accommodate sprinkler with supports (Length up to 2.5 Mtrs). | C53: Nos | D53: 200 | F53: =E53*D53 -> 0
A55: 9 | B55: Supply Installation testing of Cast iron butterfly valve with Tamper Switch rated for pressure rating PN 16 kg/sq.cm standard pattern (Horizontal / Vertical),with necessary flanged joints by providing necessary pair of M.S. flanges, nuts, bolts, gaskets, etc. all complete for
A56: 9.1 | B56: 150 NB | C56: Nos | D56: 4 | F56: =E56*D56 -> 0
A57: 9.2 | B57: 80/100 NB | C57: Nos | D57: 0 | F57: =E57*D57 -> 0
A59: 10 | B59: Supply, Installation, Testing and commissioning of Flow Switch pedal Type with dual potential free contact to monitored on the FAS system.
B60: 80/100 NB | C60: Nos | D60: 0 | F60: =E60*D60 -> 0
B61: 150 NB | C61: Nos | D61: 4 | F61: =E61*D61 -> 0
B62: UL/FM Approved
A64: 11 | B64: Supply Installation testing of 50 mm dia Gate valve as per IS 778 for sprinkler drain with Tamper switch, On/Off status shall be monitored by BMS System. | C64: Nos | D64: 0 | F64: =E64*D64 -> 0
B65: ISI MARKED
A67: 12 | B67: Supply Installation testing of 25 mm dia Ball valve, As per BS 5351, Listed type, ISI Marked. | C67: Nos | D67: 4 | F67: =E67*D67 -> 0
B68: ISI MARKED
A70: 13 | B70: Supply Installation testing of 50 mm dia Ball valve, As per BS 5351, Listed type, ISI Marked. | C70: Nos | D70: 4 | F70: =E70*D70 -> 0
B71: ISI MARKED
A73: 14 | B73: Supply Installation testing of 25 mm Test Valve Drain kit with sight Glass, Ball valve, Union & required fittings etc | C73: Nos | D73: 4 | F73: =E73*D73 -> 0
B74: UL Listed
A76: 15 | B76: Supply Installation testing of 25mm dia Air Vent Valves at Sprinkler Tapoffs with Ball Valve. | C76: Nos | D76: 0 | F76: =E76*D76 -> 0
A78: 16 | B78: Supply Installation testing of Pressure Guage 0 - 5 Kg / cm2 with mounting arrangement and ball valve. | C78: Nos | D78: 4 | F78: =E78*D78 -> 0
A80: 17 | B80: HydroTesting of Sprinkler piping Network before sprinkler installation with dead plug at 14kg/cms and after installation of sprinkler at 12Kg/cms | C80: Job | D80: 2 | F80: =E80*D80 -> 0
A82: 18 | B82: Hydroluic calculation for sprinkler system of each zone | C82: Job | D82: 4 | F82: =E82*D82 -> 0
B85: GRAND TOTAL | F85: =SUM(F9:F84) -> 0

Sheet Fire Extinguishers
A1: PROJECT : DHL - Chennai
A2: SUBJECT : Fire Extinguishers
A3: SL.NO | B3: ITEM DESCRIPTION | C3: UNIT | D3: QTY | E3: SUPPLY & INSTALLATION
E4: RATE (INR) | F4: AMOUNT (INR)
A6: 1 | B6: Supply, installation, testing and commissioning of ISI marked 4.5 kg CO₂ type fire extinguisher, complete with wall mounting brackets or MS powder-coated floor stand, including all accessories and approved fire signage, as per specifications. | C6: Nos | D6: 25 | F6: =E6*D6 -> 0
A8: 2 | B8: Supply, installation, testing and commissioning of ISI marked 6 kg ABC type (stored pressure) fire extinguisher, complete with wall mounting brackets or MS powder-coated floor stand, including all accessories and approved fire signage, as per specifications. | C8: Nos | D8: 38 | F8: =E8*D8 -> 0
A10: 3 | B10: Supply, installation of Flexible Photo luminescent Sign Board of Size 200mm x 250mm ,displaying "Fire Extinguisher" Shape of the sigange shall depend on the architect approvals, Vendor shall submit sample on site for approvals. | C10: Nos | D10: =D8+D6 -> 63 | F10: =E10*D10 -> 0
A12: 4 | B12: Providing and fixing of MS powder-coated floor stand (tripod/open type) suitable for 4/6 kg fire extinguisher, with stable base and proper support for easy placement/removal, complete with necessary accessories. Vendor to submit sample for approval. | C12: Nos | D12: =D10 -> 63 | F12: =E12*D12 -> 0
A14: 5 | B14: Evacuation Plan with Auto Glow in A3 with 3 mm mounting acrylic sheet in Frame with transparent sandwich acrylic sheet with SS studs. capable to be mountable on partition with mounting accessories. | C14: Nos | D14: 10 | F14: =E14*D14 -> 0
A16: 6 | B16: Supply, installation of Photo luminescent Sign Board of Size 200mm x 250mm ,displaying "MCP" | C16: Nos | D16: 15 | F16: =E16*D16 -> 0
A18: 7 | B18: Supply, installation of automatic 15kg Clean agent ceiling suspended Fire Extinguisher [ 68 Deg. C] with Ceiling mounting stand. | C18: Nos | D18: 0 | F18: =E18*D18 -> 0
B20: GRAND TOTAL | F20: =SUM(F6:F19) -> 0

Sheet FK-5-1-12
A1: PROJECT : DHL - Chennai
A2: SUBJECT : Fire Extinguishers system FK-5-1-12
A3: SL.NO | B3: ITEM DESCRIPTION | C3: UNIT | D3: UPS & BATTERY ROOM - 1 | E3: UPS & BATTERY ROOM - 2 | F3: SERVER | G3: HUB 1 | H3: HUB 2 | I3: HUB 3 | J3: TOTAL QTY | K3: SUPPLY & INSTALLATION
K4: RATE (INR) | L4: AMOUNT (INR)
A6: 1.1 | B6: Design, Supply, Installation, Testing and Commissioning of UL Listed Total Room Flooding System using Fluoroketone (FK 5-1-12) UL Listed Extinguishing Agent, FK-5.1.12 Gas shall be UL Listed. The system Working Pressure should be of 25/42/50 Bar. Storage Cylinder shall be Seamless & have PESO (Ex-CCOE) approved. The system also to be fitted with low pressure supervisory switch for monitoring cylinder pressure gauge with safety burst disc safety cap, elbow and other accessories, mounting bracket, container straps, NRV, Pressure operated control head which shall allow for pressure actuation of gas mounted, manually operated actuator to actuate the gas flooding process with the help of a lever, flexible rubber hose with wire braided enforcement to route the gas from the storage cylinder to the discharge piping, to be connected to the discharge outlet of gas cylinder valve & to be terminated at the system piping or discharge manifold, Flexible actuation hose complete as required. Designated to provide proper flow rate & distribution FK-5.1.12 Gas to flood the hazard area as per latest NFPA 2001.
B7: Bank of 2 Nos. ( 1 Operational + 1 standby) PESO Approved Seamless Cylinders ( as per manufacture`s recommendation) including the following: a) Master discharge valves ( electrically operated resettable type) & slave discharge valves ( Pneuomatically Operated) b) Manual Actuation Device c) Cylinder pressure monitoring system d) Pressure guage with safety burst disc e) Discharge flexible hose f) Manifold with pressure switch g) Non-Return Valves h) Mounting rack complete with brackets i) Straps j) Safety Caps h) Warning Signages (As per OEM)
B8: 34/40 Ltr | C8: Set | D8: 0 | E8: 0 | F8: 0 | G8: 1 | H8: 0 | I8: 1 | J8: =SUM(D8:I8) -> 2 | L8: =K8*J8 -> 0
B9: 80 Ltr | C9: Set | D9: 0 | E9: 1 | F9: 1 | G9: 0 | H9: 1 | I9: 0 | J9: =SUM(D9:I9) -> 3 | L9: =K9*J9 -> 0
B10: 120 Ltr | C10: Set | D10: 0 | E10: 0 | F10: 0 | G10: 0 | H10: 0 | I10: 0 | J10: =SUM(D10:I10) -> 0 | L10: =K10*J10 -> 0
B11: 140 Ltr | C11: Set | D11: 1 | E11: 0 | F11: 0 | G11: 0 | H11: 0 | I11: 0 | J11: =SUM(D11:I11) -> 1 | L11: =K11*J11 -> 0
A13: 1.2 | B13: Supply of FK -5-1-12 agent (Clean Agent Gas -UL ) including filling in the cylinder | C13: Kg | D13: 260 | E13: 84 | F13: 124 | G13: 60 | H13: 78 | I13: 60 | J13: =SUM(D13:I13) -> 666 | L13: =K13*J13 -> 0
A15: 1.3 | B15: Providing, fixing and testing Mild Steel Seamless pipes as per ASTM A 106 Gr. B, Schedule-40 including necessary fittings and accessories like tees, bends, elbows, unions, reducers, flanges, gaskets etc. as required including fixing of pipework on walls, slabs with supports, clamps etc. all complete Room Area up to 20sqm. | C15: Lot | D15: 1 | E15: 1 | F15: 1 | G15: 1 | H15: 1 | I15: 1 | J15: =SUM(D15:I15) -> 6 | L15: =K15*J15 -> 0
A17: 1.4 | B17: Providing, calibrating and fixing Gas Discharge Nozzles, of suitable dia designed to provide the proper flow rate & distribution of FK-5-1-12 to total flood a hazard area: 180 deg. / 360 deg. | C17: Nos | D17: 4 | E17: 2 | F17: 3 | G17: 3 | H17: 3 | I17: 3 | J17: =SUM(D17:I17) -> 18 | L17: =K17*J17 -> 0
A19: 1.5 | B19: Supply, installing, connecting up, testing and commissioning of the following fire alarm equipment :
B20: a) Supply of UL Listed (Listed (9th Edition) Microprocessor based Conventional Gas Release Panel, panel shall have 16X2 LCD character with 2 zones detection circuit and 2 main agent release circuits & 4 No’s of programmable Initiating Device Circuit and 2 No’s of Releasing Agent circuit, with the independent correlation of any no of initiating devices circuit with any one of Release Agent Circuit. 4 No’s Programmable (Fire, Cross Zone & Gas Release) relays for integration of third party system Separate LED indications on front facia for individual Releasing Agent Circuit. Operates on 120-220v 60 / 50 Hz, AC Mains power supply, Battery Low audio visual warning tone. PANEL SHOULD HAVE MODBUS/BACNET CARD FOR BMS INTEGRATION | C20: Nos | D20: 1 | E20: 1 | F20: 1 | G20: 1 | H20: 1 | I20: 1 | J20: =SUM(D20:I20) -> 6 | L20: =K20*J20 -> 0
B21: b) UL Listed Photo cum Thermal (multicriteria) Smoke Detector with mounting base. | C21: Nos | D21: 8 | E21: 8 | F21: 6 | G21: 6 | H21: 6 | I21: 6 | J21: =SUM(D21:I21) -> 40 | L21: =K21*J21 -> 0
B22: c) UL Listed Conventional Manual Call Point | C22: Nos | D22: 1 | E22: 1 | F22: 1 | G22: 1 | H22: 1 | I22: 1 | J22: =SUM(D22:I22) -> 6 | L22: =K22*J22 -> 0
B23: d) UL Listed Conventional Sounder Cum Strobe | C23: Nos | D23: 2 | E23: 2 | F23: 2 | G23: 2 | H23: 2 | I23: 2 | J23: =SUM(D23:I23) -> 12 | L23: =K23*J23 -> 0
B24: e) UL Listed Conventional Manual Abort Station | C24: Nos | D24: 1 | E24: 1 | F24: 1 | G24: 1 | H24: 1 | I24: 1 | J24: =SUM(D24:I24) -> 6 | L24: =K24*J24 -> 0
B25: f) UL Listed Conventional Manual Release Station | C25: Nos | D25: 1 | E25: 1 | F25: 1 | G25: 1 | H25: 1 | I25: 1 | J25: =SUM(D25:I25) -> 6 | L25: =K25*J25 -> 0
B26: g) Service Disconnecting Switch | C26: Nos | D26: 1 | E26: 1 | F26: 1 | G26: 1 | H26: 1 | I26: 1 | J26: =SUM(D26:I26) -> 6 | L26: =K26*J26 -> 0
B27: h) PVC Insulated FRLS Armoured Cable 1.5mm x 2 Core on surface or on false ceiling complete as required. | C27: M | D27: 80 | E27: 80 | F27: 80 | G27: 80 | H27: 80 | I27: 80 | J27: =SUM(D27:I27) -> 480 | L27: =K27*J27 -> 0
B28: i) Addressable Monitor Module to intigrate with Main Fire Alarm Panel | C28: Nos | D28: 1 | E28: 1 | F28: 1 | G28: 1 | H28: 1 | I28: 1 | J28: =SUM(D28:I28) -> 6 | L28: =K28*J28 -> 0
B29: j) Response Indicator | C29: Nos | D29: 2 | E29: 2 | F29: 4 | G29: 4 | H29: 4 | I29: 4 | J29: =SUM(D29:I29) -> 20 | L29: =K29*J29 -> 0
A31: 1.6 | B31: Performing for Room Inegrity test including required testing agent, all complete | C31: Nos | D31: 1 | E31: 1 | F31: 1 | G31: 1 | H31: 1 | I31: 1 | J31: =SUM(D31:I31) -> 6 | L31: =K31*J31 -> 0
C32: Nos | J32: =SUM(D32:I32) -> 0
A33: 1.7 | B33: Providing and fixing Photoluminescent ( self glowing) Signage on 1 mm thick PVC rigid sheet, of following type:
B34: a) Marked `GAS PROTECTED AREA`, Overall size 400 mm x 150 mm | C34: Nos | D34: 1 | E34: 1 | F34: 1 | G34: 1 | H34: 1 | I34: 1 | J34: =SUM(D34:I34) -> 6 | L34: =K34*J34 -> 0
B35: b) Marked `GAS BANK`, Overall size 400 mm x 150 mm | C35: Nos | D35: 1 | E35: 1 | F35: 1 | G35: 1 | H35: 1 | I35: 1 | J35: =SUM(D35:I35) -> 6 | L35: =K35*J35 -> 0
B38: GRAND TOTAL | J38: =SUM(J8:J36) -> 1302 | L38: =SUM(L8:L36) -> 0

Sheet FK-5-1-12 Design
A1: FK-5-1-12 Design Calculations Sheet
A2: SL.NO | B2: Critical Room Names | C2: Area | D2: Height | E2: Volume | F2: Design Concentration | G2: Design Temp | H2: Conversion | I2: Qty of FK-5-1-12 Required | J2: Qty of FK-5-1-12 Provided | K2: Indicative Cylinder Capacity | L2: No. Of Cylinders required | M2: Nozzles
C3: m2 | D3: m | E3: m3 | F3: % | G3: oC | H3: Kg/Mtr3 | I3: Kgs | J3: Kgs | K3: Liters
A5: 1 | B5: UPS and Battrey Room-1 | C5: 47.8 | D5: 4 | E5: =D5*C5 -> 191.2 | F5: 4.5 | G5: 21 | H5: 0.6531 | I5: =H5*E5 -> 124.87272 | J5: 130 | K5: 140 | L5: 1 | M5: 4
A7: 2 | B7: UPS and Battrey Room-2 | C7: 15 | D7: 4 | E7: =D7*C7 -> 60 | F7: 4.5 | G7: 21 | H7: 0.6531 | I7: =H7*E7 -> 39.186 | J7: 42 | K7: 80 | L7: 1 | M7: 4
A9: 3 | B9: Server room | C9: 23 | D9: 4 | E9: =D9*C9 -> 92 | F9: 4.5 | G9: 21 | H9: 0.6531 | I9: =H9*E9 -> 60.0852 | J9: 62 | K9: 80 | L9: 1 | M9: 3
A11: 4 | B11: Hub room 1 | C11: 11.1 | D11: 4 | E11: =D11*C11 -> 44.4 | F11: 4.5 | G11: 21 | H11: 0.6531 | I11: =H11*E11 -> 28.99764 | J11: 30 | K11: 34 | L11: 1 | M11: 3
A13: 5 | B13: Hub room 2 | C13: 13.6 | D13: 4 | E13: =D13*C13 -> 54.4 | F13: 4.5 | G13: 21 | H13: 0.6531 | I13: =H13*E13 -> 35.52864 | J13: 40 | K13: 80 | L13: 1 | M13: 3
A15: 6 | B15: Hub room 3 | C15: 10.4 | D15: 4 | E15: =D15*C15 -> 41.6 | F15: 4.5 | G15: 21 | H15: 0.6531 | I15: =H15*E15 -> 27.16896 | J15: 30 | K15: 34 | L15: 1 | M15: 3
F19: Total | I19: =SUM(I5:I17) -> 315.83916 | J19: =SUM(J5:J17) -> 334 | L19: =SUM(L5:L17) -> 6 | M19: =SUM(M4:M17) -> 20
B20: Notes:-
A22: 1) | B22: FK-5-1-12 designed as per NFPA 2001 recommendations.

Sheet Fire Curtain
A1: PROJECT : DHL - Chennai
A2: SUBJECT : Fire Curtain
A3: SL.NO | B3: ITEM DESCRIPTION | C3: UNIT | D3: QTY | E3: SUPPLY & INSTALLATION
E4: RATE (INR) | F4: AMOUNT (INR)
A6: 1 | B6: FIRE CURTAIN
A8: 1.1 | B8: Supply, installation, Testing and Commisioning of active fire barrier automatic drop down fire curtains, as per Indian Standards – NBC 2016, European standards – BS EN 1634-1. Performance requirements – min 120 minutes integrity, radiation min 90 minutes <20kW/m2 for single barrel and radiation min 120 minutes <20kW/m2 for Multiple barrel. Active fire curtain barrier assemblies shall comprise of a fire resistant fabric which is wound on to a steel roller, which is powered by an internal electric DC motor, enclosed within a galvanized mild steel box 200*200/400mm, including a conjoined bottom bar for entire length to suit the deflection performance requirements of the project and the desired ceiling configuration in fitted to the bottom edge of the fabric 1.Fabric: High-temperature-resistant woven glass fabric with a protective PU coating. Designed to withstand temperatures up to 1100°C. Non-combustible – Class A2-s1, d0 according to DIN EN 13501-1. Tested and certified as per EN 1634-1:2014+A1:2018 & EN 15269-11:2018 for 180 minutes. 2. Fabric Test-The fabric material is tested as part of the complete assembly, complete as either a single construction or as an overlapped and conjoined construction separately in the orientation and standard use of the application and installed in accordance with the fire resistance test in accordance with EN 1363-1 and EN 1634-2 as required by BS EN 1634-1. 240 minutes fire resistant (type of fabric) fabric Valmiera Glass UK-4415-2-SP complying with BS EN. The fabric material is tested independently to reaction to fire test in accordance with BS EN ISO 1716 to achieve an “A1” classification in accordance with BS EN 13501-1+A1. 3.Side guide-The galvanised steel side Guides should be of made of 2mm thickness 4. Motor:Equipped with a gravity fail-safe mechanism for deployment during power failure. Tested along with the complete system as per EN 1634-1:2014+A1:2018. Deployment speed meets EN standards. Includes automatic reset and integrates with fire alarm systems. CE certified from a European notified body 5. Thread:Uses high-strength, fire-resistant Kevlar or stainless-steel thread. Stitching follows best practices for durability and resistance to high heat. This must be mentioned in the test report. 6. Control Panel: Master Panel should have inbuilt batteries and Motor Control System:Integrated microprocessor-based control panel to manage deployment speed, position control, and fault monitoring. Supports communication with building management systems (BMS) and fire alarm interfaces for seamless operation. Operates on 230V AC single-phase power supply. Provides a minimum of 3 hours battery back-up of emergency power to ensure continued operation during power failure. Note: The doorset was subjected to 25 manually operated opening and closing cycles as specified in EN 7. Emergency Push Button: Manual override push button for emergency retraction. Designed to be easily accessible and fixed along the egress path. Push buttons must be provided on both sides of the fire curtain. 14600: 2005.
B9: a) Single Barrel Fire Curtains Size: 1600mm X 3000mm | C9: No. | D9: 0 | F9: =E9*D9 -> 0
B10: b) Single Barrel Fire Curtains Size: 2000mm X 3000mm | C10: No. | D10: 0 | F10: =E10*D10 -> 0
B11: c) Single Barrel Fire Curtains Size: 5350mm X 3000mm | C11: No. | D11: 1 | F11: =E11*D11 -> 0
B12: c) Single Barrel Fire Curtains Size: 6000 mm X 3000mm | C12: No. | D12: 1 | F12: =E12*D12 -> 0
B13: c) multi Barrel Fire Curtains Size: 7700 mm X 3000mm | C13: No. | D13: 1 | F13: =E13*D13 -> 0
B14: g) Beam sensor | C14: No. | D14: 3 | F14: =E14*D14 -> 0
B15: Suggested Makes: | F15: =E15*D15 -> 0
B16: a) Orient
B17: b) Double O (Globle fire curtain)
B19: GRAND TOTAL | F19: =SUM(F9:F18) -> 0

Sheet BMS
A1: PROJECT : DHL - Chennai
A2: SUBJECT : BMS
A3: SL.NO | B3: ITEM DESCRIPTION | C3: UNIT | D3: QTY | E3: SUPPLY RATE (INR) | F3: INSTALLATION RATE (INR) | G3: SUPPLY AMOUNT (INR) | H3: INSTALLATION AMOUNT (INR) | I3: TOTAL AMOUNT (INR)
B5: Supply Installation testing & Commissioning of IBMS system comprising of following :
B6: Supply, Installation, Testing & Commissioning of Building Management System (BMS). BMS shall be complete as per point schedule suitable to monitor, operate & control the total air conditioning system as well as other systems from a central location Computer. The system shall be complete with all accessories including Server Computer, System/ Network Controller, DDC, Graphics Software, sensors, control valves, actuators, network & electronic components, transformers, relays & associated cabling, conduiting, control wiring, Enclosures etc. as required to make the system operative and functional. Any accessories required for messaging (SMS on Phone) and E-Mailing of alarms to be included in BMS.
B7: BMS Vituralisation - Complete BMS including hardwares & softwares should be capable of virtualization in future without any changes in BMS set Up. 1. BMS application and hardware: a) The proposed BMS system must support DHCP b) The proposed BMS system must support 802.1xx c) The Proposed BMS system must support IPv4 and should be upgradable to IPv6.
A9: 1 | B9: MAIN BMS DATABASE AND APPLICATION SERVER HARDWARE 19" Rack Mount BMS Server shall comprise of the following minimum hardware: HP Enterprise x64class PC, Window Server 2019 Standard, Inter® Xeon® CPU @ 4GHz 20MB Cache, 32GB or more of RAM, RAID 1 configured drives for OS and BMS application RAID 6 configured 15K RPM, 3Gb/s drives for minimum 2 TB of Storage after Raid Configuration, for the DB. Raid Controller Network Interface Card Power supply unit , Standard video display adapter with AntiVirus, MS Windows Server Software and operating license; and MS SQL Server License Location: BMS Room/ Server room | C9: Set
A11: 2 | B11: BMS Client Station BMS Client workstation shall comprise of the following minimum hardware: Intel i7 7700 Processor at mim 4GHz ,12M, 4GB NVIDIA Graphic, 16GB or more of RAM, Microsoft® Windows® 11 or Higher 64 bit, 1TB SSD,10K RPM 3.0Gb/s Hard Drive for OS and BMS Applications Network Interface Card - 10/100/1000 MB DVD-R/W ; and with Nvidia Graphics Accelerator card to support 2 Multiplexed Monitors Complete with AntiVirus,MS Windows Client Software and operating license; MS SQL License Location: BMS Room | C11: Set | D11: 1 | G11: =+N(E11)*N($D11) -> 0 | H11: =F11*D11 -> 0 | I11: =SUM(G11:H11) -> 0
A13: 3 | B13: 21" colour ,Flat Screen type Professional HD monitor for above client workstation | C13: Nos. | D13: 1 | G13: =+N(E13)*N($D13) -> 0 | H13: =F13*D13 -> 0 | I13: =SUM(G13:H13) -> 0
A14: 4 | B14: 42" colour , Flat Screen Type Professional HD monitor for above client workstation | C14: Nos. | D14: 1 | G14: =+N(E14)*N($D14) -> 0 | H14: =F14*D14 -> 0 | I14: =SUM(G14:H14) -> 0
A16: 5 | B16: A4 size Color Alarm Printer suitable for the application, with driver software. | C16: Nos. | D16: 1 | G16: =+N(E16)*N($D16) -> 0 | H16: =F16*D16 -> 0 | I16: =SUM(G16:H16) -> 0
A17: 5A | B17: Required UPS for Controllers, Sensors & Computer with minium 30 minutes backup. | C17: Nos. | D17: 1 | G17: =+N(E17)*N($D17) -> 0 | H17: =F17*D17 -> 0 | I17: =SUM(G17:H17) -> 0
B19: Softwares for IBMS System
A20: 6 | B20: Server version BMS software as specified with for realtime Processing of all Data being mapped in to the system by the DDCs and Protocol Integrators as mapped in the IO Summary. For 1500 IO points License(Includes Soft and hard points) Shall provide Data dashboard for Mobile devices vide an Internet / Intranet connection Shall be Complete with Web Browser Module for Remote Login, to be able to transmit user defined data in Graphical Format. EC-Net Bms Software for 2500 points complete with Advance Graphics for Realtime Graphical Depiction of the Statuses and Controls as per the Detailed IO Summary, to Present a Powerful Single GUI for all the HVAC, Electrical, Fire, Security for the Entire Facility. Shall be complete with Dashbaords & customisable graphical interface. | C20: User License | D20: 1 | G20: =+N(E20)*N($D20) -> 0 | H20: =F20*D20 -> 0 | I20: =SUM(G20:H20) -> 0
A21: 7 | B21: Client version BMS software for "Monitor & Control" application, User Licence included in Software
A23: 8 | B23: SMS & E-mail alarm notification module with unlimited user capability,SMS Paging & Email Facility for transmitting specified alarms to designated personnel. Note :- BMS Vendor to include the cost of GSM Hardware in this line item
A25: 9 | B25: Protocol Integrator for High Level integration with following 3rd Party Equipment's as mentioned in the data point summary.
B26: >> The system will warrant a Exclusive, Dedicated Protocol Integrator for every single individual 3rd party system (No other 3rd Party Integration shall be clubbed with any one integration ) >> The Protocol Integrator shall be Capable to Integrate Open protocol systems on BACnet /Modbus/Lonworks/M-Bus/J-Bus Protocol Made available on Ethernet IP, OR on serial RS 485 / 232 interface. Such Protocol Integrator shall Be Installed the same enclosures where the DDCs are installed . >>The Protocol Integrator for Ethernet based integrations shall be a soft integrator loaded on the BMS Server Hardware. For this purpose, the Bidder shall study the IO Summary and Estimate the license costs at Mgt. server level. >> For Serial interface, hardware P I Units shall be provided.For this purpose, the Bidder shall study the IO Summary and Estimate the number of hardware P.I.s required, and license costs at Mgt. server level.
A27: a | B27: Protocol Integrator for Energy Meters - 21 nos | C27: Lot | D27: 1 | G27: =+N(E27)*N($D27) -> 0 | H27: =F27*D27 -> 0 | I27: =SUM(G27:H27) -> 0
A28: b | B28: Protocol Integrator for UPS - 3nos | C28: Lot | D28: 1 | G28: =+N(E28)*N($D28) -> 0 | H28: =F28*D28 -> 0 | I28: =SUM(G28:H28) -> 0
A29: c | B29: Protocol Integrator for VRF System [CRC in HVAC Vendor scope] | C29: Lot | D29: 1 | G29: =+N(E29)*N($D29) -> 0 | H29: =F29*D29 -> 0 | I29: =SUM(G29:H29) -> 0
A30: d | B30: Protocol Integrator for Fire alarm system - 1nos | C30: Lot | D30: 1 | G30: =+N(E30)*N($D30) -> 0 | H30: =F30*D30 -> 0 | I30: =SUM(G30:H30) -> 0
A31: e | B31: Protocol Integrator for AHU/ Motor / VFD soft Integrations - 6 nos | C31: Lot | D31: 1 | G31: =+N(E31)*N($D31) -> 0 | H31: =F31*D31 -> 0 | I31: =SUM(G31:H31) -> 0
A32: f | B32: Protocol Integrator for CSU/ Motor / VFD soft Integrations - 6 nos | C32: Lot | D32: 1 | G32: =+N(E32)*N($D32) -> 0 | H32: =F32*D32 -> 0 | I32: =SUM(G32:H32) -> 0
A33: g | B33: Protocol Integrator for VAV - 98 nos | C33: Lot | D33: 1 | G33: =+N(E33)*N($D33) -> 0 | H33: =F33*D33 -> 0 | I33: =SUM(G33:H33) -> 0
A34: h | B34: Protocol Integrator for Gas Suppression System - 6nos | C34: Lot | D34: 1 | G34: =+N(E34)*N($D34) -> 0 | H34: =F34*D34 -> 0 | I34: =SUM(G34:H34) -> 0
A35: i | B35: Protocol Integrator for water meter - 6nos | C35: Lot | D35: 1 | G35: =+N(E35)*N($D35) -> 0 | H35: =F35*D35 -> 0 | I35: =SUM(G35:H35) -> 0
A36: j | B36: Protocol Integrator for BTU Meter - 6nos | C36: Lot | D36: 1 | G36: =+N(E36)*N($D36) -> 0 | H36: =F36*D36 -> 0 | I36: =SUM(G36:H36) -> 0
A37: k | B37: Protocol Integrator for Rodent - 5nos | C37: Lot | D37: 1 | G37: =+N(E37)*N($D37) -> 0 | H37: =F37*D37 -> 0 | I37: =SUM(G37:H37) -> 0
A38: l | B38: Protocol Integrator for WLD System - 5nos | C38: Lot | D38: 1 | G38: =+N(E38)*N($D38) -> 0 | H38: =F38*D38 -> 0 | I38: =SUM(G38:H38) -> 0
... A44: r | B44: Protocol Integrator for PA - 1nos | C44: Lot | D44: 1 | G44: =+N(E44)*N($D44) -> 0 | H44: =F44*D44 -> 0 | I44: =SUM(G44:H44) -> 0
A46: 10 | B46: SITC of DDC Enclosures ( Complete with DDC controllers as per IO Schedule, Power supplies, auxiliary relays), Enclosue shall also provide for space for the Protocol integrators , LAN IO Outlets and Edge Switches as per detailed design
B47: The Enclosures shall be MS Powder Coated to Colour (As per Client/Consultant ) , IP 55 Rating for indoor; and IP 65 rating for outdoor Installations. The Enclosure shall be provided with mounting accessories for Controller / and or IO Modules and Serial Modules- such as DIN Rails, Elmex Terminals for Cable Terminations, Cable Managers, Dressings for internal cabling, ferruling, tagging etc. PSU shall also cater to power requirment of the Instrumentation, Actuators and other connected equipment. Enclosure Shall be Complete with pilot relays, fuses, overload protection relays, auxiliary power output socket etc. as required to complete the installation and intended usage. Shall have Top and Bottom Knockouts for Cable entry, and side vents for ventilation Controllers, IO Modules and Serial Modules shall confirm to Tender specs and design intent. Note:- The Direct digital controllers and the Protocol Integrators shall have maximum limit of 50 IOs on one DDC (even If used with expansion IO Modules); and 800 Soft points respectively.
A48: a | B48: DDC Enclosure of Electrical System | C48: Lot
A49: b | B49: DDC Enclosure of HVAC System | C49: Lot | D49: 6 | G49: =+N(E49)*N($D49) -> 0 | H49: =F49*D49 -> 0 | I49: =SUM(G49:H49) -> 0
A50: c | B50: DDC Enclosure of Fire & LV System | C50: Lot
A52: 11 | B52: SITC of Instrumentation controls and valves with + 2% Accuracy (For Temperature Sensor the Accuracy shall be +/- 0.5 deg C) ; Complete with required fitting and mounting accessories, Copper tubing's, PVC tubing's, terminations, Ferruling, Tagging, Lugs et al, provided to ensure technically acceptable installation
A53: a | B53: Outdoor Air Temperature & RH sensor | C53: Nos. | D53: 1 | G53: =+N(E53)*N($D53) -> 0 | H53: =F53*D53 -> 0 | I53: =SUM(G53:H53) -> 0
A54: b | B54: Air Differential Pressure switch | C54: Nos. | D54: 18 | G54: =+N(E54)*N($D54) -> 0 | H54: =F54*D54 -> 0 | I54: =SUM(G54:H54) -> 0
A55: c | B55: Air Differential Pressure sensor | C55: Nos. | D55: 18 | G55: =+N(E55)*N($D55) -> 0 | H55: =F55*D55 -> 0 | I55: =SUM(G55:H55) -> 0
A56: d | B56: Air temperature & RH sensor (Space Type) | C56: Nos. | D56: 12 | G56: =+N(E56)*N($D56) -> 0 | H56: =F56*D56 -> 0 | I56: =SUM(G56:H56) -> 0
A57: e | B57: H2 Sensor | C57: Nos. | D57: 1 | G57: =+N(E57)*N($D57) -> 0 | H57: =F57*D57 -> 0 | I57: =SUM(G57:H57) -> 0
A58: f | B58: Water Pressure Sensor (0-15 Kg/cm2 pressure) | C58: Nos. | D58: 12 | G58: =+N(E58)*N($D58) -> 0 | H58: =F58*D58 -> 0 | I58: =SUM(G58:H58) -> 0
A59: g | B59: Duct Type T + Rh Sensor | C59: Nos. | D59: 14 | G59: =+N(E59)*N($D59) -> 0 | H59: =F59*D59 -> 0 | I59: =SUM(G59:H59) -> 0
A60: h | B60: Duct Type Temp Sensor | C60: Nos. | H60: =F60*D60 -> 0 | I60: =SUM(G60:H60) -> 0
A61: i | B61: Immerssion Type Temprature Sensor | C61: Nos. | D61: 24 | G61: =+N(E61)*N($D61) -> 0 | H61: =F61*D61 -> 0 | I61: =SUM(G61:H61) -> 0
A62: j | B62: Space type CO2 Sensor | C62: Nos. | H62: =F62*D62 -> 0 | I62: =SUM(G62:H62) -> 0
A63: k | B63: Multipoint Velocity Metering sensor with probe for Fresh air flow measurement | C63: Nos. | D63: 6 | G63: =+N(E63)*N($D63) -> 0 | H63: =F63*D63 -> 0 | I63: =SUM(G63:H63) -> 0
A64: m | B64: Current Transformers | C64: Nos. | H64: =F64*D64 -> 0 | I64: =SUM(G64:H64) -> 0
A65: n | B65: Duct Static pressure sensors | C65: Nos. | D65: 14 | G65: =+N(E65)*N($D65) -> 0 | H65: =F65*D65 -> 0 | I65: =SUM(G65:H65) -> 0
A66: 0 | B66: Space type Temperature sensor | C66: Nos. | H66: =F66*D66 -> 0 | I66: =SUM(G66:H66) -> 0
B68: Cabling and Containment
A69: 12 | B69: Supply & Laying of Cabling for instrument, controls, valves to DDCs and communication cabling from DDC to central equipment complete with earthing, supports etc complete. Laid on Surface / On Cable Trays. All Cables shall be ferruled and tagged, and shall use lugs for termination at both ends. All cables shall be properly glanded at Panel and the third party field panels to ensure proper installation.
A70: a | B70: Armoured 2 Core x 1 sq mm FRLS Al-Mylar Screened with drain wire, Cable for control cabling | C70: Rmt | D70: 3500 | G70: =+N(E70)*N($D70) -> 0 | H70: =F70*D70 -> 0 | I70: =SUM(G70:H70) -> 0
A71: b | B71: Armoured 4 Core x 1 sq mm FRLS Al-Mylar Screened with drain wire, Cable for control cabling | C71: Rmt | D71: 3000 | G71: =+N(E71)*N($D71) -> 0 | H71: =F71*D71 -> 0 | I71: =SUM(G71:H71) -> 0
A72: c | B72: Armoured 8 Core x 1 sq mm FRLS Al-Mylar Screened with drain wire, Cable for control cabling | C72: Rmt | D72: 220 | G72: =+N(E72)*N($D72) -> 0 | H72: =F72*D72 -> 0 | I72: =SUM(G72:H72) -> 0
A73: d | B73: Armoured 2Core x 1.5 sq mm FRLS Unscreened Cable | C73: Rmt | D73: 1200 | G73: =+N(E73)*N($D73) -> 0 | H73: =F73*D73 -> 0 | I73: =SUM(G73:H73) -> 0
A74: e | B74: Armoured Communication cable: FRLSCommunication Cable 2 Twisted pair x 1.0 mm2 Multistranded Screened Communication cable with Al Mylar Tape and 0.5 mm2 Drain wire as per requirment by System. | C74: mtrs
A75: f | B75: Communication cable: LSZHCommunication Cable Cat 6e as per IEEE Standards complete with GI conduits | C75: mtrs
A76: g | B76: Supply & Laying of Un-Armoured Single mode 6 core Fibre optic cable, Zero Halogen Low Smoke outer Sheath. laid in Conduits / cable Trays. Shall be complete with IO Module Boxes at the Camera End, Patch Cords, GI Gang Boxes, LIUs, Pigtails, Termination lugs, Labelling and tagging, ferruling etc | C76: mtrs
A77: h | B77: Supply & Laying of 32mm GI Conduits B class with GI Saddle & Spacers, flexible GI extensions, back boxes and gang boxes, junction boxes with elemex terminals etc., complete as required to fulfill the desired objective of cabling | C77: Mtrs. | D77: 1500 | G77: =+N(E77)*N($D77) -> 0 | H77: =F77*D77 -> 0 | I77: =SUM(G77:H77) -> 0
A79: 13 | B79: Supply of Perforated GI cable tray with Cover : complete with supports, all fittings and mounting accessories, etc complete to installation requirements. All Bends / Tees for cable trays shall be factory fabricated and not site fabricated
A80: a | B80: 75 mm x 50 mm x 2mm | C80: Mtrs. | D80: 400 | G80: =+N(E80)*N($D80) -> 0 | H80: =F80*D80 -> 0 | I80: =SUM(G80:H80) -> 0
A81: b | B81: 100 mm x 100 mm x 2mm | C81: Mtrs. | D81: 500 | G81: =+N(E81)*N($D81) -> 0 | H81: =F81*D81 -> 0 | I81: =SUM(G81:H81) -> 0
A82: c | B82: 150 mm x 100 mm x 2mm | C82: Mtrs. | D82: 300 | G82: =+N(E82)*N($D82) -> 0 | H82: =F82*D82 -> 0 | I82: =SUM(G82:H82) -> 0
A83: d | B83: 200 mm x 100 mm x 2 mm | C83: Mtrs. | D83: 100 | G83: =+N(E83)*N($D83) -> 0 | H83: =F83*D83 -> 0 | I83: =SUM(G83:H83) -> 0
A84: e | B84: 250 mm x 100 mm x 2mm | C84: Mtrs.
A85: f | B85: 300 mm x 100 mm x 2 mm | C85: Mtrs.
A87: 14 | B87: SITC of Edge Switch : 24 port layer 2 switch with 10/100/1000 Managed Switches with IP multicast snooping and data-driven IGMP support and with Two 1000baseT single mode FO uplink ports and all related termination accessories as per site specific System requirement. Complete with 9U Rack. Compliance to Tender specs to be Provided | C87: No.
A88: 15 | B88: SITC of Edge Switch : 16 port layer 2 switch with 10/100/1000 Managed Switches with IP multicast snooping and data-driven IGMP support and with two 1000baseT single mode FO uplink ports and all related termination accessories as per site specific System requirement. Complete with 9U Rack. Compliance to Tender specs To be provided | C88: No. | D88: 4 | G88: =+N(E88)*N($D88) -> 0 | H88: =F88*D88 -> 0 | I88: =SUM(G88:H88) -> 0
A89: 16 | B89: SITC of Core / Aggregator Switch : Modular 24 port Layer 3 managed switch with Fiber ports; required number of 10/100/1000 ports etc. as per project requirement. Complete with 9U Rack Compliance to Tender specs To be provided | C89: No.
B91: Equipment Racks
A92: 17 | B92: SITC of 19" type Equipment racks of U size as required, for mounting the Servers & Switches in the BMS for mounting field mounted Switches at every Floor. Racks shall be complete with Modular Patch Panels for Patching the Field Cables ( Cu and FO) with the Edge Switches on floor as required. Racks shall be provided with Dual Power A&B, and should have 2 PDU Strips, Redundant Fans and lockable Door. shall be with Patch Panel, LIU, IO Modules etc.
A93: a | B93: SITC of 9 U rack | C93: Nos | D93: 1 | G93: =+N(E93)*N($D93) -> 0 | H93: =F93*D93 -> 0 | I93: =SUM(G93:H93) -> 0
B95: GRAND TOTAL | G95: =SUM(G5:G94) -> 0 | H95: =SUM(H5:H94) -> 0 | I95: =SUM(I6:I93) -> 0

Sheet Cause & Effect (Fire Alarm)
A2: FIRE ALARM CAUSE & EFFECT MATRIX
G3: ALARM SIGNAL | J3: ALERT MESSAGE | L3: EVAC MESSAGE | M3: HOOTER
B4: EFFECT CAUSE | C4: Alarm in Fire Control Panel | D4: Alarm in Repeater Panels | E4: Fire Suppression System for Critical rooms | F4: Automatic alert message in Fire Floor | G4: Automatic alert message -One floor above or below | H4: Automatic Evac message in Fire Floor (Public Address) | I4: Automatic Evac message -One floor above/below (Public Address) | J4: Hooter in Fire Floor | K4: Hooter- one floor above/below | L4: Tripping - Access Control, auto door closer, Fire damper, Fire curtains, AHU, AC unit, Fresh air fan in Fire floor | M4: Tripping - Access Control, auto door closer, Fire damper, AHU, AC unit, Fire curtains, Fresh air fan - Two floors above and One floor below | N4: Critical Room AC Units trip in Fire Floor | O4: Critical Room AC units trips in Two floors above & One floor below | P4: Remarks
A5: x | B5: Working in normal condition | P5: (see additional notes)
A6: √ | B6: Tripped / Activated condition
B7: Normal Mode | C7: x | D7: x | E7: x | F7: x | G7: x | H7: x | I7: x | J7: x | K7: x | L7: x | M7: x | N7: x | O7: x
B8: ACTIVE AREA - OFFICE AREA
A9: 1 | B9: Single Detector activation in concerned area | C9: √ | D9: √ | E9: x | F9: √ | G9: √ | H9: x | I9: x | J9: x | K9: x | L9: x | M9: x | N9: x | O9: x
A10: a | B10: After Seek & search time delay of 90 seconds | C10: √ | D10: √ | E10: x | F10: √ | G10: √ | H10: √ | I10: √ | J10: √ | K10: √ | L10: √ | M10: √ | N10: √ | O10: x
A11: b | B11: On completion of 180 Seconds from above stage. | C11: √ | D11: √ | E11: x | F11: √ | G11: √ | H11: √ | I11: √ | J11: √ | K11: √ | L11: √ | M11: √ | N11: √ | O11: x | P11: Evac msg can still continue on the floor till the battery drained completely along with the hooters.
A12: 2 | B12: Two Det or Manual Call Point activation in concerned area | C12: √ | D12: √ | E12: x | F12: √ | G12: √ | H12: √ | I12: √ | J12: √ | K12: √ | L12: √ | M12: √ | N12: √ | O12: √
A13: a | B13: On completion of 90 Seconds from above stage. | C13: √ | D13: √ | E13: x | F13: √ | G13: √ | H13: √ | I13: √ | J13: √ | K13: √ | L13: √ | M13: √ | N13: √ | O13: √ | P13: Evac msg can still continue on the floor till the battery drained completely along with the hooters.
A14: 3 | B14: Sprinkler Flow Switch activation | C14: √ | D14: x | E14: x | F14: √ | G14: x | H14: x | I14: x | J14: x | K14: x | L14: x | M14: x | N14: x | O14: x
A15: a | B15: After 180 Seconds from above stage. | C15: √ | D15: √ | E15: x | F15: √ | G15: x | H15: x | I15: x | J15: x | K15: x | L15: x | M15: x | N15: x | O15: x
A16: b | B16: On completion of 270 Seconds from above stage. | C16: √ | D16: √ | E16: x | F16: √ | G16: √ | H16: √ | I16: √ | J16: √ | K16: √ | L16: √ | M16: √ | N16: √ | O16: √ | P16: Evac msg can still continue on the floor till the battery drained completely along with the hooters.
B17: ACTIVE AREA - Server/Hub room/UPS & Battery ROOM
A18: 1 | B18: Single Detector activation in concerned area | C18: √ | D18: x | E18: √ | F18: x | G18: x | H18: x | I18: x | J18: x | K18: x | L18: x | M18: x | N18: x | O18: x | P18: Alarm only in GSS Panel & Fire Panel
A19: a | B19: After Seek & search time delay of 90 seconds | C19: √ | D19: x | E19: √ | F19: x | G19: x | H19: x | I19: x | J19: x | K19: x | L19: x | M19: x | N19: x | O19: x | P19: Alarm only in GSS Panel & Fire Panel
A20: b | B20: On completion of 180 Seconds from above stage. | C20: √ | D20: x | E20: √ | F20: x | G20: x | H20: x | I20: x | J20: x | K20: x | L20: x | M20: x | N20: x | O20: x | P20: Gas Release to be initiated
A21: 2 | B21: Two Det or Manual Call Point activation in concerned area | C21: √ | D21: x | E21: √ | F21: x | G21: x | H21: x | I21: x | J21: x | K21: x | L21: x | M21: x | N21: x | O21: x | P21: Gas Release to be initiated
B22: VESDA in Server/Hub room/UPS & Battery ROOM | C22: √ | D22: x | E22: √ | F22: x | G22: x | H22: x | I22: x | J22: x | K22: x | L22: x | M22: x | N22: x | O22: x
A23: 1 | B23: Activation in concerned area | C23: √ | D23: x | E23: √ | F23: x | G23: x | H23: x | I23: x | J23: x | K23: x | L23: x | M23: x | N23: x | O23: x | P23: Alarm only in GSS Panel & Fire Panel
A24: a | B24: After Seek & search time delay of 90 seconds | C24: √ | D24: x | E24: √ | F24: x | G24: x | H24: x | I24: x | J24: x | K24: x | L24: x | M24: x | N24: x | O24: x | P24: Alarm only in GSS Panel & Fire Panel
A25: b | B25: On completion of 180 Seconds from above stage. | C25: √ | D25: x | E25: √ | F25: x | G25: x | H25: x | I25: x | J25: x | K25: x | L25: x | M25: x | N25: x | O25: x | P25: Gas Release to be initiated
B26: ACTIVE AREA - LANDLORD AREA
A27: 3 | B27: Signal from Base builder panel | C27: √ | D27: √ | E27: x | F27: x | G27: x | H27: x | I27: x | J27: x | K27: x | L27: x | M27: x | N27: x | O27: x
B28: WATER LEAK DETECTION IN CRITICAL ROOMS | C28: √ | D28: √ | E28: x | F28: x | G28: x | H28: x | I28: x | J28: x | K28: x | L28: x | M28: x | N28: x | O28: x
A29: 4 | B29: On detection of Alarm | C29: √ | D29: √ | E29: x | F29: x | G29: x | H29: x | I29: x | J29: x | K29: x | L29: x | M29: x | N29: x | O29: x
B30: PWD TOILET PANIC ALARM | C30: √ | D30: √ | E30: x | F30: x | G30: x | H30: x | I30: x | J30: x | K30: x | L30: x | M30: x | N30: x | O30: x
A31: 5 | B31: On detection of Alarm | C31: √ | D31: √ | E31: x | F31: x | G31: x | H31: x | I31: x | J31: x | K31: x | L31: x | M31: x | N31: x | O31: x

Sheet IO - HVAC
B1: BUILDING MANAGEMENT SYSTEM - INPUT / OUTPUT POINT SUMMARY
A2: SL NO | B2: TAG NO | C2: DDC / HLI LOCATION | D2: EQUIPMENT LOCATION | E2: DESCRIPTION | F2: QTY | G2: AI | H2: AO | I2: DI | J2: DO | K2: No. of Equip for Soft Integration (Modbus or Bacnet/MSTP) | L2: No. of Soft Points | M2: MONITOR | N2: CONTROL | O2: ALARM | P2: TREND | Q2: PROVISION BY OTHER AGENCIES | R2: AGENCY TO INTERFACE | S2: DP switch-air | T2: immersion temp sensor | U2: DP sensor (Back Pressure)- Air | V2: Wall mount T+ RH sensor | W2: Duct Temp. sensor | X2: IAQ Sensor | Y2: CO2 sensor | Z2: Duct Mount T+ RH sensor | AA2: Air Flow Sensor
A3: 1 | D3: AHU Rooms | E3: DDC for AIR HANDLING UNITS
E4: Floor mounted chilled water AHU’s - LL AHU | F4: 6
E5: AHU Fan ON/OFF status | I5: =F4 -> 6 | M5: * | O5: * | Q5: Differential Pressure switch | R5: BMS Vendor | S5: =I5 -> 6
E6: Supply Fan VFD Speed Control & Feedback | G6: =F4*1 -> 6 | H6: =F4*1 -> 6 | M6: * | N6: * | Q6: VFD vendor has to provide 0-10Vdc signal for Modulation | R6: HVAC Vendor
E7: CHW Supply & Return line Temperature | G7: 12 | M7: * | O7: * | P7: * | Q7: Immersion temp sensor | R7: BMS Vendor | T7: =G7 -> 12
E8: Duct static pressure sensor | G8: 14 | M8: * | O8: * | Q8: Back Pressure Sensors | R8: BMS Vendor | U8: =G8 -> 14
E9: Fire Dampers Status Monitoring | I9: 36 | M9: * | O9: * | Q9: HVAC Vendor shall provide Potential Free Contact for fire dampers monitoring | R9: HVAC/BMS Vendor
E10: Return Air Temperature & RH Monitoring | G10: 6 | M10: * | P10: * | Q10: Temp & RH Sensor with required accessories | R10: BMS Vendor | V10: =G10 -> 6
E11: Supply Air Temperature | G11: =F4 -> 6 | M11: * | P11: * | Q11: Temp sensor with required accessories | R11: BMS Vendor | W11: =G11 -> 6
E12: CO2 Sensor | G12: 6 | M12: * | P12: * | Q12: Co2 sensor with required accessories | R12: BMS Vendor | Y12: =G12 -> 6
E13: Velocity Sensor | G13: 18 | M13: * | P13: * | Q13: Velocity sensor with required accessories | R13: BMS Vendor | AA13: 10
E14: AHU Filter Choke status - Pre filter | I14: 6 | M14: * | O14: * | Q14: Air Differential Pressure Switch | R14: BMS Vendor | S14: =I14 -> 6
E15: AHU Filter Choke status - Fine filter | I15: 6 | M15: * | O15: * | Q15: Air Differential Pressure Switch | R15: BMS Vendor | S15: =I15 -> 6
E16: Spares | G16: =ROUNDUP(SUM(G5:G15)*15%,0) -> 11 | H16: =ROUNDUP(SUM(H5:H15)*15%,0) -> 1 | I16: =ROUNDUP(SUM(I5:I15)*15%,0) -> 9 | J16: =ROUNDUP(SUM(J5:J15)*15%,0) -> 0
E17: Total Number of IO Points required for per DDC | G17: =SUM(G5:G15)+G16 -> 79 | H17: =SUM(H5:H15)+H16 -> 7 | I17: =SUM(I5:I15)+I16 -> 63 | J17: =SUM(J5:J15)+J16 -> 0
A19: 2 | D19: Floors | E19: Ceiling Suspended DX TFAs - Client | F19: 6
E20: AHU Fan ON/OFF status | I20: =F19 -> 6 | M20: * | O20: * | Q20: Differential Pressure switch | R20: BMS Vendor | S20: =I20 -> 6
E21: Supply Fan EC Motor Speed Control & Feedback | G21: =F19*1 -> 6 | H21: =F19*1 -> 6 | M21: * | N21: * | Q21: AHU vendor has to provide Potentiometer with 0-10Vdc signal for Modulation | R21: HVAC Vendor
E22: CHW Supply & Return line Temperature | G22: =F19 -> 6 | M22: * | O22: * | P22: * | Q22: Immersion temp sensor | R22: BMS Vendor | T22: =G22 -> 6
E23: Duct static pressure sensor | G23: 0 | M23: * | O23: * | Q23: Back Pressure Sensors | R23: BMS Vendor | U23: =G23 -> 0
E24: Return Air Temperature & RH Monitoring | G24: =F19 -> 6 | M24: * | P24: * | Q24: Temp & RH Sensor with required accessories | R24: BMS Vendor | V24: =G24 -> 6
E25: Supply Air Temperature | G25: =1*F19 -> 6 | M25: * | P25: * | Q25: Temp sensor with required accessories | R25: BMS Vendor | W25: =G25 -> 6
E26: AHU Filter Choke status - Pre filter | I26: 6 | M26: * | O26: * | Q26: Air Differential Pressure Switch | R26: HVAC Vendor | S26: =I26 -> 6
E27: AHU Filter Choke status - Chemical filter | I27: 6 | M27: * | O27: * | Q27: Air Differential Pressure Switch | R27: HVAC Vendor | S27: =I27 -> 6
E28: Spares | G28: =ROUNDUP(SUM(G20:G27)*15%,0) -> 4 | H28: =ROUNDUP(SUM(H20:H27)*15%,0) -> 1 | I28: =ROUNDUP(SUM(I20:I27)*15%,0) -> 3 | J28: =ROUNDUP(SUM(J20:J27)*15%,0) -> 0
E29: Total Number of IO Points required for per DDC | G29: =SUM(G20:G27)+G28 -> 28 | H29: =SUM(H20:H27)+H28 -> 7 | I29: =SUM(I20:I27)+I28 -> 21 | J29: =SUM(J20:J27)+J28 -> 0
A32: 3 | D32: Floors | E32: HLI for VAVs
E33: Soft Integrations via Modbus or Bacnet
E34: Variable Air Volume Units - Integrators | F34: 6 | K34: 17 | L34: =8*F35 -> 784 | Q34: HVAC Vendor has to provide BACNet over MSTP over RS485 output for BMS integration | R34: HVAC Vendor
E35: VAVs | F35: 98
D36: 1 | E36: Space Temperature
D37: 2 | E37: Temperature Set Point
D38: 3 | E38: Box Airflow
D39: 4 | E39: Damper Position
D40: 5 | E40: Design Flow
D41: 6 | E41: Emergency overide
D42: 7 | E42: Minimum Flow Set Point
D43: 8 | E43: Maximum Flow Set Point
E45: Spares | L45: =ROUNDUP(SUM(L34:L44)*15%,0) -> 118
E46: Total Number of IO Points required per DDC | L46: =SUM(L34:L44)+L45 -> 902
A48: 4 | D48: Floors | E48: HLI for IAQ Sensors
E49: Soft Integrations via Modbus or Bacnet
E50: Air Quality Monitors | F50: 0
E51: Air Quality Monitor Sensor Integration | K51: =F50 -> 0 | L51: =K51*6 -> 0 | M51: * | P51: * | Q51: Air Quality Monitor with Modbus over RS485 connectivity | R51: HVAC Vendor
D52: 1 | E52: PM 10
D53: 2 | E53: PM 2.5
D54: 3 | E54: CO2
D55: 4 | E55: Temperature
D56: 5 | E56: TVOC
D57: 6 | E57: Index
E58: Spares | L58: =ROUNDUP(SUM(L50:L51)*15%,0) -> 0
E59: Total Number of IO Points required for per DDC | L59: =SUM(L50:L51)+L58 -> 0
A62: 5 | D62: Floors | E62: HLI for CO2
E63: Soft Integrations via Modbus
E64: Office Space CO2 Sensor | F64: 6
E65: CO2 Sensor Integration | K65: =F64 -> 6 | L65: =K65 -> 6 | M65: * | P65: * | Q65: CO2 Sensors with Modbus over RS485 connectivity | R65: HVAC Vendor
E66: Spares | L66: =ROUNDUP(SUM(L64:L65)*15%,0) -> 1
E67: Total Number of IO Points required for per DDC | L67: =SUM(L64:L65)+L66 -> 7
A69: 6 | D69: Cafeteria | E69: Packaged Unit | F69: 0 | M69: *
E70: Fan ON/OFF command | J70: =F69 -> 0 | N70: * | Q70: HVAC Elec. Panel vendor to make electrical provision in the Fan Starter panel to execute ON/OFF Command for remote operation | R70: HVAC Vendor
E71: Fan Trip Status | I71: =F69 -> 0 | M71: * | O71: * | Q71: Potential Free Contact | R71: HVAC Vendor
E72: Auto/Manual Status | I72: =F69 -> 0 | M72: * | Q72: Wiring from Auxiliary Potential Free contact of A/M switch | R72: HVAC Vendor
E73: Run Status | I73: =F69 -> 0 | M73: * | P73: * | Q73: Differential Pressure switch | R73: BMS Vendor | S73: =I73 -> 0
E74: Spares | G74: =ROUNDUP(SUM(G69:G73)*15%,0) -> 0 | H74: =ROUNDUP(SUM(H69:H73)*15%,0) -> 0 | I74: =ROUNDUP(SUM(I69:I73)*15%,0) -> 0 | J74: =ROUNDUP(SUM(J69:J73)*15%,0) -> 0
E75: Total Number of Soft Points | G75: =SUM(G69:G73)+G74 -> 0 | H75: =SUM(H69:H73)+H74 -> 0 | I75: =SUM(I69:I73)+I74 -> 0 | J75: =SUM(J69:J73)+J74 -> 0
A77: 6 | D77: Battery Rooms | E77: Hydrogen Exhaust Fan | F77: 1 | M77: *
E78: Fan ON/OFF command | J78: =F77 -> 1 | N78: * | Q78: HVAC Elec. Panel vendor to make electrical provision in the Fan Starter panel to execute ON/OFF Command for remote operation | R78: HVAC Vendor
E79: Fan Trip Status | I79: =F77 -> 1 | M79: * | O79: * | Q79: Potential Free Contact | R79: HVAC Vendor
E80: Auto/Manual Status | I80: =F77 -> 1 | M80: * | Q80: Wiring from Auxiliary Potential Free contact of A/M switch | R80: HVAC Vendor
E81: Run Status | I81: =F77 -> 1 | M81: * | P81: * | Q81: Differential Pressure switch | R81: BMS Vendor | S81: =I81 -> 1
E82: Hydrogen Sensor | G82: 1
E83: Hydrogen Level | G83: =1*F77 -> 1 | M83: * | O83: * | P83: * | Q83: Hydrogen sensor | R83: HVAC Vendor
E84: Spares | G84: =ROUNDUP(SUM(G77:G83)*15%,0) -> 1 | H84: =ROUNDUP(SUM(H77:H83)*15%,0) -> 0 | I84: =ROUNDUP(SUM(I77:I83)*15%,0) -> 1 | J84: =ROUNDUP(SUM(J77:J83)*15%,0) -> 1
E85: Total Number of Soft Points | G85: =SUM(G77:G83)+G84 -> 3 | H85: =SUM(H77:H83)+H84 -> 0 | I85: =SUM(I77:I83)+I84 -> 4 | J85: =SUM(J77:J83)+J84 -> 2
A87: 7 | D87: Technical Rooms | E87: GAS SUPRESSION EXTRACTION SYSTEM FK-5-1-12 | F87: 6 | M87: *
E88: Fan ON/OFF command | J88: =F87 -> 6 | N88: * | Q88: HVAC Elec. Panel vendor to make electrical provision in the Fan Starter panel to execute ON/OFF Command for remote operation | R88: HVAC Vendor
E89: Fan Trip Status | I89: =F87 -> 6 | M89: * | O89: * | Q89: Potential Free Contact | R89: HVAC Vendor
E90: Auto/Manual Status | I90: =F87 -> 6 | M90: * | Q90: Wiring from Auxiliary Potential Free contact of A/M switch | R90: HVAC Vendor
E91: Run Status | I91: =F87 -> 6 | M91: * | P91: * | Q91: Differential Pressure switch | R91: BMS Vendor | S91: =I91 -> 6
E92: Spares | G92: =ROUNDUP(SUM(G87:G91)*15%,0) -> 0 | H92: =ROUNDUP(SUM(H87:H91)*15%,0) -> 0 | I92: =ROUNDUP(SUM(I87:I91)*15%,0) -> 3 | J92: =ROUNDUP(SUM(J87:J91)*15%,0) -> 1
E93: Total Number of Soft Points | G93: =SUM(G87:G91)+G92 -> 0 | H93: =SUM(H87:H91)+H92 -> 0 | I93: =SUM(I87:I91)+I92 -> 21 | J93: =SUM(J87:J91)+J92 -> 7
A95: 8 | D95: ODU at Service Balcony | E95: HLI for for VRV
E96: VRF Centralized Controller | F96: 1 | K96: 1 | L96: =(F97*7)+(F105*6) -> 162 | Q96: 1. HVAC Vendor has to provide BACNet over MSTP over RS485 output for BMS integration 2. Termination of cables in the respective device | R96: HVAC Vendor
E97: Indoor unit | F97: 18
D98: 1 | E98: Alarm Status
D99: 2 | E99: Unit On/Off Command
D100: 3 | E100: Unit On Off Status
D101: 4 | E101: Room Temperature
D102: 5 | E102: Room Temperature Set point
D103: 6 | E103: Fan status
D104: 7 | E104: Indoor unit number
E105: Outdoor unit | F105: 6
D106: 1 | E106: Alarm Status
D107: 2 | E107: Unit On/Off Command
D108: 3 | E108: Unit On Off Status
D109: 4 | E109: Fan status
D110: 5 | E110: Compressor status
D111: 6 | E111: Indoor unit number
...

Sheet IO - PFF
B1: BUILDING MANAGEMENT SYSTEM - INPUT / OUTPUT POINT SUMMARY
A2: SL NO | B2: TAG NO | C2: DDC / HLI LOCATION | D2: EQUIPMENT LOCATION | E2: DESCRIPTION | F2: QTY | G2: AI | H2: AO | I2: DI | J2: DO | K2: No. of Equip for Soft Integration (Modbus or Bacnet/MSTP) | L2: No. of Soft Points | M2: MONITOR | N2: CONTROL | O2: ALARM | P2: TREND | Q2: PROVISION BY OTHER AGENCIES | R2: AGENCY TO INTERFACE | S2: DP switch-Pump | T2: Level Switch
A3: 1 | C3: Floors | E3: HLI for Waste Water Flow Meter
E4: Flow Meter for Waste Water (Provided By Delvloper) | F4: 6 | K4: =F4 -> 6 | L4: =F4*2 -> 12 | Q4: 1. Should be BMS Compatible 2. Modbus over RS485 output to be provided 3. Termination of cables in the respective device | R4: PHE Vendor
D5: 1 | E5: Water flow rate
D6: 2 | E6: Consumption
E7: Spares | L7: =ROUNDUP(SUM(L4:L6)*15%,0) -> 2
E8: Total Number of Soft Points | L8: =SUM(L3:L4)+L7 -> 14
A10: 2 | C10: Floor | E10: HLI for NOVEC Panel
E11: NOVEC Panel | F11: 0 | K11: =F11 -> 0 | L11: =F11*8 -> 0 | Q11: 1. Should be BMS Compatible 2. Modbus over RS485 output to be provided 3. Termination of cables in the respective device | R11: PHE Vendor
D12: 1 | E12: Number of Zones
D13: 2 | E13: Zone Panel Health Status
D14: 3 | E14: Zone Panel Alarm Status
D15: 4 | E15: Fault
D16: 5 | E16: Zone Isolation
D17: 6 | E17: Alarm
D18: 7 | E18: Trouble
D19: 8 | E19: Release
E21: Spares | G21: =ROUNDUP(SUM(G11:G20)*15%,0) -> 0 | H21: =ROUNDUP(SUM(H11:H20)*15%,0) -> 0 | I21: =ROUNDUP(SUM(I11:I20)*15%,0) -> 0 | J21: =ROUNDUP(SUM(J11:J20)*15%,0) -> 0 | L21: =ROUNDUP(SUM(L11:L20)*15%,0) -> 0
E23: Total Number of Soft Points | G23: =SUM(G11:G20)+G21 -> 0 | H23: =SUM(H11:H20)+H21 -> 0 | I23: =SUM(I11:I20)+I21 -> 0 | J23: =SUM(J11:J20)+J21 -> 0 | L23: =SUM(L11:L20)+L21 -> 0
E24: Total | G24: =G8+G23 -> 0 | H24: =H8+H23 -> 0 | I24: =I8+I23 -> 0 | J24: =J8+J23 -> 0 | L24: =L8+L23 -> 14 | S24: =SUM(S4:S9) -> 0 | T24: =SUM(T4:T9) -> 0

Sheet IO - Electrical
B1: BUILDING MANAGEMENT SYSTEM - INPUT / OUTPUT POINT SUMMARY
A2: SL. NO. | B2: TAG NO | C2: DDC / HLI LOCATION | D2: EQUIPMENT LOCATION | E2: DESCRIPTION | F2: QTY | G2: AI | H2: AO | I2: DI | J2: DO | K2: No. of Equip for Soft Integration (Modbus or Bacnet/MSTP) | L2: No. of Soft Points | M2: MONITOR | N2: CONTROL | O2: ALARM | P2: TREND | Q2: PROVISION BY OTHER AGENCIES | R2: AGENCY TO INTERFACE
A5: 1 | C5: Floors | E5: FIRE ALARM SYSTEM | F5: 1 | K5: 1 | L5: =F5*3 -> 3 | Q5: 1. Should be BMS Compatible 2. BACnet / MSTP or Modbus over RS485 output to be provided 3. Termination of cables in the respective device | R5: FAS vendor
E6: Fire
E7: Supervisory
E8: Trouble
E9: Spares | L9: =ROUNDUP(SUM(L4:L8)*15%,0) -> 1
E10: Total Number of Soft Points | L10: =SUM(L4:L8)+L9 -> 4
A13: 2 | C13: Floors | E13: RODENT REPELLENT SYSTEM | F13: 5 | K13: =F13 -> 5 | L13: =1*K13 -> 5 | Q13: 1. Should be BMS Compatible 2. Modbus over RS485 output to be provided 3. Termination of cables in the respective device | R13: RRS vendor
E14: Start Frequency
E15: End Frequency
E16: Sweep Time
E17: Sweep Delay
E18: Panel Health Status / ON / off condition
E19: Spares | L19: =ROUNDUP(SUM(L13:L18)*15%,0) -> 1
E20: Total Number of IO Points required for per DDC | L20: =SUM(L13:L18)+L19 -> 6
A23: 3 | C23: Floors | E23: HLI for Energy Meters and Electrical Breakers
E24: Soft Integrations via Modbus
E25: ENERGY METERS | F25: 21 | K25: =F25 -> 21 | L25: =9*K25 -> 189 | Q25: 1. Should be BMS Compatible 2. Modbus over RS485 output to be provided 3. Termination of cables in the respective device | R25: Electrical vendor | S25: Not Required
E26: Current
E27: Voltage
E28: Frequency
E29: Power Factor
E30: KW
E31: KVA
E32: KVAR
E33: KVARH
E34: KWH
E35: Spares | G35: =ROUNDUP(SUM(G25:G34)*15%,0) -> 0 | H35: =ROUNDUP(SUM(H25:H34)*15%,0) -> 0 | I35: =ROUNDUP(SUM(I25:I34)*15%,0) -> 0 | J35: =ROUNDUP(SUM(J25:J34)*15%,0) -> 0 | L35: =ROUNDUP(SUM(L25:L34)*15%,0) -> 29
E36: Total Number of IO Points required for per DDC | G36: =SUM(G25:G34)+G35 -> 0 | H36: =SUM(H25:H34)+H35 -> 0 | I36: =SUM(I25:I34)+I35 -> 0 | J36: =SUM(J25:J34)+J35 -> 0 | L36: =SUM(L25:L34)+L35 -> 218
E38: Soft Integrations via Modbus
A39: 4 | C39: Floors | E39: UPS | F39: 3 | K39: =F39 -> 3 | L39: =45*K39 -> 135 | Q39: 1. Should be BMS Compatible 2. Modbus over RS485 output to be provided 3. Termination of cables in the respective device | R39: UPS vendor
E40: UPS Status
E41: UPS General Alarm
E42: UPS Overload Alarm
E43: Normal / Battery Mode
E44: Inverter Status
E45: Rectifier Status
E46: Output Overvoltage
E47: Bypass Voltage
E48: Bypass Frequency
E49: UPS Output Power
E50: Output Voltage Phase 1
E51: Output Voltage Phase 2
... E84: Battery Temperature
E85: Spares | L85: =ROUNDUP(SUM(L39:L84)*15%,0) -> 21
E86: Total Number of IO Points required for per DDC | L86: =L85+SUM(L39:L84) -> 156
A87: 5 | C87: Floors | E87: WLD SYSTEM | F87: 5 | K87: =F87 -> 5 | L87: =K87*1 -> 5 | Q87: 1. Should be BMS Compatible 2. Modbus RTU port equipped with RS485 output to be provided 3. Termination of cables in the respective device
E88: On
E89: Off
E90: Leakage Detection
E91: Panel Health Status
E92: Spares | L92: =ROUNDUP(SUM(L87:L91)*15%,0) -> 1
E93: Total Number of IO Points required for per DDC | L93: =L92+L87 -> 6
A95: 6 | C95: Floors | E95: VESDA SYSTEM | F95: 3 | K95: =F95 -> 3 | L95: =4*K95 -> 12 | Q95: 1. Should be BMS Compatible 2. Modbus and interface card over RS485 output to be provided 3. Termination of cables in the respective device
E96: On
E97: Off
E98: Smoke Detection
E99: Panel Health Status
E100: Spares | L100: =ROUNDUP(SUM(L95:L99)*15%,0) -> 2
E101: Total Number of IO Points required for per DDC | L101: =L100+L95 -> 14
A103: 7 | C103: Floors | E103: LMS SYSTEM | F103: 0 | K103: =F103 -> 0 | L103: =4*K103 -> 0 | Q103: 1. Should be BMS Compatible 2. Modbus and interface card over RS485 output to be provided 3. Termination of cables in the respective device
E104: On
E105: Off
E106: Status
E107: LMS Health Status
E108: Spares | L108: =ROUNDUP(SUM(L103:L107)*15%,0) -> 0
E109: Total Number of IO Points required for per DDC | L109: =L108+L103 -> 0
A111: 8 | C111: Floors | E111: PA | F111: 1 | K111: =F111 -> 1 | L111: =4*K111 -> 4 | Q111: 1. Should be BMS Compatible 2. Modbus and interface card over RS485 output to be provided 3. Termination of cables in the respective device
E112: On
E113: Off
E114: Status
E115: PA Panel Status
E116: Spares | L116: =ROUNDUP(SUM(L111:L115)*15%,0) -> 1
E117: Total Number of IO Points required for per DDC | L117: =L116+L111 -> 5
E120: Total | G120: =G10+G20+G36+G86+G93+G101 -> 0 | H120: =H10+H20+H36+H86+H93+H101 -> 0 | I120: =I10+I20+I36+I86+I93+I101 -> 0 | J120: =J10+J20+J36+J86+J93+J101 -> 0 | K120: =K10+K20+K36+K86+K93+K101 -> 0 | L120: =L10+L20+L36+L86+L93+L101+L109+L117 -> 409
